Workbook
Name Klantnaam: Algemeen!$B$4
Name Contactpersoon: Algemeen!$B$5
Name Email: Algemeen!$B$6
Name Telefoonnummer: Algemeen!$B$7
Name Object_adres: Algemeen!$B$10
Name Object_ID: Algemeen!$B$15
Name Unit_nr: Algemeen!$B$12
Name Postcode: Algemeen!$B$13
Name Plaats: Algemeen!$B$14
Name Incheck_datum: Algemeen!$B$18
Name Uitcheck_datum: Algemeen!$B$19
Name Aantal_dagen: Algemeen!$B$20
Name Voorschot_borg: Algemeen!$B$23
Name GWE_Maandbedrag: Algemeen!$B$24
Name Voorschot_GWE: Algemeen!$B$25
Name Voorschot_schoonmaak: Algemeen!$B$26
Name Overige_voorschotten: Algemeen!$B$27
Name Extra_voorschot_bedrag: Algemeen!$B$28
Name Extra_voorschot_omschrijving: Algemeen!$B$29
Name Schoonmaak_pakket: Algemeen!$B$32
Name Inbegrepen_uren: Algemeen!$B$33
Name Uurtarief_schoonmaak: Algemeen!$B$34
Name BTW_percentage_schoonmaak: Algemeen!$B$35
Name Schoonmaak_totaal_kosten: Algemeen!$B$36
Name Extra_schoonmaak_bedrag_calc: Algemeen!$B$37
Name Meterbeheerder: Algemeen!$B$38
Name Energie_leverancier: Algemeen!$B$39
Name Contractnummer: Algemeen!$B$40
Name RR_Klantnummer: Algemeen!$B$43
Name RR_Folder_link: Algemeen!$B$44
Name RR_Projectleider: Algemeen!$B$45
Name RR_Inspecteur: Algemeen!$B$46
Name RR_Factuurnummer: Algemeen!$B$47
Name Borg_gebruikt: Algemeen!$B$50
Name Borg_terug: Algemeen!$B$51
Name Restschade: Algemeen!$B$52
Name GWE_meer_minder: Algemeen!$B$53
Name Extra_voorschot_gebruikt: Algemeen!$B$54
Name Extra_voorschot_terug: Algemeen!$B$55
Name Extra_voorschot_restschade: Algemeen!$B$56
Name Totaal_eindafrekening: Algemeen!$B$57
Name KWh_begin: GWE_Detail!$B$4
Name KWh_eind: GWE_Detail!$B$5
Name KWh_verbruik: GWE_Detail!$B$6
Name Gas_begin: GWE_Detail!$B$7
Name Gas_eind: GWE_Detail!$B$8
Name Gas_verbruik: GWE_Detail!$B$9
Name Water_begin: GWE_Detail!$B$10
Name Water_eind: GWE_Detail!$B$11
Name Water_verbruik: GWE_Detail!$B$12
Name GWE_totaal_excl: GWE_Detail!$B$33
Name GWE_BTW: GWE_Detail!$B$34
Name GWE_totaal_incl: GWE_Detail!$B$35
Name Totaal_uren_gew: Schoonmaak!$B$6
Name Extra_uren: Schoonmaak!$B$7
Name Extra_schoonmaak_bedrag: Schoonmaak!$B$9
Name Schade_totaal_excl: Schade!$B$58
Name Schade_BTW: Schade!$B$59
Name Schade_totaal_incl: Schade!$B$60

Sheet Algemeen
A1: RYANRENT EINDAFREKENING - BASISGEGEVENS
A3: KLANTGEGEVENS
A4: Naam Klant *
A5: Contactpersoon (automatisch) | B5: =IFERROR(VLOOKUP(B4,Lists!$C:$F,2,FALSE),"")
A6: Email (automatisch) | B6: =IFERROR(VLOOKUP(B4,Lists!$C:$F,3,FALSE),"")
A7: Telefoonnummer (automatisch) | B7: =IFERROR(VLOOKUP(B4,Lists!$C:$F,4,FALSE),"")
A9: OBJECTGEGEVENS
A10: Adres Object *
A11: Object ID (automatisch) | B11: =IFERROR(VLOOKUP(B10,Lists!$A:$B,2,FALSE),"")
A12: Unit Nummer
A13: Postcode | B13: =IFERROR(VLOOKUP(B10,Lists!$A:$H,7,FALSE),"")
A14: Plaats | B14: =IFERROR(VLOOKUP(B10,Lists!$A:$H,8,FALSE),"")
A15: Object ID (automatisch) | B15: =IF(B10="","",VLOOKUP(B10,Lists!$A$2:$B$389,2,FALSE))
A17: VERBLIJFSPERIODE
A18: Incheck Datum *
A19: Uitcheck Datum *
A20: Aantal Dagen (automatisch) | B20: =IF(AND(B18<>"",B19<>""),B19-B18,"")
A22: VOORSCHOTTEN
A23: Voorschot Borg *
A24: GWE Maandbedrag | B24: 0
A25: Voorschot GWE (automatisch) | B25: =IF(ISNUMBER(B24), (B24 * 12 / 365) * Aantal_dagen, 0)
A26: Voorschot Schoonmaak *
A27: Overige Voorschotten | B27: 0
A28: Extra Voorschot Bedrag | B28: 0
A29: Extra Voorschot Omschrijving
A31: CONTRACTGEGEVENS
A32: Schoonmaak Pakket *
A33: Inbegrepen Uren (automatisch) | B33: =IF(B32="Basis Schoonmaak",5,IF(B32="Intensief Schoonmaak",7,IF(B32="Achteraf Betaald",0,"")))
A34: Uurtarief Schoonmaak (excl. BTW) * | B34: 50
A35: BTW Percentage Schoonmaak * | B35: 0.21
A36: Schoonmaak Totaal Kosten (automatisch) | B36: =IF(Schoonmaak!Totaal_uren_gew="","",Schoonmaak!Totaal_uren_gew*B34*(1+B35))
A37: Extra Schoonmaak Bedrag (automatisch) | B37: =MAX(0,Schoonmaak_totaal_kosten-Voorschot_schoonmaak)
A38: Meterbeheerder
A39: Energie Leverancier
A40: Contractnummer
A42: INTERNE RYANRENT GEGEVENS
A43: RR Klantnummer
A44: RR Folder Link
A45: RR Projectleider
A46: RR Inspecteur
A47: RR Factuurnummer
A49: BEREKENDE VELDEN (automatisch berekend) | C49: ← Live preview (beveiligd)
A50: Borg Gebruikt (automatisch) | B50: =Schade!Schade_totaal_incl
A51: Borg Terug (automatisch) | B51: =IF(Borg_gebruikt="","",Voorschot_borg-Borg_gebruikt)
A52: Restschade (automatisch) | B52: =IF(Borg_gebruikt="","",MAX(0,Borg_gebruikt-Voorschot_borg))
A53: GWE Meer/Minder (automatisch) | B53: =IF(GWE_Detail!GWE_totaal_incl="","",Voorschot_GWE-GWE_Detail!GWE_totaal_incl)
A54: Extra Voorschot Gebruikt * | B54: 0
A55: Extra Voorschot Terug (automatisch) | B55: =IF(Extra_voorschot_bedrag=0,"",Extra_voorschot_bedrag-Extra_voorschot_gebruikt)
A56: Extra Voorschot Restschade (automatisch) | B56: =IF(Extra_voorschot_bedrag=0,"",MAX(0,Extra_voorschot_gebruikt-Extra_voorschot_bedrag))
A57: Totaal Eindafrekening (automatisch) | B57: =IF(OR(Borg_terug="",GWE_meer_minder="",Schoonmaak!Extra_schoonmaak_bedrag=""),"",Borg_terug+GWE_meer_minder-Schoonmaak!Extra_schoonmaak_bedrag+IF(Extra_voorschot_bedrag=0,0,Extra_voorschot_terug))

Sheet Lists
A1: Address | B1: Object ID | C1: Client Name | D1: Contact Person | E1: Email | F1: Phone | G1: Postcode | H1: Plaats
A2: 1e | B2: 0388 | C2: 4 Homes B.V. | H2: Middellandstraat 104A
A3: 2e Maasbosstraat 2 a | B3: 0148 | C3: AKT Autoschade | E3: facturen@aktautoschade.com | H3: VLAARDINGEN
A4: 2e Maasbosstraat 2 b | B4: 0149 | C4: ASML Housing | E4: relocation@asml.com | G4: 2807BB | H4: Gouda
A5: 2e Maasbosstraat 2 c | B5: 0150 | C5: Aelbers | G5: 7553LC | H5: Hengelo
A6: 2e van Leydengaelstraat 6 | B6: 0022 | C6: Amdor Projecten | G6: 1779GJ | H6: Den Oever
A7: Abelenlaan 143 | B7: 0014 | C7: Autodaxx B.V. | E7: inkoopfactuur@autodaxx.nl | G7: 1779GJ | H7: Den Oever
A8: Acacia 2 | B8: 0003 | C8: BAM Wonen | E8: contact@bam.nl | G8: 3224EB | H8: Hellevoetsluis
A9: Acacialaan 9 | B9: 0223 | C9: BBTS (Vastgoed Spijkenisse) | G9: 3085CZ | H9: Rotterdam
A10: Achterdijk 47 | B10: 0190 | C10: Bakker | G10: 3071EE | H10: Rotterdam
A11: Adriaan Baasstraat 34 | B11: 0007 | C11: Buurman Vastgoed B.V. | G11: 1779GJ | H11: Den Oever
A12: Akkerweg 41 | B12: 0384 | C12: Bw-engineering | E12: r.adelaar@bw-engineering.nl | H12: [huis 58]
A13: Akkerweg 41 [010] | B13: 0341 | C13: C-Flex BV | H13: Den oever
A14: Akkerweg 41 [011] | B14: 0372 | C14: CB Construction | H14: Den oever
A15: Akkerweg 41 [014] | B15: 0293 | C15: Crown Uitzendgroep | H15: Den Oever
A16: Akkerweg 41 [015] | B16: 0294 | C16: Daan Mulder | E16: daan.mulder@example.com | H16: Den Oever
A17: Akkerweg 41 [016] | B17: 0342 | C17: Dit en Larex | H17: Den oever
A18: Akkerweg 41 [017] | B18: 0373 | C18: Dock Holland | H18: Den oever
A19: Akkerweg 41 [018] | B19: 0295 | C19: Duijndam Personeeldiensten | H19: Den oever
A20: Akkerweg 41 [019] | B20: 0343 | C20: EG Facility & Services BV | E20: facturen@egfs.nl | H20: Den oever
A21: Akkerweg 41 [020] | B21: 0383 | C21: Eastmen | G21: 1779GJ | H21: Den oever
A22: Akkerweg 41 [022] | B22: 0296 | C22: Eemsdelta | H22: Den oever
A23: Akkerweg 41 [026] | B23: 0297 | C23: Employ | H23: Den oever
A24: Akkerweg 41 [031] | B24: 0298 | C24: Estra Logistics Systems | H24: Den oever
A25: Akkerweg 41 [035] | B25: 0350 | C25: Eu Facility Services | H25: Den oever
A26: Akkerweg 41 [036] | B26: 0356 | C26: Expats Inc | E26: housing@expats.com | H26: Den oever
A27: Akkerweg 41 [037] | B27: 0299 | C27: Faciloo B.V. | H27: Den Oever
A28: Akkerweg 41 [038] | B28: 0357 | C28: Flextalent4u | H28: Den oever
A29: Akkerweg 41 [040] | B29: 0300 | C29: Flexvesting | H29: Den oever
A30: Akkerweg 41 [041] | B30: 0301 | C30: Focuzop-EU | H30: Den oever
A31: Akkerweg 41 [042] | B31: 0302 | C31: GAP Costruzioni | H31: Den oever
A32: Akkerweg 41 [055] | B32: 0303 | C32: GHS | H32: Den oever
A33: Akkerweg 41 [056] | B33: 0304 | C33: Goti verhuur | H33: Den oever
A34: Akkerweg 41 [057] | B34: 0305 | C34: H.T.C. Facility Services | H34: Den oever
A35: Akkerweg 41 [059] | B35: 0306 | C35: HTC | H35: Den oever
A36: Akkerweg 41 [068] | B36: 0326 | C36: HTC Facility | H36: Den oever
A37: Akkerweg 41 [074] | B37: 0379 | C37: Housing en Transport Facilities BV | H37: Den Oever
A38: Akkerweg 41 [075] | B38: 0307 | C38: HousingWell | H38: Den oever
A39: Allard Piersonlaan 142 | B39: 0002 | C39: I-housing Vastgoed | G39: 2522 MT | H39: Den Haag
A40: Ambergweg 14 | B40: 0201 | C40: Impes Service | G40: 3081JH | H40: Rotterdam
A41: Amperelaan 23 | B41: 0043 | C41: Impianti Industriala S.P.A. | G41: 3131 HC | H41: Vlaardingen
A42: Amperestraat 36A | B42: 0135 | C42: InAxtion Vastgoed B.V. | E42: Invoice.vastgoed@inaxtion.com | G42: 3112 GA | H42: Schiedam
A43: Archimedesstraat 6B | B43: 0353 | C43: Industrial Technical Services | G43: 3112DB | H43: Schiedam
A44: Arkelse onderweg 24a | B44: 0008 | C44: Industrial Technical Services Srl | G44: 1779GJ | H44: Den Oever
A45: Baanhoek 137 | B45: 0367 | C45: Interim Jobs B.V. | E45: e.ozel@interimjobs.nl | H45: Sliedrecht
A46: Baanhoek 19 | B46: 0055 | C46: Interwell Oost B.V. | G46: 3028GH | H46: Rotterdam
A47: Baarlelaan 27 | B47: 0012 | C47: Jan Mulder | E47: jan.mulder@example.com | G47: 1779GJ | H47: Den Oever
A48: Baarsveen 197 | B48: 0013 | C48: Jan Smit | E48: jan.smit@example.com | G48: 3205 BB | H48: Spijkenisse
A49: Beatrixstraat 3 | B49: 0040 | C49: Julia Groot | E49: julia.groot@example.com | G49: 8325BD | H49: Vollenhove
A50: Beeklaan 294 | B50: 0152 | C50: Kapitan workers | G50: 1181TV | H50: Amstelveen
A51: Besterdring 6 | B51: 0060 | C51: Klaas Bos | E51: klaas.bos@example.com | G51: 2445AN | H51: Aarlanderveen
A52: Bettingeslag 10 | B52: 0322 | C52: Klaas Jansen | E52: klaas.jansen@example.com | G52: 7824HD | H52: Emmen
A53: Beukenlaan 53 | B53: 0346 | C53: Labour Housing B.V. | G53: 3181XA | H53: Rozenburg
A54: Bisschopstraat 68 | B54: 0047 | C54: Lago perseelshuisvesting | G54: 3131 DB | H54: Vlaardingen
A55: Bliek 41 | B55: 0048 | C55: Light Personeelsdiensten | G55: 8442EX | H55: Heerenveen
A56: Bornerbroekstraat 129A | B56: 0049 | C56: LogIQ | G56: 8442GA | H56: Heerenveen
A57: Bovendijk 59 | B57: 0280 | C57: Looije | H57: Kwintsheul
A58: Bovendijk 61 | B58: 0281 | C58: Lucas Visser | E58: lucas.visser@example.com | H58: Kwintsheul
A59: Broekweg 25 | B59: 0004 | C59: Lucas Vos | E59: lucas.vos@example.com | G59: 3131 HC | H59: Vlaardingen
A60: Broersveld 150A | B60: 0155 | C60: MNA Proud Facilities B.V. | G60: 3131 TG | H60: Vlaardingen
A61: Broersvest 74 c | B61: 0156 | C61: Mila de Vries | E61: mila.de.vries@example.com | G61: 3191EH | H61: Hoogvliet
A62: Buizerdstraat 210 | B62: 0027 | C62: N2 People | G62: 3145 AD | H62: Maassluis
A63: Burchtstraat 16a | B63: 0097 | C63: NL Realty | H63: Oostburg
A64: Burgemeester Cramerlaan 82 | B64: 0276 | C64: OJP | H64: DE LIER
A65: Burgemeester Crezeelaan 76 | B65: 0275 | C65: Oostkracht Bemiddeling B.V. | E65: info@ok-groep.nl | H65: DE LIER
A66: Burgemeester Stulemeijerlaan 71 | B66: 0292 | C66: Optima | H66: Schiedam
A67: Chopinstraat 33C | B67: 0160 | C67: Orange Investments Group | G67: 3191EH | H67: Hoogvliet
A68: Chopinstraat 35A | B68: 0131 | C68: Oranjegroep | G68: 3079 KC | H68: Rotterdam
A69: Chopinstraat 39C | B69: 0026 | C69: PRP Solutions Flex Sp. Z.O.O. | G69: 2522 MT | H69: Den Haag
A70: Cloosterstraat 23a | B70: 0370 | C70: People21 Services BV | E70: administratie@people21.eu | G70: 4587CA | H70: Kloosterzande
A71: Coehoorn van Scheltingaweg 12 | B71: 0051 | C71: Professional Manpower Management | G71: 3193XA | H71: Hoogvliet
A72: Coehoorn van Scheltingaweg 66 | B72: 0052 | C72: Pythagoras Construction s.r.l. | G72: 3132PG | H72: Vlaardingen
A73: Compierekade 15 | B73: 0345 | C73: RNDV | H73: Alphen a/d Rijn
A74: Coornhertstraat 95 | B74: 0162 | C74: Randstad Wonen | E74: info@randstadwonen.nl | G74: 3191EH | H74: Hoogvliet
A75: Cubalaan 25 | B75: 0375 | C75: RoyalDS | G75: 2685 LA | H75: Poeldijk
A76: Curacaolaan 24 | B76: 0163 | C76: Sem Bos | E76: sem.bos@example.com | G76: 3191EH | H76: Hoogvliet
A77: Curacaolaan 88 | B77: 0030 | C77: Sem Meijer | E77: sem.meijer@example.com | G77: 3112DB | H77: Schiedam
A78: Curcumastraat 39 | B78: 0053 | C78: Shell Expats | E78: housing@shell.com | G78: 8918JZ | H78: Leeuwarden
A79: Datheenstraat 255 | B79: 0151 | C79: Sophie de Vries | E79: sophie.de.vries@example.com | G79: 3027AK | H79: Rotterdam
A80: De Driesprong 17 | B80: 0165 | C80: Stay21 | G80: 3255AL | H80: Oude-Tonge
A81: De Gasperistraat 11 | B81: 0054 | C81: Strukton | E81: info@strukton.com | G81: 4926DC | H81: Lage Zwaluwe
A82: De Haak | B82: 0290 | C82: Suricare | H82: De Haa
A83: De Haak, Zekkenstraat 31A | B83: 0288 | C83: THS EU B.V. | E83: invoices@tecline.com | G83: 3151 XP | H83: Hoek van Holland
A84: De Haak, Zekkenstraat 31B | B84: 0289 | C84: Team Home Rentals | G84: 3151 XP | H84: Hoek van Holland
A85: De Hooidollen 606 | B85: 0056 | C85: Team Unica (nieuw per 17-05) | G85: 5111CH | H85: Baarle-Nassau
A86: De Wingel 8B | B86: 0371 | C86: TechCorp | E86: hr@techcorp.com | H86: Lage Zwaluwe
A87: Deensestraat 6A2 | B87: 0153 | C87: Tradiro | E87: planning@tradiro.nl | G87: 2543GG | H87: Den Haag
A88: Desiree Geeraerstraat 1b | B88: 0023 | C88: Transport People B.V. | E88: facturenaalsmeer@transportpeople.nl | G88: 1779GJ | H88: Den Oever
A89: Desiree Geeraertstraat 1 C | B89: 0024 | C89: UAB Techsoma | G89: 1779GJ | H89: Den Oever
A90: Deugenweerd 18 | B90: 0058 | C90: UAB Toromega | G90: 7271XT | H90: Borculo
A91: Dieptol 63 | B91: 0059 | C91: United Homes | G91: 8332BK | H91: Steenwijk
A92: Dorpsstraat 48 | B92: 0354 | C92: United homes | G92: 2445AN | H92: Aarlanderveen
A93: Dorpsstraat 73 | B93: 0066 | C93: Vivir Wonen | E93: info@vivirwonen.nl | G93: 3133EC | H93: Vlaardingen
A94: Dorpstraat 48 | B94: 0203 | C94: WS Wonen B.V. | G94: 3114NP | H94: Schiedam
A95: Dwarsweg 44 | B95: 0061 | C95: Welcome Housing BV | H95: Rozenburg
A96: Eendrachtstraat 22 | B96: 0062 | C96: Werckpost | G96: 2841 BH | H96: Moordrecht
A97: Elisadonk 220 | B97: 0136 | C97: Wil International BV | G97: 3086KS | H97: Rotterdam
A98: Energieweg 40 | B98: 0063 | C98: Wil Vakkrachten BV | G98: 3181HG | H98: Rozenburg
A99: Engelsestraat 16L1 | B99: 0168 | C99: Workforce Housing International B.V. | G99: 3131 HR | H99: Vlaardingen
A100: Engelsestraat 16L3 | B100: 0095 | G100: 3028CG | H100: Rotterdam
...

Sheet GWE_Detail
A1: GAS / WATER / ELEKTRA DETAIL
A3: METERSTANDEN
A4: Elektra (kWh) Begin *
A5: Elektra (kWh) Eind *
A6: Elektra (kWh) Verbruik (automatisch) | B6: =IF(AND(B4<>"",B5<>""),B5-B4,"")
A7: Gas (m³) Begin *
A8: Gas (m³) Eind *
A9: Gas (m³) Verbruik (automatisch) | B9: =IF(AND(B7<>"",B8<>""),B8-B7,"")
A10: Water (m³) Begin
A11: Water (m³) Eind
A12: Water (m³) Verbruik (automatisch) | B12: =IF(AND(B10<>"",B11<>""),B11-B10,"")
A14: KOSTENREGELS - Verbruik omzetten naar Euro's
A15: 💡 Vul hier de kosten in op basis van verbruik × tarief van energieleverancier. Voorbeelden staan hieronder (grijs). Verwijder voorbeelden en vul eigen regels in.
A16: Type | B16: Omschrijving | C16: Eenheid | D16: Verbruik | E16: Tarief excl. BTW (€) | F16: Kosten excl. BTW (€) | G16: BTW % | H16: BTW (€)
A17: Elektra | B17: Elektra verbruik (zie meterstand) | C17: kWh | D17: =KWh_verbruik | E17: 0.3 | F17: =D17*E17 | G17: 0.21 | H17: =F17*G17
A18: Gas | B18: Gas verbruik (zie meterstand) | C18: m³ | D18: =Gas_verbruik | E18: 1.2 | F18: =D18*E18 | G18: 0.21 | H18: =F18*G18
A19: Elektra | B19: Vaste levering elektra per dag | C19: Dagen | D19: =Algemeen!Aantal_dagen | E19: 0.5 | F19: =D19*E19 | G19: 0.21 | H19: =F19*G19
A20: Gas | B20: Vaste levering gas per dag | C20: Dagen | D20: =Algemeen!Aantal_dagen | E20: 0.45 | F20: =D20*E20 | G20: 0.21 | H20: =F20*G20
A21: Water | B21: Waterverbruik (geschat per dag) | C21: Dagen | D21: =Algemeen!Aantal_dagen | E21: 3.5 | F21: =D21*E21 | G21: 0.09 | H21: =F21*G21
F22: =IF(OR(D22="",E22=""),"",D22*E22) | G22: 0.21 | H22: =IF(OR(F22="",G22=""),"",F22*G22)
F23: =IF(OR(D23="",E23=""),"",D23*E23) | G23: 0.21 | H23: =IF(OR(F23="",G23=""),"",F23*G23)
F24: =IF(OR(D24="",E24=""),"",D24*E24) | G24: 0.21 | H24: =IF(OR(F24="",G24=""),"",F24*G24)
F25: =IF(OR(D25="",E25=""),"",D25*E25) | G25: 0.21 | H25: =IF(OR(F25="",G25=""),"",F25*G25)
F26: =IF(OR(D26="",E26=""),"",D26*E26) | G26: 0.21 | H26: =IF(OR(F26="",G26=""),"",F26*G26)
F27: =IF(OR(D27="",E27=""),"",D27*E27) | G27: 0.21 | H27: =IF(OR(F27="",G27=""),"",F27*G27)
F28: =IF(OR(D28="",E28=""),"",D28*E28) | G28: 0.21 | H28: =IF(OR(F28="",G28=""),"",F28*G28)
F29: =IF(OR(D29="",E29=""),"",D29*E29) | G29: 0.21 | H29: =IF(OR(F29="",G29=""),"",F29*G29)
F30: =IF(OR(D30="",E30=""),"",D30*E30) | G30: 0.21 | H30: =IF(OR(F30="",G30=""),"",F30*G30)
F31: =IF(OR(D31="",E31=""),"",D31*E31) | G31: 0.21 | H31: =IF(OR(F31="",G31=""),"",F31*G31)
A32: TOTALEN (automatisch berekend)
A33: Totaal excl. BTW (automatisch) | B33: =SUM(F17:F31)
A34: BTW (Totaal, automatisch) | B34: =SUM(H17:H32)
A35: Totaal incl. BTW (automatisch) | B35: =GWE_totaal_excl+GWE_BTW

Sheet Schoonmaak
A1: SCHOONMAAK OVERZICHT
A3: SCHOONMAAK GEGEVENS
A4: Schoonmaak Pakket * | B4: =Algemeen!Schoonmaak_pakket
A5: Inbegrepen Uren (automatisch) | B5: =IF(B4="Basis Schoonmaak",5,IF(B4="Intensief Schoonmaak",7,""))
A6: Totaal Uren Gewerkt *
A7: Extra Uren (automatisch) | B7: =IF(AND(B5<>"",B6<>""),MAX(0,B6-B5),"")
A8: Uurtarief * | B8: =Algemeen!Uurtarief_schoonmaak
A9: Extra Schoonmaak Bedrag (automatisch) | B9: =IF(AND(B7<>"",B8<>""),B7*B8,"")

Sheet Schade
A1: SCHADEPOSTEN OVERZICHT
A3: Vul hieronder alle schadeposten in. Bedrag wordt automatisch berekend (Aantal × Tarief).
A5: Beschrijving | B5: Aantal | C5: Tarief excl. BTW | D5: Bedrag excl. BTW | E5: BTW % | F5: BTW (€)
D6: =IF(AND(B6<>"",C6<>""),B6*C6,"") | E6: 0.21 | F6: =IF(AND(D6<>"",E6<>""),D6*E6,"")
D7: =IF(AND(B7<>"",C7<>""),B7*C7,"") | E7: 0.21 | F7: =IF(AND(D7<>"",E7<>""),D7*E7,"")
D8: =IF(AND(B8<>"",C8<>""),B8*C8,"") | E8: 0.21 | F8: =IF(AND(D8<>"",E8<>""),D8*E8,"")
D9: =IF(AND(B9<>"",C9<>""),B9*C9,"") | E9: 0.21 | F9: =IF(AND(D9<>"",E9<>""),D9*E9,"")
D10: =IF(AND(B10<>"",C10<>""),B10*C10,"") | E10: 0.21 | F10: =IF(AND(D10<>"",E10<>""),D10*E10,"")
D11: =IF(AND(B11<>"",C11<>""),B11*C11,"") | E11: 0.21 | F11: =IF(AND(D11<>"",E11<>""),D11*E11,"")
D12: =IF(AND(B12<>"",C12<>""),B12*C12,"") | E12: 0.21 | F12: =IF(AND(D12<>"",E12<>""),D12*E12,"")
D13: =IF(AND(B13<>"",C13<>""),B13*C13,"") | E13: 0.21 | F13: =IF(AND(D13<>"",E13<>""),D13*E13,"")
D14: =IF(AND(B14<>"",C14<>""),B14*C14,"") | E14: 0.21 | F14: =IF(AND(D14<>"",E14<>""),D14*E14,"")
D15: =IF(AND(B15<>"",C15<>""),B15*C15,"") | E15: 0.21 | F15: =IF(AND(D15<>"",E15<>""),D15*E15,"")
D16: =IF(AND(B16<>"",C16<>""),B16*C16,"") | E16: 0.21 | F16: =IF(AND(D16<>"",E16<>""),D16*E16,"")
D17: =IF(AND(B17<>"",C17<>""),B17*C17,"") | E17: 0.21 | F17: =IF(AND(D17<>"",E17<>""),D17*E17,"")
... D55: =IF(AND(B55<>"",C55<>""),B55*C55,"") | E55: 0.21 | F55: =IF(AND(D55<>"",E55<>""),D55*E55,"")
A57: TOTALEN (automatisch berekend)
A58: Totaal Schade excl. BTW (automatisch) | B58: =SUM(D6:D56)
A59: BTW (Totaal, automatisch) | B59: =SUM(F6:F57)
A60: Totaal Schade incl. BTW (automatisch) | B60: =IF(B58="","",B58+B59)
