Workbook

Sheet pivot 
B3: Column Labels
B4: 01 | D4: 02 | F4: 03 | H4: 04 | J4: 05 | L4: 06 | N4: 07 | P4: 08 | R4: 09 | T4: 10 | V4: 11 | X4: 12 | Z4: (blank) | AB4: Total Sum of c | AC4: Total Sum of d
A5: Row Labels | B5: Sum of c | C5: Sum of d | D5: Sum of c | E5: Sum of d | F5: Sum of c | G5: Sum of d | H5: Sum of c | I5: Sum of d | J5: Sum of c | K5: Sum of d | L5: Sum of c | M5: Sum of d | N5: Sum of c | O5: Sum of d | P5: Sum of c | Q5: Sum of d | R5: Sum of c | S5: Sum of d | T5: Sum of c | U5: Sum of d | V5: Sum of c | W5: Sum of d | X5: Sum of c | Y5: Sum of d | Z5: Sum of c | AA5: Sum of d
A6: 00088 - L. Keizer | B6: 1837.5 | C6: 1837.5 | AB6: 1837.5 | AC6: 1837.5
A7: (blank) | B7: 1837.5 | C7: 1837.5 | AB7: 1837.5 | AC7: 1837.5
A8: 100089 - Uitzendbureau Bakker B.V. | B8: 12000 | C8: 8000 | D8: 20107.12 | E8: 10450 | F8: 25302.33 | G8: 17000 | H8: 23650 | I8: 21100 | J8: 19650 | K8: 13100 | L8: 19650 | M8: 13100 | N8: 19650 | O8: 13100 | P8: 19650 | Q8: 13100 | R8: 19650 | S8: 13100 | T8: 32676.01 | U8: 19869.44 | V8: 46353.78 | W8: 30550.67 | X8: 42600 | Y8: 28400 | AB8: 300939.24 | AC8: 200870.11
A9: 0082 - Kanaal van Steenenhoek z z 10 Gorinchem | F9: 9952.33 | G9: 4100 | H9: 12300 | I9: 8200 | J9: 12300 | K9: 8200 | L9: 12300 | M9: 8200 | N9: 12300 | O9: 8200 | P9: 12300 | Q9: 8200 | R9: 12300 | S9: 8200 | T9: 12300 | U9: 8200 | V9: 12300 | W9: 8200 | X9: 12300 | Y9: 8200 | AB9: 120652.33 | AC9: 77900
A10: Huur | F10: 5852.33 | H10: 4100 | J10: 4100 | L10: 4100 | N10: 4100 | P10: 4100 | R10: 4100 | T10: 4100 | V10: 4100 | X10: 4100 | AB10: 42752.33
A11: 8105 - Omzet laag | F11: 5852.33 | H11: 4100 | J11: 4100 | L11: 4100 | N11: 4100 | P11: 4100 | R11: 4100 | T11: 4100 | V11: 4100 | X11: 4100 | AB11: 42752.33
A12: Huur (01-01-2026 - 31-01-2026) | X12: 4100 | Y12: 4100 | AB12: 4100 | AC12: 4100
A13: 1370 - Transitoria debet | X13: 4100 | AB13: 4100
A14: 8105 - Omzet laag | Y14: 4100 | AC14: 4100
A15: Huur (01-04-2025 - 30-04-2025) | F15: 4100 | G15: 4100 | H15: 4100 | I15: 4100 | AB15: 8200 | AC15: 8200
A16: 1370 - Transitoria debet | F16: 4100 | I16: 4100 | AB16: 4100 | AC16: 4100
A17: 8105 - Omzet laag | G17: 4100 | H17: 4100 | AB17: 4100 | AC17: 4100
A18: Huur (01-05-2025 - 31-05-2025) | H18: 4100 | I18: 4100 | J18: 4100 | K18: 4100 | AB18: 8200 | AC18: 8200
A19: 1370 - Transitoria debet | H19: 4100 | K19: 4100 | AB19: 4100 | AC19: 4100
A20: 8105 - Omzet laag | I20: 4100 | J20: 4100 | AB20: 4100 | AC20: 4100
A21: Huur (01-06-2025 - 30-06-2025) | J21: 4100 | K21: 4100 | L21: 4100 | M21: 4100 | AB21: 8200 | AC21: 8200
A22: 1370 - Transitoria debet | J22: 4100 | M22: 4100 | AB22: 4100 | AC22: 4100
A23: 8105 - Omzet laag | K23: 4100 | L23: 4100 | AB23: 4100 | AC23: 4100
A24: Huur (01-07-2025 - 31-07-2025) | L24: 4100 | M24: 4100 | N24: 4100 | O24: 4100 | AB24: 8200 | AC24: 8200
A25: 1370 - Transitoria debet | L25: 4100 | O25: 4100 | AB25: 4100 | AC25: 4100
A26: 8105 - Omzet laag | M26: 4100 | N26: 4100 | AB26: 4100 | AC26: 4100
A27: Huur (01-08-2025 - 31-08-2025) | N27: 4100 | O27: 4100 | P27: 4100 | Q27: 4100 | AB27: 8200 | AC27: 8200
A28: 1370 - Transitoria debet | N28: 4100 | Q28: 4100 | AB28: 4100 | AC28: 4100
A29: 8105 - Omzet laag | O29: 4100 | P29: 4100 | AB29: 4100 | AC29: 4100
A30: Huur (01-09-2025 - 30-09-2025) | P30: 4100 | Q30: 4100 | R30: 4100 | S30: 4100 | AB30: 8200 | AC30: 8200
A31: 1370 - Transitoria debet | P31: 4100 | S31: 4100 | AB31: 4100 | AC31: 4100
A32: 8105 - Omzet laag | Q32: 4100 | R32: 4100 | AB32: 4100 | AC32: 4100
A33: Huur (01-10-2025 - 31-10-2025) | R33: 4100 | S33: 4100 | T33: 4100 | U33: 4100 | AB33: 8200 | AC33: 8200
A34: 1370 - Transitoria debet | R34: 4100 | U34: 4100 | AB34: 4100 | AC34: 4100
A35: 8105 - Omzet laag | S35: 4100 | T35: 4100 | AB35: 4100 | AC35: 4100
A36: Huur (01-11-2025 - 30-11-2025) | T36: 4100 | U36: 4100 | V36: 4100 | W36: 4100 | AB36: 8200 | AC36: 8200
A37: 1370 - Transitoria debet | T37: 4100 | W37: 4100 | AB37: 4100 | AC37: 4100
A38: 8105 - Omzet laag | U38: 4100 | V38: 4100 | AB38: 4100 | AC38: 4100
A39: Huur (01-12-2025 - 31-12-2025) | V39: 4100 | W39: 4100 | X39: 4100 | Y39: 4100 | AB39: 8200 | AC39: 8200
A40: 1370 - Transitoria debet | V40: 4100 | Y40: 4100 | AB40: 4100 | AC40: 4100
A41: 8105 - Omzet laag | W41: 4100 | X41: 4100 | AB41: 4100 | AC41: 4100
A42: 0217 - Middelrode 8, ROTTERDAM | T42: 3550.68 | U42: 1775.34 | V42: 6275.34 | W42: 4025.34 | X42: 6750 | Y42: 4500 | AB42: 16576.02 | AC42: 10300.68
A43: Huur | T43: 1775.34 | V43: 2250 | X43: 2250 | AB43: 6275.34
A44: 8105 - Omzet laag | T44: 1775.34 | V44: 2250 | X44: 2250 | AB44: 6275.34
A45: Huur (01-01-2026 - 31-01-2026) | X45: 2250 | Y45: 2250 | AB45: 2250 | AC45: 2250
A46: 1370 - Transitoria debet | X46: 2250 | AB46: 2250
A47: 8105 - Omzet laag | Y47: 2250 | AC47: 2250
A48: Huur (01-11-2025 - 30-11-2025) | T48: 1775.34 | U48: 1775.34 | V48: 1775.34 | W48: 1775.34 | AB48: 3550.68 | AC48: 3550.68
A49: 1370 - Transitoria debet | T49: 1775.34 | W49: 1775.34 | AB49: 1775.34 | AC49: 1775.34
A50: 8105 - Omzet laag | U50: 1775.34 | V50: 1775.34 | AB50: 1775.34 | AC50: 1775.34
A51: Huur (01-12-2025 - 31-12-2025) | V51: 2250 | W51: 2250 | X51: 2250 | Y51: 2250 | AB51: 4500 | AC51: 4500
A52: 1370 - Transitoria debet | V52: 2250 | Y52: 2250 | AB52: 2250 | AC52: 2250
A53: 8105 - Omzet laag | W53: 2250 | X53: 2250 | AB53: 2250 | AC53: 2250
A54: 0219 - Miltonstraat 55, ROTTERDAM | T54: 2900 | U54: 1450 | V54: 4350 | W54: 2900 | X54: 4350 | Y54: 2900 | AB54: 11600 | AC54: 7250
A55: Huur | T55: 1450 | V55: 1450 | X55: 1450 | AB55: 4350
A56: 8105 - Omzet laag | T56: 1450 | V56: 1450 | X56: 1450 | AB56: 4350
A57: Huur (01-01-2026 - 31-01-2026) | X57: 1450 | Y57: 1450 | AB57: 1450 | AC57: 1450
A58: 1370 - Transitoria debet | X58: 1450 | AB58: 1450
A59: 8105 - Omzet laag | Y59: 1450 | AC59: 1450
A60: Huur (01-11-2025 - 30-11-2025) | T60: 1450 | U60: 1450 | V60: 1450 | W60: 1450 | AB60: 2900 | AC60: 2900
A61: 1370 - Transitoria debet | T61: 1450 | W61: 1450 | AB61: 1450 | AC61: 1450
A62: 8105 - Omzet laag | U62: 1450 | V62: 1450 | AB62: 1450 | AC62: 1450
A63: Huur (01-12-2025 - 31-12-2025) | V63: 1450 | W63: 1450 | X63: 1450 | Y63: 1450 | AB63: 2900 | AC63: 2900
A64: 1370 - Transitoria debet | V64: 1450 | Y64: 1450 | AB64: 1450 | AC64: 1450
A65: 8105 - Omzet laag | W65: 1450 | X65: 1450 | AB65: 1450 | AC65: 1450
A66: 0232 - Zuidhoek 209D Rotterdam | T66: 6522.73 | U66: 3491.5 | V66: 5159.99 | W66: 6522.73 | AB66: 11682.72 | AC66: 10014.23
A67: 0293 - Akkerweg 41 [014], Den Oever | B67: 12000 | C67: 8000 | D67: 12000 | E67: 8000 | F67: 8000 | G67: 8000 | H67: 4000 | I67: 8000 | AB67: 36000 | AC67: 32000
A68: 0331 - Flankstraat 11 Sas van Gent | D68: 6913.7 | E68: 2450 | F68: 7350 | G68: 4900 | H68: 7350 | I68: 4900 | J68: 7350 | K68: 4900 | L68: 7350 | M68: 4900 | N68: 7350 | O68: 4900 | P68: 7350 | Q68: 4900 | R68: 7350 | S68: 4900 | T68: 7350 | U68: 4900 | V68: 7350 | W68: 4900 | X68: 7350 | Y68: 4900 | AB68: 80413.7 | AC68: 51450
A69: 0334 - Hof van Zeeland 2 Heinkenszand | D69: 1193.42 | AB69: 1193.42
A70: 0388 - 1e Middellandstraat 104A | T70: 52.6 | U70: 52.6 | V70: 4905.2 | W70: 1652.6 | X70: 4800 | Y70: 3200 | AB70: 9757.8 | AC70: 4905.2
A71: 0389 - Kritostraat 54, Rotterdam | V71: 6013.25 | W71: 2350 | X71: 7050 | Y71: 4700 | AB71: 13063.25 | AC71: 7050
A72: 100094 - I.T.S. SR.L. (INDUSTRIAL TECHNICAL SERVICES), BRAN | B72: 31150 | C72: 21350 | D72: 36400 | E72: 23975 | F72: 46025 | G72: 44100 | H72: 35525 | I72: 24850 | J72: 32025 | K72: 21350 | L72: 41867.22 | M72: 26561.25 | N72: 39788.07 | O72: 26525.38 | P72: 30731.35 | Q72: 21997.02 | R72: 30054.69 | S72: 25172.06 | T72: 22351.29 | U72: 17468.66 | V72: 14647.89 | W72: 9765.26 | X72: 14647.89 | Y72: 9765.26 | AB72: 375213.4 | AC72: 272879.89
A73: 0014 - Abelenlaan 143 Rozenburg | B73: 11100 | C73: 7400 | D73: 11100 | E73: 7400 | F73: 11100 | G73: 7400 | H73: 11100 | I73: 7400 | J73: 11100 | K73: 7400 | L73: 11403.4 | M73: 7551.7 | N73: 11555.1 | O73: 7703.4 | P73: 11555.1 | Q73: 7703.4 | R73: 15406.8 | S73: 15406.8 | T73: 7703.4 | U73: 7703.4 | AB73: 113123.8 | AC73: 83068.7
A74: 0089 - van Maanenstraat 14A Rotterdam | B74: 5175 | C74: 3450 | D74: 5175 | E74: 3450 | F74: 5175 | G74: 3450 | H74: 5175 | I74: 3450 | J74: 5175 | K74: 3450 | L74: 5316.46 | M74: 3520.73 | N74: 5387.19 | O74: 3591.46 | P74: 1795.73 | Q74: 1795.73 | AB74: 38374.38 | AC74: 26157.92
A75: 0170 - Goudestein 30 Rotterdam | B75: 0 | D75: 5250 | E75: 2625 | F75: 7875 | G75: 5250 | H75: 7875 | I75: 5250 | J75: 7875 | K75: 5250 | L75: 8090.26 | M75: 5357.63 | N75: 8197.89 | O75: 5465.26 | P75: 2732.63 | Q75: 2732.63 | AB75: 47895.78 | AC75: 31930.52
A76: 0184 - Mathenesserdijk 261A2 Rotterdam | B76: 7875 | C76: 5250 | D76: 7875 | E76: 5250 | F76: 7875 | G76: 5250 | H76: 7875 | I76: 5250 | J76: 7875 | K76: 5250 | L76: 8090.26 | M76: 5357.63 | N76: 8197.89 | O76: 5465.26 | P76: 8197.89 | Q76: 5465.26 | R76: 8197.89 | S76: 5465.26 | T76: 8197.89 | U76: 5465.26 | V76: 8197.89 | W76: 5465.26 | X76: 8197.89 | Y76: 5465.26 | AB76: 96652.6 | AC76: 64399.19
A77: 0206 - Kruiningenstraat 152 Rotterdam | B77: 7000 | C77: 5250 | D77: 7000 | E77: 5250 | F77: 14000 | G77: 22750 | H77: 3500 | I77: 3500 | AB77: 31500 | AC77: 36750
A78: 0239 - Schoonegge 110 Rotterdam | L78: 2899.72 | M78: 2623.56 | AB78: 2899.72 | AC78: 2623.56
A79: 0249 - Tholenstraat 114 Rotterdam | L79: 6067.12 | M79: 2150 | N79: 6450 | O79: 4300 | P79: 6450 | Q79: 4300 | R79: 6450 | S79: 4300 | T79: 6450 | U79: 4300 | V79: 6450 | W79: 4300 | X79: 6450 | Y79: 4300 | AB79: 44767.12 | AC79: 27950
A80: 100095 - JES Funding & Beheer B.V. | T80: 946.8 | U80: 946.8 | V80: 3600 | W80: 3600 | X80: 1200 | Y80: 1200 | AB80: 5746.8 | AC80: 5746.8
A81: 0044 - Pleinweg 101A Rotterdam | T81: 473.4 | W81: 2400 | AB81: 473.4 | AC81: 2400
A82: 0045 - Pleinweg 101 B, Rotterdam | T82: 473.4 | W82: 1200 | Y82: 1200 | AB82: 473.4 | AC82: 2400
A83: (blank) | U83: 946.8 | V83: 3600 | X83: 1200 | AB83: 4800 | AC83: 946.8
A84: 100096 - Thuisvesting B.V. | B84: 6900 | C84: 4600 | D84: 6900 | E84: 4600 | F84: 6900 | G84: 4600 | H84: 6900 | I84: 4600 | J84: 6900 | K84: 4600 | L84: 7088.6 | M84: 4694.3 | N84: 7182.9 | O84: 4788.6 | P84: 7182.9 | Q84: 4788.6 | R84: 7182.9 | S84: 4788.6 | T84: 7182.9 | U84: 4788.6 | V84: 7182.9 | W84: 4788.6 | X84: 4788.6 | Y84: 2394.3 | AB84: 82291.7 | AC84: 54031.6
A85: 0081 - Patrijsstraat 39 Papendrecht | B85: 6900 | C85: 4600 | D85: 6900 | E85: 4600 | F85: 6900 | G85: 4600 | H85: 6900 | I85: 4600 | J85: 6900 | K85: 4600 | L85: 7088.6 | M85: 4694.3 | N85: 7182.9 | O85: 4788.6 | P85: 7182.9 | Q85: 4788.6 | R85: 7182.9 | S85: 4788.6 | T85: 7182.9 | U85: 4788.6 | V85: 7182.9 | W85: 4788.6 | X85: 4788.6 | Y85: 2394.3 | AB85: 82291.7 | AC85: 54031.6
A86: 100099 - Jan Luijsterburg Beheer BV | H86: 2097.35 | AB86: 2097.35
A87: (blank) | H87: 2097.35 | AB87: 2097.35
A88: 100100 - J. van der Linde | B88: 5040 | C88: 5040 | D88: 5040 | E88: 5040 | F88: 5040 | G88: 5040 | H88: 2520 | I88: 2520 | J88: 5040 | K88: 5040 | L88: 5285 | M88: 5285 | N88: 5285 | O88: 5285 | P88: 5245.9 | Q88: 5245.9 | R88: 5245.9 | S88: 5245.9 | T88: 5245.9 | U88: 5245.9 | V88: 5245.9 | W88: 5245.9 | X88: 5245.9 | Y88: 5245.9 | AB88: 59479.5 | AC88: 59479.5
A89: 0076 - Molendijk 4 Oude-Tonge | C89: 2520 | E89: 2520 | G89: 2520 | I89: 2520 | K89: 2520 | M89: 2642.5 | N89: 19.55 | O89: 2642.5 | Q89: 2622.95 | S89: 2622.95 | U89: 2622.95 | W89: 2622.95 | Y89: 2622.95 | AB89: 19.55 | AC89: 30999.75
A90: 0077 - Voorstraat 10 Oude Tonge | C90: 2520 | E90: 2520 | G90: 2520 | K90: 2520 | M90: 2642.5 | N90: 19.55 | O90: 2642.5 | Q90: 2622.95 | S90: 2622.95 | U90: 2622.95 | W90: 2622.95 | Y90: 2622.95 | AB90: 19.55 | AC90: 28479.75
A91: (blank) | B91: 5040 | D91: 5040 | F91: 5040 | H91: 2520 | J91: 5040 | L91: 5285 | N91: 5245.9 | P91: 5245.9 | R91: 5245.9 | T91: 5245.9 | V91: 5245.9 | X91: 5245.9 | AB91: 59440.4
A92: 100101 - JJM Personeel B.V. | D92: 861.36 | E92: 430.68 | F92: 6980.68 | G92: 3705.68 | H92: 9825 | I92: 6550 | J92: 9825 | K92: 6550 | L92: 9825 | M92: 6550 | N92: 9825 | O92: 6550 | P92: 3275 | Q92: 3275 | AB92: 50417.04 | AC92: 33611.36
A93: 00000 - Algemeen | F93: 6550 | G93: 3275 | H93: 3275 | I93: 3275 | AB93: 9825 | AC93: 6550
A94: 0338 - Kerkweg 9a [huis 348] Hensbroek | D94: 861.36 | E94: 430.68 | F94: 430.68 | G94: 430.68 | H94: 6550 | I94: 3275 | J94: 9825 | K94: 6550 | L94: 9825 | M94: 6550 | N94: 9825 | O94: 6550 | P94: 3275 | Q94: 3275 | AB94: 40592.04 | AC94: 27061.36
A95: 100102 - Royal DS Personeel-service | B95: 50779.62 | C95: 28661.64 | D95: 50163.51 | E95: 42633.22 | F95: 43270.35 | G95: 28846.9 | H95: 43270.35 | I95: 28846.9 | J95: 43270.35 | K95: 28846.9 | L95: 43754.03 | M95: 29088.74 | N95: 39995.87 | O95: 27330.58 | P95: 43995.87 | Q95: 29330.58 | R95: 34605.58 | S95: 21565.29 | T95: 32980.58 | U95: 21940.29 | V95: 49120.87 | W95: 32080.58 | X95: 39120.87 | Y95: 26080.58 | AB95: 514327.85 | AC95: 345252.2
A96: 0066 - Dorpsstraat 73 Moordrecht | B96: 17695.35 | C96: 11796.9 | D96: 17695.35 | E96: 11796.9 | F96: 17695.35 | G96: 11796.9 | H96: 17695.35 | I96: 11796.9 | J96: 17695.35 | K96: 11796.9 | L96: 18179.03 | M96: 12038.74 | N96: 18420.87 | O96: 12280.58 | P96: 18420.87 | Q96: 12280.58 | R96: 12280.58 | S96: 6140.29 | T96: 12280.58 | U96: 6140.29 | V96: 18420.87 | W96: 12280.58 | X96: 18420.87 | Y96: 12280.58 | AB96: 204900.42 | AC96: 132426.14
A97: 0070 - Geleenstraat 1 Sittard | B97: 4051.37 | C97: 1625 | D97: 4875 | E97: 3250 | F97: 4875 | G97: 3250 | H97: 4875 | I97: 3250 | J97: 4875 | K97: 3250 | L97: 4875 | M97: 3250 | N97: 4875 | O97: 3250 | P97: 4875 | Q97: 3250 | R97: 1625 | S97: 1625 | AB97: 39801.37 | AC97: 26000
A98: 0293 - Akkerweg 41 [014], Den Oever | B98: 29032.9 | C98: 15239.74 | D98: 27593.16 | E98: 27586.32 | F98: 20700 | G98: 13800 | H98: 20700 | I98: 13800 | J98: 20700 | K98: 13800 | L98: 20700 | M98: 13800 | N98: 16700 | O98: 11800 | P98: 18700 | Q98: 11800 | R98: 20700 | S98: 13800 | T98: 18700 | U98: 13800 | V98: 16700 | W98: 13800 | X98: 14700 | Y98: 9800 | AB98: 245626.06 | AC98: 172826.06
A99: 0297 - Akkerweg 41 [026], Den oever | T99: 2000 | U99: 2000 | V99: 10000 | W99: 4000 | X99: 6000 | Y99: 4000 | AB99: 18000 | AC99: 10000
A100: 0326 - Akkerweg 41 [068], Den oever | P100: 2000 | Q100: 2000 | V100: 4000 | W100: 2000 | AB100: 6000 | AC100: 4000
A101: 100105 - VALO Facilities B.V. | B101: 7500 | C101: 5000 | D101: 7500 | E101: 5000 | F101: 7500 | G101: 5000 | H101: 7500 | I101: 5000 | J101: 2500 | K101: 2500 | L101: 2500 | M101: 2500 | N101: 2500 | O101: 2500 | P101: 2500 | Q101: 2500 | R101: 17500 | S101: 7500 | AB101: 57500 | AC101: 37500
A102: 0049 - Bornerbroekstraat 129A Almelo | B102: 7500 | C102: 5000 | D102: 7500 | E102: 5000 | F102: 7500 | G102: 5000 | H102: 7500 | I102: 5000 | J102: 2500 | K102: 2500 | L102: 2500 | M102: 2500 | N102: 2500 | O102: 2500 | P102: 2500 | Q102: 2500 | R102: 17500 | S102: 7500 | AB102: 57500 | AC102: 37500
...

Sheet Datasheet
A1: Jaar | B1: Periode | C1: Maand pivot | D1: Boekjaar / Periode | E1: Kostendrager | F1: Datum | G1: Bkst.nr. | H1: Grootboekrekening | I1: Omschrijving | J1: Kostenplaats | K1: Relatie | L1: d | M1: c | N1: saldo
A2: {=_xlfn.TEXTSPLIT(D2," - ",TRUE,1)} -> 2025 | B2: 1 | C2: =_xlfn.XLOOKUP(B2*1,List!A:A,List!B:B,"",0) -> 01 | D2: 2025 - 1 | F2: 45688 | G2: 25910187 | H2: 8105 - Omzet laag | I2: Huur (01-01-2025 - 31-01-2025) | J2: 0135 - Amperestraat 36A Schiedam | K2: 20 - Tradiro Services B.V. | M2: 1625 | N2: -1625
A3: {=_xlfn.TEXTSPLIT(D3," - ",TRUE,1)} -> 2025 | B3: 1 | C3: =_xlfn.XLOOKUP(B3*1,List!A:A,List!B:B,"",0) -> 01 | D3: 2025 - 1 | F3: 45672 | G3: 25910555 | H3: 8105 - Omzet laag | I3: Huur (01-02-2025 - 28-02-2025) | J3: 0061 - Dwarsweg 44 , Rozenburg | K3: 50329 - Impianti Industriala S.P.A. NEDERLAND BRANCH | L3: 4568.15 | N3: 4568.15
A4: {=_xlfn.TEXTSPLIT(D4," - ",TRUE,1)} -> 2025 | B4: 1 | C4: =_xlfn.XLOOKUP(B4*1,List!A:A,List!B:B,"",0) -> 01 | D4: 2025 - 1 | F4: 45688 | G4: 25910054 | H4: 8105 - Omzet laag | I4: Huur (01-01-2025 - 31-01-2025) | J4: 0020 - Mr. Troelstrastraat 37 Vlaardingen | K4: 20 - Tradiro Services B.V. | M4: 1655.56 | N4: -1655.56
A5: {=_xlfn.TEXTSPLIT(D5," - ",TRUE,1)} -> 2025 | B5: 1 | C5: =_xlfn.XLOOKUP(B5*1,List!A:A,List!B:B,"",0) -> 01 | D5: 2025 - 1 | F5: 45672 | G5: 25910909 | H5: 8105 - Omzet laag | I5: Huur (01-02-2025 - 28-02-2025) | J5: 0128 - Tesselschadelaan 45, Roosendaal | K5: 50429 - EG Facility & Services BV | L5: 2225 | N5: 2225
A6: {=_xlfn.TEXTSPLIT(D6," - ",TRUE,1)} -> 2025 | B6: 1 | C6: =_xlfn.XLOOKUP(B6*1,List!A:A,List!B:B,"",0) -> 01 | D6: 2025 - 1 | F6: 45672 | G6: 25910699 | H6: 1370 - Transitoria debet | I6: Huur (01-02-2025 - 28-02-2025) | J6: 0033 - Kethelweg 66C Vlaardingen | K6: 20 - Tradiro Services B.V. | M6: 2000 | N6: -2000
A7: {=_xlfn.TEXTSPLIT(D7," - ",TRUE,1)} -> 2025 | B7: 1 | C7: =_xlfn.XLOOKUP(B7*1,List!A:A,List!B:B,"",0) -> 01 | D7: 2025 - 1 | F7: 45672 | G7: 25800193 | H7: 8105 - Omzet laag | I7: Huur | J7: 0018 - Meester G. Groen van Prinsterlaan 313 Amstelveen | K7: 50311 - Labour Housing BV | M7: 1975 | N7: -1975
A8: {=_xlfn.TEXTSPLIT(D8," - ",TRUE,1)} -> 2025 | B8: 1 | C8: =_xlfn.XLOOKUP(B8*1,List!A:A,List!B:B,"",0) -> 01 | D8: 2025 - 1 | F8: 45688 | G8: 25910039 | H8: 1370 - Transitoria debet | I8: Huur (01-01-2025 - 31-01-2025) | J8: 0255 - Middenbaan Noord 20B, Hoogvliet | K8: 50251 - Vastgoed Spijkenisse | L8: 2795 | N8: 2795
A9: {=_xlfn.TEXTSPLIT(D9," - ",TRUE,1)} -> 2025 | B9: 1 | C9: =_xlfn.XLOOKUP(B9*1,List!A:A,List!B:B,"",0) -> 01 | D9: 2025 - 1 | F9: 45672 | G9: 25800146 | H9: 8105 - Omzet laag | I9: Huur | J9: 0170 - Goudestein 30 Rotterdam | K9: 100094 - I.T.S. SR.L. (INDUSTRIAL TECHNICAL SERVICES), BRAN | M9: 0 | N9: 0
A10: {=_xlfn.TEXTSPLIT(D10," - ",TRUE,1)} -> 2025 | B10: 1 | C10: =_xlfn.XLOOKUP(B10*1,List!A:A,List!B:B,"",0) -> 01 | D10: 2025 - 1 | F10: 45688 | G10: 25912716 | H10: 1370 - Transitoria debet | I10: Huur (01-01-2025 - 31-01-2025) | J10: 0130 - Van Langendonckstraat 80 Rotterdam | K10: 16 - United Homes B.V. | L10: 2199.12 | N10: 2199.12
A11: {=_xlfn.TEXTSPLIT(D11," - ",TRUE,1)} -> 2025 | B11: 1 | C11: =_xlfn.XLOOKUP(B11*1,List!A:A,List!B:B,"",0) -> 01 | D11: 2025 - 1 | F11: 45688 | G11: 25910020 | H11: 8105 - Omzet laag | I11: Huur (01-01-2025 - 31-01-2025) | J11: 0092 - Lange Brink 3 Luttelgeest | K11: 50188 - Werckpost Service B.V. | M11: 3500 | N11: -3500
A12: {=_xlfn.TEXTSPLIT(D12," - ",TRUE,1)} -> 2025 | B12: 1 | C12: =_xlfn.XLOOKUP(B12*1,List!A:A,List!B:B,"",0) -> 01 | D12: 2025 - 1 | F12: 45672 | G12: 25800222 | H12: 8105 - Omzet laag | I12: Huur | J12: 0106 - Prinses Wilhelminastraat 9 Hekendorp | K12: 20 - Tradiro Services B.V. | M12: 3200 | N12: -3200
A13: {=_xlfn.TEXTSPLIT(D13," - ",TRUE,1)} -> 2025 | B13: 1 | C13: =_xlfn.XLOOKUP(B13*1,List!A:A,List!B:B,"",0) -> 01 | D13: 2025 - 1 | F13: 45688 | G13: 25700545 | H13: 7100 - Huur woningen | I13: huur januari | J13: 0164 - Sint Annalandstraat 116 Rotterdam | K13: 20 - Tradiro Services B.V. | L13: 307.09 | N13: 307.09
A14: {=_xlfn.TEXTSPLIT(D14," - ",TRUE,1)} -> 2025 | B14: 1 | C14: =_xlfn.XLOOKUP(B14*1,List!A:A,List!B:B,"",0) -> 01 | D14: 2025 - 1 | F14: 45672 | G14: 25800166 | H14: 8105 - Omzet laag | I14: Huur | J14: 0312 - Kerkweg 9a [huis 333] Hensbroek | K14: 50311 - Labour Housing BV | M14: 3275 | N14: -3275
A15: {=_xlfn.TEXTSPLIT(D15," - ",TRUE,1)} -> 2025 | B15: 1 | C15: =_xlfn.XLOOKUP(B15*1,List!A:A,List!B:B,"",0) -> 01 | D15: 2025 - 1 | F15: 45688 | G15: 25910301 | H15: 8105 - Omzet laag | I15: Huur (01-01-2025 - 31-01-2025) | J15: 0010 - Kethelweg 1B Vlaardingen | K15: 20 - Tradiro Services B.V. | M15: 1641.12 | N15: -1641.12
A16: {=_xlfn.TEXTSPLIT(D16," - ",TRUE,1)} -> 2025 | B16: 1 | C16: =_xlfn.XLOOKUP(B16*1,List!A:A,List!B:B,"",0) -> 01 | D16: 2025 - 1 | F16: 45688 | G16: 25910224 | H16: 1370 - Transitoria debet | I16: Huur (01-01-2025 - 31-01-2025) | J16: 0061 - Dwarsweg 44 , Rozenburg | K16: 50329 - Impianti Industriala S.P.A. NEDERLAND BRANCH | L16: 4568.15 | N16: 4568.15
A17: {=_xlfn.TEXTSPLIT(D17," - ",TRUE,1)} -> 2025 | B17: 1 | C17: =_xlfn.XLOOKUP(B17*1,List!A:A,List!B:B,"",0) -> 01 | D17: 2025 - 1 | F17: 45688 | G17: 25910216 | H17: 8105 - Omzet laag | I17: Huur (01-01-2025 - 31-01-2025) | J17: 0024 - Desiree Geeraertstraat 1 C, Baarle-Nassau | K17: 50314 - NL Realty B.V. | M17: 3875 | N17: -3875
A18: {=_xlfn.TEXTSPLIT(D18," - ",TRUE,1)} -> 2025 | B18: 1 | C18: =_xlfn.XLOOKUP(B18*1,List!A:A,List!B:B,"",0) -> 01 | D18: 2025 - 1 | F18: 45688 | G18: 25910103 | H18: 1370 - Transitoria debet | I18: Huur (01-01-2025 - 31-01-2025) | J18: 0144 - Scheepjesbrug 433 Meerkerk | K18: 50402 - Flextalent4u Uitzenden B.V. | L18: 3798 | N18: 3798
A19: {=_xlfn.TEXTSPLIT(D19," - ",TRUE,1)} -> 2025 | B19: 1 | C19: =_xlfn.XLOOKUP(B19*1,List!A:A,List!B:B,"",0) -> 01 | D19: 2025 - 1 | F19: 45688 | G19: 25910119 | H19: 8105 - Omzet laag | I19: Huur (01-01-2025 - 31-01-2025) | J19: 0249 - Tholenstraat 114 Rotterdam | K19: 100109 - Europe-jobs B.V. | M19: 1585 | N19: -1585
A20: {=_xlfn.TEXTSPLIT(D20," - ",TRUE,1)} -> 2025 | B20: 1 | C20: =_xlfn.XLOOKUP(B20*1,List!A:A,List!B:B,"",0) -> 01 | D20: 2025 - 1 | F20: 45688 | G20: 25912828 | H20: 8105 - Omzet laag | I20: Huur (01-01-2025 - 31-01-2025) | J20: 0206 - Kruiningenstraat 152 Rotterdam | K20: 100094 - I.T.S. SR.L. (INDUSTRIAL TECHNICAL SERVICES), BRAN | L20: 1750 | N20: 1750
A21: {=_xlfn.TEXTSPLIT(D21," - ",TRUE,1)} -> 2025 | B21: 1 | C21: =_xlfn.XLOOKUP(B21*1,List!A:A,List!B:B,"",0) -> 01 | D21: 2025 - 1 | F21: 45672 | G21: 25910693 | H21: 8105 - Omzet laag | I21: Huur (01-02-2025 - 28-02-2025) | J21: 0011 - Kethelweg 1C, Vlaardingen | K21: 20 - Tradiro Services B.V. | L21: 1641.12 | N21: 1641.12
A22: {=_xlfn.TEXTSPLIT(D22," - ",TRUE,1)} -> 2025 | B22: 1 | C22: =_xlfn.XLOOKUP(B22*1,List!A:A,List!B:B,"",0) -> 01 | D22: 2025 - 1 | F22: 45672 | G22: 25910711 | H22: 8105 - Omzet laag | I22: Huur (01-02-2025 - 28-02-2025) | J22: A-00335 - Korte Singelstraat 21C Schiedam | K22: 50368 - Transport People B.V. | L22: 2270 | N22: 2270
A23: {=_xlfn.TEXTSPLIT(D23," - ",TRUE,1)} -> 2025 | B23: 1 | C23: =_xlfn.XLOOKUP(B23*1,List!A:A,List!B:B,"",0) -> 01 | D23: 2025 - 1 | F23: 45672 | G23: 25800083 | H23: 8105 - Omzet laag | I23: Huur | J23: 0142 - Wilhelmina Druckerstraat 68 Coevorden | K23: 50446 - C-Flex B.V. | M23: 2300 | N23: -2300
A24: {=_xlfn.TEXTSPLIT(D24," - ",TRUE,1)} -> 2025 | B24: 1 | C24: =_xlfn.XLOOKUP(B24*1,List!A:A,List!B:B,"",0) -> 01 | D24: 2025 - 1 | F24: 45680 | G24: 25910951 | H24: 1370 - Transitoria debet | I24: Huur (01-08-2024 - 31-08-2024) | J24: 0112 - Oudewerfslaan 84 Winschoten | K24: 16 - United Homes B.V. | L24: 2221.06 | N24: 2221.06
A25: {=_xlfn.TEXTSPLIT(D25," - ",TRUE,1)} -> 2025 | B25: 1 | C25: =_xlfn.XLOOKUP(B25*1,List!A:A,List!B:B,"",0) -> 01 | D25: 2025 - 1 | F25: 45688 | G25: 25910113 | H25: 1370 - Transitoria debet | I25: Huur (01-01-2025 - 31-01-2025) | J25: 0200 - Stal 355 Drachten | K25: 50312 - THS B.V. | L25: 2376.92 | N25: 2376.92
A26: {=_xlfn.TEXTSPLIT(D26," - ",TRUE,1)} -> 2025 | B26: 1 | C26: =_xlfn.XLOOKUP(B26*1,List!A:A,List!B:B,"",0) -> 01 | D26: 2025 - 1 | F26: 45642 | G26: 25700022 | H26: 7100 - Huur woningen | I26: Westhavendomein BV huur Januari 2025 | J26: A-00277 - 2e van Leydengaelstraat 6 Vlaardingen | K26: 50425 - Westhavendomein BV | L26: 2645 | N26: 2645
A27: {=_xlfn.TEXTSPLIT(D27," - ",TRUE,1)} -> 2025 | B27: 1 | C27: =_xlfn.XLOOKUP(B27*1,List!A:A,List!B:B,"",0) -> 01 | D27: 2025 - 1 | F27: 45688 | G27: 25910001 | H27: 1370 - Transitoria debet | I27: Huur (01-01-2025 - 31-01-2025) | J27: 0011 - Kethelweg 1C, Vlaardingen | K27: 20 - Tradiro Services B.V. | L27: 1641.12 | N27: 1641.12
A28: {=_xlfn.TEXTSPLIT(D28," - ",TRUE,1)} -> 2025 | B28: 1 | C28: =_xlfn.XLOOKUP(B28*1,List!A:A,List!B:B,"",0) -> 01 | D28: 2025 - 1 | F28: 45672 | G28: 25910369 | H28: 1370 - Transitoria debet | I28: Huur (01-02-2025 - 28-02-2025) | J28: 0239 - Schoonegge 110 Rotterdam | K28: 50182 - dockHolland Huisvesting B.V. | M28: 2468.7 | N28: -2468.7
A29: {=_xlfn.TEXTSPLIT(D29," - ",TRUE,1)} -> 2025 | B29: 1 | C29: =_xlfn.XLOOKUP(B29*1,List!A:A,List!B:B,"",0) -> 01 | D29: 2025 - 1 | F29: 45688 | G29: 25910125 | H29: 1370 - Transitoria debet | I29: Huur (01-01-2025 - 31-01-2025) | J29: 0137 - Venkelstraat 29a Brielle | K29: 50222 - Flexvesting B.V. | L29: 3125 | N29: 3125
A30: {=_xlfn.TEXTSPLIT(D30," - ",TRUE,1)} -> 2025 | B30: 1 | C30: =_xlfn.XLOOKUP(B30*1,List!A:A,List!B:B,"",0) -> 01 | D30: 2025 - 1 | F30: 45674 | G30: 25910945 | H30: 8105 - Omzet laag | I30: Huur (01-02-2025 - 28-02-2025) | J30: 0095 - Engelsestraat 16L3 Rotterdam | K30: 20 - Tradiro Services B.V. | M30: 1750 | N30: -1750
A31: {=_xlfn.TEXTSPLIT(D31," - ",TRUE,1)} -> 2025 | B31: 1 | C31: =_xlfn.XLOOKUP(B31*1,List!A:A,List!B:B,"",0) -> 01 | D31: 2025 - 1 | F31: 45688 | G31: 25910091 | H31: 1370 - Transitoria debet | I31: Huur (01-01-2025 - 31-01-2025) | J31: 0272 - Professor Kamerlingh Onneslaan 134 B3, Schiedam | K31: 50347 - Housing en Transport Facilities B.V. | L31: 1380 | N31: 1380
A32: {=_xlfn.TEXTSPLIT(D32," - ",TRUE,1)} -> 2025 | B32: 1 | C32: =_xlfn.XLOOKUP(B32*1,List!A:A,List!B:B,"",0) -> 01 | D32: 2025 - 1 | F32: 45672 | G32: 25910539 | H32: 8105 - Omzet laag | I32: Huur (01-02-2025 - 28-02-2025) | J32: 0058 - Deugenweerd 18 Borculo | K32: 50188 - Werckpost Service B.V. | L32: 2860 | N32: 2860
A33: {=_xlfn.TEXTSPLIT(D33," - ",TRUE,1)} -> 2025 | B33: 1 | C33: =_xlfn.XLOOKUP(B33*1,List!A:A,List!B:B,"",0) -> 01 | D33: 2025 - 1 | F33: 45672 | G33: 25910819 | H33: 1370 - Transitoria debet | I33: Huur (01-02-2025 - 28-02-2025) | J33: 0113 - Peursumseweg 119 Giessenburg | K33: 50402 - Flextalent4u Uitzenden B.V. | M33: 2954 | N33: -2954
A34: {=_xlfn.TEXTSPLIT(D34," - ",TRUE,1)} -> 2025 | B34: 1 | C34: =_xlfn.XLOOKUP(B34*1,List!A:A,List!B:B,"",0) -> 01 | D34: 2025 - 1 | F34: 45688 | G34: 25910056 | H34: 1370 - Transitoria debet | I34: Huur (01-01-2025 - 31-01-2025) | J34: 0104 - Narcissenstraat 37, Rozenburg | K34: 50157 - AmDor Projecten B.V. | L34: 2564.13 | N34: 2564.13
A35: {=_xlfn.TEXTSPLIT(D35," - ",TRUE,1)} -> 2025 | B35: 1 | C35: =_xlfn.XLOOKUP(B35*1,List!A:A,List!B:B,"",0) -> 01 | D35: 2025 - 1 | F35: 45672 | G35: 25800198 | H35: 8105 - Omzet laag | I35: Huur | J35: 0258 - Middenbaan Noord 22B, Hoogvliet | K35: 50251 - Vastgoed Spijkenisse | M35: 2400.13 | N35: -2400.13
A36: {=_xlfn.TEXTSPLIT(D36," - ",TRUE,1)} -> 2025 | B36: 1 | C36: =_xlfn.XLOOKUP(B36*1,List!A:A,List!B:B,"",0) -> 01 | D36: 2025 - 1 | F36: 45688 | G36: 25910175 | H36: 8105 - Omzet laag | I36: Huur (01-01-2025 - 31-01-2025) | J36: 0293 - Akkerweg 41 [014], Den Oever | K36: 50314 - NL Realty B.V. | M36: 4620.9 | N36: -4620.9
A37: {=_xlfn.TEXTSPLIT(D37," - ",TRUE,1)} -> 2025 | B37: 1 | C37: =_xlfn.XLOOKUP(B37*1,List!A:A,List!B:B,"",0) -> 01 | D37: 2025 - 1 | F37: 45685 | G37: 25910982 | H37: 8105 - Omzet laag | I37: Huur (01-02-2025 - 28-02-2025) | J37: 0164 - Sint Annalandstraat 116 Rotterdam | K37: 100174 - Workforce Housing Holland B.V. | L37: 1900 | N37: 1900
A38: {=_xlfn.TEXTSPLIT(D38," - ",TRUE,1)} -> 2025 | B38: 1 | C38: =_xlfn.XLOOKUP(B38*1,List!A:A,List!B:B,"",0) -> 01 | D38: 2025 - 1 | F38: 45688 | G38: 25910096 | H38: 8105 - Omzet laag | I38: Huur (01-01-2025 - 31-01-2025) | J38: A-00239 - Rivierdijk 794 (onder) Hardinxveld - Giessendam | K38: 35 - Interim Jobs B.V. | M38: 1972.8 | N38: -1972.8
A39: {=_xlfn.TEXTSPLIT(D39," - ",TRUE,1)} -> 2025 | B39: 1 | C39: =_xlfn.XLOOKUP(B39*1,List!A:A,List!B:B,"",0) -> 01 | D39: 2025 - 1 | F39: 45672 | G39: 25910847 | H39: 8105 - Omzet laag | I39: Huur (01-02-2025 - 28-02-2025) | J39: A-00373 - Professor Kamerlingh Onneslaan 134 A Schiedam | K39: 50347 - Housing en Transport Facilities B.V. | L39: 1860 | N39: 1860
A40: {=_xlfn.TEXTSPLIT(D40," - ",TRUE,1)} -> 2025 | B40: 1 | C40: =_xlfn.XLOOKUP(B40*1,List!A:A,List!B:B,"",0) -> 01 | D40: 2025 - 1 | F40: 45672 | G40: 25910567 | H40: 1370 - Transitoria debet | I40: Huur (01-02-2025 - 28-02-2025) | J40: 0006 - Enschotsestraat 163 Tilburg | K40: 50396 - Head Vastgoed B.V. | M40: 5486 | N40: -5486
A41: {=_xlfn.TEXTSPLIT(D41," - ",TRUE,1)} -> 2025 | B41: 1 | C41: =_xlfn.XLOOKUP(B41*1,List!A:A,List!B:B,"",0) -> 01 | D41: 2025 - 1 | F41: 45688 | G41: 25910311 | H41: 8105 - Omzet laag | I41: Huur (01-01-2025 - 31-01-2025) | J41: 0223 - Acacialaan 9 Pijnacker | K41: 20 - Tradiro Services B.V. | L41: 3224 | N41: 3224
A42: {=_xlfn.TEXTSPLIT(D42," - ",TRUE,1)} -> 2025 | B42: 1 | C42: =_xlfn.XLOOKUP(B42*1,List!A:A,List!B:B,"",0) -> 01 | D42: 2025 - 1 | F42: 45688 | G42: 25910188 | H42: 1370 - Transitoria debet | I42: Huur (01-01-2025 - 31-01-2025) | J42: 0008 - Arkelse onderweg 24a Gorichem | K42: 35 - Interim Jobs B.V. | L42: 6747.78 | N42: 6747.78
A43: {=_xlfn.TEXTSPLIT(D43," - ",TRUE,1)} -> 2025 | B43: 1 | C43: =_xlfn.XLOOKUP(B43*1,List!A:A,List!B:B,"",0) -> 01 | D43: 2025 - 1 | F43: 45688 | G43: 25910191 | H43: 1370 - Transitoria debet | I43: Huur (01-01-2025 - 31-01-2025) | J43: 0012 - Baarlelaan 27 Hoogeveen | K43: 29 - Vivir Wonen | L43: 1978.13 | N43: 1978.13
A44: {=_xlfn.TEXTSPLIT(D44," - ",TRUE,1)} -> 2025 | B44: 1 | C44: =_xlfn.XLOOKUP(B44*1,List!A:A,List!B:B,"",0) -> 01 | D44: 2025 - 1 | F44: 45687 | G44: 25800277 | H44: 8105 - Omzet laag | I44: Huur | J44: 0025 - Groenelaan 30B Schiedam | K44: 20 - Tradiro Services B.V. | L44: 1625 | N44: 1625
A45: {=_xlfn.TEXTSPLIT(D45," - ",TRUE,1)} -> 2025 | B45: 1 | C45: =_xlfn.XLOOKUP(B45*1,List!A:A,List!B:B,"",0) -> 01 | D45: 2025 - 1 | F45: 45680 | G45: 25910956 | H45: 1370 - Transitoria debet | I45: Huur (01-12-2024 - 31-12-2024) | J45: 0130 - Van Langendonckstraat 80 Rotterdam | K45: 16 - United Homes B.V. | M45: 2154.57 | N45: -2154.57
A46: {=_xlfn.TEXTSPLIT(D46," - ",TRUE,1)} -> 2025 | B46: 1 | C46: =_xlfn.XLOOKUP(B46*1,List!A:A,List!B:B,"",0) -> 01 | D46: 2025 - 1 | F46: 45688 | G46: 25910103 | H46: 8105 - Omzet laag | I46: Huur (01-01-2025 - 31-01-2025) | J46: 0144 - Scheepjesbrug 433 Meerkerk | K46: 50402 - Flextalent4u Uitzenden B.V. | M46: 3798 | N46: -3798
A47: {=_xlfn.TEXTSPLIT(D47," - ",TRUE,1)} -> 2025 | B47: 1 | C47: =_xlfn.XLOOKUP(B47*1,List!A:A,List!B:B,"",0) -> 01 | D47: 2025 - 1 | F47: 45688 | G47: 25910190 | H47: 1370 - Transitoria debet | I47: Huur (01-01-2025 - 31-01-2025) | J47: 0055 - Baanhoek 19 Sliedrecht | K47: 100112 - HousingWell B.V. | L47: 2670 | N47: 2670
A48: {=_xlfn.TEXTSPLIT(D48," - ",TRUE,1)} -> 2025 | B48: 1 | C48: =_xlfn.XLOOKUP(B48*1,List!A:A,List!B:B,"",0) -> 01 | D48: 2025 - 1 | F48: 45672 | G48: 25910733 | H48: 8105 - Omzet laag | I48: Huur (01-02-2025 - 28-02-2025) | J48: 0028 - Lange kruisweg 12 Maasdijk | K48: 20 - Tradiro Services B.V. | L48: 2813.34 | N48: 2813.34
A49: {=_xlfn.TEXTSPLIT(D49," - ",TRUE,1)} -> 2025 | B49: 1 | C49: =_xlfn.XLOOKUP(B49*1,List!A:A,List!B:B,"",0) -> 01 | D49: 2025 - 1 | F49: 45672 | G49: 25700158 | H49: 7100 - Huur woningen | I49: huur janauri | J49: 0249 - Tholenstraat 114 Rotterdam | K49: 20 - Tradiro Services B.V. | L49: 1455.38 | N49: 1455.38
A50: {=_xlfn.TEXTSPLIT(D50," - ",TRUE,1)} -> 2025 | B50: 1 | C50: =_xlfn.XLOOKUP(B50*1,List!A:A,List!B:B,"",0) -> 01 | D50: 2025 - 1 | F50: 45672 | G50: 25910341 | H50: 1370 - Transitoria debet | I50: Huur (01-02-2025 - 28-02-2025) | J50: 0199 - Kerstendijk 125 Rotterdam | K50: 50394 - Gap Costruzioni Dutch Branch | M50: 2730 | N50: -2730
A51: {=_xlfn.TEXTSPLIT(D51," - ",TRUE,1)} -> 2025 | B51: 1 | C51: =_xlfn.XLOOKUP(B51*1,List!A:A,List!B:B,"",0) -> 01 | D51: 2025 - 1 | F51: 45672 | G51: 25910639 | H51: 1370 - Transitoria debet | I51: Huur (01-02-2025 - 28-02-2025) | J51: 0159 - Kastanjelaan 232 Bergen op Zoom | K51: 50201 - DS People B.V. | M51: 2500 | N51: -2500
A52: {=_xlfn.TEXTSPLIT(D52," - ",TRUE,1)} -> 2025 | B52: 1 | C52: =_xlfn.XLOOKUP(B52*1,List!A:A,List!B:B,"",0) -> 01 | D52: 2025 - 1 | F52: 45672 | G52: 25800189 | H52: 8105 - Omzet laag | I52: Huur | J52: 0028 - Lange kruisweg 12 Maasdijk | K52: 20 - Tradiro Services B.V. | M52: 2813.34 | N52: -2813.34
A53: {=_xlfn.TEXTSPLIT(D53," - ",TRUE,1)} -> 2025 | B53: 1 | C53: =_xlfn.XLOOKUP(B53*1,List!A:A,List!B:B,"",0) -> 01 | D53: 2025 - 1 | F53: 45688 | G53: 25910109 | H53: 8105 - Omzet laag | I53: Huur (01-01-2025 - 31-01-2025) | J53: 0123 - Snecanusstraat 12 Sneek | K53: 100128 - SS Kara Yacht Painters LLP | M53: 2550 | N53: -2550
A54: {=_xlfn.TEXTSPLIT(D54," - ",TRUE,1)} -> 2025 | B54: 1 | C54: =_xlfn.XLOOKUP(B54*1,List!A:A,List!B:B,"",0) -> 01 | D54: 2025 - 1 | F54: 45672 | G54: 25800099 | H54: 8105 - Omzet laag | I54: Huur | J54: 0293 - Akkerweg 41 [014], Den Oever | K54: 100138 - Fareon Z Nederland | M54: 4600 | N54: -4600
A55: {=_xlfn.TEXTSPLIT(D55," - ",TRUE,1)} -> 2025 | B55: 1 | C55: =_xlfn.XLOOKUP(B55*1,List!A:A,List!B:B,"",0) -> 01 | D55: 2025 - 1 | F55: 45688 | G55: 25910008 | H55: 1370 - Transitoria debet | I55: Huur (01-01-2025 - 31-01-2025) | J55: 0119 - Koningin Julianalaan 27 Waarder | K55: 50282 - DIT en Larex Vakpersoneel B.V. | L55: 3275 | N55: 3275
A56: {=_xlfn.TEXTSPLIT(D56," - ",TRUE,1)} -> 2025 | B56: 1 | C56: =_xlfn.XLOOKUP(B56*1,List!A:A,List!B:B,"",0) -> 01 | D56: 2025 - 1 | F56: 45672 | G56: 25910407 | H56: 8105 - Omzet laag | I56: Huur (01-02-2025 - 28-02-2025) | J56: 0141 - Wilhelminastraat 8 Stavenisse | K56: 100139 - Horus Team Sp. Z.o.o. | L56: 2500 | N56: 2500
A57: {=_xlfn.TEXTSPLIT(D57," - ",TRUE,1)} -> 2025 | B57: 1 | C57: =_xlfn.XLOOKUP(B57*1,List!A:A,List!B:B,"",0) -> 01 | D57: 2025 - 1 | F57: 45688 | G57: 25910217 | H57: 8105 - Omzet laag | I57: Huur (01-01-2025 - 31-01-2025) | J57: 0058 - Deugenweerd 18 Borculo | K57: 50188 - Werckpost Service B.V. | M57: 2860 | N57: -2860
A58: {=_xlfn.TEXTSPLIT(D58," - ",TRUE,1)} -> 2025 | B58: 1 | C58: =_xlfn.XLOOKUP(B58*1,List!A:A,List!B:B,"",0) -> 01 | D58: 2025 - 1 | F58: 45688 | G58: 25910158 | H58: 1370 - Transitoria debet | I58: Huur (01-01-2025 - 31-01-2025) | J58: A-00277 - 2e van Leydengaelstraat 6 Vlaardingen | K58: 20 - Tradiro Services B.V. | L58: 225.4 | N58: 225.4
A59: {=_xlfn.TEXTSPLIT(D59," - ",TRUE,1)} -> 2025 | B59: 1 | C59: =_xlfn.XLOOKUP(B59*1,List!A:A,List!B:B,"",0) -> 01 | D59: 2025 - 1 | F59: 45672 | G59: 25910513 | H59: 1370 - Transitoria debet | I59: Huur (01-02-2025 - 28-02-2025) | J59: 0049 - Bornerbroekstraat 129A Almelo | K59: 100105 - VALO Facilities B.V. | M59: 2500 | N59: -2500
A60: {=_xlfn.TEXTSPLIT(D60," - ",TRUE,1)} -> 2025 | B60: 1 | C60: =_xlfn.XLOOKUP(B60*1,List!A:A,List!B:B,"",0) -> 01 | D60: 2025 - 1 | F60: 45688 | G60: 25910130 | H60: 1370 - Transitoria debet | I60: Huur (01-01-2025 - 31-01-2025) | J60: 0167 - Vogelschorstraat 24 Sluiskil | K60: 50251 - Vastgoed Spijkenisse | L60: 2352.65 | N60: 2352.65
A61: {=_xlfn.TEXTSPLIT(D61," - ",TRUE,1)} -> 2025 | B61: 1 | C61: =_xlfn.XLOOKUP(B61*1,List!A:A,List!B:B,"",0) -> 01 | D61: 2025 - 1 | F61: 45672 | G61: 25910349 | H61: 8105 - Omzet laag | I61: Huur (01-02-2025 - 28-02-2025) | J61: 0098 - Melis Stokezijde 94 Den Haag | K61: 50175 - Autodaxx B.V. | L61: 3600 | N61: 3600
A62: {=_xlfn.TEXTSPLIT(D62," - ",TRUE,1)} -> 2025 | B62: 1 | C62: =_xlfn.XLOOKUP(B62*1,List!A:A,List!B:B,"",0) -> 01 | D62: 2025 - 1 | F62: 45672 | G62: 25910619 | H62: 1370 - Transitoria debet | I62: Huur (01-02-2025 - 28-02-2025) | J62: 0075 - Hoofdstraat 110, Heeswijk-Dinther | K62: 50410 - WILL Vakkrachten B. V. | M62: 2250 | N62: -2250
A63: {=_xlfn.TEXTSPLIT(D63," - ",TRUE,1)} -> 2025 | B63: 1 | C63: =_xlfn.XLOOKUP(B63*1,List!A:A,List!B:B,"",0) -> 01 | D63: 2025 - 1 | F63: 45672 | G63: 25910377 | H63: 8105 - Omzet laag | I63: Huur (01-02-2025 - 28-02-2025) | J63: 0138 - Westercluft 134 Steenwijk | K63: 50152 - Interwel Oost B.V. | L63: 3025.21 | N63: 3025.21
A64: {=_xlfn.TEXTSPLIT(D64," - ",TRUE,1)} -> 2025 | B64: 1 | C64: =_xlfn.XLOOKUP(B64*1,List!A:A,List!B:B,"",0) -> 01 | D64: 2025 - 1 | F64: 45672 | G64: 25910849 | H64: 8105 - Omzet laag | I64: Huur (01-02-2025 - 28-02-2025) | J64: 0270 - Professor Kamerlingh Onneslaan 134 B1, Schiedam | K64: 50347 - Housing en Transport Facilities B.V. | L64: 1380 | N64: 1380
A65: {=_xlfn.TEXTSPLIT(D65," - ",TRUE,1)} -> 2025 | B65: 1 | C65: =_xlfn.XLOOKUP(B65*1,List!A:A,List!B:B,"",0) -> 01 | D65: 2025 - 1 | F65: 45688 | G65: 25910022 | H65: 1370 - Transitoria debet | I65: Huur (01-01-2025 - 31-01-2025) | J65: 0029 - Maeliefstraat 46C Rotterdam | K65: 100153 - RNDV Industries | L65: 1900 | N65: 1900
A66: {=_xlfn.TEXTSPLIT(D66," - ",TRUE,1)} -> 2025 | B66: 1 | C66: =_xlfn.XLOOKUP(B66*1,List!A:A,List!B:B,"",0) -> 01 | D66: 2025 - 1 | F66: 45672 | G66: 25800242 | H66: 8105 - Omzet laag | I66: Huur | J66: 0249 - Tholenstraat 114 Rotterdam | K66: 100109 - Europe-jobs B.V. | M66: 1585 | N66: -1585
A67: {=_xlfn.TEXTSPLIT(D67," - ",TRUE,1)} -> 2025 | B67: 1 | C67: =_xlfn.XLOOKUP(B67*1,List!A:A,List!B:B,"",0) -> 01 | D67: 2025 - 1 | F67: 45688 | G67: 25910011 | H67: 1370 - Transitoria debet | I67: Huur (01-01-2025 - 31-01-2025) | J67: A-00335 - Korte Singelstraat 21C Schiedam | K67: 50368 - Transport People B.V. | L67: 2270 | N67: 2270
A68: {=_xlfn.TEXTSPLIT(D68," - ",TRUE,1)} -> 2025 | B68: 1 | C68: =_xlfn.XLOOKUP(B68*1,List!A:A,List!B:B,"",0) -> 01 | D68: 2025 - 1 | F68: 45688 | G68: 25800909 | H68: 8105 - Omzet laag | I68: Huur | J68: 0327 - Putter 42 Etten-Leur | K68: 50286 - Employ Facilitair B.V. | M68: 1666.73 | N68: -1666.73
A69: {=_xlfn.TEXTSPLIT(D69," - ",TRUE,1)} -> 2025 | B69: 1 | C69: =_xlfn.XLOOKUP(B69*1,List!A:A,List!B:B,"",0) -> 01 | D69: 2025 - 1 | F69: 45658 | G69: 25700125 | H69: 1500 - Crediteuren | I69: S. Bakker OPH Verhuur 2025-01 | K69: 26 - S. Bakker OPH Verhuur | M69: 1031 | N69: -1031
A70: {=_xlfn.TEXTSPLIT(D70," - ",TRUE,1)} -> 2025 | B70: 1 | C70: =_xlfn.XLOOKUP(B70*1,List!A:A,List!B:B,"",0) -> 01 | D70: 2025 - 1 | F70: 45688 | G70: 25910112 | H70: 8105 - Omzet laag | I70: Huur (01-01-2025 - 31-01-2025) | J70: 0124 - Snoekenveen 242 Spijkenisse | K70: 16 - United Homes B.V. | M70: 2578.34 | N70: -2578.34
A71: {=_xlfn.TEXTSPLIT(D71," - ",TRUE,1)} -> 2025 | B71: 1 | C71: =_xlfn.XLOOKUP(B71*1,List!A:A,List!B:B,"",0) -> 01 | D71: 2025 - 1 | F71: 45672 | G71: 25700158 | H71: 7100 - Huur woningen | I71: huur janauri | J71: 0002 - Allard Piersonlaan 142 Den Haag | K71: 20 - Tradiro Services B.V. | L71: 1415.85 | N71: 1415.85
A72: {=_xlfn.TEXTSPLIT(D72," - ",TRUE,1)} -> 2025 | B72: 1 | C72: =_xlfn.XLOOKUP(B72*1,List!A:A,List!B:B,"",0) -> 01 | D72: 2025 - 1 | F72: 45688 | G72: 25910141 | H72: 8105 - Omzet laag | I72: Huur (01-01-2025 - 31-01-2025) | J72: 0105 - Wieldraaierstraat 39 Gorinchem | K72: 100110 - WIL International B.V. | M72: 2775 | N72: -2775
A73: {=_xlfn.TEXTSPLIT(D73," - ",TRUE,1)} -> 2025 | B73: 1 | C73: =_xlfn.XLOOKUP(B73*1,List!A:A,List!B:B,"",0) -> 01 | D73: 2025 - 1 | F73: 45672 | G73: 25910457 | H73: 8105 - Omzet laag | I73: Huur (01-02-2025 - 28-02-2025) | J73: 0293 - Akkerweg 41 [014], Den Oever | K73: 50314 - NL Realty B.V. | L73: 4620.9 | N73: 4620.9
A74: {=_xlfn.TEXTSPLIT(D74," - ",TRUE,1)} -> 2025 | B74: 1 | C74: =_xlfn.XLOOKUP(B74*1,List!A:A,List!B:B,"",0) -> 01 | D74: 2025 - 1 | F74: 45688 | G74: 25910239 | H74: 8105 - Omzet laag | I74: Huur (01-01-2025 - 31-01-2025) | J74: 0019 - Franselaan 273B Rotterdam | K74: 20 - Tradiro Services B.V. | M74: 1641.12 | N74: -1641.12
A75: {=_xlfn.TEXTSPLIT(D75," - ",TRUE,1)} -> 2025 | B75: 1 | C75: =_xlfn.XLOOKUP(B75*1,List!A:A,List!B:B,"",0) -> 01 | D75: 2025 - 1 | F75: 45672 | G75: 25910563 | H75: 8105 - Omzet laag | I75: Huur (01-02-2025 - 28-02-2025) | J75: 0095 - Engelsestraat 16L3 Rotterdam | K75: 20 - Tradiro Services B.V. | L75: 1750 | N75: 1750
A76: {=_xlfn.TEXTSPLIT(D76," - ",TRUE,1)} -> 2025 | B76: 1 | C76: =_xlfn.XLOOKUP(B76*1,List!A:A,List!B:B,"",0) -> 01 | D76: 2025 - 1 | F76: 45672 | G76: 25800207 | H76: 8105 - Omzet laag | I76: Huur | J76: 0041 - Nunspeetlaan 53 Den Haag | K76: 50398 - Orange Investments Group B.V. | M76: 1899 | N76: -1899
A77: {=_xlfn.TEXTSPLIT(D77," - ",TRUE,1)} -> 2025 | B77: 1 | C77: =_xlfn.XLOOKUP(B77*1,List!A:A,List!B:B,"",0) -> 01 | D77: 2025 - 1 | F77: 45672 | G77: 25800190 | H77: 8105 - Omzet laag | I77: Huur | J77: 0182 - Malzwin 34 Lelystad | K77: 50275 - M@tchm@kers International B.V. | M77: 2700.8 | N77: -2700.8
A78: {=_xlfn.TEXTSPLIT(D78," - ",TRUE,1)} -> 2025 | B78: 1 | C78: =_xlfn.XLOOKUP(B78*1,List!A:A,List!B:B,"",0) -> 01 | D78: 2025 - 1 | F78: 45688 | G78: 25910116 | H78: 1370 - Transitoria debet | I78: Huur (01-01-2025 - 31-01-2025) | J78: 0127 - Struitenweg 19B Rotterdam | K78: 50157 - AmDor Projecten B.V. | L78: 2792.7 | N78: 2792.7
A79: {=_xlfn.TEXTSPLIT(D79," - ",TRUE,1)} -> 2025 | B79: 1 | C79: =_xlfn.XLOOKUP(B79*1,List!A:A,List!B:B,"",0) -> 01 | D79: 2025 - 1 | F79: 45688 | G79: 25910162 | H79: 1370 - Transitoria debet | I79: Huur (01-01-2025 - 31-01-2025) | J79: 0223 - Acacialaan 9 Pijnacker | K79: 20 - Tradiro Services B.V. | L79: 3224 | N79: 3224
A80: {=_xlfn.TEXTSPLIT(D80," - ",TRUE,1)} -> 2025 | B80: 1 | C80: =_xlfn.XLOOKUP(B80*1,List!A:A,List!B:B,"",0) -> 01 | D80: 2025 - 1 | F80: 45672 | G80: 25800103 | H80: 8105 - Omzet laag | I80: Huur | J80: 0201 - Ambergweg 14 Rosendaal | K80: 50157 - AmDor Projecten B.V. | M80: 3275 | N80: -3275
A81: {=_xlfn.TEXTSPLIT(D81," - ",TRUE,1)} -> 2025 | B81: 1 | C81: =_xlfn.XLOOKUP(B81*1,List!A:A,List!B:B,"",0) -> 01 | D81: 2025 - 1 | F81: 45658 | G81: 25920184 | H81: 1370 - Transitoria debet | I81: Huur (01-01-2025 - 31-01-2025) | J81: 0084 - Kerkdreef 42, Axel | K81: 20 - Tradiro Services B.V. | L81: 173.08 | N81: 173.08
A82: {=_xlfn.TEXTSPLIT(D82," - ",TRUE,1)} -> 2025 | B82: 1 | C82: =_xlfn.XLOOKUP(B82*1,List!A:A,List!B:B,"",0) -> 01 | D82: 2025 - 1 | F82: 45672 | G82: 25800215 | H82: 8105 - Omzet laag | I82: Huur | J82: 0120 - Plaats 10 Montfoort | K82: 50282 - DIT en Larex Vakpersoneel B.V. | M82: 2600 | N82: -2600
A83: {=_xlfn.TEXTSPLIT(D83," - ",TRUE,1)} -> 2025 | B83: 1 | C83: =_xlfn.XLOOKUP(B83*1,List!A:A,List!B:B,"",0) -> 01 | D83: 2025 - 1 | F83: 45672 | G83: 25910691 | H83: 8105 - Omzet laag | I83: Huur (01-02-2025 - 28-02-2025) | J83: 0010 - Kethelweg 1B Vlaardingen | K83: 20 - Tradiro Services B.V. | L83: 1641.12 | N83: 1641.12
A84: {=_xlfn.TEXTSPLIT(D84," - ",TRUE,1)} -> 2025 | B84: 1 | C84: =_xlfn.XLOOKUP(B84*1,List!A:A,List!B:B,"",0) -> 01 | D84: 2025 - 1 | F84: 45688 | G84: 25910245 | H84: 8105 - Omzet laag | I84: Huur (01-01-2025 - 31-01-2025) | J84: 0017 - G.A. Brederolaan 75B Maassluis | K84: 20 - Tradiro Services B.V. | M84: 1611.81 | N84: -1611.81
A85: {=_xlfn.TEXTSPLIT(D85," - ",TRUE,1)} -> 2025 | B85: 1 | C85: =_xlfn.XLOOKUP(B85*1,List!A:A,List!B:B,"",0) -> 01 | D85: 2025 - 1 | F85: 45688 | G85: 25910306 | H85: 8105 - Omzet laag | I85: Huur (01-01-2025 - 31-01-2025) | J85: 0293 - Akkerweg 41 [014], Den Oever | K85: 100142 - FGM Solar Renewable S.R.L. | M85: 807.25 | N85: -807.25
A86: {=_xlfn.TEXTSPLIT(D86," - ",TRUE,1)} -> 2025 | B86: 1 | C86: =_xlfn.XLOOKUP(B86*1,List!A:A,List!B:B,"",0) -> 01 | D86: 2025 - 1 | F86: 45672 | G86: 25910453 | H86: 8105 - Omzet laag | I86: Huur (01-02-2025 - 28-02-2025) | J86: 0293 - Akkerweg 41 [014], Den Oever | K86: 100089 - Uitzendbureau Bakker B.V. | L86: 2000 | N86: 2000
A87: {=_xlfn.TEXTSPLIT(D87," - ",TRUE,1)} -> 2025 | B87: 1 | C87: =_xlfn.XLOOKUP(B87*1,List!A:A,List!B:B,"",0) -> 01 | D87: 2025 - 1 | F87: 45672 | G87: 25910499 | H87: 8105 - Omzet laag | I87: Huur (01-02-2025 - 28-02-2025) | J87: 0013 - Baarsveen 197 Spijkenisse | K87: 50251 - Vastgoed Spijkenisse | L87: 4571.66 | N87: 4571.66
A88: {=_xlfn.TEXTSPLIT(D88," - ",TRUE,1)} -> 2025 | B88: 1 | C88: =_xlfn.XLOOKUP(B88*1,List!A:A,List!B:B,"",0) -> 01 | D88: 2025 - 1 | F88: 45672 | G88: 25800237 | H88: 8105 - Omzet laag | I88: Huur | J88: 0123 - Snecanusstraat 12 Sneek | K88: 100128 - SS Kara Yacht Painters LLP | M88: 2550 | N88: -2550
A89: {=_xlfn.TEXTSPLIT(D89," - ",TRUE,1)} -> 2025 | B89: 1 | C89: =_xlfn.XLOOKUP(B89*1,List!A:A,List!B:B,"",0) -> 01 | D89: 2025 - 1 | F89: 45688 | G89: 25911078 | H89: 8105 - Omzet laag | I89: Huur (01-01-2025 - 31-01-2025) | J89: 0157 - Kuiper-Rietbergpad 15 Hoogvliet | K89: 50154 - OJP B.V. | M89: 4388.8 | N89: -4388.8
A90: {=_xlfn.TEXTSPLIT(D90," - ",TRUE,1)} -> 2025 | B90: 1 | C90: =_xlfn.XLOOKUP(B90*1,List!A:A,List!B:B,"",0) -> 01 | D90: 2025 - 1 | F90: 45688 | G90: 25910306 | H90: 1370 - Transitoria debet | I90: Huur (01-01-2025 - 31-01-2025) | J90: 0293 - Akkerweg 41 [014], Den Oever | K90: 100142 - FGM Solar Renewable S.R.L. | L90: 807.25 | N90: 807.25
A91: {=_xlfn.TEXTSPLIT(D91," - ",TRUE,1)} -> 2025 | B91: 1 | C91: =_xlfn.XLOOKUP(B91*1,List!A:A,List!B:B,"",0) -> 01 | D91: 2025 - 1 | F91: 45672 | G91: 25800183 | H91: 8105 - Omzet laag | I91: Huur | J91: A-00335 - Korte Singelstraat 21C Schiedam | K91: 50368 - Transport People B.V. | M91: 2270 | N91: -2270
A92: {=_xlfn.TEXTSPLIT(D92," - ",TRUE,1)} -> 2025 | B92: 1 | C92: =_xlfn.XLOOKUP(B92*1,List!A:A,List!B:B,"",0) -> 01 | D92: 2025 - 1 | F92: 45688 | G92: 25910043 | H92: 8105 - Omzet laag | I92: Huur (01-01-2025 - 31-01-2025) | J92: 0257 - Middenbaan Noord 22a Hoogvliet | K92: 50292 - Suricare B.V. | M92: 1691.15 | N92: -1691.15
A93: {=_xlfn.TEXTSPLIT(D93," - ",TRUE,1)} -> 2025 | B93: 1 | C93: =_xlfn.XLOOKUP(B93*1,List!A:A,List!B:B,"",0) -> 01 | D93: 2025 - 1 | F93: 45672 | G93: 25910355 | H93: 8105 - Omzet laag | I93: Huur (01-02-2025 - 28-02-2025) | J93: 0257 - Middenbaan Noord 22a Hoogvliet | K93: 50292 - Suricare B.V. | L93: 1691.15 | N93: 1691.15
A94: {=_xlfn.TEXTSPLIT(D94," - ",TRUE,1)} -> 2025 | B94: 1 | C94: =_xlfn.XLOOKUP(B94*1,List!A:A,List!B:B,"",0) -> 01 | D94: 2025 - 1 | F94: 45674 | G94: 25800256 | H94: 8105 - Omzet laag | I94: Huur | J94: 0080 - Voorstraat 25 Vlaardingen | K94: 100174 - Workforce Housing Holland B.V. | M94: 1272.33 | N94: -1272.33
A95: {=_xlfn.TEXTSPLIT(D95," - ",TRUE,1)} -> 2025 | B95: 1 | C95: =_xlfn.XLOOKUP(B95*1,List!A:A,List!B:B,"",0) -> 01 | D95: 2025 - 1 | F95: 45672 | G95: 25700158 | H95: 1500 - Crediteuren | I95: huur janauri | K95: 20 - Tradiro Services B.V. | M95: 13172.92 | N95: -13172.92
A96: {=_xlfn.TEXTSPLIT(D96," - ",TRUE,1)} -> 2025 | B96: 1 | C96: =_xlfn.XLOOKUP(B96*1,List!A:A,List!B:B,"",0) -> 01 | D96: 2025 - 1 | F96: 45672 | G96: 25800063 | H96: 8105 - Omzet laag | I96: Huur | J96: 0252 - Middenbaan Noord 18B, Hoogvliet | K96: 50394 - Gap Costruzioni Dutch Branch | M96: 2730 | N96: -2730
A97: {=_xlfn.TEXTSPLIT(D97," - ",TRUE,1)} -> 2025 | B97: 1 | C97: =_xlfn.XLOOKUP(B97*1,List!A:A,List!B:B,"",0) -> 01 | D97: 2025 - 1 | F97: 45680 | G97: 25800263 | H97: 8105 - Omzet laag | I97: Huur | J97: 0130 - Van Langendonckstraat 80 Rotterdam | K97: 16 - United Homes B.V. | M97: 2154.57 | N97: -2154.57
A98: {=_xlfn.TEXTSPLIT(D98," - ",TRUE,1)} -> 2025 | B98: 1 | C98: =_xlfn.XLOOKUP(B98*1,List!A:A,List!B:B,"",0) -> 01 | D98: 2025 - 1 | F98: 45672 | G98: 25910519 | H98: 1370 - Transitoria debet | I98: Huur (01-02-2025 - 28-02-2025) | J98: 0097 - Burchtstraat 16a Oostburg | K98: 16 - United Homes B.V. | M98: 3850 | N98: -3850
A99: {=_xlfn.TEXTSPLIT(D99," - ",TRUE,1)} -> 2025 | B99: 1 | C99: =_xlfn.XLOOKUP(B99*1,List!A:A,List!B:B,"",0) -> 01 | D99: 2025 - 1 | F99: 45688 | G99: 25910181 | H99: 8105 - Omzet laag | I99: Huur (01-01-2025 - 31-01-2025) | J99: 0293 - Akkerweg 41 [014], Den Oever | K99: 100142 - FGM Solar Renewable S.R.L. | M99: 2275 | N99: -2275
A100: {=_xlfn.TEXTSPLIT(D100," - ",TRUE,1)} -> 2025 | B100: 1 | C100: =_xlfn.XLOOKUP(B100*1,List!A:A,List!B:B,"",0) -> 01 | D100: 2025 - 1 | F100: 45672 | G100: 25800169 | H100: 8105 - Omzet laag | I100: Huur | J100: 0315 - Kerkweg 9a (huis 342) Hensbroek | K100: 50367 - Facili Flex BV | M100: 3275 | N100: -3275
...

Sheet List
A1: 1 | B1: 01
A2: 2 | B2: 02
A3: 3 | B3: 03
A4: 4 | B4: 04
A5: 5 | B5: 05
A6: 6 | B6: 06
A7: 7 | B7: 07
A8: 8 | B8: 08
A9: 9 | B9: 09
A10: 10 | B10: 10
A11: 11 | B11: 11
A12: 12 | B12: 12
