Workbook

Sheet VVE
A1: Jaar | B1: 2025
A2: Grootboekrekening | B2: Kosten VvE woningen
A4: object_id | B4: Omschrijving | C4: Per. | D4: Max. of Debet | E4: Max. of Credit
A5: 0 | B5: Algemeen woningen | D5: 0 | E5: 20
A6: 30 | B6: Curacaolaan 88 Vlaardingen | D6: 329.66 | E6: 0
A7: 183 | B7: Hugo de Vriesstraat 54 Vlaardingen | D7: 300 | E7: 0
A8: 191 | B8: Jan van Arkelstraat 118 Vlaardingen | D8: 185 | E8: 0
A9: 195 | B9: Keesomstraat 50 Vlaardingen | D9: 205.35 | E9: 0
A10: 208 | B10: L.A. Kesperweg 31a Vlaardingen | D10: 186.34 | E10: 0
A11: 213 | B11: Mr. Troelstrastraat 11 Vlaardingen | D11: 150 | E11: 0
A12: 228 | B12: Parallelweg 122a Vlaardingen | D12: 110 | E12: 0
A13: 234 | B13: Rotterdamsedijk 154b Schiedam | D13: 50 | E13: 0
A14: 236 | B14: Schalkeroord 389 Rotterdam | D14: 95.64 | E14: 0
A15: 238 | B15: Van der Werffstraat 370 Vlaardingen | D15: 726.26 | E15: 0
A16: 245 | B16: Van der Werffstraat 240 Vlaardingen | D16: 185.9 | E16: 0
... A20: 470 | B20: v.d. Waalstraat 16 Vlaardingen | D20: 1077.81 | E20: 0
A21: Grand Total | D21: 1077.81 | E21: 20
F283: =B283/1.09 -> 0
F284: =B284/1.09 -> 0
F285: =B285/1.09 -> 0
F286: =B286/1.09 -> 0
F287: =B287/1.09 -> 0
F288: =B288/1.09 -> 0
F289: =B289/1.09 -> 0
F290: =B290/1.09 -> 0
F291: =B291/1.09 -> 0

Sheet Internet & telefoonkosten
A1: Jaar | B1: 2025
A2: Grootboekrekening | B2: Internet en telefoonkosten woningen
A4: object_id | B4: Omschrijving | C4: Per. | D4: Max. of Debet | E4: Max. of Credit
A5: 0 | B5: Algemeen woningen | D5: 5187.65 | E5: 333.9
A6: 1 | B6: Nunspeetlaan 14 | D6: 22.82 | E6: 5.15
A7: 2 | B7: Allard Piersonlaan 142 Den Haag | D7: 25.1 | E7: 0
A8: 4 | B8: Broekweg 25 Vlaardingen | D8: 25.2 | E8: 20.92
A9: 9 | B9: Galgeweg 48A, 's-Gravenzande | D9: 50.37 | E9: 50.37
A10: 10 | B10: Kethelweg 1B Vlaardingen | D10: 25.1 | E10: 0
A11: 11 | B11: Kethelweg 1C Vlaardingen | D11: 25.1 | E11: 0
A12: 16 | B12: van Scorelstraat 73 Maassluis | D12: 67.36 | E12: 0
A13: 17 | B13: G.A. Brederolaan 75B Maassluis | D13: 33.06 | E13: 0
A14: 20 | B14: Mr. Troelstrastraat 37 Vlaardingen | D14: 25.1 | E14: 23.48
A15: 21 | B15: Vaartweg 106C Vlaardingen | D15: 25.1 | E15: 7.29
A16: 22 | B16: 2e van Leyden Gaelstraat 6, Vlaardingen | D16: 25.1 | E16: 9.2
... A114: 471 | B114: W.M. Bakkerslaan 34, Maasluis | D114: 43.39 | E114: 0
B115: Parallelweg 110A Vlaardingen | D115: 22.82 | E115: 2.94
A116: Grand Total | D116: 5187.65 | E116: 333.9
F283: =B283/1.09 -> 0
F284: =B284/1.09 -> 0
F285: =B285/1.09 -> 0
F286: =B286/1.09 -> 0
F287: =B287/1.09 -> 0
F288: =B288/1.09 -> 0
F289: =B289/1.09 -> 0
F290: =B290/1.09 -> 0
F291: =B291/1.09 -> 0

Sheet GWE woningen
A1: Jaar | B1: 2025
A2: Grootboekrekening | B2: Gas, water en electra woningen
A4: object_id | B4: Omschrijving | C4: Per. | D4: Max. of Debet | E4: Max. of Credit
A5: 0 | B5: Algemeen woningen | D5: 19375.27 | E5: 113.24
A6: 4 | B6: Broekweg 25 Vlaardingen | D6: 260.15 | E6: 0
A7: 9 | B7: Galgeweg 48A, 's-Gravenzande | D7: 773.78 | E7: 0
A8: 10 | B8: Kethelweg 1B Vlaardingen | D8: 85.24 | E8: 0
A9: 11 | B9: Kethelweg 1C Vlaardingen | D9: 32.11 | E9: 0
A10: 15 | B10: Maasdijk 69 | D10: 2470.8 | E10: 0
A11: 16 | B11: van Scorelstraat 73 Maassluis | D11: 218.11 | E11: 0
A12: 17 | B12: G.A. Brederolaan 75B Maassluis | D12: 208.85 | E12: 0
A13: 20 | B13: Mr. Troelstrastraat 37 Vlaardingen | D13: 181.36 | E13: 0
A14: 21 | B14: Vaartweg 106C Vlaardingen | D14: 256.89 | E14: 0
A15: 22 | B15: 2e van Leyden Gaelstraat 6, Vlaardingen | D15: 482.84 | E15: 0
A16: 25 | B16: Groenelaan 30B Schiedam | D16: 190.22 | E16: 467.81
... A167: 488 | B167: Goghlaan 36, Roosendaal | D167: 309.4 | E167: 0
B168: Oosterstraat 89 Vlaardingen | D168: 315.48 | E168: 1.24
A169: Grand Total | D169: 19375.27 | E169: 4543.5
F283: =B283/1.09 -> 0
F284: =B284/1.09 -> 0
F285: =B285/1.09 -> 0
F286: =B286/1.09 -> 0
F287: =B287/1.09 -> 0
F288: =B288/1.09 -> 0
F289: =B289/1.09 -> 0
F290: =B290/1.09 -> 0
F291: =B291/1.09 -> 0

Sheet Huur(belast)woningenavg
A1: Jaar | B1: 2025
A2: Grootboekrekening | B2: Huur (belast) woningen
A4: object_id | B4: Omschrijving | C4: Per. | D4: Max. of Debet | E4: Max. of Credit | G4: Average of Debet | H4: Average of Credit | I4: verschil avg-max | J4: max of niet
A5: 0 | B5: Algemeen woningen | D5: 13043.23 | E5: 90 | G5: 2142.3474 | H5: 1.125 | I5: =D5-G5 -> 10900.883
A6: 2 | B6: Allard Piersonlaan 142 Den Haag | D6: 1416.85 | E6: 0 | G6: 1393.9333 | H6: 0 | I6: =D6-G6 -> 22.916667 | J6: 1
A7: 4 | B7: Broekweg 25 Vlaardingen | D7: 1708.41 | E7: 0 | G7: 1674.765 | H7: 0 | I7: =D7-G7 -> 33.645 | J7: 1
A8: 9 | B8: Galgeweg 48A, 's-Gravenzande | D8: 3643.5 | E8: 0 | G8: 3643.5 | H8: 0 | I8: =D8-G8 -> 0 | J8: 1
A9: 10 | B9: Kethelweg 1B Vlaardingen | D9: 1708.41 | E9: 0 | G9: 1674.765 | H9: 0 | I9: =D9-G9 -> 33.645 | J9: 1
A10: 11 | B10: Kethelweg 1C Vlaardingen | D10: 1708.41 | E10: 0 | G10: 1674.765 | H10: 0 | I10: =D10-G10 -> 33.645 | J10: 1
A11: 15 | B11: Maasdijk 69 | D11: 3400 | E11: 0 | G11: 3400 | H11: 0 | I11: =D11-G11 -> 0 | J11: 1
A12: 16 | B12: van Scorelstraat 73 Maassluis | D12: 2364.3 | E12: 0 | G12: 2317.74 | H12: 0 | I12: =D12-G12 -> 46.56 | J12: 1
A13: 17 | B13: G.A. Brederolaan 75B Maassluis | D13: 1677.89 | E13: 0 | G13: 1644.85 | H13: 0 | I13: =D13-G13 -> 33.04 | J13: 1
A14: 20 | B14: Mr. Troelstrastraat 37 Vlaardingen | D14: 1723.44 | E14: 0 | G14: 1689.5 | H14: 0 | I14: =D14-G14 -> 33.94 | J14: 1
A15: 21 | B15: Vaartweg 106C Vlaardingen | D15: 1830.43 | E15: 0 | G15: 1794.385 | H15: 0 | I15: =D15-G15 -> 36.045 | J15: 1
A16: 22 | B16: 2e van Leyden Gaelstraat 6, Vlaardingen | D16: 2930.56 | E16: 2930.56 | G16: 2705.1323 | H16: 225.42769 | I16: =D16-G16 -> 225.42769 | J16: 1
A17: 25 | B17: Groenelaan 30B Schiedam | D17: 1625 | E17: 1625 | G17: 1209.7282 | H17: 147.72727 | I17: =D17-G17 -> 415.27182 | J17: 1
... A32: 88 | B32: Kethelweg 66A, Vlaardingen | D32: 2593.81 | E32: 2491.65 | G32: 2311.7692 | H32: 207.6375 | I32: =D32-G32 -> 282.04083 | J32: 1
A33: 95 | B33: Engelsestraat 16L01 Rotterdam | D33: 1993.32 | E33: 0 | G33: 948.79385 | H33: 0 | I33: =D33-G33 -> 1044.5262
A34: 95 | B34: Engelsestraat 16L3, Rotterdam | D34: 3435.06 | E34: 1750 | G34: 1906.8017 | H34: 145.83333 | I34: =D34-G34 -> 1528.2583
A35: 97 | B35: Burchstraat 16A, Oostburg | D35: 3550 | E35: 0 | G35: 3094.4983 | H35: 0 | I35: =D35-G35 -> 455.50167 | J35: 1
A36: 99 | B36: Steenen Dijck 87, Maassluis | D36: 3383.25 | E36: 0 | G36: 3316.625 | H36: 0 | I36: =D36-G36 -> 66.625 | J36: 1
A37: 103 | B37: Narcissenstraat 23 Rozenburg | D37: 1700 | E37: 0 | G37: 1680.7043 | H37: 0 | I37: =D37-G37 -> 19.295714 | J37: 1
A38: 106 | B38: Prinses Wilhelminastraat 9, Hekendorp | D38: 3200 | E38: 3200 | G38: 1920 | H38: 1280 | I38: =D38-G38 -> 1280
A39: 120 | B39: Plaats 10, Montfoort | D39: 2300 | E39: 0 | G39: 2300 | H39: 0 | I39: =D39-G39 -> 0 | J39: 1
A40: 122 | B40: Kethelweg 66B, Vlaardingen | D40: 2593.81 | E40: 0 | G40: 2542.73 | H40: 0 | I40: =D40-G40 -> 51.08 | J40: 1
A41: 131 | B41: Chopinstraat 35A, Vlaardingen | D41: 2165.26 | E41: 0 | G41: 2122.62 | H41: 0 | I41: =D41-G41 -> 42.64 | J41: 1
A42: 133 | B42: Herenpad 20A, Schiedam | D42: 2075.05 | E42: 0 | G42: 2034.185 | H42: 0 | I42: =D42-G42 -> 40.865 | J42: 1
A43: 134 | B43: Herenpad 20B, Schiedam | D43: 992.34 | E43: 0 | G43: 972.8 | H43: 0 | I43: =D43-G43 -> 19.54 | J43: 1
A44: 135 | B44: Amperestraat 36A, Schiedam | D44: 1691.63 | E44: 0 | G44: 1658.315 | H44: 0 | I44: =D44-G44 -> 33.315 | J44: 1
A45: 148 | B45: 2e Maasbosstraat 2A Vlaardingen | D45: 1570.24 | E45: 0 | G45: 1430.1377 | H45: 0 | I45: =D45-G45 -> 140.10231 | J45: 1
A46: 149 | B46: 2e Maasbosstraat 2B Vlaardingen | D46: 1570.24 | E46: 0 | G46: 1534.1667 | H46: 0 | I46: =D46-G46 -> 36.073333 | J46: 1
A47: 150 | B47: 2e Maasbosstraat 2C Vlaardingen | D47: 1475.31 | E47: 0 | G47: 1441.4125 | H47: 0 | I47: =D47-G47 -> 33.8975 | J47: 1
A48: 154 | B48: Rubensplein 6B3 Schiedam | D48: 2238.15 | E48: 0 | G48: 2198.0818 | H48: 0 | I48: =D48-G48 -> 40.068182 | J48: 1
A49: 156 | B49: Broersvest 74c Schiedam | D49: 2051.51 | E49: 0 | G49: 2024.51 | H49: 0 | I49: =D49-G49 -> 27 | J49: 1
A50: 160 | B50: Chopinstraat 33c Vlaardingen | D50: 1300 | E50: 0 | G50: 1300 | H50: 0 | I50: =D50-G50 -> 0 | J50: 1
... A66: 191 | B66: Jan van Arkelstraat 118 Vlaardingen | D66: 895 | E66: 0 | G66: 895 | H66: 0 | I66: =D66-G66 -> 0 | J66: 1
A67: 192 | B67: Kaapsebos 11 Maasdijk | D67: 8370 | E67: 0 | G67: 6654.8 | H67: 0 | I67: =D67-G67 -> 1715.2
A68: 193 | B68: Kapershoek 11 Rotterdam | D68: 1400.53 | E68: 0 | G68: 1372.95 | H68: 0 | I68: =D68-G68 -> 27.58 | J68: 1
A69: 194 | B69: Keesomstraat 22 Vlaardingen | D69: 2336 | E69: 0 | G69: 2257.3077 | H69: 0 | I69: =D69-G69 -> 78.692308 | J69: 1
A70: 195 | B70: Keesomstraat 50 Vlaardingen | D70: 895 | E70: 0 | G70: 895 | H70: 0 | I70: =D70-G70 -> 0 | J70: 1
A71: 196 | B71: Keesomstraat 54 Vlaardingen | D71: 1405 | E71: 0 | G71: 1368.3333 | H71: 0 | I71: =D71-G71 -> 36.666667 | J71: 1
A72: 199 | B72: Kerstendijk 125 Rotterdam | D72: 1200 | E72: 0 | G72: 1200 | H72: 0 | I72: =D72-G72 -> 0 | J72: 1
A73: 202 | B73: Kimbrenoord 15 Rotterdam | D73: 1993.32 | E73: 0 | G73: 1447.4862 | H73: 0 | I73: =D73-G73 -> 545.83385
A74: 203 | B74: Dorpstraat 48 Lopik | D74: 11100 | E74: 11100 | G74: 5083.3333 | H74: 5083.3333 | I74: =D74-G74 -> 6016.6667
A75: 203 | B75: Dorpstraat 48, Aarlanderveen | D75: 8640.3 | E75: 0 | G75: 7338.0929 | H75: 0 | I75: =D75-G75 -> 1302.2071
A76: 205 | B76: Kreekrug 1 De Lier | D76: 4800 | E76: 0 | G76: 4792.3077 | H76: 0 | I76: =D76-G76 -> 7.6923077 | J76: 1
A77: 206 | B77: Kruiningenstraat 152 Rotterdam | D77: 1552.05 | E77: 0 | G77: 1523.455 | H77: 0 | I77: =D77-G77 -> 28.595 | J77: 1
A78: 207 | B78: Kwikstaartweg 45 | D78: 1970 | E78: 0 | G78: 1942.5 | H78: 0 | I78: =D78-G78 -> 27.5 | J78: 1
A79: 208 | B79: L.A. Kesperweg 31a Vlaardingen | D79: 895 | E79: 0 | G79: 895 | H79: 0 | I79: =D79-G79 -> 0 | J79: 1
A80: 210 | B80: Lorentzstraat 73 Vlaardingen | D80: 1865.5 | E80: 0 | G80: 1865.5 | H80: 0 | I80: =D80-G80 -> 0 | J80: 1
A81: 211 | B81: Maasdijk 206 's Gravenzande | D81: 3400 | E81: 0 | G81: 2076.9286 | H81: 0 | I81: =D81-G81 -> 1323.0714
A82: 213 | B82: Mr. Troelstrastraat 11 Vlaardingen | D82: 895 | E82: 0 | G82: 895 | H82: 0 | I82: =D82-G82 -> 0 | J82: 1
A83: 214 | B83: Mendelssohnplein 13D Vlaardingen | D83: 2801 | E83: 0 | G83: 2520.5986 | H83: 0 | I83: =D83-G83 -> 280.40143 | J83: 1
A84: 215 | B84: Mendelssohnplein 10C Vlaardingen | D84: 2801 | E84: 0 | G84: 2707.0769 | H84: 0 | I84: =D84-G84 -> 93.923077 | J84: 1
A85: 216 | B85: Mendelssohnplein 46A Vlaardingen | D85: 1561.5 | E85: 0 | G85: 1413 | H85: 0 | I85: =D85-G85 -> 148.5 | J85: 1
A86: 217 | B86: Middelrode 8 Rotterdam | D86: 1400.53 | E86: 0 | G86: 1372.95 | H86: 0 | I86: =D86-G86 -> 27.58 | J86: 1
A87: 219 | B87: Miltonstraat 55 Rotterdam | D87: 1345.37 | E87: 1345.37 | G87: 999.76643 | H87: 180.48929 | I87: =D87-G87 -> 345.60357 | J87: 1
A88: 221 | B88: Molenstraat 10 Naaldwijk | D88: 2088.66 | E88: 0 | G88: 2033.82 | H88: 0 | I88: =D88-G88 -> 54.84 | J88: 1
A89: 222 | B89: Molenstraat 23 Naaldwijk | D89: 1282.51 | E89: 0 | G89: 1250.3673 | H89: 0 | I89: =D89-G89 -> 32.142727 | J89: 1
A90: 223 | B90: Acacialaan 9 Pijnacker | D90: 6753.42 | E90: 3224 | G90: 2675.484 | H90: 957.786 | I90: =D90-G90 -> 4077.936
A91: 225 | B91: Kerkwervesingel 127 Rotterdam | D91: 3226.47 | E91: 0 | G91: 1228.9592 | H91: 0 | I91: =D91-G91 -> 1997.5108
A92: 227 | B92: Oostlaan 3 De Lier | D92: 2561.5 | E92: 0 | G92: 2541 | H92: 0 | I92: =D92-G92 -> 20.5 | J92: 1
A93: 228 | B93: Parallelweg 122a Vlaardingen | D93: 895 | E93: 0 | G93: 895 | H93: 0 | I93: =D93-G93 -> 0 | J93: 1
A94: 229 | B94: Parallelweg 98B Vlaardingen | D94: 1397 | E94: 0 | G94: 1270 | H94: 0 | I94: =D94-G94 -> 127 | J94: 1
A95: 230 | B95: Pasteursingel 61B Rotterdam | D95: 1776 | E95: 0 | G95: 1738.3077 | H95: 0 | I95: =D95-G95 -> 37.692308 | J95: 1
A96: 231 | B96: Platostraat 80 Rotterdam | D96: 1200 | E96: 0 | G96: 1162.5 | H96: 0 | I96: =D96-G96 -> 37.5 | J96: 1
A97: 232 | B97: Zuidhoek 209D Rotterdam | D97: 1872 | E97: 0 | G97: 1809.3846 | H97: 0 | I97: =D97-G97 -> 62.615385 | J97: 1
A98: 233 | B98: Rembrandtstraat 20B Naaldwijk | D98: 1603.14 | E98: 0 | G98: 1561.0467 | H98: 0 | I98: =D98-G98 -> 42.093333 | J98: 1
A99: 234 | B99: Rotterdamsedijk 154b Schiedam | D99: 895 | E99: 0 | G99: 895 | H99: 0 | I99: =D99-G99 -> 0 | J99: 1
A100: 235 | B100: Rubensplein 3b Schiedam | D100: 895 | E100: 0 | G100: 895 | H100: 0 | I100: =D100-G100 -> 0 | J100: 1
A101: 236 | B101: Schalkeroord 389 Rotterdam | D101: 1623.9 | E101: 0 | G101: 1500.425 | H101: 0 | I101: =D101-G101 -> 123.475 | J101: 1
A102: 237 | B102: Schere 238 Rotterdam | D102: 1345.37 | E102: 0 | G102: 1345.37 | H102: 0 | I102: =D102-G102 -> 0 | J102: 1
A103: 238 | B103: Van der Werffstraat 370 Vlaardingen | D103: 895 | E103: 0 | G103: 895 | H103: 0 | I103: =D103-G103 -> 0 | J103: 1
A104: 239 | B104: Schoonegge 110 Rotterdam | D104: 1327 | E104: 0 | G104: 1301 | H104: 0 | I104: =D104-G104 -> 26 | J104: 1
A105: 240 | B105: Schoonegge 84 Rotterdam | D105: 4141.5 | E105: 4141.5 | G105: 2306.0981 | H105: 436.18062 | I105: =D105-G105 -> 1835.4019
A106: 241 | B106: Van der Werffstraat 166, Vlaardingen | D106: 1250 | E106: 0 | G106: 1250 | H106: 0 | I106: =D106-G106 -> 0 | J106: 1
A107: 242 | B107: Sint Liduinastraat 76A Schiedam | D107: 900 | E107: 0 | G107: 900 | H107: 0 | I107: =D107-G107 -> 0 | J107: 1
A108: 243 | B108: Sint Liduinastraat 80 A B Schiedam | D108: 4216.22 | E108: 0 | G108: 4147.0283 | H108: 0 | I108: =D108-G108 -> 69.191667 | J108: 1
A109: 245 | B109: Van der Werffstraat 240 Vlaardingen | D109: 895 | E109: 0 | G109: 895 | H109: 0 | I109: =D109-G109 -> 0 | J109: 1
A110: 246 | B110: Socratesstraat 168 Rotterdam | D110: 1200 | E110: 0 | G110: 1162.5 | H110: 0 | I110: =D110-G110 -> 37.5 | J110: 1
A111: 247 | B111: Spoorsingel 154B, Vlaardingen | D111: 2129.12 | E111: 0 | G111: 2052.96 | H111: 0 | I111: =D111-G111 -> 76.16 | J111: 1
A112: 249 | B112: Tholenstraat 114 Rotterdam | D112: 1400.53 | E112: 0 | G112: 1372.95 | H112: 0 | I112: =D112-G112 -> 27.58 | J112: 1
A113: 250 | B113: Van der Waalsstraat 70 Vlaardingen | D113: 895 | E113: 0 | G113: 895 | H113: 0 | I113: =D113-G113 -> 0 | J113: 1
A114: 273 | B114: Fenacoliuslaan 56b, Maassluis | D114: 1003.21 | E114: 0 | G114: 354.67 | H114: 0 | I114: =D114-G114 -> 648.54
A115: 277 | B115: Gerberalaan 113 | D115: 111.47 | E115: 111.47 | G115: 74.313333 | H115: 37.156667 | I115: =D115-G115 -> 37.156667 | J115: 1
A116: 279 | B116: Haagkamp 11 | D116: 2006.42 | E116: 0 | G116: 231.60405 | H116: 0 | I116: =D116-G116 -> 1774.8159
A117: 291 | B117: Koperwerf 28 | D117: 3009.63 | E117: 111.47 | G117: 1243.9143 | H117: 3.0127027 | I117: =D117-G117 -> 1765.7157
A118: 292 | B118: Burgemeester Stulemeijerlaan 71, Schiedam | D118: 1019 | E118: 0 | G118: 986 | H118: 0 | I118: =D118-G118 -> 33 | J118: 1
A119: 333 | B119: Kethelweg 66D, Vlaardingen | D119: 4293.83 | E119: 0 | G119: 2671.868 | H119: 0 | I119: =D119-G119 -> 1621.962
A120: 336 | B120: Ofwegen 1A, Woubrugge | D120: 2900 | E120: 0 | G120: 2900 | H120: 0 | I120: =D120-G120 -> 0 | J120: 1
A121: 337 | B121: Kruisweg 16, Wobrugge | D121: 4750 | E121: 0 | G121: 4750 | H121: 0 | I121: =D121-G121 -> 0 | J121: 1
A122: 340 | B122: Professor Poelslaan 58c Rotterdam | D122: 2840.41 | E122: 0 | G122: 2759.041 | H122: 0 | I122: =D122-G122 -> 81.369 | J122: 1
A123: 345 | B123: Compierekade 15, Alphen a/d Rijn | D123: 6250 | E123: 6250 | G123: 3125 | H123: 3125 | I123: =D123-G123 -> 3125
A124: 347 | B124: Van Ruijsdaellaan 72A, Schiedam | D124: 1560 | E124: 0 | G124: 1560 | H124: 0 | I124: =D124-G124 -> 0 | J124: 1
A125: 348 | B125: Wagenstraat 70, Wagenberg | D125: 7570 | E125: 7570 | G125: 5204.375 | H125: 1892.5 | I125: =D125-G125 -> 2365.625
A126: 351 | B126: Van Ruijsdaellaan 72B, Schiedam | D126: 1560 | E126: 0 | G126: 1560 | H126: 0 | I126: =D126-G126 -> 0 | J126: 1
A127: 352 | B127: Van Ruijsdaellaan 72C, Schiedam | D127: 1560 | E127: 0 | G127: 1560 | H127: 0 | I127: =D127-G127 -> 0 | J127: 1
A128: 353 | B128: Archimedesstraat 6B, Schiedam | D128: 1623.96 | E128: 0 | G128: 1623.96 | H128: 0 | I128: =D128-G128 -> 0 | J128: 1
A129: 358 | B129: Monsterseweg 26A | D129: 8450 | E129: 0 | G129: 6042.0822 | H129: 0 | I129: =D129-G129 -> 2407.9178
A130: 359 | B130: Kimbrenoord 49, Rotterdam | D130: 2386.52 | E130: 0 | G130: 2189.92 | H130: 0 | I130: =D130-G130 -> 196.6 | J130: 1
...

Sheet Huur(belast)woningenmax
A1: Jaar | B1: 2025
A2: Grootboekrekening | B2: Huur (belast) woningen
A4: object_id | B4: Omschrijving | C4: Per. | D4: Max. of Debet | E4: Max. of Credit
A5: 0 | B5: Algemeen woningen | D5: 13043.23 | E5: 90
A6: 2 | B6: Allard Piersonlaan 142 Den Haag | D6: 1416.85 | E6: 0
A7: 4 | B7: Broekweg 25 Vlaardingen | D7: 1708.41 | E7: 0
A8: 9 | B8: Galgeweg 48A, 's-Gravenzande | D8: 3643.5 | E8: 0
A9: 10 | B9: Kethelweg 1B Vlaardingen | D9: 1708.41 | E9: 0
A10: 11 | B10: Kethelweg 1C Vlaardingen | D10: 1708.41 | E10: 0
A11: 15 | B11: Maasdijk 69 | D11: 3400 | E11: 0
A12: 16 | B12: van Scorelstraat 73 Maassluis | D12: 2364.3 | E12: 0
A13: 17 | B13: G.A. Brederolaan 75B Maassluis | D13: 1677.89 | E13: 0
A14: 20 | B14: Mr. Troelstrastraat 37 Vlaardingen | D14: 1723.44 | E14: 0
A15: 21 | B15: Vaartweg 106C Vlaardingen | D15: 1830.43 | E15: 0
A16: 22 | B16: 2e van Leyden Gaelstraat 6, Vlaardingen | D16: 2930.56 | E16: 2930.56
... A18: 26 | B18: Chopinstraat 39C Vlaardingen | D18: 1952.46 | E18: 0
A19: 27 | B19: Buizerdstraat 210 Maassluis | D19: 1677.89 | E19: 0 | F19: 430.32 | G19: 456.54
A20: 28 | B20: Lange Kruisweg 12 Maasdijk | D20: 2928.69 | E20: 0
A21: 30 | B21: Curacaolaan 88 Vlaardingen | D21: 895 | E21: 0
A22: 31 | B22: Hogenbanweg 331 Schiedam | D22: 1568.43 | E22: 0
A23: 33 | B23: Kethelweg 66C | D23: 2082 | E23: 0
A24: 34 | B24: Kethelweg 68A | D24: 2269.38 | E24: 0
A25: 35 | B25: Messchaertplein 39, Vlaardingen | D25: 1784.67 | E25: 0
A26: 36 | B26: Messchaertplein 40, Vlaardingen | D26: 2810.7 | E26: 0
A27: 57 | B27: Markt 5 Bovenwoning, Massluis | D27: 1715.6 | E27: 0
A28: 67 | B28: Franz Liszstraat 5, Terneuzen | D28: 3643.5 | E28: 0
A29: 79 | B29: Ploegstraat 2a, Schiedam | D29: 2166.65 | E29: 0
A30: 80 | B30: Voorstraat 25, Vlaardingen | D30: 2170 | E30: 0
A31: 84 | B31: Kerkdreef 42 Axel | D31: 2250 | E31: 0
... A187: 477 | B187: Hotel de Sluiskop | D187: 16986.67 | E187: 0
B188: 1e Verdeligsweg 6 - 821, Putte | D188: 475 | E188: 475
B189: Oosterstraat 89 Vlaardingen | D189: 1569.3 | E189: 0
B190: Parallelweg 110A Vlaardingen | D190: 2082 | E190: 0
F283: =B283/1.09 -> 0
F284: =B284/1.09 -> 0
F285: =B285/1.09 -> 0
F286: =B286/1.09 -> 0
F287: =B287/1.09 -> 0
F288: =B288/1.09 -> 0
F289: =B289/1.09 -> 0
F290: =B290/1.09 -> 0
F291: =B291/1.09 -> 0

Sheet Financiele mutaties uitgebreid
A1: Jaar | B1: Per. | C1: Boekstuk | D1: Jrnpstnr. | E1: Vlgnr. jrnpst. | F1: Rek.nr. | G1: Grootboekrekening | H1: Debet | I1: Credit | J1: Saldo | K1: Verb. 1 | L1: object_id | M1: Omschrijving | N1: Verb. 2 | O1: Omschrijving | P1: Btw | Q1: Boeking | R1: Bkstk.nr. | S1: Fact.nr. | T1: Dagboek | U1: Ltst. wijz. | V1: Gewijzigd door
A2: 2025 | B2: 12 | C2: 46022 | D2: 87488 | E2: 2 | F2: 4230 | G2: Internet en telefoonkosten woningen | H2: 158.84 | I2: 0 | J2: 158.84 | K2: 526 | L2: =_xlfn.XLOOKUP(M2,Sheet6!B:B,Sheet6!A:A,"",0) -> 371 | M2: Zwingel 8B | P2: 4 | Q2: Tot Uw Dienst | R2: 1021507250249 | S2: I255314 | T2: Inkoopdagboek | U2: 46027.625 | V2: 86806.admin
A3: 2025 | B3: 12 | C3: 46022 | D3: 87490 | E3: 2 | F3: 4220 | G3: Kleine inventaris/inrichting woningen | H3: 400 | I3: 0 | J3: 400 | K3: 526 | L3: =_xlfn.XLOOKUP(M3,Sheet6!B:B,Sheet6!A:A,"",0) -> 371 | M3: Zwingel 8B | P3: 4 | Q3: Tot Uw Dienst, wk 52 | R3: 07250248 | S3: I255316 | T3: Inkoopdagboek | U3: 46027.625 | V3: 86806.admin
A4: 2025 | B4: 12 | C4: 46021 | D4: 87425 | E4: 2 | F4: 4270 | G4: Kosten VvE woningen | H4: 0 | I4: 20 | J4: -20 | K4: 999 | L4: =_xlfn.XLOOKUP(M4,Sheet6!B:B,Sheet6!A:A,"",0) -> 0 | M4: Algemeen woningen | Q4: VVE FLATGEBOUW JAN Te veel betaalde VvE bijdrage 2025/2025-12-30 | R4: 25425 | T4: Rabobank betaalrekening | U4: 46029.471 | V4: 86806.1002315
A5: 2025 | B5: 12 | C5: 46020 | D5: 87423 | E5: 97 | F5: 4250 | G5: Gas, water en electra woningen | H5: 24.73 | I5: 0 | J5: 24.73 | K5: 518 | L5: =_xlfn.XLOOKUP(M5,Sheet6!B:B,Sheet6!A:A,"",0) -> 203 | M5: Dorpstraat 48, Aarlanderveen | P5: 5 | Q5: OASEN NV Voorschot dec, BTW 2,23, Dorpsstraat 48, 2445 AN AARLANDERVEEN/2025-12-29 7017893706202501 178937 | R5: 25424 | T5: Rabobank betaalrekening | U5: 46029.581 | V5: 86806.1002315
A6: 2025 | B6: 12 | C6: 46015 | D6: 87374 | E6: 2 | F6: 4250 | G6: Gas, water en electra woningen | H6: 78.85 | I6: 0 | J6: 78.85 | K6: 542 | L6: =_xlfn.XLOOKUP(M6,Sheet6!B:B,Sheet6!A:A,"",0) -> 370 | M6: Cloosterstraat 23A, Kloosterzande | P6: 4 | Q6: Evides september | R6: 111100156488 | S6: I255282 | T6: Inkoopdagboek | U6: 46022.547 | V6: 86806.admin
A7: 2025 | B7: 12 | C7: 46015 | D7: 87493 | E7: 2 | F7: 4250 | G7: Gas, water en electra woningen | H7: 0 | I7: 148.37 | J7: -148.37 | K7: 469 | L7: =_xlfn.XLOOKUP(M7,Sheet6!B:B,Sheet6!A:A,"",0) -> 177 | M7: Hoge Noordweg 27B Naaldwijk | P7: 4 | Q7: Audax Renewables afrekening | R7: 6509100 | S7: I255319 | T7: Inkoopdagboek | U7: 46027.626 | V7: 86806.admin
A8: 2025 | B8: 12 | C8: 46015 | D8: 87493 | E8: 3 | F8: 4250 | G8: Gas, water en electra woningen | H8: 0 | I8: 507.86 | J8: -507.86 | K8: 197 | L8: =_xlfn.XLOOKUP(M8,Sheet6!B:B,Sheet6!A:A,"",0) -> 225 | M8: Kerkwervesingel 127 Rotterdam | P8: 4 | Q8: Audax Renewables afrekening | R8: 6509100 | S8: I255319 | T8: Inkoopdagboek | U8: 46027.626 | V8: 86806.admin
A9: 2025 | B9: 12 | C9: 46015 | D9: 87493 | E9: 4 | F9: 4250 | G9: Gas, water en electra woningen | H9: 0 | I9: 41.56 | J9: -41.56 | K9: 545 | L9: =_xlfn.XLOOKUP(M9,Sheet6!B:B,Sheet6!A:A,"",0) -> 361 | M9: Putsebocht 136 B01 | P9: 4 | Q9: Audax Renewables afrekening | R9: 6509100 | S9: I255319 | T9: Inkoopdagboek | U9: 46027.626 | V9: 86806.admin
A10: 2025 | B10: 12 | C10: 46015 | D10: 87493 | E10: 5 | F10: 4250 | G10: Gas, water en electra woningen | H10: 1806.92 | I10: 0 | J10: 1806.92 | K10: 297 | L10: =_xlfn.XLOOKUP(M10,Sheet6!B:B,Sheet6!A:A,"",0) -> 243 | M10: Sint Liduinastraat 80 A B Schiedam | P10: 4 | Q10: Audax Renewables afrekening | R10: 6509100 | S10: I255319 | T10: Inkoopdagboek | U10: 46027.626 | V10: 86806.admin
A11: 2025 | B11: 12 | C11: 46015 | D11: 87493 | E11: 6 | F11: 4250 | G11: Gas, water en electra woningen | H11: 0 | I11: 299.64 | J11: -299.64 | K11: 477 | L11: =_xlfn.XLOOKUP(M11,Sheet6!B:B,Sheet6!A:A,"",0) -> 88 | M11: Kethelweg 66A, Vlaardingen | P11: 4 | Q11: Audax Renewables afrekening | R11: 6509100 | S11: I255319 | T11: Inkoopdagboek | U11: 46027.626 | V11: 86806.admin
A12: 2025 | B12: 12 | C12: 46014 | D12: 87262 | E12: 2 | F12: 4250 | G12: Gas, water en electra woningen | H12: 0 | I12: 304.71 | J12: -304.71 | K12: 544 | L12: =_xlfn.XLOOKUP(M12,Sheet6!B:B,Sheet6!A:A,"",0) -> 450 | M12: Laan van Zuid 949 | P12: 4 | Q12: ENECO SERVICES Kenmerk 7005642756500011 Omschrijving Restitutie creditsaldo Laan op Zuid 949 ROTTERDAM/2025-12-23 7005642756500011 | R12: 25421 | T12: Rabobank betaalrekening | U12: 46024.649 | V12: 86806.1002315
A13: 2025 | B13: 12 | C13: 46014 | D13: 87362 | E13: 2 | F13: 4220 | G13: Kleine inventaris/inrichting woningen | H13: 918.67 | I13: 0 | J13: 918.67 | K13: 999 | L13: =_xlfn.XLOOKUP(M13,Sheet6!B:B,Sheet6!A:A,"",0) -> 0 | M13: Algemeen woningen | P13: 4 | Q13: Hakzo sleutels 4ekw25 | R13: 231225588 | S13: I255271 | T13: Inkoopdagboek | U13: 46022.546 | V13: 86806.admin
A14: 2025 | B14: 12 | C14: 46014 | D14: 87495 | E14: 2 | F14: 4220 | G14: Kleine inventaris/inrichting woningen | H14: 400 | I14: 0 | J14: 400 | K14: 526 | L14: =_xlfn.XLOOKUP(M14,Sheet6!B:B,Sheet6!A:A,"",0) -> 371 | M14: Zwingel 8B | P14: 4 | Q14: Tot Uw Dienst, wk 51 | R14: 07250246 | S14: I255321 | T14: Inkoopdagboek | U14: 46027.626 | V14: 86806.admin
A15: 2025 | B15: 12 | C15: 46013 | D15: 87340 | E15: 2 | F15: 4220 | G15: Kleine inventaris/inrichting woningen | H15: 400 | I15: 0 | J15: 400 | K15: 526 | L15: =_xlfn.XLOOKUP(M15,Sheet6!B:B,Sheet6!A:A,"",0) -> 371 | M15: Zwingel 8B | P15: 4 | Q15: Tot Uw Dienst, wk 50 | R15: 07250244 | S15: I255249 | T15: Inkoopdagboek | U15: 46021.6 | V15: 86806.admin
A16: 2025 | B16: 12 | C16: 46013 | D16: 87341 | E16: 2 | F16: 4200 | G16: Huur (belast) woningen | H16: 2117.89 | I16: 0 | J16: 2117.89 | K16: 495 | L16: =_xlfn.XLOOKUP(M16,Sheet6!B:B,Sheet6!A:A,"",0) -> 291 | M16: Koperwerf 28 | P16: 5 | Q16: AUB van Bergen Personeelsdiensten; wk 52 | R16: 250155 | S16: I255250 | T16: Inkoopdagboek | U16: 46021.6 | V16: 86806.admin
A17: 2025 | B17: 12 | C17: 46013 | D17: 87341 | E17: 3 | F17: 4200 | G17: Huur (belast) woningen | H17: 111.47 | I17: 0 | J17: 111.47 | K17: 496 | L17: =_xlfn.XLOOKUP(M17,Sheet6!B:B,Sheet6!A:A,"",0) -> 279 | M17: Haagkamp 11 | P17: 5 | Q17: AUB van Bergen Personeelsdiensten; wk 52 | R17: 250155 | S17: I255250 | T17: Inkoopdagboek | U17: 46021.6 | V17: 86806.admin
A18: 2025 | B18: 12 | C18: 46012 | D18: 86962 | E18: 2 | F18: 4250 | G18: Gas, water en electra woningen | H18: 0 | I18: 24.77 | J18: -24.77 | K18: 544 | L18: =_xlfn.XLOOKUP(M18,Sheet6!B:B,Sheet6!A:A,"",0) -> 450 | M18: Laan van Zuid 949 | P18: 5 | Q18: Evides december | R18: 144200006889 | S18: I255071 | T18: Inkoopdagboek | U18: 46002.611 | V18: 86806.admin
A19: 2025 | B19: 12 | C19: 46012 | D19: 86963 | E19: 2 | F19: 4250 | G19: Gas, water en electra woningen | H19: 0 | I19: 22.94 | J19: -22.94 | K19: 545 | L19: =_xlfn.XLOOKUP(M19,Sheet6!B:B,Sheet6!A:A,"",0) -> 361 | M19: Putsebocht 136 B01 | P19: 5 | Q19: Evides december | R19: 142000006282 | S19: I255072 | T19: Inkoopdagboek | U19: 46002.612 | V19: 86806.admin
A20: 2025 | B20: 12 | C20: 46012 | D20: 87046 | E20: 2 | F20: 4250 | G20: Gas, water en electra woningen | H20: 0 | I20: 29.36 | J20: -29.36 | K20: 251 | L20: =_xlfn.XLOOKUP(M20,Sheet6!B:B,Sheet6!A:A,"",0) -> 63 | M20: Energieweg 40 Vlaardingen | P20: 5 | Q20: Evides april | R20: 145300006170 | S20: I255113 | T20: Inkoopdagboek | U20: 46006.665 | V20: 86806.admin
A21: 2025 | B21: 12 | C21: 46012 | D21: 87047 | E21: 2 | F21: 4250 | G21: Gas, water en electra woningen | H21: 0 | I21: 30.28 | J21: -30.28 | K21: 323 | L21: =_xlfn.XLOOKUP(M21,Sheet6!B:B,Sheet6!A:A,"",0) -> 193 | M21: Kapershoek 11 Rotterdam | P21: 5 | Q21: Evides december | R21: 146800006269 | S21: I255114 | T21: Inkoopdagboek | U21: 46006.665 | V21: 86806.admin
A22: 2025 | B22: 12 | C22: 46012 | D22: 87048 | E22: 2 | F22: 4250 | G22: Gas, water en electra woningen | H22: 0 | I22: 30.28 | J22: -30.28 | K22: 318 | L22: =_xlfn.XLOOKUP(M22,Sheet6!B:B,Sheet6!A:A,"",0) -> 37 | M22: Westfrankelandsestraat 108 Schiedam | P22: 5 | Q22: Evides december | R22: 141100006160 | S22: I255115 | T22: Inkoopdagboek | U22: 46006.665 | V22: 86806.admin
A23: 2025 | B23: 12 | C23: 46012 | D23: 87434 | E23: 2 | F23: 4250 | G23: Gas, water en electra woningen | H23: 0 | I23: 76.95 | J23: -76.95 | K23: 415 | L23: =_xlfn.XLOOKUP(M23,Sheet6!B:B,Sheet6!A:A,"",0) -> 241 | M23: Van der Werffstraat 166, Vlaardingen | P23: 5 | Q23: Noord Energie Afrekening 2025 | R23: F0800161 | S23: I255309 | T23: Inkoopdagboek | U23: 46024.662 | V23: 86806.admin
A24: 2025 | B24: 8 | C24: 46010 | D24: 87223 | E24: 2 | F24: 4200 | G24: Huur (belast) woningen | H24: 895 | I24: 0 | J24: 895 | K24: 154 | L24: =_xlfn.XLOOKUP(M24,Sheet6!B:B,Sheet6!A:A,"",0) -> 235 | M24: Rubensplein 3b Schiedam | P24: 6 | Q24: Tradiro Housing 2025-08 | R24: V05250008 | S24: I255202 | T24: Inkoopdagboek | U24: 46010.495 | V24: 86806.1002315
... A631: 2025 | B631: 12 | C631: 45992 | D631: 86591 | E631: 2 | F631: 4250 | G631: Gas, water en electra woningen | H631: 0 | I631: 461.26 | J631: -461.26 | K631: 180 | L631: =_xlfn.XLOOKUP(M631,Sheet6!B:B,Sheet6!A:A,"",0) -> 236 | M631: Schalkeroord 389 Rotterdam | P631: 6 | Q631: Kalmeijer e/o Klootwijk stookkosten 01-07-2024 - 30-06-2025 | R631: S2514 | S631: I254908 | T631: Inkoopdagboek | U631: 45988.389 | V631: 86806.admin
A632: 2025 | B632: 12 | C632: 45992 | D632: 86771 | E632: 1 | F632: 4270 | G632: Kosten VvE woningen | H632: 192.71 | I632: 0 | J632: 192.71 | K632: 222 | L632: =_xlfn.XLOOKUP(M632,Sheet6!B:B,Sheet6!A:A,"",0) -> 238 | M632: Van der Werffstraat 370 Vlaardingen | Q632: Vve van der Werffstraat 254-380 OO9B005161840292 Vve Van der Werffstraat 370/2025-12-01 | R632: 25404 | T632: Rabobank betaalrekening | U632: 46029.582 | V632: 86806.1002315
A633: 2025 | B633: 12 | C633: 45992 | D633: 86771 | E633: 2 | F633: 4270 | G633: Kosten VvE woningen | H633: 300 | I633: 0 | J633: 300 | K633: 226 | L633: =_xlfn.XLOOKUP(M633,Sheet6!B:B,Sheet6!A:A,"",0) -> 183 | M633: Hugo de Vriesstraat 54 Vlaardingen | Q633: Vve Hugo de Vriesstraat 50 tm 64 OO9B005161957968 VvE bijdrage Hugo de Vriesstraat 54 Vlaardingen/2025-12-01 | R633: 25404 | T633: Rabobank betaalrekening | U633: 46029.582 | V633: 86806.1002315
A634: 2025 | B634: 12 | C634: 45992 | D634: 86771 | E634: 3 | F634: 4270 | G634: Kosten VvE woningen | H634: 205.35 | I634: 0 | J634: 205.35 | K634: 229 | L634: =_xlfn.XLOOKUP(M634,Sheet6!B:B,Sheet6!A:A,"",0) -> 195 | M634: Keesomstraat 50 Vlaardingen | Q634: VvE Keesomstraat 2-64, te Vlaardingen OO9B005162138280 VvE bijdrage Keesomstraat 50 Vlaardingen/2025-12-01 | R634: 25404 | T634: Rabobank betaalrekening | U634: 46029.582 | V634: 86806.1002315
A635: 2025 | B635: 12 | C635: 45992 | D635: 86771 | E635: 4 | F635: 4270 | G635: Kosten VvE woningen | H635: 185 | I635: 0 | J635: 185 | K635: 228 | L635: =_xlfn.XLOOKUP(M635,Sheet6!B:B,Sheet6!A:A,"",0) -> 191 | M635: Jan van Arkelstraat 118 Vlaardingen | Q635: Vereniging van eigenaars flatgebouw Jan van Arkelstraat 62 t/m 148 OO9B005162193097 Maandbijdrage Vve Jan van Arkelstraat 118 Vlaardingen/2025-12-01 | R635: 25404 | T635: Rabobank betaalrekening | U635: 46029.582 | V635: 86806.1002315
A636: 2025 | B636: 12 | C636: 45992 | D636: 86771 | E636: 5 | F636: 4270 | G636: Kosten VvE woningen | H636: 186.34 | I636: 0 | J636: 186.34 | K636: 189 | L636: =_xlfn.XLOOKUP(M636,Sheet6!B:B,Sheet6!A:A,"",0) -> 208 | M636: L.A. Kesperweg 31a Vlaardingen | Q636: VvE Mr. L.A. Kesperweg 1-39 Vlaardingen OO9B005162322475 VvE-bijdrage Mr. L.A. Kesperweg 31A/2025-12-01 | R636: 25404 | T636: Rabobank betaalrekening | U636: 46029.582 | V636: 86806.1002315
A637: 2025 | B637: 12 | C637: 45992 | D637: 86771 | E637: 6 | F637: 4270 | G637: Kosten VvE woningen | H637: 185.9 | I637: 0 | J637: 185.9 | K637: 241 | L637: =_xlfn.XLOOKUP(M637,Sheet6!B:B,Sheet6!A:A,"",0) -> 245 | M637: Van der Werffstraat 240 Vlaardingen | Q637: VvE van der Werffstraat 132-252 te Vlaardingen OO9B005162494509 Maandbijdrage Vve Van der Werffstraat 240/2025-12-01 | R637: 25404 | T637: Rabobank betaalrekening | U637: 46029.582 | V637: 86806.1002315
A638: 2025 | B638: 12 | C638: 45992 | D638: 86771 | E638: 7 | F638: 4270 | G638: Kosten VvE woningen | H638: 115 | I638: 0 | J638: 115 | K638: 156 | L638: =_xlfn.XLOOKUP(M638,Sheet6!B:B,Sheet6!A:A,"",0) -> 452 | M638: Nic. Beetsstraat 29 Vlaardingen | Q638: VvE Nicolaas Beetsstraat 25 t/m 35 OO9B005162795473 VvE-bijdrage Nic. Beetsstraat 29/2025-12-01 | R638: 25404 | T638: Rabobank betaalrekening | U638: 46029.582 | V638: 86806.1002315
A639: 2025 | B639: 12 | C639: 45992 | D639: 86771 | E639: 8 | F639: 4270 | G639: Kosten VvE woningen | H639: 110 | I639: 0 | J639: 110 | K639: 193 | L639: =_xlfn.XLOOKUP(M639,Sheet6!B:B,Sheet6!A:A,"",0) -> 228 | M639: Parallelweg 122a Vlaardingen | Q639: Vve Parallelweg 112-134 OO9B005163007651 Maandbijdrage Vve Parallelweg 122a Vlaardingen/2025-12-01 | R639: 25404 | T639: Rabobank betaalrekening | U639: 46029.582 | V639: 86806.1002315
A640: 2025 | B640: 12 | C640: 45992 | D640: 86771 | E640: 10 | F640: 4250 | G640: Gas, water en electra woningen | H640: 131.4 | I640: 0 | J640: 131.4 | K640: 544 | L640: =_xlfn.XLOOKUP(M640,Sheet6!B:B,Sheet6!A:A,"",0) -> 450 | M640: Laan van Zuid 949 | P640: 4 | Q640: ENECO SERVICES Kenmerk 5000011325936612 Omschrijving Klantnummer 56427565-1 Termijnnota Periode 2025-12 Laan op Zuid 949 ROTTERDAM/2025-12-01 5000011325936612 4235176 | R640: 25404 | T640: Rabobank betaalrekening | U640: 46029.582 | V640: 86806.1002315
A641: 2025 | B641: 12 | C641: 45992 | D641: 86774 | E641: 2 | F641: 4210 | G641: Reparatie en onderhoud woningen | H641: 20.59 | I641: 0 | J641: 20.59 | K641: 999 | L641: =_xlfn.XLOOKUP(M641,Sheet6!B:B,Sheet6!A:A,"",0) -> 0 | M641: Algemeen woningen | P641: 4 | Q641: P. Goinski 1-12-2025 decl. action | R641: 220015 1-12-2025 | S641: I254971 | T641: Inkoopdagboek | U641: 45993.45 | V641: 86806.admin
A642: 2025 | B642: 12 | C642: 45992 | D642: 86782 | E642: 2 | F642: 4270 | G642: Kosten VvE woningen | H642: 50 | I642: 0 | J642: 50 | K642: 191 | L642: =_xlfn.XLOOKUP(M642,Sheet6!B:B,Sheet6!A:A,"",0) -> 234 | M642: Rotterdamsedijk 154b Schiedam | Q642: VVE Rotterdamsedijk 154b december | R642: 2025-024 | S642: I254978 | T642: Inkoopdagboek | U642: 45994.367 | V642: 86806.admin
A643: 2025 | B643: 11 | C643: 45992 | D643: 86820 | E643: 2 | F643: 4200 | G643: Huur (belast) woningen | H643: 2187 | I643: 0 | J643: 2187 | K643: 501 | L643: =_xlfn.XLOOKUP(M643,Sheet6!B:B,Sheet6!A:A,"",0) -> 441 | M643: Grimbergen 19 | P643: 6 | Q643: Alvonto Steenbergen B.V. wk 45 tm 48 met huuropslag | R643: V01250086 | S643: I255013 | T643: Inkoopdagboek | U643: 45996.348 | V643: 86806.admin
A644: 2025 | B644: 11 | C644: 45992 | D644: 86820 | E644: 3 | F644: 4200 | G644: Huur (belast) woningen | H644: 972 | I644: 0 | J644: 972 | K644: 511 | L644: =_xlfn.XLOOKUP(M644,Sheet6!B:B,Sheet6!A:A,"",0) -> 454 | M644: Oostene 23 | P644: 6 | Q644: Alvonto Steenbergen B.V. wk 45 tm 48 met huuropslag | R644: V01250086 | S644: I255013 | T644: Inkoopdagboek | U644: 45996.348 | V644: 86806.admin
A645: 2025 | B645: 11 | C645: 45992 | D645: 86820 | E645: 4 | F645: 4200 | G645: Huur (belast) woningen | H645: 5589 | I645: 0 | J645: 5589 | K645: 502 | L645: =_xlfn.XLOOKUP(M645,Sheet6!B:B,Sheet6!A:A,"",0) -> 472 | M645: Westlandse Langeweg 14 | P645: 6 | Q645: Alvonto Steenbergen B.V. wk 45 tm 48 met huuropslag | R645: V01250086 | S645: I255013 | T645: Inkoopdagboek | U645: 45996.348 | V645: 86806.admin
A646: 2025 | B646: 11 | C646: 45992 | D646: 86820 | E646: 5 | F646: 4200 | G646: Huur (belast) woningen | H646: 1620 | I646: 0 | J646: 1620 | K646: 999 | L646: =_xlfn.XLOOKUP(M646,Sheet6!B:B,Sheet6!A:A,"",0) -> 0 | M646: Algemeen woningen | P646: 6 | Q646: Alvonto Steenbergen B.V. wk 45 tm 48 met huuropslag | R646: V01250086 | S646: I255013 | T646: Inkoopdagboek | U646: 45996.348 | V646: 86806.admin
A647: 2025 | B647: 12 | C647: 45992 | D647: 86900 | E647: 2 | F647: 4270 | G647: Kosten VvE woningen | H647: 164.83 | I647: 0 | J647: 164.83 | K647: 227 | L647: =_xlfn.XLOOKUP(M647,Sheet6!B:B,Sheet6!A:A,"",0) -> 30 | M647: Curacaolaan 88 Vlaardingen | Q647: VVE Curacaolaan 34 t/m 96 even december | R647: 25010530 | S647: I255026 | T647: Inkoopdagboek | U647: 45999.35 | V647: 86806.admin
A648: 2025 | B648: 12 | C648: 45992 | D648: 86901 | E648: 2 | F648: 4250 | G648: Gas, water en electra woningen | H648: 5583.1 | I648: 0 | J648: 5583.1 | K648: 282 | L648: =_xlfn.XLOOKUP(M648,Sheet6!B:B,Sheet6!A:A,"",0) -> 27 | M648: Buizerdstraat 210 Maassluis | P648: 99 | Q648: Ryanrent BV afrekening GWE 2023-08 tot 2025-12 | R648: 25803587 | S648: I255027 | T648: Inkoopdagboek | U648: 45999.35 | V648: 86806.admin
A649: 2025 | B649: 12 | C649: 45992 | D649: 86902 | E649: 2 | F649: 4250 | G649: Gas, water en electra woningen | H649: 25 | I649: 0 | J649: 25 | K649: 341 | L649: =_xlfn.XLOOKUP(M649,Sheet6!B:B,Sheet6!A:A,"",0) -> 139 | M649: Wilgensingel 63 Rozenburg | P649: 4 | Q649: GGP B.V. december | R649: 25876735 | S649: I255028 | T649: Inkoopdagboek | U649: 45999.351 | V649: 86806.admin
A650: 2025 | B650: 12 | C650: 45992 | D650: 87026 | E650: 2 | F650: 4230 | G650: Internet en telefoonkosten woningen | H650: 25.1 | I650: 0 | J650: 25.1 | K650: 336 | L650: =_xlfn.XLOOKUP(M650,Sheet6!B:B,Sheet6!A:A,"",0) -> 10 | M650: Kethelweg 1B Vlaardingen | P650: 4 | Q650: Ziggo Zakelijk Services B.V. december | R650: 77743896021 | S650: I255105 | T650: Inkoopdagboek | U650: 46003.661 | V650: 86806.admin
A651: 2025 | B651: 12 | C651: 45992 | D651: 87026 | E651: 3 | F651: 4230 | G651: Internet en telefoonkosten woningen | H651: 25.1 | I651: 0 | J651: 25.1 | K651: 338 | L651: =_xlfn.XLOOKUP(M651,Sheet6!B:B,Sheet6!A:A,"",0) -> 11 | M651: Kethelweg 1C Vlaardingen | P651: 4 | Q651: Ziggo Zakelijk Services B.V. december | R651: 77743896021 | S651: I255105 | T651: Inkoopdagboek | U651: 46003.661 | V651: 86806.admin
A652: 2025 | B652: 12 | C652: 45992 | D652: 87026 | E652: 4 | F652: 4230 | G652: Internet en telefoonkosten woningen | H652: 25.1 | I652: 0 | J652: 25.1 | K652: 238 | L652: =_xlfn.XLOOKUP(M652,Sheet6!B:B,Sheet6!A:A,"",0) -> 95 | M652: Engelsestraat 16L01 Rotterdam | P652: 4 | Q652: Ziggo Zakelijk Services B.V. december | R652: 77743896021 | S652: I255105 | T652: Inkoopdagboek | U652: 46003.661 | V652: 86806.admin
A653: 2025 | B653: 12 | C653: 45992 | D653: 87026 | E653: 5 | F653: 4230 | G653: Internet en telefoonkosten woningen | H653: 25.1 | I653: 0 | J653: 25.1 | K653: 340 | L653: =_xlfn.XLOOKUP(M653,Sheet6!B:B,Sheet6!A:A,"",0) -> 229 | M653: Parallelweg 98B Vlaardingen | P653: 4 | Q653: Ziggo Zakelijk Services B.V. december | R653: 77743896021 | S653: I255105 | T653: Inkoopdagboek | U653: 46003.661 | V653: 86806.admin
A654: 2025 | B654: 12 | C654: 45992 | D654: 87026 | E654: 6 | F654: 4230 | G654: Internet en telefoonkosten woningen | H654: 25.1 | I654: 0 | J654: 25.1 | K654: 409 | L654: =_xlfn.XLOOKUP(M654,Sheet6!B:B,Sheet6!A:A,"",0) -> 152 | M654: Beeklaan 294-1/294-2, Den Haag | P654: 4 | Q654: Ziggo Zakelijk Services B.V. december | R654: 77743896021 | S654: I255105 | T654: Inkoopdagboek | U654: 46003.661 | V654: 86806.admin
A655: 2025 | B655: 12 | C655: 45992 | D655: 87026 | E655: 7 | F655: 4230 | G655: Internet en telefoonkosten woningen | H655: 25.1 | I655: 0 | J655: 25.1 | K655: 394 | L655: =_xlfn.XLOOKUP(M655,Sheet6!B:B,Sheet6!A:A,"",0) -> 2 | M655: Allard Piersonlaan 142 Den Haag | P655: 4 | Q655: Ziggo Zakelijk Services B.V. december | R655: 77743896021 | S655: I255105 | T655: Inkoopdagboek | U655: 46003.661 | V655: 86806.admin
A656: 2025 | B656: 12 | C656: 45992 | D656: 87026 | E656: 8 | F656: 4230 | G656: Internet en telefoonkosten woningen | H656: 24.18 | I656: 0 | J656: 24.18 | K656: 180 | L656: =_xlfn.XLOOKUP(M656,Sheet6!B:B,Sheet6!A:A,"",0) -> 236 | M656: Schalkeroord 389 Rotterdam | P656: 4 | Q656: Ziggo Zakelijk Services B.V. december | R656: 77743896021 | S656: I255105 | T656: Inkoopdagboek | U656: 46003.661 | V656: 86806.admin
A657: 2025 | B657: 12 | C657: 45992 | D657: 87026 | E657: 9 | F657: 4230 | G657: Internet en telefoonkosten woningen | H657: 25.1 | I657: 0 | J657: 25.1 | K657: 474 | L657: =_xlfn.XLOOKUP(M657,Sheet6!B:B,Sheet6!A:A,"",0) -> 95 | M657: Engelsestraat 16L3, Rotterdam | P657: 4 | Q657: Ziggo Zakelijk Services B.V. december | R657: 77743896021 | S657: I255105 | T657: Inkoopdagboek | U657: 46003.661 | V657: 86806.admin
A658: 2025 | B658: 12 | C658: 45992 | D658: 87026 | E658: 10 | F658: 4230 | G658: Internet en telefoonkosten woningen | H658: 25.1 | I658: 0 | J658: 25.1 | K658: 335 | L658: =_xlfn.XLOOKUP(M658,Sheet6!B:B,Sheet6!A:A,"",0) -> 170 | M658: Goudestein 30 Rotterdam | P658: 4 | Q658: Ziggo Zakelijk Services B.V. december | R658: 77743896021 | S658: I255105 | T658: Inkoopdagboek | U658: 46003.661 | V658: 86806.admin
A659: 2025 | B659: 12 | C659: 45992 | D659: 87026 | E659: 11 | F659: 4230 | G659: Internet en telefoonkosten woningen | H659: 25.1 | I659: 0 | J659: 25.1 | K659: 263 | L659: =_xlfn.XLOOKUP(M659,Sheet6!B:B,Sheet6!A:A,"",0) -> 403 | M659: Hontenissestraat 124A Rotterdam | P659: 4 | Q659: Ziggo Zakelijk Services B.V. december | R659: 77743896021 | S659: I255105 | T659: Inkoopdagboek | U659: 46003.661 | V659: 86806.admin
... A718: 2025 | B718: 11 | C718: 45988 | D718: 87323 | E718: 2 | F718: 4220 | G718: Kleine inventaris/inrichting woningen | H718: 400 | I718: 0 | J718: 400 | K718: 526 | L718: =_xlfn.XLOOKUP(M718,Sheet6!B:B,Sheet6!A:A,"",0) -> 371 | M718: Zwingel 8B | P718: 4 | Q718: Tot Uw Dienst inboedel week 30 | R718: 07250236 | S718: I255243 | T718: Inkoopdagboek | U718: 46020.652 | V718: 86806.admin
A719: 2025 | B719: 11 | C719: 45987 | D719: 86734 | E719: 1 | F719: 4250 | G719: Gas, water en electra woningen | H719: 22.28 | I719: 0 | J719: 22.28 | K719: 518 | L719: =_xlfn.XLOOKUP(M719,Sheet6!B:B,Sheet6!A:A,"",0) -> 203 | M719: Dorpstraat 48, Aarlanderveen | P719: 4 | Q719: OASEN NV Voorschot nov, BTW 2,23, Dorpsstraat 48, 2445 AN AARLANDERVEEN/2025-11-26 3017893705202501 178937 | R719: 25400 | T719: Rabobank betaalrekening | U719: 45989.37 | V719: 86806.1002315
A720: 2025 | B720: 11 | C720: 45987 | D720: 86764 | E720: 2 | F720: 4210 | G720: Reparatie en onderhoud woningen | H720: 150 | I720: 0 | J720: 150 | K720: 353 | L720: =_xlfn.XLOOKUP(M720,Sheet6!B:B,Sheet6!A:A,"",0) -> 411 | M720: Homeflex Park Honselersdijk | P720: 4 | Q720: Homeflex boswoning 23 schade voordeur | R720: 25805898 | S720: I254962 | T720: Inkoopdagboek | U720: 45993.365 | V720: 86806.admin
A721: 2025 | B721: 11 | C721: 45987 | D721: 86765 | E721: 2 | F721: 4210 | G721: Reparatie en onderhoud woningen | H721: 1743.32 | I721: 0 | J721: 1743.32 | K721: 999 | L721: =_xlfn.XLOOKUP(M721,Sheet6!B:B,Sheet6!A:A,"",0) -> 0 | M721: Algemeen woningen | P721: 4 | Q721: AUB van Bergen Personeelsdiensten; MKS Security | R721: 250143 | S721: I254963 | T721: Inkoopdagboek | U721: 45993.365 | V721: 86806.admin
A722: 2025 | B722: 12 | C722: 45987 | D722: 86766 | E722: 2 | F722: 4200 | G722: Huur (belast) woningen | H722: 1552.05 | I722: 0 | J722: 1552.05 | K722: 293 | L722: =_xlfn.XLOOKUP(M722,Sheet6!B:B,Sheet6!A:A,"",0) -> 206 | M722: Kruiningenstraat 152 Rotterdam | P722: 6 | Q722: Lili Pogosjan | R722: RL2025-000157 | S722: I254964 | T722: Inkoopdagboek | U722: 45993.365 | V722: 86806.admin
A723: 2025 | B723: 11 | C723: 45987 | D723: 86767 | E723: 2 | F723: 4210 | G723: Reparatie en onderhoud woningen | H723: 145 | I723: 0 | J723: 145 | K723: 353 | L723: =_xlfn.XLOOKUP(M723,Sheet6!B:B,Sheet6!A:A,"",0) -> 411 | M723: Homeflex Park Honselersdijk | P723: 4 | Q723: Homeflex boswoning 51 kakkerlakken | R723: 25805895 | S723: I254965 | T723: Inkoopdagboek | U723: 45993.365 | V723: 86806.admin
A724: 2025 | B724: 11 | C724: 45986 | D724: 86576 | E724: 2 | F724: 4250 | G724: Gas, water en electra woningen | H724: 188.43 | I724: 0 | J724: 188.43 | K724: 450 | L724: =_xlfn.XLOOKUP(M724,Sheet6!B:B,Sheet6!A:A,"",0) -> 186 | M724: Woutersweg 20 | P724: 4 | Q724: Z Yilmaz OO9B005246561558 Aanvulling factuur WW20-10a.2025 Evides Wouterseweg 20/2025-11-25 | R724: 25399 | T724: Rabobank betaalrekening | U724: 46008.511 | V724: 86806.1002315
A725: 2025 | B725: 11 | C725: 45986 | D725: 86593 | E725: 2 | F725: 4250 | G725: Gas, water en electra woningen | H725: 488.07 | I725: 0 | J725: 488.07 | K725: 391 | L725: =_xlfn.XLOOKUP(M725,Sheet6!B:B,Sheet6!A:A,"",0) -> 240 | M725: Schoonegge 84 Rotterdam | P725: 99 | Q725: Direct Rendement; jaarafrekening water | R725: 25703068 | S725: I254910 | T725: Inkoopdagboek | U725: 45988.39 | V725: 86806.admin
A726: 2025 | B726: 11 | C726: 45985 | D726: 86598 | E726: 2 | F726: 4250 | G726: Gas, water en electra woningen | H726: 97.06 | I726: 0 | J726: 97.06 | K726: 263 | L726: =_xlfn.XLOOKUP(M726,Sheet6!B:B,Sheet6!A:A,"",0) -> 403 | M726: Hontenissestraat 124A Rotterdam | P726: 4 | Q726: Audax Renewables oktober | R726: 6462677 | S726: I254915 | T726: Inkoopdagboek | U726: 45988.39 | V726: 86806.admin
A727: 2025 | B727: 11 | C727: 45985 | D727: 86598 | E727: 3 | F727: 4250 | G727: Gas, water en electra woningen | H727: 0 | I727: 96.43 | J727: -96.43 | K727: 293 | L727: =_xlfn.XLOOKUP(M727,Sheet6!B:B,Sheet6!A:A,"",0) -> 206 | M727: Kruiningenstraat 152 Rotterdam | P727: 4 | Q727: Audax Renewables eindnota | R727: 6462677 | S727: I254915 | T727: Inkoopdagboek | U727: 45988.39 | V727: 86806.admin
A728: 2025 | B728: 11 | C728: 45985 | D728: 86598 | E728: 4 | F728: 4250 | G728: Gas, water en electra woningen | H728: 0 | I728: 595.56 | J728: -595.56 | K728: 334 | L728: =_xlfn.XLOOKUP(M728,Sheet6!B:B,Sheet6!A:A,"",0) -> 217 | M728: Middelrode 8 Rotterdam | P728: 4 | Q728: Audax Renewables eindnota | R728: 6462677 | S728: I254915 | T728: Inkoopdagboek | U728: 45988.39 | V728: 86806.admin
A729: 2025 | B729: 11 | C729: 45985 | D729: 86598 | E729: 5 | F729: 4250 | G729: Gas, water en electra woningen | H729: 0 | I729: 143.69 | J729: -143.69 | K729: 266 | L729: =_xlfn.XLOOKUP(M729,Sheet6!B:B,Sheet6!A:A,"",0) -> 219 | M729: Miltonstraat 55 Rotterdam | P729: 4 | Q729: Audax Renewables eindnota | R729: 6462677 | S729: I254915 | T729: Inkoopdagboek | U729: 45988.39 | V729: 86806.admin
A730: 2025 | B730: 11 | C730: 45985 | D730: 86598 | E730: 6 | F730: 4250 | G730: Gas, water en electra woningen | H730: 97.37 | I730: 0 | J730: 97.37 | K730: 332 | L730: =_xlfn.XLOOKUP(M730,Sheet6!B:B,Sheet6!A:A,"",0) -> 231 | M730: Platostraat 80 Rotterdam | P730: 4 | Q730: Audax Renewables eindnota | R730: 6462677 | S730: I254915 | T730: Inkoopdagboek | U730: 45988.39 | V730: 86806.admin
A731: 2025 | B731: 11 | C731: 45985 | D731: 86598 | E731: 7 | F731: 4250 | G731: Gas, water en electra woningen | H731: 0 | I731: 26.88 | J731: -26.88 | K731: 301 | L731: =_xlfn.XLOOKUP(M731,Sheet6!B:B,Sheet6!A:A,"",0) -> 246 | M731: Socratesstraat 168 Rotterdam | P731: 4 | Q731: Audax Renewables eindnota | R731: 6462677 | S731: I254915 | T731: Inkoopdagboek | U731: 45988.39 | V731: 86806.admin
A732: 2025 | B732: 12 | C732: 45985 | D732: 86599 | E732: 2 | F732: 4200 | G732: Huur (belast) woningen | H732: 2051.51 | I732: 0 | J732: 2051.51 | K732: 140 | L732: =_xlfn.XLOOKUP(M732,Sheet6!B:B,Sheet6!A:A,"",0) -> 156 | M732: Broersvest 74c Schiedam | P732: 6 | Q732: Bestate | R732: VF20252445 | S732: I254916 | T732: Inkoopdagboek | U732: 45988.39 | V732: 86806.admin
A733: 2025 | B733: 12 | C733: 45985 | D733: 86600 | E733: 2 | F733: 4200 | G733: Huur (belast) woningen | H733: 1776 | I733: 0 | J733: 1776 | K733: 354 | L733: =_xlfn.XLOOKUP(M733,Sheet6!B:B,Sheet6!A:A,"",0) -> 230 | M733: Pasteursingel 61B Rotterdam | P733: 6 | Q733: Direct-Housing | R733: 2025114 | S733: I254917 | T733: Inkoopdagboek | U733: 45988.39 | V733: 86806.admin
A734: 2025 | B734: 12 | C734: 45985 | D734: 86600 | E734: 3 | F734: 4250 | G734: Gas, water en electra woningen | H734: 450 | I734: 0 | J734: 450 | K734: 354 | L734: =_xlfn.XLOOKUP(M734,Sheet6!B:B,Sheet6!A:A,"",0) -> 230 | M734: Pasteursingel 61B Rotterdam | P734: 6 | Q734: Direct-Housing | R734: 2025114 | S734: I254917 | T734: Inkoopdagboek | U734: 45988.39 | V734: 86806.admin
A735: 2025 | B735: 11 | C735: 45985 | D735: 86822 | E735: 2 | F735: 4230 | G735: Internet en telefoonkosten woningen | H735: 53.72 | I735: 0 | J735: 53.72 | K735: 103 | L735: =_xlfn.XLOOKUP(M735,Sheet6!B:B,Sheet6!A:A,"",0) -> 192 | M735: Kaapsebos 11 Maasdijk | P735: 4 | Q735: Caiway december | R735: 1065048140 | S735: I255015 | T735: Inkoopdagboek | U735: 45996.349 | V735: 86806.admin
A736: 2025 | B736: 11 | C736: 45985 | D736: 86822 | E736: 3 | F736: 4230 | G736: Internet en telefoonkosten woningen | H736: 43.39 | I736: 0 | J736: 43.39 | K736: 250 | L736: =_xlfn.XLOOKUP(M736,Sheet6!B:B,Sheet6!A:A,"",0) -> 31 | M736: Hogenbanweg 331 Schiedam | P736: 4 | Q736: Caiway december | R736: 1065048140 | S736: I255015 | T736: Inkoopdagboek | U736: 45996.349 | V736: 86806.admin
... A789: 2025 | B789: 11 | C789: 45981 | D789: 87356 | E789: 2 | F789: 4220 | G789: Kleine inventaris/inrichting woningen | H789: 400 | I789: 0 | J789: 400 | K789: 526 | L789: =_xlfn.XLOOKUP(M789,Sheet6!B:B,Sheet6!A:A,"",0) -> 371 | M789: Zwingel 8B | P789: 4 | Q789: Tot Uw Dienst inboedel week 29 | R789: 07250233 | S789: I255265 | T789: Inkoopdagboek | U789: 46021.61 | V789: 86806.admin
A790: 2025 | B790: 11 | C790: 45980 | D790: 86492 | E790: 2 | F790: 4270 | G790: Kosten VvE woningen | H790: 1077.81 | I790: 0 | J790: 1077.81 | K790: 190 | L790: =_xlfn.XLOOKUP(M790,Sheet6!B:B,Sheet6!A:A,"",0) -> 470 | M790: v.d. Waalstraat 16 Vlaardingen | Q790: VVE v.d. Waalstraat 2-32 achterstanden 2024 & 2025, bijdrage nov & dec | R790: 2025-16-01 | S790: I254846 | T790: Inkoopdagboek | U790: 45982.346 | V790: 86806.admin
A791: 2025 | B791: 11 | C791: 45980 | D791: 86511 | E791: 2 | F791: 4250 | G791: Gas, water en electra woningen | H791: 0 | I791: 45.79 | J791: -45.79 | K791: 332 | L791: =_xlfn.XLOOKUP(M791,Sheet6!B:B,Sheet6!A:A,"",0) -> 231 | M791: Platostraat 80 Rotterdam | P791: 99 | Q791: Evides eindafrekening | R791: 112400158933 | S791: I254854 | T791: Inkoopdagboek | U791: 45985.388 | V791: 86806.admin
A792: 2025 | B792: 11 | C792: 45979 | D792: 86410 | E792: 3 | F792: 4250 | G792: Gas, water en electra woningen | H792: 177.92 | I792: 0 | J792: 177.92 | K792: 999 | L792: =_xlfn.XLOOKUP(M792,Sheet6!B:B,Sheet6!A:A,"",0) -> 0 | M792: Algemeen woningen | P792: 4 | Q792: CM.COM STICHTING Noord Energie: Factuur F0778005/2025-11-18 1212770086 DDPS-170537557548168790 | R792: 25394 | T792: Rabobank betaalrekening | U792: 45999.481 | V792: 86806.1002315
A793: 2025 | B793: 11 | C793: 45979 | D793: 86513 | E793: 2 | F793: 4200 | G793: Huur (belast) woningen | H793: 25 | I793: 0 | J793: 25 | K793: 353 | L793: =_xlfn.XLOOKUP(M793,Sheet6!B:B,Sheet6!A:A,"",0) -> 411 | M793: Homeflex Park Honselersdijk | P793: 4 | Q793: Homeflex vervangen blusdeken boswoning 49 | R793: 25805775 | S793: I254856 | T793: Inkoopdagboek | U793: 45985.388 | V793: 86806.admin
A794: 2025 | B794: 11 | C794: 45979 | D794: 86514 | E794: 2 | F794: 4200 | G794: Huur (belast) woningen | H794: 300 | I794: 0 | J794: 300 | K794: 353 | L794: =_xlfn.XLOOKUP(M794,Sheet6!B:B,Sheet6!A:A,"",0) -> 411 | M794: Homeflex Park Honselersdijk | P794: 4 | Q794: Homeflex vervangen deur slaapkamer 2 boswoning 65 | R794: 25805777 | S794: I254857 | T794: Inkoopdagboek | U794: 45985.388 | V794: 86806.admin
A795: 2025 | B795: 11 | C795: 45979 | D795: 86515 | E795: 2 | F795: 4200 | G795: Huur (belast) woningen | H795: 300 | I795: 0 | J795: 300 | K795: 353 | L795: =_xlfn.XLOOKUP(M795,Sheet6!B:B,Sheet6!A:A,"",0) -> 411 | M795: Homeflex Park Honselersdijk | P795: 4 | Q795: HomeFlex B.V. badkamerdeur met gat boswoning 65 | R795: 25805778 | S795: I254858 | T795: Inkoopdagboek | U795: 45985.388 | V795: 86806.admin
A796: 2025 | B796: 11 | C796: 45979 | D796: 86516 | E796: 2 | F796: 4200 | G796: Huur (belast) woningen | H796: 50 | I796: 0 | J796: 50 | K796: 353 | L796: =_xlfn.XLOOKUP(M796,Sheet6!B:B,Sheet6!A:A,"",0) -> 411 | M796: Homeflex Park Honselersdijk | P796: 4 | Q796: Homeflex vervangen sleutel slaapkamer 1 boswoning 43 | R796: 25805776 | S796: I254859 | T796: Inkoopdagboek | U796: 45985.388 | V796: 86806.admin
A797: 2025 | B797: 11 | C797: 45979 | D797: 86518 | E797: 2 | F797: 4200 | G797: Huur (belast) woningen | H797: 85 | I797: 0 | J797: 85 | K797: 353 | L797: =_xlfn.XLOOKUP(M797,Sheet6!B:B,Sheet6!A:A,"",0) -> 411 | M797: Homeflex Park Honselersdijk | P797: 4 | Q797: Homeflex vervangen rookmelder hal boswoning 21 | R797: 25805779 | S797: I254861 | T797: Inkoopdagboek | U797: 45985.388 | V797: 86806.admin
A798: 2025 | B798: 11 | C798: 45978 | D798: 86389 | E798: 2 | F798: 4250 | G798: Gas, water en electra woningen | H798: 193.05 | I798: 0 | J798: 193.05 | K798: 550 | L798: =_xlfn.XLOOKUP(M798,Sheet6!B:B,Sheet6!A:A,"",0) -> 399 | M798: Maasdijk 67, 's-gravenzande | P798: 4 | Q798: Engie Energie Nederland N.V. | R798: 708740652790 | S798: I254806 | T798: Inkoopdagboek | U798: 45980.384 | V798: 86806.admin
A799: 2025 | B799: 12 | C799: 45978 | D799: 86390 | E799: 2 | F799: 4200 | G799: Huur (belast) woningen | H799: 1400.53 | I799: 0 | J799: 1400.53 | K799: 333 | L799: =_xlfn.XLOOKUP(M799,Sheet6!B:B,Sheet6!A:A,"",0) -> 249 | M799: Tholenstraat 114 Rotterdam | P799: 6 | Q799: Jes Funding & Beheer december | R799: 0146.F25.3727 | S799: I254807 | T799: Inkoopdagboek | U799: 45980.384 | V799: 86806.admin
A800: 2025 | B800: 12 | C800: 45978 | D800: 86391 | E800: 2 | F800: 4200 | G800: Huur (belast) woningen | H800: 1400.53 | I800: 0 | J800: 1400.53 | K800: 334 | L800: =_xlfn.XLOOKUP(M800,Sheet6!B:B,Sheet6!A:A,"",0) -> 217 | M800: Middelrode 8 Rotterdam | P800: 6 | Q800: Jes Funding & Beheer december | R800: 0129.F25.3658 | S800: I254808 | T800: Inkoopdagboek | U800: 45980.384 | V800: 86806.admin
A801: 2025 | B801: 11 | C801: 45978 | D801: 86392 | E801: 2 | F801: 4250 | G801: Gas, water en electra woningen | H801: 234.76 | I801: 0 | J801: 234.76 | K801: 467 | L801: =_xlfn.XLOOKUP(M801,Sheet6!B:B,Sheet6!A:A,"",0) -> 133 | M801: Herenpad 20A, Schiedam | P801: 4 | Q801: Engie Energie Nederland N.V. | R801: 708740652789 | S801: I254809 | T801: Inkoopdagboek | U801: 45980.384 | V801: 86806.admin
A802: 2025 | B802: 11 | C802: 45978 | D802: 86393 | E802: 2 | F802: 4250 | G802: Gas, water en electra woningen | H802: 452.17 | I802: 0 | J802: 452.17 | K802: 191 | L802: =_xlfn.XLOOKUP(M802,Sheet6!B:B,Sheet6!A:A,"",0) -> 234 | M802: Rotterdamsedijk 154b Schiedam | P802: 4 | Q802: Engie Energie Nederland N.V. | R802: 708740652788 | S802: I254810 | T802: Inkoopdagboek | U802: 45980.384 | V802: 86806.admin
A803: 2025 | B803: 11 | C803: 45978 | D803: 86393 | E803: 3 | F803: 4250 | G803: Gas, water en electra woningen | H803: 332.77 | I803: 0 | J803: 332.77 | K803: 179 | L803: =_xlfn.XLOOKUP(M803,Sheet6!B:B,Sheet6!A:A,"",0) -> 242 | M803: Sint Liduinastraat 76A Schiedam | P803: 4 | Q803: Engie Energie Nederland N.V. | R803: 708740652788 | S803: I254810 | T803: Inkoopdagboek | U803: 45980.384 | V803: 86806.admin
A804: 2025 | B804: 11 | C804: 45978 | D804: 86393 | E804: 4 | F804: 4250 | G804: Gas, water en electra woningen | H804: 181.36 | I804: 0 | J804: 181.36 | K804: 315 | L804: =_xlfn.XLOOKUP(M804,Sheet6!B:B,Sheet6!A:A,"",0) -> 20 | M804: Mr. Troelstrastraat 37 Vlaardingen | P804: 4 | Q804: Engie Energie Nederland N.V. | R804: 708740652788 | S804: I254810 | T804: Inkoopdagboek | U804: 45980.384 | V804: 86806.admin
... A975: 2025 | B975: 11 | C975: 45972 | D975: 85834 | E975: 2 | F975: 4200 | G975: Huur (belast) woningen | H975: 1327 | I975: 0 | J975: 1327 | K975: 324 | L975: =_xlfn.XLOOKUP(M975,Sheet6!B:B,Sheet6!A:A,"",0) -> 239 | M975: Schoonegge 110 Rotterdam | P975: 6 | Q975: S.H.M. de Swart; november | R975: 2025-11-110 | S975: I254511 | T975: Inkoopdagboek | U975: 45959.635 | V975: 86806.admin
A976: 2025 | B976: 11 | C976: 45972 | D976: 86144 | E976: 1 | F976: 4250 | G976: Gas, water en electra woningen | H976: 102.92 | I976: 0 | J976: 102.92 | K976: 999 | L976: =_xlfn.XLOOKUP(M976,Sheet6!B:B,Sheet6!A:A,"",0) -> 0 | M976: Algemeen woningen | P976: 4 | Q976: CM.COM STICHTING Noord Energie: Factuur F0768032/2025-11-11 1210852797 DDPS-170477077455418623 | R976: 25385 | T976: Rabobank betaalrekening | U976: 45980.617 | V976: 86806.1002315
A977: 2025 | B977: 12 | C977: 45972 | D977: 86148 | E977: 2 | F977: 4200 | G977: Huur (belast) woningen | H977: 3269 | I977: 0 | J977: 3269 | K977: 239 | L977: =_xlfn.XLOOKUP(M977,Sheet6!B:B,Sheet6!A:A,"",0) -> 163 | M977: Curacaolaan 24 Vlaardingen | P977: 6 | Q977: HHS J.P. Stoel | R977: 2025-12-01 | S977: I254660 | T977: Inkoopdagboek | U977: 45973.335 | V977: 86806.admin
A978: 2025 | B978: 12 | C978: 45972 | D978: 86148 | E978: 3 | F978: 4200 | G978: Huur (belast) woningen | H978: 2336 | I978: 0 | J978: 2336 | K978: 306 | L978: =_xlfn.XLOOKUP(M978,Sheet6!B:B,Sheet6!A:A,"",0) -> 194 | M978: Keesomstraat 22 Vlaardingen | P978: 6 | Q978: HHS J.P. Stoel | R978: 2025-12-01 | S978: I254660 | T978: Inkoopdagboek | U978: 45973.335 | V978: 86806.admin
A979: 2025 | B979: 12 | C979: 45972 | D979: 86148 | E979: 4 | F979: 4200 | G979: Huur (belast) woningen | H979: 2801 | I979: 0 | J979: 2801 | K979: 240 | L979: =_xlfn.XLOOKUP(M979,Sheet6!B:B,Sheet6!A:A,"",0) -> 215 | M979: Mendelssohnplein 10C Vlaardingen | P979: 6 | Q979: HHS J.P. Stoel | R979: 2025-12-01 | S979: I254660 | T979: Inkoopdagboek | U979: 45973.335 | V979: 86806.admin
A980: 2025 | B980: 12 | C980: 45972 | D980: 86148 | E980: 5 | F980: 4200 | G980: Huur (belast) woningen | H980: 2801 | I980: 0 | J980: 2801 | K980: 245 | L980: =_xlfn.XLOOKUP(M980,Sheet6!B:B,Sheet6!A:A,"",0) -> 214 | M980: Mendelssohnplein 13D Vlaardingen | P980: 6 | Q980: HHS J.P. Stoel | R980: 2025-12-01 | S980: I254660 | T980: Inkoopdagboek | U980: 45973.335 | V980: 86806.admin
A981: 2025 | B981: 12 | C981: 45972 | D981: 86148 | E981: 6 | F981: 4200 | G981: Huur (belast) woningen | H981: 1872 | I981: 0 | J981: 1872 | K981: 283 | L981: =_xlfn.XLOOKUP(M981,Sheet6!B:B,Sheet6!A:A,"",0) -> 232 | M981: Zuidhoek 209D Rotterdam | P981: 6 | Q981: HHS J.P. Stoel | R981: 2025-12-01 | S981: I254660 | T981: Inkoopdagboek | U981: 45973.335 | V981: 86806.admin
A982: 2025 | B982: 12 | C982: 45972 | D982: 86279 | E982: 2 | F982: 4200 | G982: Huur (belast) woningen | H982: 4506 | I982: 0 | J982: 4506 | K982: 551 | L982: =_xlfn.XLOOKUP(M982,Sheet6!B:B,Sheet6!A:A,"",0) -> 382 | M982: Kwekerslaan 7, 's-Gravenzande | P982: 5 | Q982: Ryanrent BV december | R982: 25803413 | S982: I254728 | T982: Inkoopdagboek | U982: 45975.539 | V982: 86806.admin
A983: 2025 | B983: 12 | C983: 45972 | D983: 86279 | E983: 3 | F983: 4250 | G983: Gas, water en electra woningen | H983: 450 | I983: 0 | J983: 450 | K983: 551 | L983: =_xlfn.XLOOKUP(M983,Sheet6!B:B,Sheet6!A:A,"",0) -> 382 | M983: Kwekerslaan 7, 's-Gravenzande | P983: 4 | Q983: Ryanrent BV december | R983: 25803413 | S983: I254728 | T983: Inkoopdagboek | U983: 45975.539 | V983: 86806.admin
A984: 2025 | B984: 12 | C984: 45972 | D984: 86280 | E984: 2 | F984: 4200 | G984: Huur (belast) woningen | H984: 2850 | I984: 0 | J984: 2850 | K984: 542 | L984: =_xlfn.XLOOKUP(M984,Sheet6!B:B,Sheet6!A:A,"",0) -> 370 | M984: Cloosterstraat 23A, Kloosterzande | P984: 5 | Q984: Ryanrent BV december | R984: 25803337 | S984: I254729 | T984: Inkoopdagboek | U984: 45975.539 | V984: 86806.admin
A985: 2025 | B985: 12 | C985: 45972 | D985: 86281 | E985: 2 | F985: 4200 | G985: Huur (belast) woningen | H985: 4750 | I985: 0 | J985: 4750 | K985: 532 | L985: =_xlfn.XLOOKUP(M985,Sheet6!B:B,Sheet6!A:A,"",0) -> 337 | M985: Kruisweg 16, Wobrugge | P985: 5 | Q985: Ryanrent BV december | R985: 25803412 | S985: I254730 | T985: Inkoopdagboek | U985: 45975.539 | V985: 86806.admin
A986: 2025 | B986: 12 | C986: 45972 | D986: 86281 | E986: 3 | F986: 4250 | G986: Gas, water en electra woningen | H986: 600 | I986: 0 | J986: 600 | K986: 532 | L986: =_xlfn.XLOOKUP(M986,Sheet6!B:B,Sheet6!A:A,"",0) -> 337 | M986: Kruisweg 16, Wobrugge | P986: 4 | Q986: Ryanrent BV december | R986: 25803412 | S986: I254730 | T986: Inkoopdagboek | U986: 45975.539 | V986: 86806.admin
...

Sheet Sheet6
A1: object_id | B1: tradiro_adres
A2: 1 | B2: Nunspeetlaan 14
A3: 2 | B3: Allard Piersonlaan 142 Den Haag
A4: 4 | B4: Broekweg 25 Vlaardingen
A5: 9 | B5: Galgeweg 48A, 's-Gravenzande
A6: 10 | B6: Kethelweg 1B Vlaardingen
A7: 11 | B7: Kethelweg 1C Vlaardingen
A8: 15 | B8: Maasdijk 69
A9: 16 | B9: van Scorelstraat 73 Maassluis
A10: 17 | B10: G.A. Brederolaan 75B Maassluis
A11: 20 | B11: Mr. Troelstrastraat 37 Vlaardingen
A12: 21 | B12: Vaartweg 106C Vlaardingen
A13: 22 | B13: 2e van Leyden Gaelstraat 6, Vlaardingen
... A237: 488 | B237: Goghlaan 36, Roosendaal
B238: Algemeen woningen
