Workbook

Sheet relaties_export_2026-01-12_1609
A1: id | B1: naam | C1: type | D1: contactpersoon | E1: email | F1: telefoonnummer | G1: adres | H1: postcode | I1: plaats | J1: land | K1: kvk_nummer | L1: btw_nummer | M1: iban | N1: is_klant | O1: is_leverancier | P1: is_eigenaar | Q1: marge_max | R1: created_at
A2: 1 | B2: M.C. Claassen | C2: bureau | E2: mcc.2006@hotmail.com | G2: Camino Viejo de Valencia 8 1e izq | J2: Nederland | M2: NL05 RABO 0383 7113 04 | N2: 1 | O2: 0 | P2: 0 | R2: 46034.625
A3: 2 | B3: Bright Home Rentals B.V. | C3: bureau | E3: administratie@brighthomerentals.nl | G3: Ebweg 73 | I3: BARENDRECHT | J3: Nederland | K3: 66838452.0 | M3: NL62 RABO 0312 8075 46 | N3: 1 | O3: 1 | P3: 0 | R3: 46034.625
A4: 3 | B4: T.A. van der Burg | C4: bureau | E4: vanderburgron@gmail.com | G4: Heeswijk 113 | I4: Montfoort | J4: Nederland | K4: 53093623.0 | M4: NL67 INGB 0795 2367 27 | N4: 1 | O4: 1 | P4: 0 | R4: 46034.625
A5: 4 | B5: Randstad Wonen | C5: bureau | E5: info@randstadwonen.nl | N5: 1 | O5: 0 | P5: 0 | R5: 46034.625
A6: 5 | B6: Ruva Vastgoed B.V. | C6: zakelijk | E6: beheer@ruvavastgoed.nl | G6: Burgemeester van Campenhoutstraat 2 | I6: MADE | J6: Nederland | K6: 52768384.0 | M6: NL93 RABO 0116 6871 50 | N6: 1 | O6: 1 | P6: 0 | R6: 46034.625
A7: 6 | B7: GOTI Verhuur B.V. | C7: zakelijk | E7: info@gotiverhuur.nl | G7: Noorderhaven 63 | I7: Harlingen | J7: Nederland | K7: 1098148.0 | M7: NL94 INGB 0665 1314 02 | N7: 1 | O7: 1 | P7: 0 | R7: 46034.625
A8: 7 | B8: Maatschap J.W. Meershoek & W.M. Meershoek | C8: zakelijk | E8: j.meershoek1@chello.nl | G8: Grootzand 11 | I8: HOEK VAN HOLLAND | J8: Nederland | M8: NL37 ABNA 0406 1514 07 | N8: 1 | O8: 1 | P8: 0 | R8: 46034.625
A9: 8 | B9: Joost de Jong Holding B.V. | C9: particulier | E9: jcdejong@aol.nl | G9: Wetterkrite 49 | I9: Goutum | J9: Nederland | K9: 63936070.0 | M9: NL70 INGB 0007 1264 17 | N9: 1 | O9: 1 | P9: 0 | R9: 46034.625
A10: 9 | B10: H.C. van Os - Remeeus | C10: particulier | E10: marcel@cohousingnederland.nl | G10: Iependaal 19 | I10: ROZENBURG | J10: Nederland | M10: NL60 RABO 0369 8896 57 | N10: 1 | O10: 1 | P10: 0 | R10: 46034.625
A11: 10 | B11: Klaas Bos | C11: particulier | E11: klaas.bos@example.com | N11: 1 | O11: 0 | P11: 0 | R11: 46034.625
A12: 11 | B12: Finest Housing B.V. | C12: particulier | E12: backoffice@finesthousing.nl | G12: John F. Kennedylaan 246 | I12: PANNINGEN | J12: Nederland | K12: 75080060.0 | M12: NL57 RABO 0342 8897 61 | N12: 1 | O12: 1 | P12: 0 | R12: 46034.625
A13: 12 | B13: M.J. van Os | C13: particulier | E13: marcelvanos0@gmail.com | G13: Burg Letteweg 31 | I13: OOSTVOORNE | J13: Nederland | M13: NL21 INGB 0664 8003 94 | N13: 1 | O13: 0 | P13: 0 | R13: 46034.625
A14: 13 | B14: United Homes B.V. | C14: particulier | E14: administratie@unitedhomes.eu | G14: Van Vollenhovenstraat 10 | I14: Rotterdam | J14: Nederland | M14: NL85 RABO 0131 3612 60 | N14: 1 | O14: 1 | P14: 0 | R14: 46034.625
A15: 14 | B15: Edy Comert BV | C15: particulier | E15: office@edycom.ro | G15: Bergerweg 61 | I15: Sittard | J15: Nederland | K15: 51124769.0 | N15: 1 | O15: 0 | P15: 0 | R15: 46034.625
A16: 15 | B16: Flexcraft SSC BV | C16: particulier | E16: huisvesting@flexcraft.eu | G16: Einsteinstraat 9 B | I16: Gorinchem | J16: Nederland | K16: 67541690.0 | N16: 1 | O16: 0 | P16: 0 | R16: 46034.625
A17: 16 | B17: Vaktec BV | C17: particulier | E17: j.deboer@vaktec.nl | G17: Kielerbocht 29A | I17: Groningen | J17: Nederland | N17: 1 | O17: 0 | P17: 0 | R17: 46034.625
A18: 17 | B18: Tradiro Services B.V. | C18: particulier | E18: facturen@tradiro.nl | G18: Honderdland 960 | I18: Maasdijk | J18: Nederland | K18: 59979135.0 | M18: NL05 RABO 0154 0739 89 | N18: 1 | O18: 1 | P18: 0 | R18: 46034.625
A19: 18 | B19: Sagius Uitzenders B.V. | C19: particulier | E19: facturen@sagiusuitzenders.nl | G19: Bleiswijkseweg 43 | I19: ZOETERMEER | J19: Nederland | M19: NL41 RABO 0145 8741 25 | N19: 1 | O19: 0 | P19: 0 | R19: 46034.625
A20: 19 | B20: Groene Hart Service Detachering B.V. | C20: bureau | E20: facturatie@groenehartservice.nl | G20: Fokkerstraat 5 | I20: REEUWIJK | J20: Nederland | M20: NL41 INGB 0650 5389 00 | N20: 1 | O20: 1 | P20: 0 | R20: 46034.625
A21: 20 | B21: S. Dolstra | C21: particulier | E21: dolstra@yahoo.com | G21: Molenweg 10 a | I21: KRUISLAND | J21: Nederland | M21: NL51 RABO 0194 3333 02 | N21: 1 | O21: 1 | P21: 0 | R21: 46034.625
A22: 21 | B22: The Housing Guild B.V. | C22: particulier | E22: r.nijboer@degildegroep.nl | G22: Blankenstein 136 | I22: MEPPEL | J22: Nederland | M22: NL81 ABNA 0823 0941 54 | N22: 1 | O22: 0 | P22: 0 | R22: 46034.625
A23: 22 | B23: J. Hermans | C23: particulier | E23: frankjolanda@online.nl | G23: Meedhuizerweg 5 | I23: MEEDHUIZEN | J23: Nederland | M23: NL92 RABO 0154 3249 14 | N23: 1 | O23: 0 | P23: 0 | R23: 46034.625
A24: 23 | B24: S. Bakker OPH Verhuur | C24: particulier | G24: Hoofdweg 7 | I24: Hitzum | J24: Nederland | M24: NL85 INGB 0102 8401 21 | N24: 1 | O24: 1 | P24: 0 | R24: 46034.625
A25: 24 | B25: V.O.F. Groepsaccommodaties Drenthe | C25: particulier | G25: Westeind 12 | I25: Norg | J25: Nederland | K25: 67963692.0 | N25: 1 | O25: 0 | P25: 0 | R25: 46034.625
A26: 25 | B26: O.J.P Soc Constru√ß√µes | C26: particulier | E26: romeu.ferreira@ojp.pt | G26: Rua Quinta da Tapada 20 R C | J26: Portugal | M26: PT50 0010 0000 5582 3720 0019 1 | N26: 1 | O26: 0 | P26: 0 | R26: 46034.625
A27: 26 | B27: Vivir Wonen | C27: particulier | E27: info@vivirwonen.nl | G27: Postbus 811 | I27: Gorinchem | J27: Nederland | K27: 58693807.0 | M27: NL52 RABO 0106 0699 77 | N27: 1 | O27: 1 | P27: 0 | R27: 46034.625
A28: 27 | B28: Global Accomodation Solutions (Incassobureau) | C28: particulier | E28: info@globalaccommodation.solutions | G28: Jan Pietersz. Coenstraat 7 | I28: 'S-GRAVENHAGE | J28: Nederland | K28: 78155797.0 | M28: NL76 INGB 0008 9801 73 | N28: 1 | O28: 0 | P28: 0 | R28: 46034.625
A29: 28 | B29: Alis Vastgoed B.V. | C29: particulier | E29: rifat@prokonak.nl | G29: Fruitweg 25 | I29: 'S-GRAVENHAGE | J29: Nederland | N29: 1 | O29: 1 | P29: 0 | R29: 46034.625
A30: 29 | B30: Resource One B.V. | C30: particulier | E30: info@qualityhomerentals.nl | G30: Nobelstraat 76 | I30: BRIELLE | J30: Nederland | K30: 74887068.0 | M30: NL95 KNAB 0259 2344 78 | N30: 1 | O30: 1 | P30: 0 | R30: 46034.625
A31: 30 | B31: Team Home Rentals B.V. | C31: particulier | E31: administratie@teamhomerentals.nl | G31: Dopplerweg1 | I31: Spijkenisse | J31: Nederland | K31: 71523561.0 | M31: NL61 RABO 0330 2631 02 | N31: 1 | O31: 1 | P31: 0 | R31: 46034.625
A32: 31 | B32: Direct Rendement B.V. | C32: particulier | E32: info@directrendement.nl | G32: Kortedijk 57 | I32: VLAARDINGEN | J32: Nederland | K32: 72724382.0 | M32: NL09 INGB 0008 5322 69 | N32: 1 | O32: 1 | P32: 0 | R32: 46034.625
A33: 32 | B33: Interim Jobs B.V. | C33: particulier | E33: e.ozel@interimjobs.nl | G33: Vlierwerf 3 d | I33: ROOSENDAAL | J33: Nederland | K33: 67044360.0 | M33: NL83 RABO 0313 5561 05 | N33: 1 | O33: 1 | P33: 0 | R33: 46034.625
A34: 33 | B34: L.M. Schilstra | C34: particulier | G34: Adres onbekend | J34: Nederland | M34: NL17 RABO 0158 8674 16 | N34: 1 | O34: 1 | P34: 0 | R34: 46034.625
A35: 34 | B35: Employ | C35: particulier | N35: 1 | O35: 0 | P35: 0 | R35: 46034.625
A36: 35 | B36: Best@Work B.V. | C36: particulier | E36: info@bestatwork.nl | G36: Industrieweg 74-76 | I36: WAALWIJK | J36: Nederland | K36: 74210025.0 | N36: 1 | O36: 0 | P36: 0 | R36: 46034.625
A37: 36 | B37: WS Detachering BV | C37: particulier | E37: administratie@workstead.nl | G37: Barneveldsestraat 44 | I37: Renswoude | J37: Nederland | N37: 1 | O37: 0 | P37: 0 | R37: 46034.625
A38: 37 | B38: Flowerhill B.V. | C38: bureau | E38: jb.heuvel@quicknet.nl | G38: Prinses Marijkestraat 36 | I38: Andijk | J38: Nederland | K38: 69891478.0 | N38: 1 | O38: 0 | P38: 0 | R38: 46034.625
A39: 38 | B39: J.D. Jongsma | C39: particulier | E39: jand.jongsma@icloud.com | G39: Tamboerstraat 16 | I39: LOON OP ZAND | J39: Nederland | M39: NL88 INGB 0794 4823 68 | N39: 1 | O39: 0 | P39: 0 | R39: 46034.625
A40: 39 | B40: Multiserwis SP z o.o. | C40: particulier | E40: karol.pastucha@bilfinger.com | G40: ul. Prudnicka 40 | I40: Krapkowise | J40: Polen | K40: 120630.0 | M40: DE81 7007 0010 0206 0184 00 | N40: 1 | O40: 0 | P40: 0 | R40: 46034.625
A41: 40 | B41: A.W.N. Alkemade | C41: particulier | E41: melkveebedrijfalkemade@kpnmail.nl | G41: Laan van Pluymestein 36 | I41: WASSENAAR | J41: Nederland | M41: NL80 ABNA 0608 8189 41 | N41: 1 | O41: 0 | P41: 0 | R41: 46034.625
A42: 41 | B42: HBBwonen.nu B.V. | C42: particulier | E42: info@hbbwonen.nu | G42: Stationsstraat 13 | I42: ROSMALEN | J42: Nederland | K42: 70532222.0 | M42: NL79 INGB 0006 8359 34 | N42: 1 | O42: 1 | P42: 0 | R42: 46034.625
A43: 42 | B43: S. Meijer | C43: particulier | E43: siebmeijer@msn.com | G43: Zevenhuizen 2 | I43: FRANEKER | J43: Nederland | M43: NL76 INGB 0679 9560 42 | N43: 1 | O43: 1 | P43: 0 | R43: 46034.625
A44: 43 | B44: De Pagter Vastgoed B.V. | C44: particulier | E44: info@depagtervastgoed.nl | G44: Molenwater 2 | I44: MIDDELBURG | J44: Nederland | K44: 22033473.0 | M44: NL91 INGB 0650 5095 79 | N44: 1 | O44: 1 | P44: 0 | R44: 46034.625
A45: 44 | B45: Marco is Vastgoed B.V. | C45: particulier | E45: marco@dewitteaap.nl | G45: Lombardkade 29 C | I45: ROTTERDAM | J45: Nederland | M45: NL33 RABO 0349 6595 32 | N45: 1 | O45: 1 | P45: 0 | R45: 46034.625
A46: 45 | B46: Kiose Yacht Finishing | C46: particulier | E46: metinkiose@yahoo.co.uk | G46: Kiou 6 | I46: Keatsini Athens | J46: Griekenland | N46: 1 | O46: 0 | P46: 0 | R46: 46034.625
A47: 46 | B47: European Business Brokers | C47: particulier | E47: daniel@reppz.com | G47: Dr. Duyvendakhof 32 | I47: Oud Beijerland | J47: Nederland | N47: 1 | O47: 0 | P47: 0 | R47: 46034.625
A48: 47 | B48: Global Expatriate Services SL | C48: particulier | E48: lodewijk@globexs.com | G48: Calle Del Pintor Salvador Abril 35 | I48: Valencia | J48: Spanje | M48: ES59 0049 0621 1228 1065 0833 | N48: 1 | O48: 1 | P48: 0 | R48: 46034.625
A49: 48 | B49: Light Personeelsdiensten | C49: particulier | N49: 1 | O49: 0 | P49: 0 | R49: 46034.625
A50: 49 | B50: Pol Flex B.V. | C50: bureau | E50: administratie@polflexbv.nl | G50: Ouddeelstraat 7 a | I50: LEEUWARDEN | J50: Nederland | K50: 73251127.0 | M50: NL22 SNSB 0267 9799 16 | N50: 1 | O50: 0 | P50: 0 | R50: 46034.625
A51: 50 | B51: I.I. Bhaggoe | C51: particulier | G51: Jan Campertlaan 8 | I51: SPIJKENISSE | J51: Nederland | M51: NL56 INGB 0671 6016 95 | N51: 1 | O51: 0 | P51: 0 | R51: 46034.625
A52: 51 | B52: De Borgmeren B.V. | C52: particulier | E52: borgmeren@live.nl | G52: Hoofdweg 34 | I52: SCHARMER | J52: Nederland | M52: NL54 RABO 0366 9535 75 | N52: 1 | O52: 1 | P52: 0 | R52: 46034.625
A53: 52 | B53: van Heeswijk | C53: particulier | E53: verhuur@reham.nl | G53: Adres onbekend | J53: Nederland | M53: NL32 INGB 0007 1086 71 | N53: 1 | O53: 0 | P53: 0 | R53: 46034.625
A54: 53 | B54: Business Housing | C54: particulier | E54: eliane@zamens.nl | G54: Oosteinde 26 | I54: Oud Alblas | J54: Nederland | K54: 69861846.0 | M54: NL50 RABO 0323 5939 68 | N54: 1 | O54: 1 | P54: 0 | R54: 46034.625
A55: 54 | B55: Finishing De Luxe GmbH | C55: particulier | E55: katja.korotchenko@finishing-deluxe.com | G55: Burgermeister Schade Strasse 20 | I55: SCHONKIRCHEN | J55: Nederland | N55: 1 | O55: 0 | P55: 0 | R55: 46034.625
A56: 55 | B56: Zeeland Housing Facility B.V. | C56: particulier | E56: info@housingzeeland.nl | G56: Prinsenhove 168 | I56: Middelburg | J56: Nederland | K56: 75463547.0 | N56: 1 | O56: 0 | P56: 0 | R56: 46034.625
A57: 56 | B57: MvB Services | C57: particulier | E57: driver@meindertvanbuuren.com | G57: Windgatseweg 2 | I57: ROCKANJE | J57: Nederland | K57: 70892865.0 | M57: NL70 RABO 0327 4853 45 | N57: 1 | O57: 1 | P57: 0 | R57: 46034.625
A58: 57 | B58: Vleesbewerking van der Pijl B.V. | C58: particulier | E58: facturen@vleesbewerkingvanderpijl.nl | G58: Cypresbaan 6a | I58: CAPELLE AAN DEN IJSSEL | J58: Nederland | K58: 70437769.0 | N58: 1 | O58: 0 | P58: 0 | R58: 46034.625
A59: 58 | B59: City Estate B.V. | C59: particulier | E59: huren@cityestate.nl | G59: Oudegracht 312 | I59: UTRECHT | J59: Nederland | K59: 77525027.0 | M59: NL95 INGB 0006 7773 49 | N59: 1 | O59: 1 | P59: 0 | R59: 46034.625
A60: 59 | B60: A.Y. Nicolai | C60: particulier | E60: famnicolai@hotmail.com | G60: De Setangel 14 | I60: GROU | J60: Nederland | M60: NL44 INGB 0006 4538 99 | N60: 1 | O60: 0 | P60: 0 | R60: 46034.625
A61: 60 | B61: M. Poel | C61: bureau | E61: monique_pruijsen@hotmail.com | G61: Esdoornlaan 64 | I61: ROZENBURG | J61: Nederland | M61: NL96 RABO 0138 5699 08 | N61: 1 | O61: 1 | P61: 0 | R61: 46034.625
A62: 61 | B62: Space4U B.V. | C62: particulier | E62: info@space4ubv.nl | G62: Kastelenplein 4 | I62: EINDHOVEN | J62: Nederland | K62: 77266099.0 | M62: NL44 INGB 0007 4063 42 | N62: 1 | O62: 1 | P62: 0 | R62: 46034.625
A63: 62 | B63: S. Marinus (zie 50200) | C63: particulier | G63: 't Deel 29 | I63: Drachten | J63: Nederland | M63: NL16 RABO 0348 0756 34 | N63: 1 | O63: 0 | P63: 0 | R63: 46034.625
A64: 63 | B64: J. van Heeswijk | C64: particulier | E64: verhuur@reham.nl | G64: Kortrijksesteenweg 1004 | J64: Nederland | M64: NL32 INGB 0007 1086 71 | N64: 1 | O64: 0 | P64: 0 | R64: 46034.625
A65: 64 | B65: V.B.A. Beheer B.V. | C65: particulier | E65: vbabv@outlook.com | G65: Ouddeelstraat 9 | I65: Leeuwarden | J65: Nederland | K65: 60392525.0 | M65: NL72 ABNA 0508 0206 62 | N65: 1 | O65: 1 | P65: 0 | R65: 46034.625
A66: 65 | B66: Quality Home Rentals | C66: particulier | E66: info@qualityhomerentals.nl | G66: Vlinderslag 4 | I66: OOSTVOORNE | J66: Nederland | K66: 76436357.0 | M66: NL19 KNAB 0259 8013 56 | N66: 1 | O66: 1 | P66: 0 | R66: 46034.625
A67: 66 | B67: P. Gryspeerdt | C67: particulier | E67: verhuur@reham.nl | G67: Klimopstraat 1 | J67: Nederland | M67: NL32 INGB 0007 1086 71 | N67: 1 | O67: 0 | P67: 0 | R67: 46034.625
A68: 67 | B68: A. Verschueren | C68: particulier | E68: verhuur@reham.nl | G68: Mangelbeekstraat 1 | J68: Nederland | M68: NL32 INGB 0007 1086 71 | N68: 1 | O68: 0 | P68: 0 | R68: 46034.625
A69: 68 | B69: Langweer Vastgoed B.V. | C69: particulier | E69: jan@wassenaarvastgoed.nl | G69: Buorren 15 | I69: LANGWEER | J69: Nederland | M69: NL64 RABO 0312 3429 77 | N69: 1 | O69: 1 | P69: 0 | R69: 46034.625
A70: 69 | B70: A. Dzaka | C70: bureau | E70: adisa-kemo@hotmail.com | G70: Merwedepad 29 | I70: Rozenburg ZH | J70: Nederland | N70: 1 | O70: 0 | P70: 0 | R70: 46034.625
A71: 70 | B71: M.A. Pronk | C71: particulier | E71: mp64@hotmail.com | G71: Oosteinde 102 | I71: BERKHOUT | J71: Nederland | M71: NL31 INGB 0799 7542 77 | N71: 1 | O71: 0 | P71: 0 | R71: 46034.625
A72: 71 | B72: HJC Service | C72: particulier | E72: benhanan010@gmail.com | G72: Maarland Zuidzijde 27 | I72: Brielle | J72: Nederland | K72: 71585737.0 | M72: NL78 SNSB 0786 0245 77 | N72: 1 | O72: 1 | P72: 0 | R72: 46034.625
A73: 72 | B73: StayProjects Group Netherlands B.V. | C73: particulier | E73: sametkaya@staysolutions.com | G73: Bijdorpplein 9 - 11 | I73: BARENDRECHT | J73: Nederland | K73: 20160652.0 | M73: NL34 RABO 0152 5813 16 | N73: 1 | O73: 1 | P73: 0 | R73: 46034.625
A74: 73 | B74: Vast-PS Housing | C74: bureau | E74: info@vast-ps.nl | G74: Verlaatsweg 33 | I74: SPIERDIJK | J74: Nederland | M74: NL79 RABO 0335 3714 77 | N74: 1 | O74: 1 | P74: 0 | R74: 46034.625
A75: 74 | B75: Edy Comert SRL | C75: particulier | E75: office@edycom.ro | G75: Strada Rapsodiei 47 | I75: Constanta | J75: Roemeni√´ | M75: RO73 BACX 0000 0008 7210 3014 | N75: 1 | O75: 0 | P75: 0 | R75: 46034.625
A76: 75 | B76: Frysl√¢n Homes | C76: bureau | E76: backoffice@fryslanhomes.frl | G76: Struikheide 6 | I76: Heerenveen | J76: Nederland | K76: 63969823.0 | M76: NL44 INGB 0006 4538 99 | N76: 1 | O76: 1 | P76: 0 | R76: 46034.625
A77: 76 | B77: K-Power Netherlands Kft | C77: particulier | G77: Wetering Oost 48 | I77: Wetering | J77: Nederland | N77: 1 | O77: 0 | P77: 0 | R77: 46034.625
A78: 77 | B78: A.P.W. Koedooder | C78: particulier | E78: apwkoedooder@gmail.com | G78: Isaac Beeckmanhof 1 | I78: ROTTERDAM | J78: Nederland | M78: NL21 INGB 0006 8135 04 | N78: 1 | O78: 1 | P78: 0 | R78: 46034.625
A79: 78 | B79: Gridin's Group LT | C79: particulier | E79: a.kozlova@gridins.com | G79: Tomo g. 20-2 | I79: Klaipeda | J79: Litouwen | N79: 1 | O79: 0 | P79: 0 | R79: 46034.625
A80: 79 | B80: L. Keizer | C80: zakelijk | E80: leendertkeizer@hotmail.com | G80: Rettichlaan 8 | I80: 'S-GRAVENZANDE | J80: Nederland | M80: NL16 INGB 0675 4147 09 | N80: 1 | O80: 1 | P80: 0 | R80: 46034.625
A81: 80 | B81: Flex House Renting B.V. | C81: zakelijk | E81: e.ozel@interimjobs.nl | G81: Vlierwerf 3 d | I81: ROOSENDAAL | J81: Nederland | K81: 78002222.0 | M81: NL35 INGB 0008 0442 79 | N81: 1 | O81: 0 | P81: 0 | R81: 46034.625
A82: 81 | B82: T.A. Middelkoop | C82: zakelijk | E82: tunny.10@hotmail.com | G82: Vlietskade 9015 | I82: ARKEL | J82: Nederland | M82: NL70 RABO 0397 2182 57 | N82: 1 | O82: 1 | P82: 0 | R82: 46034.625
A83: 82 | B83: Crown Uitzendgroep | C83: zakelijk | N83: 1 | O83: 0 | P83: 0 | R83: 46034.625
A84: 83 | B84: UAB Toromega | C84: zakelijk | N84: 1 | O84: 0 | P84: 0 | R84: 46034.625
A85: 84 | B85: Orange Investments Group | C85: zakelijk | N85: 1 | O85: 0 | P85: 0 | R85: 46034.625
A86: 85 | B86: 4 Homes B.V. | C86: zakelijk | N86: 1 | O86: 0 | P86: 0 | R86: 46034.625
A87: 86 | B87: Eastmen | C87: zakelijk | N87: 1 | O87: 0 | P87: 0 | R87: 46034.625
A88: 87 | B88: Industrial Technical Services Srl | C88: zakelijk | N88: 1 | O88: 0 | P88: 0 | R88: 46034.625
A89: 88 | B89: Housing en Transport Facilities BV | C89: zakelijk | N89: 1 | O89: 0 | P89: 0 | R89: 46034.625
A90: 89 | B90: Stay21 | C90: zakelijk | N90: 1 | O90: 0 | P90: 0 | R90: 46034.625
A91: 90 | B91: Marseille Bax Van Maanen Rotterdamse account. | C91: particulier | G91: Molenweg 11-13 | I91: Rozenburg | J91: Nederland | K91: 24220887.0 | M91: NL39 ABNA 0800 7349 55 | N91: 1 | O91: 1 | P91: 0 | R91: 46034.625
A92: 91 | B92: Autobedrijf W. Bronder | C92: particulier | E92: k.bronder@outlook.com | G92: Boomweg 17 | I92: Rockanje | J92: Nederland | K92: 24234431.0 | M92: NL22 RABO 0350 2406 63 | N92: 1 | O92: 1 | P92: 0 | R92: 46034.625
A93: 92 | B93: DNACC B.V. / Rolbakkie | C93: particulier | G93: Aziehavenweg 18 | I93: Amsterdam | J93: Nederland | K93: 37155744.0 | M93: NL94 INGB 0007 2004 81 | N93: 1 | O93: 1 | P93: 0 | R93: 46034.625
A94: 93 | B94: Dynalinx B.V. | C94: particulier | G94: Pascalweg 15 | I94: Hellevoetsluis | J94: Nederland | K94: 6092423.0 | M94: NL70 RABO 0351 6436 80 | N94: 1 | O94: 1 | P94: 0 | R94: 46034.625
A95: 94 | B95: Furniture Lease | C95: particulier | G95: Sint Walburg 20 b | I95: Zetten | J95: Nederland | K95: 73701297.0 | M95: NL67 RABO 0133 9564 31 | N95: 1 | O95: 1 | P95: 0 | R95: 46034.625
A96: 95 | B96: Hiltermann Lease B.V. | C96: particulier | G96: Diamantlaan 6 | I96: Hoofddorp | J96: Nederland | K96: 34216188.0 | M96: NL32 ABNA 0633 0060 76 | N96: 1 | O96: 1 | P96: 0 | R96: 46034.625
A97: 96 | B97: Kadaster | C97: particulier | G97: George Hintzenweg 77 | I97: Rotterdam | J97: Nederland | K97: 8215619.0 | M97: NL42 INGB 0006 3919 52 | N97: 1 | O97: 1 | P97: 0 | R97: 46034.625
A98: 97 | B98: Keypro B.V. | C98: particulier | G98: Suikerlaan 15 | I98: Groningen | J98: Nederland | K98: 52688844.0 | M98: NL76 INGB 0007 4343 81 | N98: 1 | O98: 1 | P98: 0 | R98: 46034.625
A99: 98 | B99: Lago Personeelshuisvesting B.V. | C99: particulier | E99: facturen@lagopersoneelshuisvesting.nl | G99: Kwinkweerd 100A | I99: Lochem | J99: Nederland | K99: 67649815.0 | N99: 1 | O99: 1 | P99: 0 | R99: 46034.625
A100: 99 | B100: TOTAL Nederland N.V. | C100: particulier | G100: Bezuidenhoutseweg 273 | I100: 's-Gravenhage | J100: Nederland | K100: 24106171.0 | M100: NL83 DEUT 0265 2210 48 | N100: 1 | O100: 1 | P100: 0 | R100: 46034.625
...

Sheet Sheet1
A1: Overzicht woningen RyanRent BV
C2: Facturatie | D2: Adres | E2: Postcode | F2: Plaats | G2: Aant. pers. | H2: Aant. SK | I2: Startdatum | J2: Einddatum Min. Per. | K2: Opgezegd | L2: Huurder | M2: relatie_id | N2: relatie | O2: Mutatie Daan | P2: Marge | Q2: Verhuur INCL. BTW | R2: Verhuur EXCL. BTW | S2: Verhuur PPPW | T2: Kale verhuurprijs | U2: Voorschot GWE | V2: Overige kosten | W2: Afval | Y2: Eigenaar | Z2: relatie_id | AA2: relatie | AB2: Telefoonnummer | AC2: Inhuur INCL BTW | AD2: Inhuur EXCL BTW | AE2: Kale inhuurprijs | AF2: Inhuur PPPW | AG2: Startdatum | AH2: Einddatum Min. Per. | AI2: HOVK | AJ2: minimale duur | AK2: start | AL2: eind | AM2: opzegtermijn | AN2: opmerking | AO2: Rechtsvorm | AR2: VHOVK | AS2: minimale duur | AT2: start | AU2: eind | AV2: Opzegtermijn | AW2: rechtsvorm
B3: =_xlfn.XLOOKUP(D3,'[1]Sleutelplan nieuw'!B:B,'[1]Sleutelplan nieuw'!A:A,"",2) -> 0388 | C3: Factuur | D3: 1e Middellandstraat 104A | E3: 3021BH | F3: Rotterdam | G3: 2 | H3: 2 | I3: 45961 | J3: 46112 | L3: Bakker | M3: =_xlfn.XLOOKUP(L3,'relaties_export_2026-01-12_1609'!B:B,'relaties_export_2026-01-12_1609'!A:A,"",3) -> 23 | N3: =_xlfn.XLOOKUP(M3,'relaties_export_2026-01-12_1609'!A:A,'relaties_export_2026-01-12_1609'!B:B,"",3) -> S. Bakker OPH Verhuur | P3: =R3-U3-V3-AD3 -> 500 | Q3: =T3*1.09+U3*1.21 -> 1986 | R3: =T3+U3 -> 1800 | S3: =(R3/G3)/4.33333 -> 207.69247 | T3: 1600 | U3: 200 | V3: 0 | Y3: Orange Invesments Group | Z3: =_xlfn.XLOOKUP(Y3,'relaties_export_2026-01-12_1609'!B:B,'relaties_export_2026-01-12_1609'!A:A,"",3) -> 751 | AA3: =_xlfn.XLOOKUP(Z3,'relaties_export_2026-01-12_1609'!A:A,'relaties_export_2026-01-12_1609'!B:B,"",3) -> Orange Invesments Group | AB3: 0174-504792 | AC3: 1100 | AD3: 1100 | AE3: 1100 | AF3: =(AD3/G3)/4.33333 -> 126.92317 | AG3: 45961 | AH3: 46112
A4: 1 | B4: =_xlfn.XLOOKUP(D4,'[1]Sleutelplan nieuw'!B:B,'[1]Sleutelplan nieuw'!A:A,"",2) -> 0022 | C4: Factuur | D4: 2e van Leydengaelstraat 6 | E4: 3134 LL | F4: Vlaardingen | G4: 8 | H4: 4 | I4: 44958 | J4: 45323 | L4: Tradiro | M4: =_xlfn.XLOOKUP(L4,'relaties_export_2026-01-12_1609'!B:B,'relaties_export_2026-01-12_1609'!A:A,"",3) -> 17 | N4: =_xlfn.XLOOKUP(M4,'relaties_export_2026-01-12_1609'!A:A,'relaties_export_2026-01-12_1609'!B:B,"",3) -> Tradiro Services B.V. | P4: =R4-U4-V4-AD4 -> 285.56 | Q4: =T4*1.09+U4*1.21 -> 3194.3104 | R4: =T4+U4 -> 2930.56 | S4: =(R4/G4)/4.33333 -> 84.53545 | T4: 2930.56 | U4: 0 | V4: 0 | Y4: Verknocht | Z4: =_xlfn.XLOOKUP(Y4,'relaties_export_2026-01-12_1609'!B:B,'relaties_export_2026-01-12_1609'!A:A,"",3) -> 574 | AA4: =_xlfn.XLOOKUP(Z4,'relaties_export_2026-01-12_1609'!A:A,'relaties_export_2026-01-12_1609'!B:B,"",3) -> Verknocht | AC4: 2645 | AD4: 2645 | AE4: 2645 | AF4: =(AD4/G4)/4.33333 -> 76.298136 | AG4: 44927 | AH4: 45292
B5: =_xlfn.XLOOKUP(D5,'[1]Sleutelplan nieuw'!B:B,'[1]Sleutelplan nieuw'!A:A,"",2) -> 0148 | C5: DS | D5: 2e Maasbosstraat 2 a | E5: 3134XJ | F5: Vlaardingen | L5: Tradiro | M5: =_xlfn.XLOOKUP(L5,'relaties_export_2026-01-12_1609'!B:B,'relaties_export_2026-01-12_1609'!A:A,"",3) -> 17 | N5: =_xlfn.XLOOKUP(M5,'relaties_export_2026-01-12_1609'!A:A,'relaties_export_2026-01-12_1609'!B:B,"",3) -> Tradiro Services B.V. | Y5: A.J. Maat | Z5: 306 | AA5: =_xlfn.XLOOKUP(Z5,'relaties_export_2026-01-12_1609'!A:A,'relaties_export_2026-01-12_1609'!B:B,"",3) -> Jacco Maat | AC5: 1570.24 | AD5: 1570.24 | AE5: 1570.24
B6: =_xlfn.XLOOKUP(D6,'[1]Sleutelplan nieuw'!B:B,'[1]Sleutelplan nieuw'!A:A,"",2) -> 0149 | C6: DS | D6: 2e Maasbosstraat 2 b | E6: 3134XJ | F6: Vlaardingen | L6: Tradiro | M6: =_xlfn.XLOOKUP(L6,'relaties_export_2026-01-12_1609'!B:B,'relaties_export_2026-01-12_1609'!A:A,"",3) -> 17 | N6: =_xlfn.XLOOKUP(M6,'relaties_export_2026-01-12_1609'!A:A,'relaties_export_2026-01-12_1609'!B:B,"",3) -> Tradiro Services B.V. | Y6: A.J. Maat | Z6: 306 | AA6: =_xlfn.XLOOKUP(Z6,'relaties_export_2026-01-12_1609'!A:A,'relaties_export_2026-01-12_1609'!B:B,"",3) -> Jacco Maat | AC6: 1570.24 | AD6: 1570.24 | AE6: 1570.24
B7: =_xlfn.XLOOKUP(D7,'[1]Sleutelplan nieuw'!B:B,'[1]Sleutelplan nieuw'!A:A,"",2) -> 0150 | C7: DS | D7: 2e Maasbosstraat 2 c | E7: 3134XJ | F7: Vlaardingen | L7: Tradiro | M7: =_xlfn.XLOOKUP(L7,'relaties_export_2026-01-12_1609'!B:B,'relaties_export_2026-01-12_1609'!A:A,"",3) -> 17 | N7: =_xlfn.XLOOKUP(M7,'relaties_export_2026-01-12_1609'!A:A,'relaties_export_2026-01-12_1609'!B:B,"",3) -> Tradiro Services B.V. | Y7: A.J. Maat | Z7: 306 | AA7: =_xlfn.XLOOKUP(Z7,'relaties_export_2026-01-12_1609'!A:A,'relaties_export_2026-01-12_1609'!B:B,"",3) -> Jacco Maat | AC7: 1475.31 | AD7: 1475.31 | AE7: 1475.31
A8: 3 | B8: =_xlfn.XLOOKUP(D8,'[1]Sleutelplan nieuw'!B:B,'[1]Sleutelplan nieuw'!A:A,"",2) -> 0003 | C8: Factuur | D8: Acacia 2 | E8: 3224EB | F8: Hellevoetsluis | G8: 5 | H8: 5 | I8: 44991 | J8: 45356 | L8: United Homes | M8: =_xlfn.XLOOKUP(L8,'relaties_export_2026-01-12_1609'!B:B,'relaties_export_2026-01-12_1609'!A:A,"",3) -> 13 | N8: =_xlfn.XLOOKUP(M8,'relaties_export_2026-01-12_1609'!A:A,'relaties_export_2026-01-12_1609'!B:B,"",3) -> United Homes B.V. | P8: =R8-U8-V8-AD8 -> 1195.81 | Q8: =T8*1.09+U8*1.21 -> 4164.6829 | R8: =T8+U8 -> 3820.81 | S8: =(R8/G8)/4.3333 -> 176.34643 | T8: 3820.81 | U8: 0 | V8: 0 | Y8: MvB Services BV (Meindert van Buuren) | Z8: =_xlfn.XLOOKUP(Y8,'relaties_export_2026-01-12_1609'!B:B,'relaties_export_2026-01-12_1609'!A:A,"",2) -> 789 | AA8: =_xlfn.XLOOKUP(Z8,'relaties_export_2026-01-12_1609'!A:A,'relaties_export_2026-01-12_1609'!B:B,"",3) -> MvB Services BV (Meindert van Buuren) | AB8: 06-23234296 | AC8: 2625 | AD8: 2625 | AE8: 2625 | AF8: =(AD8/G8)/4.33333 -> 121.15394 | AG8: 44986 | AH8: 45351
A9: 5 | B9: =_xlfn.XLOOKUP(D9,'[1]Sleutelplan nieuw'!B:B,'[1]Sleutelplan nieuw'!A:A,"",2) -> 0190 | C9: Factuur | D9: Achterdijk 47a | E9: 4243 TM | F9: Nieuwland | G9: 7 | H9: 4 | I9: 45241 | J9: 45606 | L9: Dock Holland | M9: 145 | N9: =_xlfn.XLOOKUP(M9,'relaties_export_2026-01-12_1609'!A:A,'relaties_export_2026-01-12_1609'!B:B,"",3) -> dockHolland Huisvesting B.V. | P9: =R9-U9-V9-AD9 -> 370.78 | Q9: =T9*1.09+U9*1.21 -> 4543.4534 | R9: =T9+U9 -> 4113.26 | S9: =(R9/G9)/4.3333 -> 135.60302 | T9: 3613.26 | U9: 500 | V9: 0 | Y9: Vivir wonen (Mendy) | Z9: =_xlfn.XLOOKUP(Y9,'relaties_export_2026-01-12_1609'!B:B,'relaties_export_2026-01-12_1609'!A:A,"",2) -> 824 | AA9: =_xlfn.XLOOKUP(Z9,'relaties_export_2026-01-12_1609'!A:A,'relaties_export_2026-01-12_1609'!B:B,"",3) -> Vivir wonen (Mendy) | AB9: 06-12333496 | AC9: 3347.48 | AD9: 3242.48 | AE9: 2742.48 | AF9: =(AD9/G9)/4.33333 -> 106.89503 | AG9: 45038 | AH9: 45403
A10: 6 | B10: =_xlfn.XLOOKUP(D10,'[1]Sleutelplan nieuw'!B:B,'[1]Sleutelplan nieuw'!A:A,"",2) -> 0007 | C10: DS | D10: Adriaan Baasstraat 34 | E10: 7902HN | F10: Hoogeveen | G10: 4 | H10: 4 | I10: 45765 | J10: 46129 | L10: InAxtion Vastgoed B.V. | M10: =_xlfn.XLOOKUP(L10,'relaties_export_2026-01-12_1609'!B:B,'relaties_export_2026-01-12_1609'!A:A,"",3) -> 154 | N10: =_xlfn.XLOOKUP(M10,'relaties_export_2026-01-12_1609'!A:A,'relaties_export_2026-01-12_1609'!B:B,"",3) -> InAxtion Vastgoed B.V. | P10: =R10-U10-V10-AD10 -> 550 | Q10: =T10*1.09+U10*1.21 -> 2700.5 | R10: =T10+U10 -> 2450 | S10: =(R10/G10)/4.3333 -> 141.34724 | T10: 2200 | U10: 250 | V10: 0 | Y10: Eva Laus | Z10: =_xlfn.XLOOKUP(Y10,'relaties_export_2026-01-12_1609'!B:B,'relaties_export_2026-01-12_1609'!A:A,"",3) -> 790 | AA10: =_xlfn.XLOOKUP(Z10,'relaties_export_2026-01-12_1609'!A:A,'relaties_export_2026-01-12_1609'!B:B,"",3) -> Eva Laus | AB10: 06-12707279 | AC10: 1650 | AD10: 1650 | AE10: 1650 | AF10: =(AD10/G10)/4.33333 -> 95.192381 | AG10: 44682 | AH10: 45412
A11: 7 | B11: 0341 | C11: Factuur | D11: Akkerweg 41 [huis 10] | E11: 1779GJ | F11: Den Oever | G11: 6 | H11: 3 | I11: 45709 | J11: 45992 | L11: NL Realty | M11: =_xlfn.XLOOKUP(L11,'relaties_export_2026-01-12_1609'!B:B,'relaties_export_2026-01-12_1609'!A:A,"",3) -> 236 | N11: =_xlfn.XLOOKUP(M11,'relaties_export_2026-01-12_1609'!A:A,'relaties_export_2026-01-12_1609'!B:B,"",3) -> NL Realty B.V. | P11: =R11-U11-V11-AD11 -> 0 | Y11: Cris | Z11: =_xlfn.XLOOKUP(Y11,'relaties_export_2026-01-12_1609'!B:B,'relaties_export_2026-01-12_1609'!A:A,"",3) -> 726 | AA11: =_xlfn.XLOOKUP(Z11,'relaties_export_2026-01-12_1609'!A:A,'relaties_export_2026-01-12_1609'!B:B,"",3) -> Cris | AB11: 06-4537722 | AG11: 45709 | AH11: 45992
A12: 8 | B12: 0372 | C12: Factuur | D12: Akkerweg 41 [huis 11] | E12: 1779GJ | F12: Den Oever | G12: 6 | H12: 3 | I12: 45765 | J12: 45931 | L12: MNA Proud Facilities B.V. | M12: =_xlfn.XLOOKUP(L12,'relaties_export_2026-01-12_1609'!B:B,'relaties_export_2026-01-12_1609'!A:A,"",3) -> 348 | N12: =_xlfn.XLOOKUP(M12,'relaties_export_2026-01-12_1609'!A:A,'relaties_export_2026-01-12_1609'!B:B,"",3) -> MNA Proud Facilities B.V. | O12: Verhuisd naar huis 10 | P12: =R12-U12-V12-AD12 -> 395.18 | Q12: =T12*1.09+U12*1.21 -> 3911.5 | R12: =T12+U12 -> 3550 | S12: =(R12/G12)/4.3333 -> 136.53951 | T12: 3200 | U12: 350 | Y12: Cris | Z12: =_xlfn.XLOOKUP(Y12,'relaties_export_2026-01-12_1609'!B:B,'relaties_export_2026-01-12_1609'!A:A,"",3) -> 726 | AA12: =_xlfn.XLOOKUP(Z12,'relaties_export_2026-01-12_1609'!A:A,'relaties_export_2026-01-12_1609'!B:B,"",3) -> Cris | AB12: 06-4537722 | AC12: 3055.3 | AD12: 2804.82 | AE12: 2094.5 | AF12: =(AD12/G12)/4.33333 -> 107.87778 | AG12: 45765 | AH12: 46494
A13: 9 | B13: {=_xlfn.XLOOKUP(LEFT(D13,3),LEFT('[1]Sleutelplan nieuw'!B:B,3),'[1]Sleutelplan nieuw'!A:A,"",2)} -> 0293 | C13: Factuur | D13: Akkerweg 41 [huis 14] | E13: 1779GJ | F13: Den Oever | G13: 6 | H13: 3 | I13: 45913 | J13: 46022 | L13: Buurman Vastgoed E B.V. | M13: =_xlfn.XLOOKUP(L13,'relaties_export_2026-01-12_1609'!B:B,'relaties_export_2026-01-12_1609'!A:A,"",3) -> 346 | N13: =_xlfn.XLOOKUP(M13,'relaties_export_2026-01-12_1609'!A:A,'relaties_export_2026-01-12_1609'!B:B,"",3) -> Buurman Vastgoed E B.V. | O13: Terug naar eigenaar 31-12 | P13: =R13-U13-V13-AD13 -> 505 | Q13: =T13*1.09+U13*1.21 -> 4282.65 | R13: =T13+U13 -> 3885 | S13: =(R13/G13)/4.3333 -> 149.42423 | T13: 3485 | U13: 400 | Y13: Cris | Z13: =_xlfn.XLOOKUP(Y13,'relaties_export_2026-01-12_1609'!B:B,'relaties_export_2026-01-12_1609'!A:A,"",3) -> 726 | AA13: =_xlfn.XLOOKUP(Z13,'relaties_export_2026-01-12_1609'!A:A,'relaties_export_2026-01-12_1609'!B:B,"",3) -> Cris | AB13: 06-4537722 | AC13: =3260.2+363 -> 3623.2 | AD13: 2980 | AE13: 2880 | AF13: =(AD13/G13)/4.33333 -> 114.61547 | AG13: 45913 | AH13: 46022
A14: 10 | B14: 0294 | C14: Factuur | D14: Akkerweg 41 [huis 15] | E14: 1779GJ | F14: Den Oever | G14: 6 | H14: 4 | I14: 45325 | J14: 45690 | L14: NL Realty | M14: =_xlfn.XLOOKUP(L14,'relaties_export_2026-01-12_1609'!B:B,'relaties_export_2026-01-12_1609'!A:A,"",3) -> 236 | N14: =_xlfn.XLOOKUP(M14,'relaties_export_2026-01-12_1609'!A:A,'relaties_export_2026-01-12_1609'!B:B,"",3) -> NL Realty B.V. | P14: =R14-U14-V14-AD14 -> 704.39 | Q14: =T14*1.09+U14*1.21 -> 4295.4693 | R14: =T14+U14 -> 3907.77 | S14: =(R14/G14)/4.3333 -> 150.3 | T14: 3607.77 | U14: 300 | V14: 0 | Y14: C. van Driel e/o B.M. Verdouw | Z14: =_xlfn.XLOOKUP(Y14,'relaties_export_2026-01-12_1609'!B:B,'relaties_export_2026-01-12_1609'!A:A,"",3) -> 766 | AA14: =_xlfn.XLOOKUP(Z14,'relaties_export_2026-01-12_1609'!A:A,'relaties_export_2026-01-12_1609'!B:B,"",3) -> C. van Driel e/o B.M. Verdouw | AB14: 06 53141599 | AC14: 3181.85 | AD14: 2903.38 | AE14: 2394.13 | AF14: =(AD14/G14)/4.33333 -> 111.66855 | AG14: 45200 | AH14: 46873
A15: 12 | B15: 0373 | C15: Factuur | D15: Akkerweg 41 [huis 17] | E15: 1779GJ | F15: Den Oever | G15: 6 | H15: 4 | I15: 45765 | J15: 45931 | L15: MNA Proud Facilities B.V. | M15: =_xlfn.XLOOKUP(L15,'relaties_export_2026-01-12_1609'!B:B,'relaties_export_2026-01-12_1609'!A:A,"",3) -> 348 | N15: =_xlfn.XLOOKUP(M15,'relaties_export_2026-01-12_1609'!A:A,'relaties_export_2026-01-12_1609'!B:B,"",3) -> MNA Proud Facilities B.V. | P15: =R15-V15-AD15 -> 595.2 | Q15: =T15*1.09+U15*1.21 -> 3851 | R15: =T15+U15 -> 3500 | S15: =(R15/G15)/4.3333 -> 134.61642 | T15: 3200 | U15: 300 | Y15: Cris | Z15: =_xlfn.XLOOKUP(Y15,'relaties_export_2026-01-12_1609'!B:B,'relaties_export_2026-01-12_1609'!A:A,"",3) -> 726 | AA15: =_xlfn.XLOOKUP(Z15,'relaties_export_2026-01-12_1609'!A:A,'relaties_export_2026-01-12_1609'!B:B,"",3) -> Cris | AB15: 06-4537722 | AC15: 3176.3 | AD15: 2904.8 | AE15: 2094.5 | AF15: =(AD15/G15)/4.33333 -> 111.72316 | AG15: 45765 | AH15: 46494
B16: 0383 | C16: Factuur | D16: Akkerweg 41 [huis 20] | E16: 1779GJ | F16: Den Oever | G16: 7 | H16: 4 | I16: 45915 | J16: 46022 | L16: Buurman Vastgoed E B.V. | M16: =_xlfn.XLOOKUP(L16,'relaties_export_2026-01-12_1609'!B:B,'relaties_export_2026-01-12_1609'!A:A,"",3) -> 346 | N16: =_xlfn.XLOOKUP(M16,'relaties_export_2026-01-12_1609'!A:A,'relaties_export_2026-01-12_1609'!B:B,"",3) -> Buurman Vastgoed E B.V. | O16: Terug naar eigenaar 31-12 | P16: =R16-V16-AD16 -> 620 | Q16: =T16*1.09+U16*1.21 -> 4975.35 | R16: 3600 | S16: =(R16/G16)/4.3333 -> 118.68223 | T16: 4065 | U16: 450 | Y16: Cris | Z16: =_xlfn.XLOOKUP(Y16,'relaties_export_2026-01-12_1609'!B:B,'relaties_export_2026-01-12_1609'!A:A,"",3) -> 726 | AA16: =_xlfn.XLOOKUP(Z16,'relaties_export_2026-01-12_1609'!A:A,'relaties_export_2026-01-12_1609'!B:B,"",3) -> Cris | AB16: 06-4537722 | AC16: =3260.2+363 -> 3623.2 | AD16: 2980 | AE16: 2880 | AF16: =(AD16/G16)/4.33333 -> 98.241834 | AG16: 45915 | AH16: 46022
B17: 0297 | C17: Factuur | D17: Akkerweg 41 [huis 26] | E17: 1779GJ | F17: Den Oever | G17: 3 | H17: 3 | I17: 45931 | J17: 46022 | L17: Royal DS Personeel-service | M17: =_xlfn.XLOOKUP(L17,'relaties_export_2026-01-12_1609'!B:B,'relaties_export_2026-01-12_1609'!A:A,"",3) -> 304 | N17: =_xlfn.XLOOKUP(M17,'relaties_export_2026-01-12_1609'!A:A,'relaties_export_2026-01-12_1609'!B:B,"",3) -> Royal DS Personeel-service | O17: Terug naar eigenaar 31-12 | P17: =R17-V17-AD17 -> 540 | Q17: =T17*1.09+U17*1.21+V17*1.21 -> 2543 | R17: =T17+U17+V17 -> 2300 | S17: =(R17/G17)/4.3333 -> 176.92444 | T17: 2000 | U17: 200 | V17: 100 | Y17: Cris | Z17: =_xlfn.XLOOKUP(Y17,'relaties_export_2026-01-12_1609'!B:B,'relaties_export_2026-01-12_1609'!A:A,"",3) -> 726 | AA17: =_xlfn.XLOOKUP(Z17,'relaties_export_2026-01-12_1609'!A:A,'relaties_export_2026-01-12_1609'!B:B,"",3) -> Cris | AB17: 06-4537722 | AC17: =3260.2 -> 3260.2 | AD17: 1660 | AE17: 1560 | AF17: =(AD17/G17)/4.33333 -> 127.69241
A18: 15 | B18: 0350 | C18: Factuur | D18: Akkerweg 41 [huis 35] | E18: 1779GJ | F18: Den Oever | G18: 4 | H18: 3 | I18: 45765 | J18: 45931 | L18: MNA Proud Facilities B.V. | M18: =_xlfn.XLOOKUP(L18,'relaties_export_2026-01-12_1609'!B:B,'relaties_export_2026-01-12_1609'!A:A,"",3) -> 348 | N18: =_xlfn.XLOOKUP(M18,'relaties_export_2026-01-12_1609'!A:A,'relaties_export_2026-01-12_1609'!B:B,"",3) -> MNA Proud Facilities B.V. | P18: =R18-V18-AD18 -> 423.12 | Q18: =T18*1.09+U18*1.21 -> 2646 | R18: =T18+U18 -> 2400 | S18: =(R18/G18)/4.3333 -> 138.4626 | T18: 2150 | U18: 250 | Y18: Cris | Z18: =_xlfn.XLOOKUP(Y18,'relaties_export_2026-01-12_1609'!B:B,'relaties_export_2026-01-12_1609'!A:A,"",3) -> 726 | AA18: =_xlfn.XLOOKUP(Z18,'relaties_export_2026-01-12_1609'!A:A,'relaties_export_2026-01-12_1609'!B:B,"",3) -> Cris | AB18: 06-4537722 | AC18: 2161.5 | AD18: 1976.88 | AE18: 1362.66 | AF18: =(AD18/G18)/4.33333 -> 114.05086 | AG18: 45765 | AH18: 46494
A19: 16 | B19: 0356 | C19: Factuur | D19: Akkerweg 41 [huis 36] | E19: 1779GJ | F19: Den Oever | G19: 3 | H19: 3 | I19: 45853 | J19: 46582 | L19: MNA Proud Facilities B.V. | M19: =_xlfn.XLOOKUP(L19,'relaties_export_2026-01-12_1609'!B:B,'relaties_export_2026-01-12_1609'!A:A,"",3) -> 348 | N19: =_xlfn.XLOOKUP(M19,'relaties_export_2026-01-12_1609'!A:A,'relaties_export_2026-01-12_1609'!B:B,"",3) -> MNA Proud Facilities B.V. | P19: =R19-V19-AD19 -> 282.09 | Q19: =T19*1.09+U19*1.21 -> 2646 | R19: 2100 | S19: =(R19/G19)/4.3333 -> 161.5397 | T19: 2150 | U19: 250 | Y19: Cris | Z19: =_xlfn.XLOOKUP(Y19,'relaties_export_2026-01-12_1609'!B:B,'relaties_export_2026-01-12_1609'!A:A,"",3) -> 726 | AA19: =_xlfn.XLOOKUP(Z19,'relaties_export_2026-01-12_1609'!A:A,'relaties_export_2026-01-12_1609'!B:B,"",3) -> Cris | AB19: 06-4537722 | AC19: 1992.5 | AD19: 1817.91 | AE19: 1251.74 | AF19: =(AD19/G19)/4.33333 -> 139.83934 | AG19: 45853 | AH19: 46491
A20: 17 | B20: 0299 | C20: Factuur | D20: Akkerweg 41 [huis 37] | E20: 1779GJ | F20: Den Oever | G20: 8 | H20: 4 | I20: 45304 | J20: 45669 | L20: NL Realty | M20: =_xlfn.XLOOKUP(L20,'relaties_export_2026-01-12_1609'!B:B,'relaties_export_2026-01-12_1609'!A:A,"",3) -> 236 | N20: =_xlfn.XLOOKUP(M20,'relaties_export_2026-01-12_1609'!A:A,'relaties_export_2026-01-12_1609'!B:B,"",3) -> NL Realty B.V. | P20: =R20-V20-AD20 -> 1340.31 | Q20: =T20*1.09+U20*1.21 -> 5606.2924 | R20: =T20+U20 -> 5110.36 | S20: =(R20/G20)/4.3333 -> 147.41536 | T20: 4810.36 | U20: 300 | V20: 0 | Y20: C. van Driel e/o B.M. Verdouw | Z20: =_xlfn.XLOOKUP(Y20,'relaties_export_2026-01-12_1609'!B:B,'relaties_export_2026-01-12_1609'!A:A,"",3) -> 766 | AA20: =_xlfn.XLOOKUP(Z20,'relaties_export_2026-01-12_1609'!A:A,'relaties_export_2026-01-12_1609'!B:B,"",3) -> C. van Driel e/o B.M. Verdouw | AB20: 06 53141599 | AC20: 4126.52 | AD20: 3770.05 | AE20: 3260.8 | AF20: =(AD20/G20)/4.33333 -> 108.75153 | AG20: 45200 | AH20: 46873
A21: 19 | B21: 0300 | C21: Factuur | D21: Akkerweg 41 [huis 40] | E21: 1779GJ | F21: Den Oever | G21: 8 | H21: 8 | I21: 45609 | J21: 45701 | L21: Eemsdelta | M21: =_xlfn.XLOOKUP(L21,'relaties_export_2026-01-12_1609'!B:B,'relaties_export_2026-01-12_1609'!A:A,"",3) -> 218 | N21: =_xlfn.XLOOKUP(M21,'relaties_export_2026-01-12_1609'!A:A,'relaties_export_2026-01-12_1609'!B:B,"",3) -> Eemsdelta Housing B.V. | O21: Gaat eruit 30-11 | P21: =R21-V21-AD21 -> -4490.05 | U21: 600 | Y21: C. van Driel e/o B.M. Verdouw | Z21: =_xlfn.XLOOKUP(Y21,'relaties_export_2026-01-12_1609'!B:B,'relaties_export_2026-01-12_1609'!A:A,"",3) -> 766 | AA21: =_xlfn.XLOOKUP(Z21,'relaties_export_2026-01-12_1609'!A:A,'relaties_export_2026-01-12_1609'!B:B,"",3) -> C. van Driel e/o B.M. Verdouw | AB21: 06 53141599 | AC21: 4935.32 | AD21: 4490.05 | AE21: 3780.8 | AF21: =(AD21/G21)/4.33333 -> 129.52077 | AG21: 45609 | AH21: 45701
A22: 20 | B22: 0301 | C22: Factuur | D22: Akkerweg 41 [huis 41] | E22: 1779GJ | F22: Den Oever | G22: 8 | H22: 8 | I22: 45660 | J22: 45841 | L22: Royal DS Personeel-service | M22: =_xlfn.XLOOKUP(L22,'relaties_export_2026-01-12_1609'!B:B,'relaties_export_2026-01-12_1609'!A:A,"",3) -> 304 | N22: =_xlfn.XLOOKUP(M22,'relaties_export_2026-01-12_1609'!A:A,'relaties_export_2026-01-12_1609'!B:B,"",3) -> Royal DS Personeel-service | P22: =R22-V22-AD22 -> 1009.95 | Q22: =T22*1.09+U22*1.21 -> 6067 | R22: =T22+U22 -> 5500 | S22: =(R22/G22)/4.3333 -> 158.65507 | T22: 4900 | U22: 600 | Y22: C. van Driel e/o B.M. Verdouw | Z22: =_xlfn.XLOOKUP(Y22,'relaties_export_2026-01-12_1609'!B:B,'relaties_export_2026-01-12_1609'!A:A,"",3) -> 766 | AA22: =_xlfn.XLOOKUP(Z22,'relaties_export_2026-01-12_1609'!A:A,'relaties_export_2026-01-12_1609'!B:B,"",3) -> C. van Driel e/o B.M. Verdouw | AB22: 06 53141599 | AC22: 4935.32 | AD22: 4490.05 | AE22: 3780.8 | AF22: =(AD22/G22)/4.33333 -> 129.52077
A23: 21 | B23: 0302 | C23: Factuur | D23: Akkerweg 41 [huis 42] | E23: 1779GJ | F23: Den Oever | G23: 8 | H23: 8 | I23: 45913 | J23: 46022 | L23: Buurman Vastgoed E B.V. | M23: =_xlfn.XLOOKUP(L23,'relaties_export_2026-01-12_1609'!B:B,'relaties_export_2026-01-12_1609'!A:A,"",3) -> 346 | N23: =_xlfn.XLOOKUP(M23,'relaties_export_2026-01-12_1609'!A:A,'relaties_export_2026-01-12_1609'!B:B,"",3) -> Buurman Vastgoed E B.V. | O23: Gaat eruit 31-12 | P23: =R23-V23-AD23 -> 609.95 | Q23: =T23*1.09+U23*1.21 -> 5613 | R23: =T23+U23 -> 5100 | S23: =(R23/G23)/4.3333 -> 147.11652 | T23: 4650 | U23: 450 | Y23: C. van Driel e/o B.M. Verdouw | Z23: =_xlfn.XLOOKUP(Y23,'relaties_export_2026-01-12_1609'!B:B,'relaties_export_2026-01-12_1609'!A:A,"",3) -> 766 | AA23: =_xlfn.XLOOKUP(Z23,'relaties_export_2026-01-12_1609'!A:A,'relaties_export_2026-01-12_1609'!B:B,"",3) -> C. van Driel e/o B.M. Verdouw | AB23: 06 53141599 | AC23: 4935.32 | AD23: 4490.05 | AE23: 3780.8 | AF23: =(AD23/G23)/4.33333 -> 129.52077
A24: 22 | B24: 0303 | C24: Factuur | D24: Akkerweg 41 [huis 55] | E24: 1779GJ | F24: Den Oever | G24: 6 | H24: 6 | I24: 45695 | J24: 45992 | L24: NL Realty | M24: =_xlfn.XLOOKUP(L24,'relaties_export_2026-01-12_1609'!B:B,'relaties_export_2026-01-12_1609'!A:A,"",3) -> 236 | N24: =_xlfn.XLOOKUP(M24,'relaties_export_2026-01-12_1609'!A:A,'relaties_export_2026-01-12_1609'!B:B,"",3) -> NL Realty B.V. | O24: Gaat eruit 01-12 | P24: =R24-V24-AD24 -> -3293.38 | Y24: C. van Driel e/o B.M. Verdouw | Z24: =_xlfn.XLOOKUP(Y24,'relaties_export_2026-01-12_1609'!B:B,'relaties_export_2026-01-12_1609'!A:A,"",3) -> 766 | AA24: =_xlfn.XLOOKUP(Z24,'relaties_export_2026-01-12_1609'!A:A,'relaties_export_2026-01-12_1609'!B:B,"",3) -> C. van Driel e/o B.M. Verdouw | AB24: 06 53141599 | AC24: 3606.95 | AD24: 3293.38 | AE24: 2784.13 | AF24: =(AD24/G24)/4.33333 -> 126.66856 | AG24: 45672 | AH24: 47498
A25: 23 | B25: 0304 | C25: Factuur | D25: Akkerweg 41 [huis 56] | E25: 1779GJ | F25: Den Oever | G25: 8 | H25: 8 | I25: 45702 | J25: 45992 | L25: NL Realty | M25: =_xlfn.XLOOKUP(L25,'relaties_export_2026-01-12_1609'!B:B,'relaties_export_2026-01-12_1609'!A:A,"",3) -> 236 | N25: =_xlfn.XLOOKUP(M25,'relaties_export_2026-01-12_1609'!A:A,'relaties_export_2026-01-12_1609'!B:B,"",3) -> NL Realty B.V. | O25: Gaat eruit 01-12 | P25: =R25-V25-AD25 -> -4490.05 | Y25: C. van Driel e/o B.M. Verdouw | Z25: =_xlfn.XLOOKUP(Y25,'relaties_export_2026-01-12_1609'!B:B,'relaties_export_2026-01-12_1609'!A:A,"",3) -> 766 | AA25: =_xlfn.XLOOKUP(Z25,'relaties_export_2026-01-12_1609'!A:A,'relaties_export_2026-01-12_1609'!B:B,"",3) -> C. van Driel e/o B.M. Verdouw | AB25: 06 53141599 | AC25: 4935.32 | AD25: 4490.05 | AE25: 3780.8 | AF25: =(AD25/G25)/4.33333 -> 129.52077 | AG25: 45672 | AH25: 47498
A26: 24 | B26: 0305 | C26: Factuur | D26: Akkerweg 41 [huis 57] | E26: 1779GJ | F26: Den Oever | G26: 4 | H26: 3 | I26: 45772 | J26: 45931 | L26: MNA Proud Facilities B.V. | M26: =_xlfn.XLOOKUP(L26,'relaties_export_2026-01-12_1609'!B:B,'relaties_export_2026-01-12_1609'!A:A,"",3) -> 348 | N26: =_xlfn.XLOOKUP(M26,'relaties_export_2026-01-12_1609'!A:A,'relaties_export_2026-01-12_1609'!B:B,"",3) -> MNA Proud Facilities B.V. | P26: =R26-V26-AD26 -> 173.63 | Q26: =T26*1.09+U26*1.21+V26*1.21 -> 2646 | R26: =T26+U26+V26 -> 2400 | S26: =(R26/G26)/4.3333 -> 138.4626 | T26: 2150 | U26: 250 | Y26: Cris | Z26: =_xlfn.XLOOKUP(Y26,'relaties_export_2026-01-12_1609'!B:B,'relaties_export_2026-01-12_1609'!A:A,"",3) -> 726 | AA26: =_xlfn.XLOOKUP(Z26,'relaties_export_2026-01-12_1609'!A:A,'relaties_export_2026-01-12_1609'!B:B,"",3) -> Cris | AB26: 06-4537722 | AC26: 2434 | AD26: 2226.37 | AE26: 1618.35 | AF26: =(AD26/G26)/4.33333 -> 128.44452 | AG26: 45772 | AH26: 46501
B27: 0384 | C27: Factuur | D27: Akkerweg 41 [huis 58] | E27: 1779GJ | F27: Den Oever | G27: 3 | H27: 3 | I27: 45913 | J27: 46022 | L27: Buurman Vastgoed E B.V. | M27: =_xlfn.XLOOKUP(L27,'relaties_export_2026-01-12_1609'!B:B,'relaties_export_2026-01-12_1609'!A:A,"",3) -> 346 | N27: =_xlfn.XLOOKUP(M27,'relaties_export_2026-01-12_1609'!A:A,'relaties_export_2026-01-12_1609'!B:B,"",3) -> Buurman Vastgoed E B.V. | O27: Terug naar eigenaar 30-11 | P27: =R27-V27-AD27 -> 0 | Y27: Cris | Z27: =_xlfn.XLOOKUP(Y27,'relaties_export_2026-01-12_1609'!B:B,'relaties_export_2026-01-12_1609'!A:A,"",3) -> 726 | AA27: =_xlfn.XLOOKUP(Z27,'relaties_export_2026-01-12_1609'!A:A,'relaties_export_2026-01-12_1609'!B:B,"",3) -> Cris | AB27: 06-4537722 | AG27: 45913 | AH27: 46022
B28: 0327 | C28: Factuur | D28: Akkerweg 41 [huis 74] | E28: 1779GJ | F28: Den Oever | G28: 5 | H28: 3 | I28: 45893 | J28: 46011 | L28: FISSH B.V. | M28: =_xlfn.XLOOKUP(L28,'relaties_export_2026-01-12_1609'!B:B,'relaties_export_2026-01-12_1609'!A:A,"",3) -> 347 | N28: =_xlfn.XLOOKUP(M28,'relaties_export_2026-01-12_1609'!A:A,'relaties_export_2026-01-12_1609'!B:B,"",3) -> FISSH B.V. | P28: =R28-V28-AD28 -> 877 | Q28: =T28*1.09+U28*1.21+V28*1.21 -> 3896.78 | R28: =T28+U28+V28 -> 3542 | S28: =(R28/G28)/4.3333 -> 163.47818 | T28: 3242 | U28: 300 | Y28: Cris | Z28: =_xlfn.XLOOKUP(Y28,'relaties_export_2026-01-12_1609'!B:B,'relaties_export_2026-01-12_1609'!A:A,"",3) -> 726 | AA28: =_xlfn.XLOOKUP(Z28,'relaties_export_2026-01-12_1609'!A:A,'relaties_export_2026-01-12_1609'!B:B,"",3) -> Cris | AB28: 06-4537722 | AC28: 2952.85 | AD28: 2665 | AE28: 2265 | AF28: =(AD28/G28)/4.33333 -> 123.00009 | AG28: 45893 | AH28: 46011
B29: 0307 | C29: Factuur | D29: Akkerweg 41 [huis 75] | E29: 1779GJ | F29: Den Oever | G29: 3 | H29: 4 | I29: 45962 | L29: FISSH B.V. | M29: =_xlfn.XLOOKUP(L29,'relaties_export_2026-01-12_1609'!B:B,'relaties_export_2026-01-12_1609'!A:A,"",3) -> 347 | N29: =_xlfn.XLOOKUP(M29,'relaties_export_2026-01-12_1609'!A:A,'relaties_export_2026-01-12_1609'!B:B,"",3) -> FISSH B.V. | P29: =R29-V29-AD29 -> 478.12 | Q29: =T29*1.09+U29*1.21 -> 3197 | R29: =T29+U29 -> 2900 | S29: =(R29/G29)/4.3333 -> 223.07864 | T29: 2600 | U29: 300 | Y29: Cris | Z29: =_xlfn.XLOOKUP(Y29,'relaties_export_2026-01-12_1609'!B:B,'relaties_export_2026-01-12_1609'!A:A,"",3) -> 726 | AA29: =_xlfn.XLOOKUP(Z29,'relaties_export_2026-01-12_1609'!A:A,'relaties_export_2026-01-12_1609'!B:B,"",3) -> Cris | AB29: 06-4537722 | AC29: 2658.55 | AD29: 2421.88 | AE29: 1707.66 | AF29: =(AD29/G29)/4.33333 -> 186.2986 | AG29: 45962
A30: 26 | B30: =_xlfn.XLOOKUP(D30,'[1]Sleutelplan nieuw'!B:B,'[1]Sleutelplan nieuw'!A:A,"",2) -> 0002 | C30: DS | D30: Allard Piersonlaan 142 | E30: 2522 MT | F30: Den Haag | G30: 4 | H30: 3 | I30: 44946 | J30: 45311 | L30: Looije | M30: =_xlfn.XLOOKUP(L30,'relaties_export_2026-01-12_1609'!B:B,'relaties_export_2026-01-12_1609'!A:A,"",3) -> 260 | N30: =_xlfn.XLOOKUP(M30,'relaties_export_2026-01-12_1609'!A:A,'relaties_export_2026-01-12_1609'!B:B,"",3) -> Looije Facilities B.V. | P30: =R30-U30-V30-AD30 -> 412.68 | Q30: =T30*1.09+U30*1.21 -> 1994.1877 | R30: =T30+U30 -> 1829.53 | S30: =(R30/G30)/4.33333 -> 105.54989 | T30: 1829.53 | U30: 0 | V30: 0 | Y30: R. Paltan | Z30: =_xlfn.XLOOKUP(Y30,'relaties_export_2026-01-12_1609'!B:B,'relaties_export_2026-01-12_1609'!A:A,"",3) | AA30: =_xlfn.XLOOKUP(Z30,'relaties_export_2026-01-12_1609'!A:A,'relaties_export_2026-01-12_1609'!B:B,"",3) -> naam | AC30: 1416.85 | AD30: 1416.85 | AE30: 1391.85 | AF30: =(AD30/G30)/4.33333 -> 81.741409 | AG30: 44946
A31: 28 | B31: =_xlfn.XLOOKUP(D31,'[1]Sleutelplan nieuw'!B:B,'[1]Sleutelplan nieuw'!A:A,"",2) -> 0043 | C31: DS | D31: Amperelaan 23 | E31: 8451BW | F31: Oudeschoot | G31: 4 | H31: 4 | I31: 45208 | J31: 45573 | L31: Vivir Wonen | M31: =_xlfn.XLOOKUP(L31,'relaties_export_2026-01-12_1609'!B:B,'relaties_export_2026-01-12_1609'!A:A,"",3) -> 26 | N31: =_xlfn.XLOOKUP(M31,'relaties_export_2026-01-12_1609'!A:A,'relaties_export_2026-01-12_1609'!B:B,"",3) -> Vivir Wonen | P31: =R31-U31-V31-AD31 -> 753.42 | Q31: =T31*1.09+U31*1.21 -> 2693.4663 | R31: =T31+U31 -> 2471.07 | S31: =(R31/G31)/4.3333 -> 142.56283 | T31: 2471.07 | U31: 0 | V31: 0 | Y31: H. Samson | Z31: =_xlfn.XLOOKUP(Y31,'relaties_export_2026-01-12_1609'!B:B,'relaties_export_2026-01-12_1609'!A:A,"",3) -> 792 | AA31: =_xlfn.XLOOKUP(Z31,'relaties_export_2026-01-12_1609'!A:A,'relaties_export_2026-01-12_1609'!B:B,"",3) -> H. Samson | AB31: 06-22487252 | AC31: 1717.65 | AD31: 1717.65 | AE31: 1717.65 | AF31: =(AD31/G31)/4.33333 -> 99.095269 | AG31: 44381 | AH31: 45474
A32: 29 | B32: 0135 | C32: Factuur | D32: Amperestraat 36A | E32: 3112MD | F32: Schiedam | G32: 3 | H32: 2 | I32: 45405 | J32: 45769 | L32: Tradiro | M32: =_xlfn.XLOOKUP(L32,'relaties_export_2026-01-12_1609'!B:B,'relaties_export_2026-01-12_1609'!A:A,"",3) -> 17 | N32: =_xlfn.XLOOKUP(M32,'relaties_export_2026-01-12_1609'!A:A,'relaties_export_2026-01-12_1609'!B:B,"",3) -> Tradiro Services B.V. | P32: =R32-U32-V32-AD32 -> 130.13 | Q32: =T32*1.09+U32*1.21 -> 1843.8767 | R32: =T32+U32 -> 1691.63 | S32: =(R32/G32)/4.3333 -> 130.12639 | T32: 1691.63 | U32: 0 | V32: 0 | Y32: Parkwonen | Z32: =_xlfn.XLOOKUP(Y32,'relaties_export_2026-01-12_1609'!B:B,'relaties_export_2026-01-12_1609'!A:A,"",3) -> 258 | AA32: =_xlfn.XLOOKUP(Z32,'relaties_export_2026-01-12_1609'!A:A,'relaties_export_2026-01-12_1609'!B:B,"",3) -> Parkwonen | AC32: 1561.5 | AD32: 1561.5 | AE32: 1561.5 | AF32: =(AD32/G32)/4.33333 -> 120.11548
A33: 30 | B33: {=_xlfn.XLOOKUP(LEFT(D33,3),LEFT('[1]Sleutelplan nieuw'!B:B,3),'[1]Sleutelplan nieuw'!A:A,"",2)} -> 0353 | C33: Factuur | D33: Archimedesstraat 6B | E33: 3112DB | F33: Schiedam | G33: 4 | H33: 2 | I33: 45748 | J33: OBT | L33: Tradiro | M33: =_xlfn.XLOOKUP(L33,'relaties_export_2026-01-12_1609'!B:B,'relaties_export_2026-01-12_1609'!A:A,"",3) -> 17 | N33: =_xlfn.XLOOKUP(M33,'relaties_export_2026-01-12_1609'!A:A,'relaties_export_2026-01-12_1609'!B:B,"",3) -> Tradiro Services B.V. | P33: =R33-U33-V33-AD33 -> 373.96 | Q33: =T33*1.09+U33*1.21 -> 1770.1164 | R33: =T33+U33 -> 1623.96 | S33: =(R33/G33)/4.3333 -> 93.690721 | T33: 1623.96 | U33: 0 | Y33: Houses2Rent | Z33: =_xlfn.XLOOKUP(Y33,'relaties_export_2026-01-12_1609'!B:B,'relaties_export_2026-01-12_1609'!A:A,"",3) -> 271 | AA33: =_xlfn.XLOOKUP(Z33,'relaties_export_2026-01-12_1609'!A:A,'relaties_export_2026-01-12_1609'!B:B,"",3) -> Houses2Rent | AB33: 06-20877085 | AC33: 1250 | AD33: 1250 | AE33: 1250 | AF33: =(AD33/G33)/4.33333 -> 72.11544 | AG33: 45748
A34: 32 | B34: =_xlfn.XLOOKUP(D34,'[1]Sleutelplan nieuw'!B:B,'[1]Sleutelplan nieuw'!A:A,"",2) -> 0055 | C34: DS | D34: Baanhoek 139 | E34: 3361 GC | F34: Sliedrecht | G34: 4 | H34: 4 | L34: HousingWell | M34: =_xlfn.XLOOKUP(L34,'relaties_export_2026-01-12_1609'!B:B,'relaties_export_2026-01-12_1609'!A:A,"",3) -> 310 | N34: =_xlfn.XLOOKUP(M34,'relaties_export_2026-01-12_1609'!A:A,'relaties_export_2026-01-12_1609'!B:B,"",3) -> HousingWell B.V. | P34: =R34-U34-V34-AD34 -> 697.47 | Q34: =T34*1.09+U34*1.21 -> 3332.1223 | R34: =T34+U34 -> 3029.47 | S34: =(R34/G34)/4.33333 -> 174.77725 | T34: 2779.47 | U34: 250 | Y34: R. Verspui | Z34: =_xlfn.XLOOKUP(Y34,'relaties_export_2026-01-12_1609'!B:B,'relaties_export_2026-01-12_1609'!A:A,"",3) -> 852 | AA34: =_xlfn.XLOOKUP(Z34,'relaties_export_2026-01-12_1609'!A:A,'relaties_export_2026-01-12_1609'!B:B,"",3) -> R. Verspui | AB34: 06-22268830 | AC34: 2082 | AD34: 2082 | AE34: 2082 | AF34: =(AD34/G34)/4.33333 -> 120.11548 | AG34: 45473 | AH34: 45837
A35: 33 | B35: =_xlfn.XLOOKUP(D35,'[1]Sleutelplan nieuw'!B:B,'[1]Sleutelplan nieuw'!A:A,"",2) -> 0012 | C35: DS | D35: Baarlelaan 27 | E35: 7906GB | F35: Hoogeveen | G35: 4 | H35: 4 | I35: 44932 | J35: 45296 | L35: Vivir Wonen | M35: =_xlfn.XLOOKUP(L35,'relaties_export_2026-01-12_1609'!B:B,'relaties_export_2026-01-12_1609'!A:A,"",3) -> 26 | N35: =_xlfn.XLOOKUP(M35,'relaties_export_2026-01-12_1609'!A:A,'relaties_export_2026-01-12_1609'!B:B,"",3) -> Vivir Wonen | P35: =R35-U35-V35-AD35 -> 409.23 | Q35: =T35*1.09+U35*1.21 -> 2244.5607 | R35: =T35+U35 -> 2059.23 | S35: =(R35/G35)/4.33333 -> 118.80182 | T35: 2059.23 | U35: 0 | V35: 0 | Y35: Eva Laus | Z35: =_xlfn.XLOOKUP(Y35,'relaties_export_2026-01-12_1609'!B:B,'relaties_export_2026-01-12_1609'!A:A,"",3) -> 790 | AA35: =_xlfn.XLOOKUP(Z35,'relaties_export_2026-01-12_1609'!A:A,'relaties_export_2026-01-12_1609'!B:B,"",3) -> Eva Laus | AB35: 06-12707279 | AC35: 1650 | AD35: 1650 | AE35: 1650 | AF35: =(AD35/G35)/4.33333 -> 95.192381 | AG35: 44986 | AH35: 45351
A36: 34 | B36: =_xlfn.XLOOKUP(D36,'[1]Sleutelplan nieuw'!B:B,'[1]Sleutelplan nieuw'!A:A,"",2) -> 0013 | C36: DS | D36: Baarsveen 197 | E36: 3205 BB | F36: Spijkenisse | G36: 5 | H36: 5 | I36: 45231 | J36: 45412 | L36: BBTS (Vastgoed Spijkenisse) | M36: =_xlfn.XLOOKUP(L36,'relaties_export_2026-01-12_1609'!B:B,'relaties_export_2026-01-12_1609'!A:A,"",1) -> 190 | N36: =_xlfn.XLOOKUP(M36,'relaties_export_2026-01-12_1609'!A:A,'relaties_export_2026-01-12_1609'!B:B,"",3) -> BBTS (Vastgoed Spijkenisse) | P36: =R36-U36-V36-AD36 -> 2233.04 | Q36: =T36*1.09+U36*1.21 -> 5580.669 | R36: =T36+U36 -> 5084.1 | S36: =(R36/G36)/4.33333 -> 234.65095 | T36: 4759.1 | U36: 325 | V36: 0 | Y36: Beking | Z36: =_xlfn.XLOOKUP(Y36,'relaties_export_2026-01-12_1609'!B:B,'relaties_export_2026-01-12_1609'!A:A,"",3) -> 185 | AA36: =_xlfn.XLOOKUP(Z36,'relaties_export_2026-01-12_1609'!A:A,'relaties_export_2026-01-12_1609'!B:B,"",3) -> Dhr. R. J. Beking | AB36: 06-53714776 | AC36: 2526.06 | AD36: 2526.06 | AE36: 2526.06 | AF36: =(AD36/G36)/4.33333 -> 116.58747 | AG36: 44835 | AH36: 45200
A37: 35 | B37: =_xlfn.XLOOKUP(D37,'[1]Sleutelplan nieuw'!B:B,'[1]Sleutelplan nieuw'!A:A,"",2) -> 0040 | C37: DS | D37: Beatrixstraat 3 | E37: 3181GA | F37: Rozenburg | G37: 3 | H37: 3 | I37: 45940 | J37: 46304 | L37: Impes Service | M37: =_xlfn.XLOOKUP(L37,'relaties_export_2026-01-12_1609'!B:B,'relaties_export_2026-01-12_1609'!A:A,"",3) -> 220 | N37: =_xlfn.XLOOKUP(M37,'relaties_export_2026-01-12_1609'!A:A,'relaties_export_2026-01-12_1609'!B:B,"",3) -> Impes Service S.p.A. | O37: Nieuw per 10-10-25 | P37: =R37-U37-V37-AD37 -> 743 | Q37: =T37*1.09+U37*1.21 -> 3627 | R37: =T37+U37 -> 3300 | S37: =(R37/G37)/4.33333 -> 253.84635 | T37: 3050 | U37: 250 | V37: 0 | Y37: Crul | Z37: =_xlfn.XLOOKUP(Y37,'relaties_export_2026-01-12_1609'!B:B,'relaties_export_2026-01-12_1609'!A:A,"",3) -> 180 | AA37: =_xlfn.XLOOKUP(Z37,'relaties_export_2026-01-12_1609'!A:A,'relaties_export_2026-01-12_1609'!B:B,"",3) -> Mw. M. Hyllested Poulsen en Dhr. S. Crull | AB37: 0045-28180001 | AC37: 2307 | AD37: 2307 | AE37: 2307 | AF37: =(AD37/G37)/4.33333 -> 177.46167 | AG37: 44835 | AH37: 5--5-2024
A38: 36 | B38: =_xlfn.XLOOKUP(D38,'[1]Sleutelplan nieuw'!B:B,'[1]Sleutelplan nieuw'!A:A,"",2) -> 0152 | C38: Factuur | D38: Beeklaan 294 | E38: 2562AV | F38: Den Haag | G38: 8 | H38: 4 | I38: 45898 | J38: 46262 | L38: Duijndam Personeelsdiensten B.V. | M38: =_xlfn.XLOOKUP(L38,'relaties_export_2026-01-12_1609'!B:B,'relaties_export_2026-01-12_1609'!A:A,"",3) -> 360 | N38: =_xlfn.XLOOKUP(M38,'relaties_export_2026-01-12_1609'!A:A,'relaties_export_2026-01-12_1609'!B:B,"",3) -> Duijndam Personeelsdiensten B.V. | P38: =R38-U38-V38-AD38 -> 394 | Q38: =T38*1.09+U38*1.21 -> 5558.5 | R38: =T38+U38 -> 5050 | S38: =(R38/G38)/4.33333 -> 145.67319 | T38: 4600 | U38: 450 | V38: 0 | Y38: Homescout21 B.V. | Z38: =_xlfn.XLOOKUP(Y38,'relaties_export_2026-01-12_1609'!B:B,'relaties_export_2026-01-12_1609'!A:A,"",3) -> 211 | AA38: =_xlfn.XLOOKUP(Z38,'relaties_export_2026-01-12_1609'!A:A,'relaties_export_2026-01-12_1609'!B:B,"",3) -> Homescout21 B.V. | AC38: 4206 | AD38: 4206 | AE38: 4206 | AF38: =(AD38/G38)/4.33333 -> 121.32702
A39: 38 | B39: =_xlfn.XLOOKUP(D39,'[1]Sleutelplan nieuw'!B:B,'[1]Sleutelplan nieuw'!A:A,"",2) -> 0322 | C39: Factuur | D39: Bettingeslag 10 | E39: 7824HD | F39: Emmen | G39: 4 | H39: 4 | I39: 45803 | J39: 45925 | L39: CB Construction | M39: =_xlfn.XLOOKUP(L39,'relaties_export_2026-01-12_1609'!B:B,'relaties_export_2026-01-12_1609'!A:A,"",3) -> 352 | N39: =_xlfn.XLOOKUP(M39,'relaties_export_2026-01-12_1609'!A:A,'relaties_export_2026-01-12_1609'!B:B,"",3) -> CB Construction UAB | O39: Gaat eruit 28-12 | P39: =R39-U39-V39-AD39 -> -1650 | U39: 250 | Y39: J.P. Stoel | Z39: =_xlfn.XLOOKUP(Y39,'relaties_export_2026-01-12_1609'!B:B,'relaties_export_2026-01-12_1609'!A:A,"",3) -> 795 | AA39: =_xlfn.XLOOKUP(Z39,'relaties_export_2026-01-12_1609'!A:A,'relaties_export_2026-01-12_1609'!B:B,"",3) -> J.P. Stoel | AB39: 06-40896047 | AC39: 1400 | AD39: 1400 | AE39: 1400 | AF39: =(AD39/G39)/4.33333 -> 80.769293 | AG39: 45689 | AH39: 46054
A40: 39 | B40: =_xlfn.XLOOKUP(D40,'[1]Sleutelplan nieuw'!B:B,'[1]Sleutelplan nieuw'!A:A,"",2) -> 0346 | C40: Factuur | D40: Beukenlaan 53 | E40: 3181XA | F40: Rozenburg | G40: 6 | H40: 3 | I40: 45717 | L40: PMM Workforce Management Ltd | M40: =_xlfn.XLOOKUP(L40,'relaties_export_2026-01-12_1609'!B:B,'relaties_export_2026-01-12_1609'!A:A,"",2) -> 277 | N40: =_xlfn.XLOOKUP(M40,'relaties_export_2026-01-12_1609'!A:A,'relaties_export_2026-01-12_1609'!B:B,"",3) -> PMM Workforce Management Ltd | O40: Terug naar eigenaar per 31-12 | P40: =R40-U40-V40-AD40 -> 0 | Y40: TwinsBV | Z40: =_xlfn.XLOOKUP(Y40,'relaties_export_2026-01-12_1609'!B:B,'relaties_export_2026-01-12_1609'!A:A,"",3) -> 796 | AA40: =_xlfn.XLOOKUP(Z40,'relaties_export_2026-01-12_1609'!A:A,'relaties_export_2026-01-12_1609'!B:B,"",3) -> TwinsBV
A41: 40 | B41: =_xlfn.XLOOKUP(D41,'[1]Sleutelplan nieuw'!B:B,'[1]Sleutelplan nieuw'!A:A,"",2) -> 0047 | C41: DS | D41: Bisschopstraat 68 | E41: 8325BD | F41: Vollenhove | G41: 6 | H41: 7 | I41: 45496 | J41: 45860 | L41: Werckpost | M41: =_xlfn.XLOOKUP(L41,'relaties_export_2026-01-12_1609'!B:B,'relaties_export_2026-01-12_1609'!A:A,"",3) -> 149 | N41: =_xlfn.XLOOKUP(M41,'relaties_export_2026-01-12_1609'!A:A,'relaties_export_2026-01-12_1609'!B:B,"",3) -> Werckpost Service B.V. | P41: =R41-U41-V41-AD41 -> 1123.24 | Q41: =T41*1.09+U41*1.21 -> 4401.4636 | R41: =T41+U41 -> 4038.04 | S41: =(R41/G41)/4.33333 -> 155.30935 | T41: 4038.04 | U41: 0 | V41: 0 | Y41: T. Hoolhorst | Z41: =_xlfn.XLOOKUP(Y41,'relaties_export_2026-01-12_1609'!B:B,'relaties_export_2026-01-12_1609'!A:A,"",3) -> 147 | AA41: =_xlfn.XLOOKUP(Z41,'relaties_export_2026-01-12_1609'!A:A,'relaties_export_2026-01-12_1609'!B:B,"",3) -> T. Hoolhorst | AB41: 06-10656043 | AC41: 2914.8 | AD41: 2914.8 | AE41: 2914.8 | AF41: =(AD41/G41)/4.33333 -> 112.10778 | AG41: 44621
A42: 41 | B42: =_xlfn.XLOOKUP(D42,'[1]Sleutelplan nieuw'!B:B,'[1]Sleutelplan nieuw'!A:A,"",2) -> 0048 | C42: DS | D42: Bliek 41 | E42: 3225XB | F42: Hellevoetsluis | G42: 5 | H42: 5 | I42: 45292 | J42: 45657 | L42: AmDor Projecten B.V. | M42: =_xlfn.XLOOKUP(L42,'relaties_export_2026-01-12_1609'!B:B,'relaties_export_2026-01-12_1609'!A:A,"",3) -> 124 | N42: =_xlfn.XLOOKUP(M42,'relaties_export_2026-01-12_1609'!A:A,'relaties_export_2026-01-12_1609'!B:B,"",3) -> AmDor Projecten B.V. | P42: =R42-U42-V42-AD42 -> 1801.77 | Q42: =T42*1.09+U42*1.21 -> 5117.3175 | R42: =T42+U42 -> 4650.75 | S42: =(R42/G42)/4.333 -> 214.66651 | T42: 4250.75 | U42: 400 | V42: 0 | Y42: A.P.W. Koedooder | Z42: =_xlfn.XLOOKUP(Y42,'relaties_export_2026-01-12_1609'!B:B,'relaties_export_2026-01-12_1609'!A:A,"",3) -> 77 | AA42: =_xlfn.XLOOKUP(Z42,'relaties_export_2026-01-12_1609'!A:A,'relaties_export_2026-01-12_1609'!B:B,"",3) -> A.P.W. Koedooder | AB42: 06-34970003 | AC42: 2448.98 | AD42: 2448.98 | AE42: 2448.98 | AF42: =(AD42/G42)/4.33333 -> 113.02993 | AG42: 44228 | AH42: 44592
B43: =_xlfn.XLOOKUP(D43,'[1]Sleutelplan nieuw'!B:B,'[1]Sleutelplan nieuw'!A:A,"",2) -> 0397 | D43: Boogertstraat 5A | E43: 3141VN | F43: Maassluis | G43: 3 | H43: 3 | I43: 46023 | J43: 46387 | L43: Bakker | M43: =_xlfn.XLOOKUP(L43,'relaties_export_2026-01-12_1609'!B:B,'relaties_export_2026-01-12_1609'!A:A,"",3) -> 23 | N43: =_xlfn.XLOOKUP(M43,'relaties_export_2026-01-12_1609'!A:A,'relaties_export_2026-01-12_1609'!B:B,"",3) -> S. Bakker OPH Verhuur | O43: Nieuw per 01-01-2026 | P43: =R43-U43-V43-AD43 -> 585 | Q43: =T43*1.09+U43*1.21 -> 3086.35 | R43: =T43+U43 -> 2815 | S43: =(R43/G43)/4.333 -> 216.55512 | T43: 2665 | U43: 150 | Y43: Holland Huisvesting B.V. | Z43: =_xlfn.XLOOKUP(Y43,'relaties_export_2026-01-12_1609'!B:B,'relaties_export_2026-01-12_1609'!A:A,"",3) -> 145 | AA43: =_xlfn.XLOOKUP(Z43,'relaties_export_2026-01-12_1609'!A:A,'relaties_export_2026-01-12_1609'!B:B,"",3) -> dockHolland Huisvesting B.V. | AB43: 06-57541069 | AC43: =AD43*1.21 -> 2516.8 | AD43: 2080 | AE43: 2020 | AF43: =(AD43/G43)/4.33333 -> 160.00012 | AG43: 46023 | AH43: 46387
B44: =_xlfn.XLOOKUP(D44,'[1]Sleutelplan nieuw'!B:B,'[1]Sleutelplan nieuw'!A:A,"",2) -> 0398 | D44: Boogertstraat 7A | E44: 3141VN | F44: Maassluis | G44: 3 | H44: 3 | I44: 46023 | J44: 46387 | L44: Bakker | M44: =_xlfn.XLOOKUP(L44,'relaties_export_2026-01-12_1609'!B:B,'relaties_export_2026-01-12_1609'!A:A,"",3) -> 23 | N44: =_xlfn.XLOOKUP(M44,'relaties_export_2026-01-12_1609'!A:A,'relaties_export_2026-01-12_1609'!B:B,"",3) -> S. Bakker OPH Verhuur | O44: Nieuw per 01-01-2026 | P44: =R44-U44-V44-AD44 -> 585 | Q44: =T44*1.09+U44*1.21 -> 3086.35 | R44: =T44+U44 -> 2815 | S44: =(R44/G44)/4.333 -> 216.55512 | T44: 2665 | U44: 150 | Y44: Holland Huisvesting B.V. | Z44: =_xlfn.XLOOKUP(Y44,'relaties_export_2026-01-12_1609'!B:B,'relaties_export_2026-01-12_1609'!A:A,"",3) -> 145 | AA44: =_xlfn.XLOOKUP(Z44,'relaties_export_2026-01-12_1609'!A:A,'relaties_export_2026-01-12_1609'!B:B,"",3) -> dockHolland Huisvesting B.V. | AB44: 06-57541069 | AC44: =AD44*1.21 -> 2516.8 | AD44: 2080 | AE44: 2020 | AF44: =(AD44/G44)/4.33333 -> 160.00012 | AG44: 46023 | AH44: 46387
A45: 42 | B45: =_xlfn.XLOOKUP(D45,'[1]Sleutelplan nieuw'!B:B,'[1]Sleutelplan nieuw'!A:A,"",2) -> 0049 | C45: DS | D45: Bornerbroeksestraat 129A | E45: 7601BE | F45: Almelo | G45: 4 | H45: 4 | I45: 45982 | J45: 46101 | L45: Team Unica B.V. | M45: =_xlfn.XLOOKUP(L45,'relaties_export_2026-01-12_1609'!B:B,'relaties_export_2026-01-12_1609'!A:A,"",3) -> 286 | N45: =_xlfn.XLOOKUP(M45,'relaties_export_2026-01-12_1609'!A:A,'relaties_export_2026-01-12_1609'!B:B,"",3) -> Team Unica B.V. | O45: Nieuw per 21-11-2025 | P45: =R45-U45-V45-AD45 -> 377.54 | Q45: =T45*1.09+U45*1.21 -> 2864 | R45: =T45+U45 -> 2600 | S45: =(R45/G45)/4.333 -> 150.01154 | T45: 2350 | U45: 250 | V45: 0 | Y45: J.L. Meerding | Z45: =_xlfn.XLOOKUP(Y45,'relaties_export_2026-01-12_1609'!B:B,'relaties_export_2026-01-12_1609'!A:A,"",3) -> 175 | AA45: =_xlfn.XLOOKUP(Z45,'relaties_export_2026-01-12_1609'!A:A,'relaties_export_2026-01-12_1609'!B:B,"",3) -> Dhr. J.L. Meerding | AB45: 06-41557847 | AC45: 1972.46 | AD45: 1972.46 | AE45: 1972.46 | AF45: =(AD45/G45)/4.33333 -> 113.79586 | AG45: 44805 | AH45: 46630
B46: =_xlfn.XLOOKUP(D46,'[1]Sleutelplan nieuw'!B:B,'[1]Sleutelplan nieuw'!A:A,"",2) -> 0280 | C46: DS | D46: Bovendijk 59 | F46: Kwintsheul | M46: =_xlfn.XLOOKUP(L46,'relaties_export_2026-01-12_1609'!B:B,'relaties_export_2026-01-12_1609'!A:A,"",3) -> id | N46: =_xlfn.XLOOKUP(M46,'relaties_export_2026-01-12_1609'!A:A,'relaties_export_2026-01-12_1609'!B:B,"",3) -> naam | Y46: M. Nottet | Z46: =_xlfn.XLOOKUP(Y46,'relaties_export_2026-01-12_1609'!B:B,'relaties_export_2026-01-12_1609'!A:A,"",3) -> 952 | AA46: =_xlfn.XLOOKUP(Z46,'relaties_export_2026-01-12_1609'!A:A,'relaties_export_2026-01-12_1609'!B:B,"",3) -> M. Nottet
B47: =_xlfn.XLOOKUP(D47,'[1]Sleutelplan nieuw'!B:B,'[1]Sleutelplan nieuw'!A:A,"",2) -> 0281 | C47: DS | D47: Bovendijk 61 | F47: Kwintsheul | M47: =_xlfn.XLOOKUP(L47,'relaties_export_2026-01-12_1609'!B:B,'relaties_export_2026-01-12_1609'!A:A,"",3) -> id | N47: =_xlfn.XLOOKUP(M47,'relaties_export_2026-01-12_1609'!A:A,'relaties_export_2026-01-12_1609'!B:B,"",3) -> naam | Y47: M. Nottet | Z47: =_xlfn.XLOOKUP(Y47,'relaties_export_2026-01-12_1609'!B:B,'relaties_export_2026-01-12_1609'!A:A,"",3) -> 952 | AA47: =_xlfn.XLOOKUP(Z47,'relaties_export_2026-01-12_1609'!A:A,'relaties_export_2026-01-12_1609'!B:B,"",3) -> M. Nottet
A48: 43 | B48: =_xlfn.XLOOKUP(D48,'[1]Sleutelplan nieuw'!B:B,'[1]Sleutelplan nieuw'!A:A,"",2) -> 0004 | C48: Factuur | D48: Broekweg 25 | E48: 3131 HC | F48: Vlaardingen | G48: 4 | I48: 44958 | J48: 45352 | L48: Tradiro | M48: =_xlfn.XLOOKUP(L48,'relaties_export_2026-01-12_1609'!B:B,'relaties_export_2026-01-12_1609'!A:A,"",3) -> 17 | N48: =_xlfn.XLOOKUP(M48,'relaties_export_2026-01-12_1609'!A:A,'relaties_export_2026-01-12_1609'!B:B,"",3) -> Tradiro Services B.V. | P48: =R48-U48-V48-AD48 -> 308.41 | Q48: =T48*1.09+U48*1.21 -> 1862.1669 | R48: =T48+U48 -> 1708.41 | S48: =(R48/G48)/4.33333 -> 98.562191 | T48: 1708.41 | U48: 0 | V48: 0 | Y48: Parkwonen | Z48: =_xlfn.XLOOKUP(Y48,'relaties_export_2026-01-12_1609'!B:B,'relaties_export_2026-01-12_1609'!A:A,"",3) -> 258 | AA48: =_xlfn.XLOOKUP(Z48,'relaties_export_2026-01-12_1609'!A:A,'relaties_export_2026-01-12_1609'!B:B,"",3) -> Parkwonen | AC48: 1400 | AD48: 1400 | AE48: 1400 | AF48: =(AD48/G48)/4.33333 -> 80.769293 | AG48: 44927 | AH48: 45292
A49: 44 | B49: =_xlfn.XLOOKUP(D49,'[1]Sleutelplan nieuw'!B:B,'[1]Sleutelplan nieuw'!A:A,"",2) -> 0027 | C49: Factuur | D49: Buizerdstraat 210 | E49: 3145 AD | F49: Maassluis | G49: 4 | H49: 5 | I49: 44986 | J49: 45352 | L49: Tradiro | M49: =_xlfn.XLOOKUP(L49,'relaties_export_2026-01-12_1609'!B:B,'relaties_export_2026-01-12_1609'!A:A,"",3) -> 17 | N49: =_xlfn.XLOOKUP(M49,'relaties_export_2026-01-12_1609'!A:A,'relaties_export_2026-01-12_1609'!B:B,"",3) -> Tradiro Services B.V. | P49: =R49-U49-V49-AD49 -> 232.89 | Q49: =T49*1.09+U49*1.21 -> 1828.9001 | R49: =T49+U49 -> 1677.89 | S49: =(R49/G49)/4.33333 -> 96.801421 | T49: 1677.89 | U49: 0 | V49: 0 | Y49: W. van Straalen | Z49: =_xlfn.XLOOKUP(Y49,'relaties_export_2026-01-12_1609'!B:B,'relaties_export_2026-01-12_1609'!A:A,"",3) -> 797 | AA49: =_xlfn.XLOOKUP(Z49,'relaties_export_2026-01-12_1609'!A:A,'relaties_export_2026-01-12_1609'!B:B,"",3) -> W. van Straalen | AC49: 1445 | AD49: 1445 | AE49: 1445 | AF49: =(AD49/G49)/4.33333 -> 83.365449 | AG49: 44986 | AH49: 45352
A50: 45 | B50: =_xlfn.XLOOKUP(D50,'[1]Sleutelplan nieuw'!B:B,'[1]Sleutelplan nieuw'!A:A,"",2) -> 0097 | C50: DS | D50: Burchstraat 16A | E50: 4501 BJ | F50: Oostburg | G50: 7 | H50: 7 | I50: 45863 | L50: Tradiro | M50: =_xlfn.XLOOKUP(L50,'relaties_export_2026-01-12_1609'!B:B,'relaties_export_2026-01-12_1609'!A:A,"",3) -> 17 | N50: =_xlfn.XLOOKUP(M50,'relaties_export_2026-01-12_1609'!A:A,'relaties_export_2026-01-12_1609'!B:B,"",3) -> Tradiro Services B.V. | P50: =R50-U50-V50-AD50 -> 942.5 | Q50: =T50*1.09+U50*1.21 -> 4414 | R50: =T50+U50 -> 4000 | S50: =(R50/G50)/4.33333 -> 131.86823 | T50: 3550 | U50: 450 | V50: 0 | Y50: A.H.S. Willemsen | Z50: =_xlfn.XLOOKUP(Y50,'relaties_export_2026-01-12_1609'!B:B,'relaties_export_2026-01-12_1609'!A:A,"",3) -> 302 | AA50: =_xlfn.XLOOKUP(Z50,'relaties_export_2026-01-12_1609'!A:A,'relaties_export_2026-01-12_1609'!B:B,"",3) -> A.H.S. Willemsen | AB50: 06-20061294 | AC50: 2607.5 | AD50: 2607.5 | AE50: 2582.5 | AF50: =(AD50/G50)/4.33333 -> 85.961605 | AG50: 45413 | AH50: 46142
B51: =_xlfn.XLOOKUP(D51,'[1]Sleutelplan nieuw'!B:B,'[1]Sleutelplan nieuw'!A:A,"",2) -> 0160 | C51: Factuur | D51: Chopinstraat 33C | F51: Vlaardingen | L51: Tradiro | M51: =_xlfn.XLOOKUP(L51,'relaties_export_2026-01-12_1609'!B:B,'relaties_export_2026-01-12_1609'!A:A,"",3) -> 17 | N51: =_xlfn.XLOOKUP(M51,'relaties_export_2026-01-12_1609'!A:A,'relaties_export_2026-01-12_1609'!B:B,"",3) -> Tradiro Services B.V. | Y51: In Stones | Z51: 295 | AA51: =_xlfn.XLOOKUP(Z51,'relaties_export_2026-01-12_1609'!A:A,'relaties_export_2026-01-12_1609'!B:B,"",3) -> In Stijl Totaalbouw BV | AC51: 1300 | AD51: 1300 | AE51: 1300
A52: 46 | B52: 0131 | C52: Factuur | D52: Chopinstraat 35A | E52: 3131 BD | F52: Vlaardingen | G52: 4 | H52: 3 | I52: 45323 | J52: 45688 | L52: Tradiro | M52: =_xlfn.XLOOKUP(L52,'relaties_export_2026-01-12_1609'!B:B,'relaties_export_2026-01-12_1609'!A:A,"",3) -> 17 | N52: =_xlfn.XLOOKUP(M52,'relaties_export_2026-01-12_1609'!A:A,'relaties_export_2026-01-12_1609'!B:B,"",3) -> Tradiro Services B.V. | P52: =R52-U52-V52-AD52 -> 665.26 | Q52: =T52*1.09+U52*1.21 -> 2360.1334 | R52: =T52+U52 -> 2165.26 | S52: =(R52/G52)/4.33333 -> 124.91894 | T52: 2165.26 | U52: 0 | V52: 0 | Y52: Parkwonen | Z52: =_xlfn.XLOOKUP(Y52,'relaties_export_2026-01-12_1609'!B:B,'relaties_export_2026-01-12_1609'!A:A,"",3) -> 258 | AA52: =_xlfn.XLOOKUP(Z52,'relaties_export_2026-01-12_1609'!A:A,'relaties_export_2026-01-12_1609'!B:B,"",3) -> Parkwonen | AC52: 1500 | AD52: 1500 | AE52: 1500 | AF52: =(AD52/G52)/4.33333 -> 86.538528 | AG52: 45323 | AH52: 45689
A53: 47 | B53: =_xlfn.XLOOKUP(D53,'[1]Sleutelplan nieuw'!B:B,'[1]Sleutelplan nieuw'!A:A,"",2) -> 0026 | C53: Factuur | D53: Chopinstraat 39C | E53: 3131 DB | F53: Vlaardingen | G53: 5 | H53: 3 | I53: 44958 | J53: 45323 | L53: Tradiro | M53: =_xlfn.XLOOKUP(L53,'relaties_export_2026-01-12_1609'!B:B,'relaties_export_2026-01-12_1609'!A:A,"",3) -> 17 | N53: =_xlfn.XLOOKUP(M53,'relaties_export_2026-01-12_1609'!A:A,'relaties_export_2026-01-12_1609'!B:B,"",3) -> Tradiro Services B.V. | P53: =R53-U53-V53-AD53 -> 352.46 | Q53: =T53*1.09+U53*1.21 -> 2128.1814 | R53: =T53+U53 -> 1952.46 | S53: =(R53/G53)/4.33333 -> 90.113608 | T53: 1952.46 | U53: 0 | V53: 0 | Y53: Parkwonen | Z53: =_xlfn.XLOOKUP(Y53,'relaties_export_2026-01-12_1609'!B:B,'relaties_export_2026-01-12_1609'!A:A,"",3) -> 258 | AA53: =_xlfn.XLOOKUP(Z53,'relaties_export_2026-01-12_1609'!A:A,'relaties_export_2026-01-12_1609'!B:B,"",3) -> Parkwonen | AC53: 1600 | AD53: 1600 | AE53: 1600 | AF53: =(AD53/G53)/4.33333 -> 73.846211 | AG53: 44927 | AH53: 45292
B54: =_xlfn.XLOOKUP(D54,'[1]Sleutelplan nieuw'!B:B,'[1]Sleutelplan nieuw'!A:A,"",2) -> 0370 | C54: Factuur | D54: Cloosterstraat 23a | E54: 4587CA | F54: Kloosterzande | G54: 5 | H54: 4 | I54: 45818 | J54: 45899 | L54: Tradiro | M54: =_xlfn.XLOOKUP(L54,'relaties_export_2026-01-12_1609'!B:B,'relaties_export_2026-01-12_1609'!A:A,"",3) -> 17 | N54: =_xlfn.XLOOKUP(M54,'relaties_export_2026-01-12_1609'!A:A,'relaties_export_2026-01-12_1609'!B:B,"",3) -> Tradiro Services B.V. | O54: Terug naar eigenaar per 15-12 | P54: =R54-U54-V54-AD54 -> 0 | Y54: 4 Homes | Z54: =_xlfn.XLOOKUP(Y54,'relaties_export_2026-01-12_1609'!B:B,'relaties_export_2026-01-12_1609'!A:A,"",3) -> 85 | AA54: =_xlfn.XLOOKUP(Z54,'relaties_export_2026-01-12_1609'!A:A,'relaties_export_2026-01-12_1609'!B:B,"",3) -> 4 Homes B.V. | AB54: 0167-745023
A55: 48 | B55: =_xlfn.XLOOKUP(D55,'[1]Sleutelplan nieuw'!B:B,'[1]Sleutelplan nieuw'!A:A,"",2) -> 0051 | C55: Factuur | D55: Coehoorn van Scheltingaweg 12 | E55: 8442EX | F55: Heerenveen | G55: 4 | H55: 3 | I55: 44835 | J55: 45412 | L55: United Homes | M55: =_xlfn.XLOOKUP(L55,'relaties_export_2026-01-12_1609'!B:B,'relaties_export_2026-01-12_1609'!A:A,"",3) -> 13 | N55: =_xlfn.XLOOKUP(M55,'relaties_export_2026-01-12_1609'!A:A,'relaties_export_2026-01-12_1609'!B:B,"",3) -> United Homes B.V. | P55: =R55-U55-V55-AD55 -> 647.66 | Q55: =T55*1.09+U55*1.21 -> 2171.1928 | R55: =T55+U55 -> 1991.92 | S55: =(R55/G55)/4.33333 -> 114.91855 | T55: 1991.92 | U55: 0 | V55: 0 | Y55: Sill Marinus Dijkstra Vastgoedbeheer) | Z55: =_xlfn.XLOOKUP(Y55,'relaties_export_2026-01-12_1609'!B:B,'relaties_export_2026-01-12_1609'!A:A,"",3) -> #VALUE! | AA55: =_xlfn.XLOOKUP(Z55,'relaties_export_2026-01-12_1609'!A:A,'relaties_export_2026-01-12_1609'!B:B,"",3) -> #VALUE! | AB55: 0512-541400 | AC55: 1344.26 | AD55: 1344.26 | AE55: 1344.26 | AF55: =(AD55/G55)/4.33333 -> 77.553521 | AG55: 44620 | AH55: 44984
A56: 49 | B56: =_xlfn.XLOOKUP(D56,'[1]Sleutelplan nieuw'!B:B,'[1]Sleutelplan nieuw'!A:A,"",2) -> 0052 | C56: Factuur | D56: Coehoorn van Scheltingaweg 66 | E56: 8442GA | F56: Heerenveen | G56: 4 | H56: 3 | I56: 44835 | J56: 45412 | L56: United Homes | M56: =_xlfn.XLOOKUP(L56,'relaties_export_2026-01-12_1609'!B:B,'relaties_export_2026-01-12_1609'!A:A,"",3) -> 13 | N56: =_xlfn.XLOOKUP(M56,'relaties_export_2026-01-12_1609'!A:A,'relaties_export_2026-01-12_1609'!B:B,"",3) -> United Homes B.V. | P56: =R56-U56-V56-AD56 -> 598.11 | Q56: =T56*1.09+U56*1.21 -> 2083.8511 | R56: =T56+U56 -> 1911.79 | S56: =(R56/G56)/4.33333 -> 110.29566 | T56: 1911.79 | U56: 0 | V56: 0 | Y56: Sill Marinus Dijkstra Vastgoedbeheer) | Z56: =_xlfn.XLOOKUP(Y56,'relaties_export_2026-01-12_1609'!B:B,'relaties_export_2026-01-12_1609'!A:A,"",3) -> #VALUE! | AA56: =_xlfn.XLOOKUP(Z56,'relaties_export_2026-01-12_1609'!A:A,'relaties_export_2026-01-12_1609'!B:B,"",3) -> #VALUE! | AB56: 0512-541400 | AC56: 1313.68 | AD56: 1313.68 | AE56: 1313.68 | AF56: =(AD56/G56)/4.33333 -> 75.789289 | AG56: 44682 | AH56: 45046
B57: {=_xlfn.XLOOKUP(LEFT(D57,3),LEFT('[1]Sleutelplan nieuw'!B:B,3),'[1]Sleutelplan nieuw'!A:A,"",2)} -> 0375 | C57: Factuur | D57: Cubalaan 25 | E57: 2685 LA | F57: Poeldijk | G57: 8 | H57: 5 | I57: 45856 | L57: Tradiro | M57: =_xlfn.XLOOKUP(L57,'relaties_export_2026-01-12_1609'!B:B,'relaties_export_2026-01-12_1609'!A:A,"",3) -> 17 | N57: =_xlfn.XLOOKUP(M57,'relaties_export_2026-01-12_1609'!A:A,'relaties_export_2026-01-12_1609'!B:B,"",3) -> Tradiro Services B.V. | P57: =R57-U57-V57-AD57 -> 1250 | Q57: =T57*1.09+U57*1.21 -> 5831 | R57: =T57+U57 -> 5300 | S57: =(R57/G57)/4.33333 -> 152.88473 | T57: 4850 | U57: 450 | Y57: Z. Yilmaz | Z57: =_xlfn.XLOOKUP(Y57,'relaties_export_2026-01-12_1609'!B:B,'relaties_export_2026-01-12_1609'!A:A,"",3) -> 799 | AA57: =_xlfn.XLOOKUP(Z57,'relaties_export_2026-01-12_1609'!A:A,'relaties_export_2026-01-12_1609'!B:B,"",3) -> Z. Yilmaz | AB57: 06-19418327 | AC57: 3600 | AD57: 3600 | AE57: 3600 | AF57: =(AD57/G57)/4.33333 -> 103.84623 | AG57: 45853 | AH57: 46265
A58: 51 | B58: =_xlfn.XLOOKUP(D58,'[1]Sleutelplan nieuw'!B:B,'[1]Sleutelplan nieuw'!A:A,"",2) -> 0053 | C58: Factuur | D58: Curcumastraat 39 | E58: 3193XA | F58: Hoogvliet | G58: 4 | H58: 4 | I58: 45667 | J58: 46032 | L58: OJP | M58: =_xlfn.XLOOKUP(L58,'relaties_export_2026-01-12_1609'!B:B,'relaties_export_2026-01-12_1609'!A:A,"",3) -> 123 | N58: =_xlfn.XLOOKUP(M58,'relaties_export_2026-01-12_1609'!A:A,'relaties_export_2026-01-12_1609'!B:B,"",3) -> OJP B.V. | P58: =R58-U58-V58-AD58 -> 1869.91 | Q58: =T58*1.09+U58*1.21 -> 3990.2425 | R58: =T58+U58 -> 3633.25 | S58: =(R58/G58)/4.33333 -> 209.61074 | T58: 3383.25 | U58: 250 | V58: 0 | Y58: Ruva Vastgoed B.V. | Z58: =_xlfn.XLOOKUP(Y58,'relaties_export_2026-01-12_1609'!B:B,'relaties_export_2026-01-12_1609'!A:A,"",3) -> 5 | AA58: =_xlfn.XLOOKUP(Z58,'relaties_export_2026-01-12_1609'!A:A,'relaties_export_2026-01-12_1609'!B:B,"",3) -> Ruva Vastgoed B.V. | AB58: 06-53168285 | AC58: 1513.34 | AD58: 1513.34 | AE58: 1513.34 | AF58: =(AD58/G58)/4.33333 -> 87.308144 | AG58: 43560 | AH58: 43921 | AI58: onbepaalde tijd | AJ58: 12 maanden | AK58: 43560 | AL58: 43921 | AM58: 1 kalendermaand | AO58: eenmans | AR58: bepaalde tijd | AS58: 11 maand, 16 d | AT58: 44212 | AU58: 44561 | AW58: BV | AZ58: inhuur contract aanpassen
A59: 52 | B59: =_xlfn.XLOOKUP(D59,'[1]Sleutelplan nieuw'!B:B,'[1]Sleutelplan nieuw'!A:A,"",2) -> 0151 | C59: Factuur | D59: Datheenstraat 255 | E59: 3132PG | F59: Vlaardingen | G59: 3 | H59: 3 | I59: 45292 | J59: 45657 | L59: GAP Costruzioni | M59: =_xlfn.XLOOKUP(L59,'relaties_export_2026-01-12_1609'!B:B,'relaties_export_2026-01-12_1609'!A:A,"",3) -> 374 | N59: =_xlfn.XLOOKUP(M59,'relaties_export_2026-01-12_1609'!A:A,'relaties_export_2026-01-12_1609'!B:B,"",3) -> GAP Costruzioni S.r.l. | P59: =R59-U59-V59-AD59 -> 1141.93 | Q59: =T59*1.09+U59*1.21 -> 3097.7037 | R59: =T59+U59 -> 2841.93 | S59: =(R59/G59)/4.33333 -> 218.61017 | T59: 2841.93 | U59: 0 | V59: 0 | Y59: Houses2Rent | Z59: =_xlfn.XLOOKUP(Y59,'relaties_export_2026-01-12_1609'!B:B,'relaties_export_2026-01-12_1609'!A:A,"",3) -> 271 | AA59: =_xlfn.XLOOKUP(Z59,'relaties_export_2026-01-12_1609'!A:A,'relaties_export_2026-01-12_1609'!B:B,"",3) -> Houses2Rent | AC59: =AD59*1.09 -> 1853 | AD59: 1700 | AE59: 1700 | AF59: =(AD59/G59)/4.33333 -> 130.76933
B60: =_xlfn.XLOOKUP(D60,'[1]Sleutelplan nieuw'!B:B,'[1]Sleutelplan nieuw'!A:A,"",2) -> 0165 | C60: Factuur | D60: De Driesprong 17 | E60: 2295LL | F60: KWINTSHEUL | L60: Tradiro | M60: =_xlfn.XLOOKUP(L60,'relaties_export_2026-01-12_1609'!B:B,'relaties_export_2026-01-12_1609'!A:A,"",3) -> 17 | N60: =_xlfn.XLOOKUP(M60,'relaties_export_2026-01-12_1609'!A:A,'relaties_export_2026-01-12_1609'!B:B,"",3) -> Tradiro Services B.V. | Y60: Ruu vd Hoeven en Raymond Vijverberg | Z60: =_xlfn.XLOOKUP(Y60,'relaties_export_2026-01-12_1609'!B:B,'relaties_export_2026-01-12_1609'!A:A,"",3) | AA60: =_xlfn.XLOOKUP(Z60,'relaties_export_2026-01-12_1609'!A:A,'relaties_export_2026-01-12_1609'!B:B,"",3) -> naam | AC60: 5048 | AD60: 5048 | AE60: 4761
A61: 53 | B61: =_xlfn.XLOOKUP(D61,'[1]Sleutelplan nieuw'!B:B,'[1]Sleutelplan nieuw'!A:A,"",2) -> 0056 | C61: DS | D61: De Hooidollen 606 | E61: 8918JZ | F61: Leeuwarden | G61: 4 | H61: 4 | I61: 45000 | J61: 45365 | L61: Interwel Oost B.V. | M61: =_xlfn.XLOOKUP(L61,'relaties_export_2026-01-12_1609'!B:B,'relaties_export_2026-01-12_1609'!A:A,"",3) -> 122 | N61: =_xlfn.XLOOKUP(M61,'relaties_export_2026-01-12_1609'!A:A,'relaties_export_2026-01-12_1609'!B:B,"",3) -> Interwel Oost B.V. | P61: =R61-U61-V61-AD61 -> 540.93 | Q61: =T61*1.09+U61*1.21 -> 2230.5978 | R61: =T61+U61 -> 2046.42 | S61: =(R61/G61)/4.33333 -> 118.06278 | T61: 2046.42 | U61: 0 | V61: 0 | Y61: L. Schilstra / Eigenaar.nl | Z61: =_xlfn.XLOOKUP(Y61,'relaties_export_2026-01-12_1609'!B:B,'relaties_export_2026-01-12_1609'!A:A,"",3) -> 800 | AA61: =_xlfn.XLOOKUP(Z61,'relaties_export_2026-01-12_1609'!A:A,'relaties_export_2026-01-12_1609'!B:B,"",3) -> L. Schilstra / Eigenaar.nl | AB61: 085-1306475 / 06-16913859 | AC61: 1505.49 | AD61: 1505.49 | AE61: 1505.49 | AF61: =(AD61/G61)/4.33333 -> 86.855259 | AG61: 43896 | AH61: 44316 | AI61: onbepaalde tijd | AJ61: 14 maanden | AK61: 43896 | AL61: 44316 | AM61: 1 kalendermaand | AO61: eenmans | AR61: onbepaalde tijd | AS61: 1 maand | AT61: 43897 | AU61: 43927 | AV61: 1 maand | AW61: eenmans | AZ61: eigenaar bellen + nieuwe contracten
A62: 54 | B62: 0371 | C62: Factuur | D62: De Zwingel 8B | E62: 4926DC | F62: Lage Zwaluwe | G62: 28 | I62: 45778 | J62: nog invullen | L62: Tradiro | M62: =_xlfn.XLOOKUP(L62,'relaties_export_2026-01-12_1609'!B:B,'relaties_export_2026-01-12_1609'!A:A,"",3) -> 17 | N62: =_xlfn.XLOOKUP(M62,'relaties_export_2026-01-12_1609'!A:A,'relaties_export_2026-01-12_1609'!B:B,"",3) -> Tradiro Services B.V. | P62: =R62-U62-V62-AD62 -> 1516.57 | Q62: =T62*1.09+U62*1.21 -> 14217.124 | R62: 13043.23 | S62: =(R62/G62)/4.33333 -> 107.49923 | T62: =107.5*28*4.3333 -> 13043.233 | U62: 0 | Y62: Tetering en Martens | Z62: =_xlfn.XLOOKUP(Y62,'relaties_export_2026-01-12_1609'!B:B,'relaties_export_2026-01-12_1609'!A:A,"",3) -> 683 | AA62: =_xlfn.XLOOKUP(Z62,'relaties_export_2026-01-12_1609'!A:A,'relaties_export_2026-01-12_1609'!B:B,"",3) -> Tetering en Martens | AB62: 06-23368727 / 06-11270302 | AC62: 11526.66 | AD62: 11526.66 | AE62: 11526.66 | AF62: =(AD62/G62)/4.33333 -> 95.000018 | AG62: 45778 | AH62: 46873
A63: 55 | B63: =_xlfn.XLOOKUP(D63,'[1]Sleutelplan nieuw'!B:B,'[1]Sleutelplan nieuw'!A:A,"",2) -> 0153 | C63: Factuur | D63: Deensestraat 6A2 | E63: 3028GH | F63: Rotterdam | G63: 4 | H63: 4 | I63: 45292 | J63: 45657 | L63: GAP Costruzioni | M63: =_xlfn.XLOOKUP(L63,'relaties_export_2026-01-12_1609'!B:B,'relaties_export_2026-01-12_1609'!A:A,"",3) -> 374 | N63: =_xlfn.XLOOKUP(M63,'relaties_export_2026-01-12_1609'!A:A,'relaties_export_2026-01-12_1609'!B:B,"",3) -> GAP Costruzioni S.r.l. | P63: =R63-U63-V63-AD63 -> 2089.24 | Q63: =T63*1.09+U63*1.21 -> 4130.2716 | R63: =T63+U63 -> 3789.24 | S63: =(R63/G63)/4.33333 -> 218.61017 | T63: 3789.24 | U63: 0 | V63: 0 | Y63: Houses2Rent | Z63: =_xlfn.XLOOKUP(Y63,'relaties_export_2026-01-12_1609'!B:B,'relaties_export_2026-01-12_1609'!A:A,"",3) -> 271 | AA63: =_xlfn.XLOOKUP(Z63,'relaties_export_2026-01-12_1609'!A:A,'relaties_export_2026-01-12_1609'!B:B,"",3) -> Houses2Rent | AC63: =AD63*1.09 -> 1853 | AD63: 1700 | AE63: 1700 | AF63: =(AD63/G63)/4.33333 -> 98.076999
A64: 56 | B64: {=_xlfn.XLOOKUP(LEFT(D64,3),LEFT('[1]Sleutelplan nieuw'!B:B,3),'[1]Sleutelplan nieuw'!A:A,"",2)} -> 0023 | C64: DS | D64: Desiree Geerartstraat 1B | E64: 5111CH | F64: Baarle-Nassau | G64: 8 | H64: 5 | I64: 45583 | J64: 45765 | L64: NL Realty | M64: =_xlfn.XLOOKUP(L64,'relaties_export_2026-01-12_1609'!B:B,'relaties_export_2026-01-12_1609'!A:A,"",3) -> 236 | N64: =_xlfn.XLOOKUP(M64,'relaties_export_2026-01-12_1609'!A:A,'relaties_export_2026-01-12_1609'!B:B,"",3) -> NL Realty B.V. | P64: =R64-U64-V64-AD64 -> 514.88 | Q64: =T64*1.09+U64*1.21 -> 4396.9292 | R64: =T64+U64 -> 4033.88 | S64: =(R64/G64)/4.33333 -> 116.36201 | T64: 4033.88 | U64: 0 | Y64: S. Kleiren | Z64: =_xlfn.XLOOKUP(Y64,'relaties_export_2026-01-12_1609'!B:B,'relaties_export_2026-01-12_1609'!A:A,"",3) -> 326 | AA64: =_xlfn.XLOOKUP(Z64,'relaties_export_2026-01-12_1609'!A:A,'relaties_export_2026-01-12_1609'!B:B,"",3) -> S. Kleiren | AB64: 06-30085250 | AC64: 3519 | AD64: 3519 | AE64: 3519 | AF64: =(AD64/G64)/4.33333 -> 101.50969 | AG64: 45583 | AH64: 46678
A65: 57 | B65: 0024 | C65: DS | D65: Desiree Geerartstraat 1C | E65: 5111CH | F65: Baarle-Nassau | G65: 8 | H65: 6 | I65: 45583 | J65: 45765 | L65: NL Realty | M65: =_xlfn.XLOOKUP(L65,'relaties_export_2026-01-12_1609'!B:B,'relaties_export_2026-01-12_1609'!A:A,"",3) -> 236 | N65: =_xlfn.XLOOKUP(M65,'relaties_export_2026-01-12_1609'!A:A,'relaties_export_2026-01-12_1609'!B:B,"",3) -> NL Realty B.V. | P65: =R65-U65-V65-AD65 -> 514.88 | Q65: =T65*1.09+U65*1.21 -> 4396.9292 | R65: =T65+U65 -> 4033.88 | S65: =(R65/G65)/4.33333 -> 116.36201 | T65: 4033.88 | U65: 0 | Y65: S. Kleiren | Z65: =_xlfn.XLOOKUP(Y65,'relaties_export_2026-01-12_1609'!B:B,'relaties_export_2026-01-12_1609'!A:A,"",3) -> 326 | AA65: =_xlfn.XLOOKUP(Z65,'relaties_export_2026-01-12_1609'!A:A,'relaties_export_2026-01-12_1609'!B:B,"",3) -> S. Kleiren | AB65: 06-30085250 | AC65: 3519 | AD65: 3519 | AE65: 3519 | AF65: =(AD65/G65)/4.33333 -> 101.50969 | AG65: 45583 | AH65: 46678
A66: 58 | B66: =_xlfn.XLOOKUP(D66,'[1]Sleutelplan nieuw'!B:B,'[1]Sleutelplan nieuw'!A:A,"",2) -> 0058 | C66: DS | D66: Deugenweerd 18 | E66: 7271XT | F66: Borculo | G66: 6 | H66: 6 | I66: 45807 | J66: 45898 | L66: Employ | M66: =_xlfn.XLOOKUP(L66,'relaties_export_2026-01-12_1609'!B:B,'relaties_export_2026-01-12_1609'!A:A,"",3) -> 34 | N66: =_xlfn.XLOOKUP(M66,'relaties_export_2026-01-12_1609'!A:A,'relaties_export_2026-01-12_1609'!B:B,"",3) -> Employ | P66: =R66-U66-V66-AD66 -> 343 | Q66: =T66*1.09+U66*1.21 -> 2997.5 | R66: 2750 | S66: =(R66/G66)/4.33333 -> 105.76931 | T66: 2750 | Y66: Roestenberg | Z66: =_xlfn.XLOOKUP(Y66,'relaties_export_2026-01-12_1609'!B:B,'relaties_export_2026-01-12_1609'!A:A,"",3) -> 206 | AA66: =_xlfn.XLOOKUP(Z66,'relaties_export_2026-01-12_1609'!A:A,'relaties_export_2026-01-12_1609'!B:B,"",3) -> Dhr. T. Roestenberg en Mw. Roestenberg - Hustinx | AB66: 06-19914413 | AC66: 2407 | AD66: 2407 | AE66: 2407 | AF66: =(AD66/G66)/4.33333 -> 92.576994 | AG66: =#REF! -> #REF! | AH66: =X66 -> 0
A67: 59 | B67: =_xlfn.XLOOKUP(D67,'[1]Sleutelplan nieuw'!B:B,'[1]Sleutelplan nieuw'!A:A,"",2) -> 0059 | C67: DS | D67: Dieptol 63 | E67: 8332BK | F67: Steenwijk | G67: 6 | H67: 6 | I67: 45931 | J67: 46295 | L67: Kapitan workers | M67: 367 | N67: =_xlfn.XLOOKUP(M67,'relaties_export_2026-01-12_1609'!A:A,'relaties_export_2026-01-12_1609'!B:B,"",3) -> Kapitan Workers Sp. Z.o.o. | O67: Nieuw per 04-10-2025 | P67: =R67-U67-V67-AD67 -> 808.8 | Q67: =T67*1.09+U67*1.21 -> 4081 | R67: =T67+U67 -> 3700 | S67: =(R67/G67)/4.33333 -> 142.3078 | T67: 3300 | U67: 400 | V67: 0 | Y67: P. Ter Haar - Ros | Z67: =_xlfn.XLOOKUP(Y67,'relaties_export_2026-01-12_1609'!B:B,'relaties_export_2026-01-12_1609'!A:A,"",3) -> 801 | AA67: =_xlfn.XLOOKUP(Z67,'relaties_export_2026-01-12_1609'!A:A,'relaties_export_2026-01-12_1609'!B:B,"",3) -> P. Ter Haar - Ros | AB67: 06-51117154 / 06-27036919 | AC67: 2491.2 | AD67: 2491.2 | AE67: 2491.2 | AF67: =(AD67/G67)/4.33333 -> 95.815458 | AG67: 44986 | AH67: 45351
C68: Factuur | D68: Donze visserstraat | E68: 4531BA | F68: Terneuzen | G68: 5 | H68: 4 | I68: 46006 | J68: 46142 | L68: Tradiro | M68: =_xlfn.XLOOKUP(L68,'relaties_export_2026-01-12_1609'!B:B,'relaties_export_2026-01-12_1609'!A:A,"",3) -> 17 | N68: =_xlfn.XLOOKUP(M68,'relaties_export_2026-01-12_1609'!A:A,'relaties_export_2026-01-12_1609'!B:B,"",3) -> Tradiro Services B.V. | O68: Nieuw per 15-12-2025 | P68: =R68-U68-V68-AD68 -> 250 | Q68: =T68*1.09+U68*1.21 -> 3106.5 | R68: =T68+U68 -> 2850 | S68: =(R68/G68)/4.33333 -> 131.53856 | T68: 2850 | Y68: 4 Homes B.V. | Z68: =_xlfn.XLOOKUP(Y68,'relaties_export_2026-01-12_1609'!B:B,'relaties_export_2026-01-12_1609'!A:A,"",3) -> 85 | AA68: =_xlfn.XLOOKUP(Z68,'relaties_export_2026-01-12_1609'!A:A,'relaties_export_2026-01-12_1609'!B:B,"",3) -> 4 Homes B.V. | AB68: 0167-745023 | AC68: 2600 | AD68: 2600 | AE68: 2600 | AF68: =(AD68/G68)/4.33333 -> 120.00009
A69: 60 | B69: =_xlfn.XLOOKUP(D69,'[1]Sleutelplan nieuw'!B:B,'[1]Sleutelplan nieuw'!A:A,"",2) -> 0354 | C69: Factuur | D69: Dorpsstraat 48 | E69: 2445AN | F69: Aarlanderveen | G69: 15 | H69: 8 | I69: 45745 | J69: OBT | L69: Tradiro | M69: =_xlfn.XLOOKUP(L69,'relaties_export_2026-01-12_1609'!B:B,'relaties_export_2026-01-12_1609'!A:A,"",3) -> 17 | N69: =_xlfn.XLOOKUP(M69,'relaties_export_2026-01-12_1609'!A:A,'relaties_export_2026-01-12_1609'!B:B,"",3) -> Tradiro Services B.V. | O69: terug naar eigenaar 03-10-2025 | P69: =R69-U69-V69-AD69 -> 0 | S69: =(R69/G69)/4.33333 -> 0 | Y69: Facili Flex BV | Z69: =_xlfn.XLOOKUP(Y69,'relaties_export_2026-01-12_1609'!B:B,'relaties_export_2026-01-12_1609'!A:A,"",3) -> 253 | AA69: =_xlfn.XLOOKUP(Z69,'relaties_export_2026-01-12_1609'!A:A,'relaties_export_2026-01-12_1609'!B:B,"",3) -> Facili Flex BV | AB69: 0297-389680 | AF69: =(AD69/G69)/4.33333 -> 0 | AG69: 45745 | AH69: 45929
A70: 62 | B70: {=_xlfn.XLOOKUP(LEFT(D70,3),LEFT('[1]Sleutelplan nieuw'!B:B,3),'[1]Sleutelplan nieuw'!A:A,"",2)} -> 0066 | C70: Factuur | D70: Dorpsstraat 73 | E70: 2841 BH | F70: Moordrecht | G70: 9 | H70: 9 | I70: 45472 | J70: 45836 | L70: Royal DS Personeel-service | M70: =_xlfn.XLOOKUP(L70,'relaties_export_2026-01-12_1609'!B:B,'relaties_export_2026-01-12_1609'!A:A,"",3) -> 304 | N70: =_xlfn.XLOOKUP(M70,'relaties_export_2026-01-12_1609'!A:A,'relaties_export_2026-01-12_1609'!B:B,"",3) -> Royal DS Personeel-service | P70: =R70-U70-V70-AD70 -> 118.73 | Q70: =T70*1.09+U70*1.21 -> 7176.9161 | R70: 6298.45 | S70: =(R70/G70)/4.33333 -> 161.49884 | T70: 6140.29 | U70: 400 | V70: 0 | Y70: Maatschap vd Vlist -Teuben | Z70: =_xlfn.XLOOKUP(Y70,'relaties_export_2026-01-12_1609'!B:B,'relaties_export_2026-01-12_1609'!A:A,"",3) -> 802 | AA70: =_xlfn.XLOOKUP(Z70,'relaties_export_2026-01-12_1609'!A:A,'relaties_export_2026-01-12_1609'!B:B,"",3) -> Maatschap vd Vlist -Teuben | AB70: 06 53141599 | AC70: =AD70*1.21 -> 6993.4612 | AD70: =5638.75+140.97 -> 5779.72 | AE70: =5638.75+140.97 -> 5779.72 | AF70: =(AD70/G70)/4.33333 -> 148.19806
A71: 63 | B71: =_xlfn.XLOOKUP(D71,'[1]Sleutelplan nieuw'!B:B,'[1]Sleutelplan nieuw'!A:A,"",2) -> 0061 | C71: Factuur | D71: Dwarsweg 44 | E71: 3181HG | F71: Rozenburg | G71: 5 | H71: 5 | I71: 45170 | J71: 45322 | L71: Impianti Industriala S.P.A. | M71: 240 | N71: =_xlfn.XLOOKUP(M71,'relaties_export_2026-01-12_1609'!A:A,'relaties_export_2026-01-12_1609'!B:B,"",3) -> Impianti Industriala S.P.A. NEDERLAND BRANCH | P71: =R71-U71-V71-AD71 -> 1362.12 | Q71: =T71*1.09+U71*1.21 -> 5425.4296 | R71: =T71+U71 -> 4955.44 | S71: =(R71/G71)/4.33333 -> 228.71279 | T71: 4755.44 | U71: 200 | V71: 0 | Y71: Hugo Vastgoed | Z71: =_xlfn.XLOOKUP(Y71,'relaties_export_2026-01-12_1609'!B:B,'relaties_export_2026-01-12_1609'!A:A,"",3) -> 111 | AA71: =_xlfn.XLOOKUP(Z71,'relaties_export_2026-01-12_1609'!A:A,'relaties_export_2026-01-12_1609'!B:B,"",3) -> Hugo Vastgoed B.V. | AB71: 076-5218999 | AC71: =AD71*1.21 -> 4105.9172 | AD71: 3393.32 | AE71: 3393.32 | AF71: =(AD71/G71)/4.33333 -> 156.61489 | AI71: onbepaalde tijd | AJ71: 24 maanden | AK71: 44317 | AL71: 45046 | AM71: 3 maanden | AN71: (verlenging 24 maanden) | AO71: BV | AR71: onbepaalde tijd | AS71: 12 maanden | AT71: 44044 | AU71: 44408 | AV71: 1 kalendermaand | AW71: eenmans | AZ71: aanbieden per 1-8
A72: 65 | B72: =_xlfn.XLOOKUP(D72,'[1]Sleutelplan nieuw'!B:B,'[1]Sleutelplan nieuw'!A:A,"",2) -> 0136 | C72: DS | D72: Elisadonk 220 | E72: 4707ER | F72: Roosendaal | G72: 4 | H72: 4 | I72: 45352 | J72: 45716 | L72: EG Facility & Services BV | M72: =_xlfn.XLOOKUP(L72,'relaties_export_2026-01-12_1609'!B:B,'relaties_export_2026-01-12_1609'!A:A,"",3) -> 276 | N72: =_xlfn.XLOOKUP(M72,'relaties_export_2026-01-12_1609'!A:A,'relaties_export_2026-01-12_1609'!B:B,"",3) -> EG Facility & Services BV | P72: =R72-U72-V72-AD72 -> 315.57 | Q72: =T72*1.09+U72*1.21 -> 2666.5215 | R72: =T72+U72 -> 2446.35 | S72: =(R72/G72)/4.33333 -> 141.13569 | T72: 2446.35 | U72: 0 | V72: 0 | Y72: M&M Hendriks | Z72: =_xlfn.XLOOKUP(Y72,'relaties_export_2026-01-12_1609'!B:B,'relaties_export_2026-01-12_1609'!A:A,"",3) -> 803 | AA72: =_xlfn.XLOOKUP(Z72,'relaties_export_2026-01-12_1609'!A:A,'relaties_export_2026-01-12_1609'!B:B,"",3) -> M&M Hendriks | AB72: 06-57885442 | AC72: 2130.78 | AD72: 2130.78 | AE72: 2130.78 | AF72: =(AD72/G72)/4.33333 -> 122.92971 | AG72: 45352 | AH72: 46081
A73: 66 | B73: {=_xlfn.XLOOKUP(LEFT(D73,3),LEFT('[1]Sleutelplan nieuw'!B:B,3),'[1]Sleutelplan nieuw'!A:A,"",2)} -> 0063 | C73: Factuur | D73: Energieweg 40 | E73: 3133EC | F73: Vlaardingen | G73: 4 | H73: 3 | I73: 45292 | J73: 45657 | L73: GAP Costruzioni | M73: =_xlfn.XLOOKUP(L73,'relaties_export_2026-01-12_1609'!B:B,'relaties_export_2026-01-12_1609'!A:A,"",3) -> 374 | N73: =_xlfn.XLOOKUP(M73,'relaties_export_2026-01-12_1609'!A:A,'relaties_export_2026-01-12_1609'!B:B,"",3) -> GAP Costruzioni S.r.l. | P73: =R73-U73-V73-AD73 -> 841.93 | Q73: =T73*1.09+U73*1.21 -> 3097.7037 | R73: =T73+U73 -> 2841.93 | S73: =(R73/G73)/4.33333 -> 163.95763 | T73: 2841.93 | U73: 0 | V73: 0 | Y73: Quadrant Vastgoed B.V. | Z73: =_xlfn.XLOOKUP(Y73,'relaties_export_2026-01-12_1609'!B:B,'relaties_export_2026-01-12_1609'!A:A,"",3) -> 569 | AA73: =_xlfn.XLOOKUP(Z73,'relaties_export_2026-01-12_1609'!A:A,'relaties_export_2026-01-12_1609'!B:B,"",3) -> Quadrant Vastgoed B.V. | AC73: 2000 | AD73: 2000 | AE73: 2000 | AF73: =(AD73/G73)/4.33333 -> 115.3847 | AG73: 45035 | AH73: 45400
B74: {=_xlfn.XLOOKUP(LEFT(D74,3),LEFT('[1]Sleutelplan nieuw'!B:B,3),'[1]Sleutelplan nieuw'!A:A,"",2)} -> 0095 | C74: Factuur | D74: Engelsestraat 16L1 | E74: 3028CG | F74: ROTTERDAM | L74: Tradiro | M74: =_xlfn.XLOOKUP(L74,'relaties_export_2026-01-12_1609'!B:B,'relaties_export_2026-01-12_1609'!A:A,"",3) -> 17 | N74: =_xlfn.XLOOKUP(M74,'relaties_export_2026-01-12_1609'!A:A,'relaties_export_2026-01-12_1609'!B:B,"",3) -> Tradiro Services B.V. | Y74: In Stones | Z74: 295 | AA74: =_xlfn.XLOOKUP(Z74,'relaties_export_2026-01-12_1609'!A:A,'relaties_export_2026-01-12_1609'!B:B,"",3) -> In Stijl Totaalbouw BV | AC74: 894 | AD74: 894 | AE74: 894
A75: 67 | B75: =_xlfn.XLOOKUP(D75,'[1]Sleutelplan nieuw'!B:B,'[1]Sleutelplan nieuw'!A:A,"",2) -> 0095 | C75: Factuur | D75: Engelsestraat 16L3 | E75: 3028CG | F75: Rotterdam | G75: 4 | H75: 2 | I75: 45695 | J75: 46060 | L75: Tradiro | M75: =_xlfn.XLOOKUP(L75,'relaties_export_2026-01-12_1609'!B:B,'relaties_export_2026-01-12_1609'!A:A,"",3) -> 17 | N75: =_xlfn.XLOOKUP(M75,'relaties_export_2026-01-12_1609'!A:A,'relaties_export_2026-01-12_1609'!B:B,"",3) -> Tradiro Services B.V. | P75: =R75-U75-V75-AD75 -> 668.32 | Q75: =T75*1.09+U75*1.21 -> 2172.7188 | R75: =T75+U75 -> 1993.32 | S75: =(R75/G75)/4.33333 -> 114.99932 | T75: 1993.32 | V75: 0 | Y75: Houses2Rent | Z75: =_xlfn.XLOOKUP(Y75,'relaties_export_2026-01-12_1609'!B:B,'relaties_export_2026-01-12_1609'!A:A,"",3) -> 271 | AA75: =_xlfn.XLOOKUP(Z75,'relaties_export_2026-01-12_1609'!A:A,'relaties_export_2026-01-12_1609'!B:B,"",3) -> Houses2Rent | AC75: =AD75*1.09 -> 1444.25 | AD75: 1325 | AE75: 1325 | AF75: =(AD75/G75)/4.33333 -> 76.442366
A76: 68 | B76: =_xlfn.XLOOKUP(D76,'[1]Sleutelplan nieuw'!B:B,'[1]Sleutelplan nieuw'!A:A,"",2) -> 0064 | C76: DS | D76: Enk 6 | E76: 7621ES | F76: Borne | G76: 5 | H76: 4 | I76: 45051 | J76: - | L76: Lago perseelshuisvesting | M76: 98 | N76: =_xlfn.XLOOKUP(M76,'relaties_export_2026-01-12_1609'!A:A,'relaties_export_2026-01-12_1609'!B:B,"",3) -> Lago Personeelshuisvesting B.V. | P76: =R76-U76-V76-AD76 -> 153.77 | Q76: =T76*1.09+U76*1.21 -> 2456.6093 | R76: =T76+U76 -> 2253.77 | S76: =(R76/G76)/4.33333 -> 104.02023 | T76: 2253.77 | U76: 0 | V76: 0 | Y76: Veurink | Z76: =_xlfn.XLOOKUP(Y76,'relaties_export_2026-01-12_1609'!B:B,'relaties_export_2026-01-12_1609'!A:A,"",3) -> 168 | AA76: =_xlfn.XLOOKUP(Z76,'relaties_export_2026-01-12_1609'!A:A,'relaties_export_2026-01-12_1609'!B:B,"",3) -> F. Veurink en P. Neleman | AB76: 06-28555669 | AC76: 2100 | AD76: 2100 | AE76: 2100 | AF76: =(AD76/G76)/4.33333 -> 96.923151 | AG76: 44743 | AH76: 45838
A77: 69 | B77: =_xlfn.XLOOKUP(D77,'[1]Sleutelplan nieuw'!B:B,'[1]Sleutelplan nieuw'!A:A,"",2) -> 0006 | C77: Factuur | D77: Enschotsestraat 163 | E77: 5014 DD | F77: Tilburg | G77: 8 | H77: 8 | I77: 45829 | J77: 46194 | L77: Optima | M77: =_xlfn.XLOOKUP(L77,'relaties_export_2026-01-12_1609'!B:B,'relaties_export_2026-01-12_1609'!A:A,"",3) -> 353 | N77: =_xlfn.XLOOKUP(M77,'relaties_export_2026-01-12_1609'!A:A,'relaties_export_2026-01-12_1609'!B:B,"",3) -> Optima Uitzendbureau B.V. | P77: =R77-U77-V77-AD77 -> 275 | Q77: =T77*1.09+U77*1.21 -> 4986.75 | R77: =T77+U77 -> 4575 | S77: =(R77/G77)/4.33333 -> 131.97126 | T77: 4575 | U77: 0 | V77: 0 | Y77: T. Eenhuistra/J. Pluimakers | Z77: =_xlfn.XLOOKUP(Y77,'relaties_export_2026-01-12_1609'!B:B,'relaties_export_2026-01-12_1609'!A:A,"",3) -> 763 | AA77: =_xlfn.XLOOKUP(Z77,'relaties_export_2026-01-12_1609'!A:A,'relaties_export_2026-01-12_1609'!B:B,"",3) -> T. Eenhuistra/J. Pluimakers | AC77: 4300 | AD77: 4300 | AE77: 4300 | AF77: =(AD77/G77)/4.33333 -> 124.03856 | AG77: 45870 | AH77: 46600
A78: 70 | B78: =_xlfn.XLOOKUP(D78,'[1]Sleutelplan nieuw'!B:B,'[1]Sleutelplan nieuw'!A:A,"",2) -> 0065 | C78: DS | D78: Esdoornlaan 68 | E78: 3181XD | F78: Rozenburg | G78: 6 | H78: 4 | I78: 45019 | J78: 45384 | L78: AmDor Projecten B.V. | M78: =_xlfn.XLOOKUP(L78,'relaties_export_2026-01-12_1609'!B:B,'relaties_export_2026-01-12_1609'!A:A,"",3) -> 124 | N78: =_xlfn.XLOOKUP(M78,'relaties_export_2026-01-12_1609'!A:A,'relaties_export_2026-01-12_1609'!B:B,"",3) -> AmDor Projecten B.V. | P78: =R78-U78-V78-AD78 -> 1327.01 | Q78: =T78*1.09+U78*1.21 -> 3894.4365 | R78: =T78+U78 -> 3539.85 | S78: =(R78/G78)/4.33333 -> 136.14818 | T78: 3239.85 | U78: 300 | V78: 0 | Y78: Leendert Keizer | Z78: =_xlfn.XLOOKUP(Y78,'relaties_export_2026-01-12_1609'!B:B,'relaties_export_2026-01-12_1609'!A:A,"",3) -> 846 | AA78: =_xlfn.XLOOKUP(Z78,'relaties_export_2026-01-12_1609'!A:A,'relaties_export_2026-01-12_1609'!B:B,"",3) -> Leendert Keizer | AB78: 06-24555909 | AC78: 1912.84 | AD78: 1912.84 | AE78: 1912.84 | AF78: =(AD78/G78)/4.33333 -> 73.570826 | AG78: 44986 | AH78: 45716 | AI78: onbepaalde tijd | AJ78: 24 maanden | AK78: 44256 | AL78: 44985 | AM78: 1 maand | AO78: BV | AR78: onbepaalde tijd | AS78: 3 maanden | AT78: 43831 | AU78: 43921 | AV78: 3 kalendermaand | AW78: M. van Os
C79: Factuur | D79: Europalaan 50 | F79: Sas van Gent | L79: Tradiro | M79: =_xlfn.XLOOKUP(L79,'relaties_export_2026-01-12_1609'!B:B,'relaties_export_2026-01-12_1609'!A:A,"",3) -> 17 | N79: =_xlfn.XLOOKUP(M79,'relaties_export_2026-01-12_1609'!A:A,'relaties_export_2026-01-12_1609'!B:B,"",3) -> Tradiro Services B.V. | Y79: All In Rentals | Z79: =_xlfn.XLOOKUP(Y79,'relaties_export_2026-01-12_1609'!B:B,'relaties_export_2026-01-12_1609'!A:A,"",3) | AA79: =_xlfn.XLOOKUP(Z79,'relaties_export_2026-01-12_1609'!A:A,'relaties_export_2026-01-12_1609'!B:B,"",3) -> naam | AB79: 085-0606351 | AC79: 4233.26 | AD79: 3832.5 | AE79: 3347.25
A80: 74 | B80: =_xlfn.XLOOKUP(D80,'[1]Sleutelplan nieuw'!B:B,'[1]Sleutelplan nieuw'!A:A,"",2) -> 0331 | C80: DS | D80: Flankstraat 11 | E80: 4551AR | F80: Sas van Gent | G80: 4 | H80: 4 | I80: 38387 | J80: 45781 | L80: Bakker | M80: =_xlfn.XLOOKUP(L80,'relaties_export_2026-01-12_1609'!B:B,'relaties_export_2026-01-12_1609'!A:A,"",3) -> 23 | N80: =_xlfn.XLOOKUP(M80,'relaties_export_2026-01-12_1609'!A:A,'relaties_export_2026-01-12_1609'!B:B,"",3) -> S. Bakker OPH Verhuur | P80: =R80-U80-V80-AD80 -> 650 | Q80: =T80*1.09+U80*1.21 -> 3033.5 | R80: =T80+U80 -> 2750 | S80: =(R80/G80)/4.33333 -> 158.65397 | T80: 2450 | U80: 300 | Y80: TH Mungroop | Z80: =_xlfn.XLOOKUP(Y80,'relaties_export_2026-01-12_1609'!B:B,'relaties_export_2026-01-12_1609'!A:A,"",3) -> 805 | AA80: =_xlfn.XLOOKUP(Z80,'relaties_export_2026-01-12_1609'!A:A,'relaties_export_2026-01-12_1609'!B:B,"",3) -> TH Mungroop | AB80: 06-22146488 | AC80: 1800 | AD80: 1800 | AE80: 1800 | AF80: =(AD80/G80)/4.33333 -> 103.84623
A81: 75 | B81: =_xlfn.XLOOKUP(D81,'[1]Sleutelplan nieuw'!B:B,'[1]Sleutelplan nieuw'!A:A,"",2) -> 0067 | C81: Factuur | D81: Franz Liszstraat 5 | E81: 4536EA | F81: Terneuzen | G81: 7 | H81: 4 | I81: 45394 | J81: 45758 | L81: Tradiro | M81: =_xlfn.XLOOKUP(L81,'relaties_export_2026-01-12_1609'!B:B,'relaties_export_2026-01-12_1609'!A:A,"",3) -> 17 | N81: =_xlfn.XLOOKUP(M81,'relaties_export_2026-01-12_1609'!A:A,'relaties_export_2026-01-12_1609'!B:B,"",3) -> Tradiro Services B.V. | P81: =R81-U81-V81-AD81 -> 1977.9 | Q81: =T81*1.09+U81*1.21 -> 3971.415 | R81: =T81+U81 -> 3643.5 | S81: =(R81/G81)/4.33333 -> 120.11548 | T81: 3643.5 | U81: 0 | V81: 0 | Y81: Value+ Vastgoedmanagement | Z81: 806 | AA81: =_xlfn.XLOOKUP(Z81,'relaties_export_2026-01-12_1609'!A:A,'relaties_export_2026-01-12_1609'!B:B,"",3) -> Value+ Vastgoedmanagement | AB81: 085-0441816 | AC81: 1665.6 | AD81: 1665.6 | AE81: 1665.6 | AF81: =(AD81/G81)/4.33333 -> 54.909932 | AG81: 44582 | AH81: 46407
A82: 76 | B82: =_xlfn.XLOOKUP(D82,'[1]Sleutelplan nieuw'!B:B,'[1]Sleutelplan nieuw'!A:A,"",2) -> 0017 | C82: Factuur | D82: G.A. Brederolaan 75B | E82: 3141 CD | F82: Maassluis | G82: 4 | H82: 3 | I82: 44958 | J82: 45323 | L82: Tradiro | M82: =_xlfn.XLOOKUP(L82,'relaties_export_2026-01-12_1609'!B:B,'relaties_export_2026-01-12_1609'!A:A,"",3) -> 17 | N82: =_xlfn.XLOOKUP(M82,'relaties_export_2026-01-12_1609'!A:A,'relaties_export_2026-01-12_1609'!B:B,"",3) -> Tradiro Services B.V. | P82: =R82-U82-V82-AD82 -> 227.89 | Q82: =T82*1.09+U82*1.21 -> 1828.9001 | R82: =T82+U82 -> 1677.89 | S82: =(R82/G82)/4.33333 -> 96.801421 | T82: 1677.89 | U82: 0 | V82: 0 | Y82: M.C. Mostert | Z82: =_xlfn.XLOOKUP(Y82,'relaties_export_2026-01-12_1609'!B:B,'relaties_export_2026-01-12_1609'!A:A,"",3) -> 807 | AA82: =_xlfn.XLOOKUP(Z82,'relaties_export_2026-01-12_1609'!A:A,'relaties_export_2026-01-12_1609'!B:B,"",3) -> M.C. Mostert | AC82: 1450 | AD82: 1450 | AE82: 1450 | AF82: =(AD82/G82)/4.33333 -> 83.653911 | AG82: 44958 | AH82: 45689
D83: Galgeweg 48A | F83: s-Gravenzande | L83: Tradiro | M83: =_xlfn.XLOOKUP(L83,'relaties_export_2026-01-12_1609'!B:B,'relaties_export_2026-01-12_1609'!A:A,"",3) -> 17 | N83: =_xlfn.XLOOKUP(M83,'relaties_export_2026-01-12_1609'!A:A,'relaties_export_2026-01-12_1609'!B:B,"",3) -> Tradiro Services B.V. | Y83: THEM | Z83: =_xlfn.XLOOKUP(Y83,'relaties_export_2026-01-12_1609'!B:B,'relaties_export_2026-01-12_1609'!A:A,"",3) | AA83: =_xlfn.XLOOKUP(Z83,'relaties_export_2026-01-12_1609'!A:A,'relaties_export_2026-01-12_1609'!B:B,"",3) -> naam | AC83: 3803.81 | AD83: 3803.81 | AE83: 3803.81
A84: 78 | B84: =_xlfn.XLOOKUP(D84,'[1]Sleutelplan nieuw'!B:B,'[1]Sleutelplan nieuw'!A:A,"",2) -> 0109 | C84: DS | D84: Geldersestraat 91 | E84: 4191BB | F84: Geldermalsen | G84: 7 | H84: 7 | I84: 45425 | J84: 45789 | L84: Vivir Wonen | M84: =_xlfn.XLOOKUP(L84,'relaties_export_2026-01-12_1609'!B:B,'relaties_export_2026-01-12_1609'!A:A,"",3) -> 26 | N84: =_xlfn.XLOOKUP(M84,'relaties_export_2026-01-12_1609'!A:A,'relaties_export_2026-01-12_1609'!B:B,"",3) -> Vivir Wonen | P84: =R84-U84-V84-AD84 -> 872.2 | Q84: =T84*1.09+U84*1.21 -> 5370.698 | R84: =T84+U84 -> 4872.2 | S84: =(R84/G84)/4.33333 -> 160.6221 | T84: 4372.2 | U84: 500 | V84: 0 | Y84: Johan ven der Burg | Z84: =_xlfn.XLOOKUP(Y84,'relaties_export_2026-01-12_1609'!B:B,'relaties_export_2026-01-12_1609'!A:A,"",3) -> 783 | AA84: =_xlfn.XLOOKUP(Z84,'relaties_export_2026-01-12_1609'!A:A,'relaties_export_2026-01-12_1609'!B:B,"",3) -> Johan ven der Burg | AB84: 06-23666051 | AC84: 3500 | AD84: 3500 | AE84: 3500 | AF84: =(AD84/G84)/4.33333 -> 115.3847 | AG84: 45383 | AH84: 46112
A85: 79 | B85: =_xlfn.XLOOKUP(D85,'[1]Sleutelplan nieuw'!B:B,'[1]Sleutelplan nieuw'!A:A,"",2) -> 0070 | C85: DS | D85: Geleenstraat 1 | E85: 6133XK | F85: Sittard | G85: 3 | H85: 3 | M85: =_xlfn.XLOOKUP(L85,'relaties_export_2026-01-12_1609'!B:B,'relaties_export_2026-01-12_1609'!A:A,"",3) -> id | N85: =_xlfn.XLOOKUP(M85,'relaties_export_2026-01-12_1609'!A:A,'relaties_export_2026-01-12_1609'!B:B,"",3) -> naam | P85: =R85-U85-V85-AD85 -> -1450 | S85: =(R85/G85)/4.33333 -> 0 | U85: 200 | V85: 0 | Y85: Bart Vlastuin | Z85: =_xlfn.XLOOKUP(Y85,'relaties_export_2026-01-12_1609'!B:B,'relaties_export_2026-01-12_1609'!A:A,"",3) -> 808 | AA85: =_xlfn.XLOOKUP(Z85,'relaties_export_2026-01-12_1609'!A:A,'relaties_export_2026-01-12_1609'!B:B,"",3) -> Bart Vlastuin | AB85: 06-29862823 | AC85: 1250 | AD85: 1250 | AE85: 1250 | AF85: =(AD85/G85)/4.33333 -> 96.15392 | AG85: 44682 | AH85: 45412
A86: 80 | B86: =_xlfn.XLOOKUP(D86,'[1]Sleutelplan nieuw'!B:B,'[1]Sleutelplan nieuw'!A:A,"",2) -> 0170 | C86: Factuur | D86: Goudestein 30 | E86: 3085 DB | F86: Rotterdam | G86: 3 | H86: 3 | I86: 45911 | J86: 46275 | L86: LogIQ | M86: =_xlfn.XLOOKUP(L86,'relaties_export_2026-01-12_1609'!B:B,'relaties_export_2026-01-12_1609'!A:A,"",3) -> 355 | N86: =_xlfn.XLOOKUP(M86,'relaties_export_2026-01-12_1609'!A:A,'relaties_export_2026-01-12_1609'!B:B,"",3) -> LogIQ Barendrecht B.V. | P86: =R86-U86-V86-AD86 -> 773 | Q86: =T86*1.09+U86*1.21 -> 2591.5 | R86: =T86+U86 -> 2350 | S86: =(R86/G86)/4.33333 -> 180.76937 | T86: 2100 | U86: 250 | Y86: S.H.M de Swart | Z86: =_xlfn.XLOOKUP(Y86,'relaties_export_2026-01-12_1609'!B:B,'relaties_export_2026-01-12_1609'!A:A,"",3) | AA86: =_xlfn.XLOOKUP(Z86,'relaties_export_2026-01-12_1609'!A:A,'relaties_export_2026-01-12_1609'!B:B,"",3) -> naam | AB86: 06-24210114 | AC86: 1327 | AD86: 1327 | AE86: 1327 | AF86: =(AD86/G86)/4.33333 -> 102.077
A87: 81 | B87: =_xlfn.XLOOKUP(D87,'[1]Sleutelplan nieuw'!B:B,'[1]Sleutelplan nieuw'!A:A,"",2) -> 0025 | C87: Factuur | D87: Groenelaan 30B | E87: 3114 CH | F87: Schiedam | G87: 3 | H87: 3 | I87: 45807 | J87: obt | L87: Tradiro | M87: =_xlfn.XLOOKUP(L87,'relaties_export_2026-01-12_1609'!B:B,'relaties_export_2026-01-12_1609'!A:A,"",3) -> 17 | N87: =_xlfn.XLOOKUP(M87,'relaties_export_2026-01-12_1609'!A:A,'relaties_export_2026-01-12_1609'!B:B,"",3) -> Tradiro Services B.V. | P87: =R87-U87-V87-AD87 -> 530 | Q87: =T87*1.09+U87*1.21 -> 1558.7 | R87: =T87+U87 -> 1430 | S87: =(R87/G87)/4.33333 -> 110.00008 | T87: 1430 | V87: 0 | Y87: Verknocht | Z87: =_xlfn.XLOOKUP(Y87,'relaties_export_2026-01-12_1609'!B:B,'relaties_export_2026-01-12_1609'!A:A,"",3) -> 574 | AA87: =_xlfn.XLOOKUP(Z87,'relaties_export_2026-01-12_1609'!A:A,'relaties_export_2026-01-12_1609'!B:B,"",3) -> Verknocht | AC87: 900 | AD87: 900 | AE87: 900 | AF87: =(AD87/G87)/4.33333 -> 69.230822 | AG87: 44927 | AH87: 45292
A88: 82 | B88: =_xlfn.XLOOKUP(D88,'[1]Sleutelplan nieuw'!B:B,'[1]Sleutelplan nieuw'!A:A,"",2) -> 0071 | C88: DS | D88: H. Algraplein 25 | E88: 8802RE | F88: Franeker | G88: 7 | H88: 4 | I88: 45885 | J88: 46188 | L88: DIT en Larex Vakpersoneel B.V. | M88: =_xlfn.XLOOKUP(L88,'relaties_export_2026-01-12_1609'!B:B,'relaties_export_2026-01-12_1609'!A:A,"",3) -> 210 | N88: =_xlfn.XLOOKUP(M88,'relaties_export_2026-01-12_1609'!A:A,'relaties_export_2026-01-12_1609'!B:B,"",3) -> DIT en Larex Vakpersoneel B.V. | P88: =R88-U88-V88-AD88 -> 425 | Q88: =T88*1.09+U88*1.21 -> 3109.25 | R88: =T88+U88 -> 2825 | S88: =(R88/G88)/4.33333 -> 93.13194 | T88: 2575 | U88: 250 | V88: 0 | Y88: B. Bakker | Z88: =_xlfn.XLOOKUP(Y88,'relaties_export_2026-01-12_1609'!B:B,'relaties_export_2026-01-12_1609'!A:A,"",3) -> 241 | AA88: =_xlfn.XLOOKUP(Z88,'relaties_export_2026-01-12_1609'!A:A,'relaties_export_2026-01-12_1609'!B:B,"",3) -> BJ Bakker | AB88: 06-83008788 | AC88: 2150 | AD88: 2150 | AE88: 2150 | AF88: =(AD88/G88)/4.33333 -> 70.879175
C89: DS | D89: Hagastraat 8 | E89: 3114 ND | F89: Schiedam | L89: Tradiro | M89: =_xlfn.XLOOKUP(L89,'relaties_export_2026-01-12_1609'!B:B,'relaties_export_2026-01-12_1609'!A:A,"",3) -> 17 | N89: =_xlfn.XLOOKUP(M89,'relaties_export_2026-01-12_1609'!A:A,'relaties_export_2026-01-12_1609'!B:B,"",3) -> Tradiro Services B.V. | Y89: Ton Xie | Z89: =_xlfn.XLOOKUP(Y89,'relaties_export_2026-01-12_1609'!B:B,'relaties_export_2026-01-12_1609'!A:A,"",3) | AA89: =_xlfn.XLOOKUP(Z89,'relaties_export_2026-01-12_1609'!A:A,'relaties_export_2026-01-12_1609'!B:B,"",3) -> naam | AC89: 1451.23 | AD89: 1451.23 | AE89: 1451.23
B90: =_xlfn.XLOOKUP(D90,'[1]Sleutelplan nieuw'!B:B,'[1]Sleutelplan nieuw'!A:A,"",2) -> 0396 | D90: Haven 24 | E90: 3143 BC | F90: Maassluis | G90: 6 | H90: 6 | M90: =_xlfn.XLOOKUP(L90,'relaties_export_2026-01-12_1609'!B:B,'relaties_export_2026-01-12_1609'!A:A,"",3) -> id | N90: =_xlfn.XLOOKUP(M90,'relaties_export_2026-01-12_1609'!A:A,'relaties_export_2026-01-12_1609'!B:B,"",3) -> naam | Y90: Holland Huisvesting B.V. | Z90: =_xlfn.XLOOKUP(Y90,'relaties_export_2026-01-12_1609'!B:B,'relaties_export_2026-01-12_1609'!A:A,"",3) -> 145 | AA90: =_xlfn.XLOOKUP(Z90,'relaties_export_2026-01-12_1609'!A:A,'relaties_export_2026-01-12_1609'!B:B,"",3) -> dockHolland Huisvesting B.V. | AB90: 06-57541069 | AC90: =AD90*1.21 -> 5033.6 | AD90: 4160 | AE90: 4100 | AF90: =(AD90/G90)/4.33333 -> 160.00012 | AG90: 46023 | AH90: 46387
A91: 83 | B91: =_xlfn.XLOOKUP(D91,'[1]Sleutelplan nieuw'!B:B,'[1]Sleutelplan nieuw'!A:A,"",2) -> 0072 | C91: DS | D91: Heemskerkstraat 19 | E91: 9866AR | F91: Lutjegast | G91: 4 | H91: 4 | I91: 45720 | J91: 45751 | L91: DIT en Larex Vakpersoneel B.V. | M91: =_xlfn.XLOOKUP(L91,'relaties_export_2026-01-12_1609'!B:B,'relaties_export_2026-01-12_1609'!A:A,"",3) -> 210 | N91: =_xlfn.XLOOKUP(M91,'relaties_export_2026-01-12_1609'!A:A,'relaties_export_2026-01-12_1609'!B:B,"",3) -> DIT en Larex Vakpersoneel B.V. | P91: =R91-U91-V91-AD91 -> 450 | Q91: =T91*1.09+U91*1.21 -> 2755 | R91: =T91+U91 -> 2500 | S91: =(R91/G91)/4.33333 -> 144.23088 | T91: 2250 | U91: 250 | V91: 0 | Y91: Robert de Jonge | Z91: =_xlfn.XLOOKUP(Y91,'relaties_export_2026-01-12_1609'!B:B,'relaties_export_2026-01-12_1609'!A:A,"",3) -> 810 | AA91: =_xlfn.XLOOKUP(Z91,'relaties_export_2026-01-12_1609'!A:A,'relaties_export_2026-01-12_1609'!B:B,"",3) -> Robert de Jonge | AB91: 035-5335822 / 06-53253144 | AC91: 1800 | AD91: 1800 | AE91: 1800 | AF91: =(AD91/G91)/4.33 -> 103.9261 | AG91: 44967 | AH91: 45331
A92: 84 | B92: =_xlfn.XLOOKUP(D92,'[1]Sleutelplan nieuw'!B:B,'[1]Sleutelplan nieuw'!A:A,"",2) -> 0073 | C92: DS | D92: Hendrik Deddenstraat 26 | E92: 8395PX | F92: Steggerda | G92: 5 | H92: 5 | I92: 44835 | L92: United Homes | M92: =_xlfn.XLOOKUP(L92,'relaties_export_2026-01-12_1609'!B:B,'relaties_export_2026-01-12_1609'!A:A,"",3) -> 13 | N92: =_xlfn.XLOOKUP(M92,'relaties_export_2026-01-12_1609'!A:A,'relaties_export_2026-01-12_1609'!B:B,"",3) -> United Homes B.V. | P92: =R92-U92-V92-AD92 -> 464.47 | Q92: =T92*1.09+U92*1.21 -> 2686.2723 | R92: =T92+U92 -> 2464.47 | S92: =(R92/G92)/4.33333 -> 113.74486 | T92: 2464.47 | U92: 0 | V92: 0 | Y92: Derwig | Z92: =_xlfn.XLOOKUP(Y92,'relaties_export_2026-01-12_1609'!B:B,'relaties_export_2026-01-12_1609'!A:A,"",3) -> 146 | AA92: =_xlfn.XLOOKUP(Z92,'relaties_export_2026-01-12_1609'!A:A,'relaties_export_2026-01-12_1609'!B:B,"",3) -> Fam. Derwig | AB92: 06-20498826 | AC92: 2000 | AD92: 2000 | AE92: 2000 | AF92: =(AD92/G92)/4.33333 -> 92.307763 | AG92: 44621 | AH92: 45716
A93: 85 | B93: =_xlfn.XLOOKUP(D93,'[1]Sleutelplan nieuw'!B:B,'[1]Sleutelplan nieuw'!A:A,"",2) -> 0325 | C93: Factuur | D93: Hendriklaan 49 | E93: 6043 BN | F93: Roermond | G93: 10 | H93: 6 | I93: 45660 | J93: 46025 | L93: VALO Facilities B.V. | M93: =_xlfn.XLOOKUP(L93,'relaties_export_2026-01-12_1609'!B:B,'relaties_export_2026-01-12_1609'!A:A,"",3) -> 305 | N93: =_xlfn.XLOOKUP(M93,'relaties_export_2026-01-12_1609'!A:A,'relaties_export_2026-01-12_1609'!B:B,"",3) -> VALO Facilities B.V. | P93: =R93-U93-V93-AD93 -> 998.21 | Q93: =T93*1.09+(U93+V93)*1.21 -> 6636.3 | R93: =T93+U93+V93 -> 6030 | S93: =(R93/G93)/4.33333 -> 139.15395 | T93: 5500 | U93: 450 | V93: 80 | Y93: M. Koolhaas | Z93: =_xlfn.XLOOKUP(Y93,'relaties_export_2026-01-12_1609'!B:B,'relaties_export_2026-01-12_1609'!A:A,"",3) -> 811 | AA93: =_xlfn.XLOOKUP(Z93,'relaties_export_2026-01-12_1609'!A:A,'relaties_export_2026-01-12_1609'!B:B,"",3) -> M. Koolhaas | AB93: 06-47075677 | AC93: 4529 | AD93: 4501.79 | AE93: 4372.2 | AF93: =(AD93/G93)/4.33 -> 103.96744 | AG93: 45661 | AH93: 46026
B94: =_xlfn.XLOOKUP(D94,'[1]Sleutelplan nieuw'!B:B,'[1]Sleutelplan nieuw'!A:A,"",2) -> 0176 | C94: Factuur | D94: Herautpad 22 | F94: Schiedam | L94: Tradiro | M94: =_xlfn.XLOOKUP(L94,'relaties_export_2026-01-12_1609'!B:B,'relaties_export_2026-01-12_1609'!A:A,"",3) -> 17 | N94: =_xlfn.XLOOKUP(M94,'relaties_export_2026-01-12_1609'!A:A,'relaties_export_2026-01-12_1609'!B:B,"",3) -> Tradiro Services B.V. | Y94: In Stones | Z94: 295 | AA94: =_xlfn.XLOOKUP(Z94,'relaties_export_2026-01-12_1609'!A:A,'relaties_export_2026-01-12_1609'!B:B,"",3) -> In Stijl Totaalbouw BV | AC94: 1125 | AD94: 1125 | AE94: 1125
A95: 86 | B95: {=_xlfn.XLOOKUP(LEFT(D95,3),LEFT('[1]Sleutelplan nieuw'!B:B,3),'[1]Sleutelplan nieuw'!A:A,"",2)} -> 0133 | C95: Factuur | D95: Herenpad 20A | E95: 3111 LP | F95: Schiedam | G95: 2 | H95: 2 | I95: 46031 | J95: 46395 | L95: Bakker | M95: =_xlfn.XLOOKUP(L95,'relaties_export_2026-01-12_1609'!B:B,'relaties_export_2026-01-12_1609'!A:A,"",3) -> 23 | N95: =_xlfn.XLOOKUP(M95,'relaties_export_2026-01-12_1609'!A:A,'relaties_export_2026-01-12_1609'!B:B,"",3) -> S. Bakker OPH Verhuur | P95: =R95-U95-V95-AD95 -> 125 | Q95: =T95*1.21+(U95+V95)*1.21 -> 2178 | R95: =T95+U95+V95 -> 1800 | S95: =(R95/G95)/4.33333 -> 207.69247 | T95: 1700 | U95: 100 | V95: 0 | Y95: Westhavendomein | Z95: =_xlfn.XLOOKUP(Y95,'relaties_export_2026-01-12_1609'!B:B,'relaties_export_2026-01-12_1609'!A:A,"",3) -> 602 | AA95: =_xlfn.XLOOKUP(Z95,'relaties_export_2026-01-12_1609'!A:A,'relaties_export_2026-01-12_1609'!B:B,"",3) -> Westhavendomein BV | AB95: 010-2477477 | AC95: 1575 | AD95: 1575 | AE95: 1575 | AF95: =(AD95/G95)/4.33333 -> 181.73091
A96: 88 | B96: =_xlfn.XLOOKUP(D96,'[1]Sleutelplan nieuw'!B:B,'[1]Sleutelplan nieuw'!A:A,"",2) -> 0107 | C96: DS | D96: Hoefslag 8 | E96: 8391BJ | F96: Noordwolde | G96: 5 | H96: 5 | I96: 45562 | J96: 45653 | L96: DIT en Larex Vakpersoneel B.V. | M96: =_xlfn.XLOOKUP(L96,'relaties_export_2026-01-12_1609'!B:B,'relaties_export_2026-01-12_1609'!A:A,"",3) -> 210 | N96: =_xlfn.XLOOKUP(M96,'relaties_export_2026-01-12_1609'!A:A,'relaties_export_2026-01-12_1609'!B:B,"",3) -> DIT en Larex Vakpersoneel B.V. | P96: =R96-U96-V96-AD96 -> 312.3 | Q96: =T96*1.09+U96*1.21 -> 2969.0215 | R96: =T96+U96 -> 2696.35 | S96: =(R96/G96)/4.33333 -> 124.44702 | T96: 2446.35 | U96: 250 | V96: 0 | Y96: H. Samson | Z96: =_xlfn.XLOOKUP(Y96,'relaties_export_2026-01-12_1609'!B:B,'relaties_export_2026-01-12_1609'!A:A,"",3) -> 792 | AA96: =_xlfn.XLOOKUP(Z96,'relaties_export_2026-01-12_1609'!A:A,'relaties_export_2026-01-12_1609'!B:B,"",3) -> H. Samson | AC96: 2134.05 | AD96: 2134.05 | AE96: 2134.05 | AF96: =(AD96/G96)/4.33333 -> 98.494691 | AG96: 45383 | AH96: 46477
A97: 90 | B97: =_xlfn.XLOOKUP(D97,'[1]Sleutelplan nieuw'!B:B,'[1]Sleutelplan nieuw'!A:A,"",2) -> 0031 | C97: DS | D97: Hogenbanweg 331 | E97: 3112 CK | F97: Schiedam | G97: 3 | H97: 2 | I97: 44986 | J97: 45352 | L97: Tradiro | M97: =_xlfn.XLOOKUP(L97,'relaties_export_2026-01-12_1609'!B:B,'relaties_export_2026-01-12_1609'!A:A,"",3) -> 17 | N97: =_xlfn.XLOOKUP(M97,'relaties_export_2026-01-12_1609'!A:A,'relaties_export_2026-01-12_1609'!B:B,"",3) -> Tradiro Services B.V. | P97: =R97-U97-V97-AD97 -> 268.43 | Q97: =T97*1.09+U97*1.21 -> 1709.5887 | R97: =T97+U97 -> 1568.43 | S97: =(R97/G97)/4.33333 -> 120.64855 | T97: 1568.43 | U97: 0 | V97: 0 | Y97: M. Dogan | Z97: =_xlfn.XLOOKUP(Y97,'relaties_export_2026-01-12_1609'!B:B,'relaties_export_2026-01-12_1609'!A:A,"",3) -> 812 | AA97: =_xlfn.XLOOKUP(Z97,'relaties_export_2026-01-12_1609'!A:A,'relaties_export_2026-01-12_1609'!B:B,"",3) -> M. Dogan | AC97: 1300 | AD97: 1300 | AE97: 1300 | AF97: =(AD97/G97)/4.33333 -> 100.00008 | AG97: 44986 | AH97: 45291
A98: 91 | B98: =_xlfn.XLOOKUP(D98,'[1]Sleutelplan nieuw'!B:B,'[1]Sleutelplan nieuw'!A:A,"",2) -> 0181 | C98: Factuur | D98: Hontenissestraat 124 | E98: 3086KJ | F98: Rotterdam | G98: 4 | H98: 2 | M98: =_xlfn.XLOOKUP(L98,'relaties_export_2026-01-12_1609'!B:B,'relaties_export_2026-01-12_1609'!A:A,"",3) -> id | N98: =_xlfn.XLOOKUP(M98,'relaties_export_2026-01-12_1609'!A:A,'relaties_export_2026-01-12_1609'!B:B,"",3) -> naam | O98: MOETEN OPTIJD OPZEGGEN. Terug naar eigenaar 14-12 | P98: =R98-U98-V98-AD98 -> -1762 | U98: 250 | Y98: Tradiro | Z98: =_xlfn.XLOOKUP(Y98,'relaties_export_2026-01-12_1609'!B:B,'relaties_export_2026-01-12_1609'!A:A,"",3) -> 17 | AA98: =_xlfn.XLOOKUP(Z98,'relaties_export_2026-01-12_1609'!A:A,'relaties_export_2026-01-12_1609'!B:B,"",3) -> Tradiro Services B.V. | AC98: =AD98*1.09 -> 1648.08 | AD98: 1512 | AE98: 1512 | AF98: =(AD98/G98)/4.33333 -> 87.230836
A99: 92 | B99: =_xlfn.XLOOKUP(D99,'[1]Sleutelplan nieuw'!B:B,'[1]Sleutelplan nieuw'!A:A,"",2) -> 0075 | C99: Factuur | D99: Hoofdstraat 110 | E99: 5473AT | F99: Heeswijk-Dinther | G99: 4 | H99: 4 | I99: 45306 | J99: 45488 | L99: WILL Vakkrachten B. V. | M99: =_xlfn.XLOOKUP(L99,'relaties_export_2026-01-12_1609'!B:B,'relaties_export_2026-01-12_1609'!A:A,"",3) -> 270 | N99: =_xlfn.XLOOKUP(M99,'relaties_export_2026-01-12_1609'!A:A,'relaties_export_2026-01-12_1609'!B:B,"",3) -> WILL Vakkrachten B. V. | P99: =R99-U99-V99-AD99 -> 663.12 | Q99: =T99*1.09+U99*1.21 -> 2553.0525 | R99: =T99+U99 -> 2342.25 | S99: =(R99/G99)/4.33333 -> 135.12991 | T99: 2342.25 | U99: 0 | V99: 0 | Y99: HBB Wonen (Danielle Hanegraaf) | Z99: 813 | AA99: =_xlfn.XLOOKUP(Z99,'relaties_export_2026-01-12_1609'!A:A,'relaties_export_2026-01-12_1609'!B:B,"",3) -> HBB Wonen (Danielle Hanegraaf) | AB99: 073-2089102 / 06-33886674 | AC99: 1679.13 | AD99: 1679.13 | AE99: 1679.13 | AF99: =(AD99/G99)/4.33333 -> 96.872959 | AG99: 43947 | AH99: 44068 | AI99: onbepaalde tijd | AJ99: 4 maanden | AK99: 43947 | AL99: 44075 | AM99: 1 maand | AO99: eenmans | AR99: onbepaalde tijd | AS99: 4 maanden | AT99: 43947 | AU99: 44068 | AV99: 1 kalendermaand | AW99: eenmans | AZ99: facturatie checken + 2 man GHS
A100: 93 | B100: =_xlfn.XLOOKUP(D100,'[1]Sleutelplan nieuw'!B:B,'[1]Sleutelplan nieuw'!A:A,"",2) -> 0078 | C100: DS | D100: Hooizolder 6 | E100: 9205 CA | F100: Drachten | G100: 4 | H100: 4 | I100: 45366 | J100: 45549 | L100: DIT en Larex Vakpersoneel B.V. | M100: =_xlfn.XLOOKUP(L100,'relaties_export_2026-01-12_1609'!B:B,'relaties_export_2026-01-12_1609'!A:A,"",3) -> 210 | N100: =_xlfn.XLOOKUP(M100,'relaties_export_2026-01-12_1609'!A:A,'relaties_export_2026-01-12_1609'!B:B,"",3) -> DIT en Larex Vakpersoneel B.V. | P100: =R100-U100-V100-AD100 -> 884.85 | Q100: =T100*1.09+U100*1.21 -> 3139.225 | R100: =T100+U100 -> 2852.5 | S100: =(R100/G100)/4.33333 -> 164.56743 | T100: 2602.5 | U100: 250 | V100: 0 | Y100: H. Samson | Z100: =_xlfn.XLOOKUP(Y100,'relaties_export_2026-01-12_1609'!B:B,'relaties_export_2026-01-12_1609'!A:A,"",3) -> 792 | AA100: =_xlfn.XLOOKUP(Z100,'relaties_export_2026-01-12_1609'!A:A,'relaties_export_2026-01-12_1609'!B:B,"",3) -> H. Samson | AB100: 06-22487252 | AC100: 1717.65 | AD100: 1717.65 | AE100: 1717.65 | AF100: =(AD100/G100)/4.33333 -> 99.095269 | AG100: 44774 | AH100: 45504
...

Sheet relaties_marked
A1: Object_id | B1: relatie_id | C1: huurder | D1: relatie_id | E1: eigenaar
A2: 0388 | B2: 23 | C2: S. Bakker OPH Verhuur | D2: 751 | E2: Orange Invesments Group
A3: 0022 | B3: 17 | C3: Tradiro Services B.V. | D3: 574 | E3: Verknocht
A4: 0148 | B4: 17 | C4: Tradiro Services B.V. | D4: 306 | E4: Jacco Maat
A5: 0149 | B5: 17 | C5: Tradiro Services B.V. | D5: 306 | E5: Jacco Maat
A6: 0150 | B6: 17 | C6: Tradiro Services B.V. | D6: 306 | E6: Jacco Maat
A7: 0003 | B7: 13 | C7: United Homes B.V. | D7: 789 | E7: MvB Services BV (Meindert van Buuren)
A8: 0190 | B8: 145 | C8: dockHolland Huisvesting B.V. | D8: 824 | E8: Vivir wonen (Mendy)
A9: 0007 | B9: 154 | C9: InAxtion Vastgoed B.V. | D9: 790 | E9: Eva Laus
A10: 0341 | B10: 236 | C10: NL Realty B.V. | D10: 726 | E10: Cris
A11: 0372 | B11: 348 | C11: MNA Proud Facilities B.V. | D11: 726 | E11: Cris
A12: 0293 | B12: 346 | C12: Buurman Vastgoed E B.V. | D12: 726 | E12: Cris
A13: 0294 | B13: 236 | C13: NL Realty B.V. | D13: 766 | E13: C. van Driel e/o B.M. Verdouw
... A28: 0307 | B28: 347 | C28: FISSH B.V. | D28: 726 | E28: Cris
A29: 0002 | B29: 260 | C29: Looije Facilities B.V. | E29: naam
A30: 0043 | B30: 26 | C30: Vivir Wonen | D30: 792 | E30: H. Samson
A31: 0135 | B31: 17 | C31: Tradiro Services B.V. | D31: 258 | E31: Parkwonen
A32: 0353 | B32: 17 | C32: Tradiro Services B.V. | D32: 271 | E32: Houses2Rent
A33: 0055 | B33: 310 | C33: HousingWell B.V. | D33: 852 | E33: R. Verspui
A34: 0012 | B34: 26 | C34: Vivir Wonen | D34: 790 | E34: Eva Laus
A35: 0013 | B35: 190 | C35: BBTS (Vastgoed Spijkenisse) | D35: 185 | E35: Dhr. R. J. Beking
A36: 0040 | B36: 220 | C36: Impes Service S.p.A. | D36: 180 | E36: Mw. M. Hyllested Poulsen en Dhr. S. Crull
A37: 0152 | B37: 360 | C37: Duijndam Personeelsdiensten B.V. | D37: 211 | E37: Homescout21 B.V.
A38: 0322 | B38: 352 | C38: CB Construction UAB | D38: 795 | E38: J.P. Stoel
A39: 0346 | B39: 277 | C39: PMM Workforce Management Ltd | D39: 796 | E39: TwinsBV
A40: 0047 | B40: 149 | C40: Werckpost Service B.V. | D40: 147 | E40: T. Hoolhorst
A41: 0048 | B41: 124 | C41: AmDor Projecten B.V. | D41: 77 | E41: A.P.W. Koedooder
... A44: 0049 | B44: 286 | C44: Team Unica B.V. | D44: 175 | E44: Dhr. J.L. Meerding
A45: 0280 | B45: id | C45: naam | D45: 952 | E45: M. Nottet
A46: 0281 | B46: id | C46: naam | D46: 952 | E46: M. Nottet
A47: 0004 | B47: 17 | C47: Tradiro Services B.V. | D47: 258 | E47: Parkwonen
A48: 0027 | B48: 17 | C48: Tradiro Services B.V. | D48: 797 | E48: W. van Straalen
A49: 0097 | B49: 17 | C49: Tradiro Services B.V. | D49: 302 | E49: A.H.S. Willemsen
A50: 0160 | B50: 17 | C50: Tradiro Services B.V. | D50: 295 | E50: In Stijl Totaalbouw BV
A51: 0131 | B51: 17 | C51: Tradiro Services B.V. | D51: 258 | E51: Parkwonen
A52: 0026 | B52: 17 | C52: Tradiro Services B.V. | D52: 258 | E52: Parkwonen
A53: 0370 | B53: 17 | C53: Tradiro Services B.V. | D53: 85 | E53: 4 Homes B.V.
A54: 0051 | B54: 13 | C54: United Homes B.V. | D54: #VALUE! | E54: #VALUE!
A55: 0052 | B55: 13 | C55: United Homes B.V. | D55: #VALUE! | E55: #VALUE!
A56: 0375 | B56: 17 | C56: Tradiro Services B.V. | D56: 799 | E56: Z. Yilmaz
A57: 0053 | B57: 123 | C57: OJP B.V. | D57: 5 | E57: Ruva Vastgoed B.V.
A58: 0151 | B58: 374 | C58: GAP Costruzioni S.r.l. | D58: 271 | E58: Houses2Rent
A59: 0165 | B59: 17 | C59: Tradiro Services B.V. | E59: naam
A60: 0056 | B60: 122 | C60: Interwel Oost B.V. | D60: 800 | E60: L. Schilstra / Eigenaar.nl
A61: 0371 | B61: 17 | C61: Tradiro Services B.V. | D61: 683 | E61: Tetering en Martens
A62: 0153 | B62: 374 | C62: GAP Costruzioni S.r.l. | D62: 271 | E62: Houses2Rent
A63: 0023 | B63: 236 | C63: NL Realty B.V. | D63: 326 | E63: S. Kleiren
A64: 0024 | B64: 236 | C64: NL Realty B.V. | D64: 326 | E64: S. Kleiren
A65: 0058 | B65: 34 | C65: Employ | D65: 206 | E65: Dhr. T. Roestenberg en Mw. Roestenberg - Hustinx
A66: 0059 | B66: 367 | C66: Kapitan Workers Sp. Z.o.o. | D66: 801 | E66: P. Ter Haar - Ros
B67: 0 | C67: 0 | D67: 0 | E67: 0
A68: 0354 | B68: 17 | C68: Tradiro Services B.V. | D68: 253 | E68: Facili Flex BV
A69: 0066 | B69: 304 | C69: Royal DS Personeel-service | D69: 802 | E69: Maatschap vd Vlist -Teuben
A70: 0061 | B70: 240 | C70: Impianti Industriala S.P.A. NEDERLAND BRANCH | D70: 111 | E70: Hugo Vastgoed B.V.
A71: 0136 | B71: 276 | C71: EG Facility & Services BV | D71: 803 | E71: M&M Hendriks
A72: 0063 | B72: 374 | C72: GAP Costruzioni S.r.l. | D72: 569 | E72: Quadrant Vastgoed B.V.
A73: 0095 | B73: 17 | C73: Tradiro Services B.V. | D73: 295 | E73: In Stijl Totaalbouw BV
A74: 0095 | B74: 17 | C74: Tradiro Services B.V. | D74: 295 | E74: In Stijl Totaalbouw BV
A75: 0064 | B75: 98 | C75: Lago Personeelshuisvesting B.V. | D75: 168 | E75: F. Veurink en P. Neleman
A76: 0006 | B76: 353 | C76: Optima Uitzendbureau B.V. | D76: 763 | E76: T. Eenhuistra/J. Pluimakers
A77: 0065 | B77: 124 | C77: AmDor Projecten B.V. | D77: 846 | E77: Leendert Keizer
B78: 0 | C78: 0 | D78: 0 | E78: 0
A79: 0331 | B79: 23 | C79: S. Bakker OPH Verhuur | D79: 805 | E79: TH Mungroop
A80: 0067 | B80: 17 | C80: Tradiro Services B.V. | D80: 806 | E80: Value+ Vastgoedmanagement
A81: 0017 | B81: 17 | C81: Tradiro Services B.V. | D81: 807 | E81: M.C. Mostert
B82: 0 | C82: 0 | D82: 0 | E82: 0
A83: 0109 | B83: 26 | C83: Vivir Wonen | D83: 783 | E83: Johan ven der Burg
A84: 0070 | B84: id | C84: naam | D84: 808 | E84: Bart Vlastuin
A85: 0170 | B85: 355 | C85: LogIQ Barendrecht B.V. | E85: naam
A86: 0025 | B86: 17 | C86: Tradiro Services B.V. | D86: 574 | E86: Verknocht
A87: 0071 | B87: 210 | C87: DIT en Larex Vakpersoneel B.V. | D87: 241 | E87: BJ Bakker
B88: 0 | C88: 0 | D88: 0 | E88: 0
A89: 0396 | B89: id | C89: naam | D89: 145 | E89: dockHolland Huisvesting B.V.
A90: 0072 | B90: 210 | C90: DIT en Larex Vakpersoneel B.V. | D90: 810 | E90: Robert de Jonge
A91: 0073 | B91: 13 | C91: United Homes B.V. | D91: 146 | E91: Fam. Derwig
A92: 0325 | B92: 305 | C92: VALO Facilities B.V. | D92: 811 | E92: M. Koolhaas
A93: 0176 | B93: 17 | C93: Tradiro Services B.V. | D93: 295 | E93: In Stijl Totaalbouw BV
A94: 0133 | B94: 23 | C94: S. Bakker OPH Verhuur | D94: 602 | E94: Westhavendomein BV
A95: 0107 | B95: 210 | C95: DIT en Larex Vakpersoneel B.V. | D95: 792 | E95: H. Samson
A96: 0031 | B96: 17 | C96: Tradiro Services B.V. | D96: 812 | E96: M. Dogan
A97: 0181 | B97: id | C97: naam | D97: 17 | E97: Tradiro Services B.V.
A98: 0075 | B98: 270 | C98: WILL Vakkrachten B. V. | D98: 813 | E98: HBB Wonen (Danielle Hanegraaf)
A99: 0078 | B99: 210 | C99: DIT en Larex Vakpersoneel B.V. | D99: 792 | E99: H. Samson
A100: 0147 | B100: 82 | C100: Crown Uitzendgroep | D100: 573 | E100: Risa Beheer B.V.
A101: 0391 | B101: id | C101: naam | D101: 375 | E101: B. van Abeelen
A102: 0039 | B102: 329 | C102: RNDV Industries | D102: 644 | E102: J.G. van Pieterson
A103: 0187 | B103: 17 | C103: Tradiro Services B.V. | E103: naam
A104: 0188 | B104: 17 | C104: Tradiro Services B.V. | E104: naam
A105: 0087 | B105: 136 | C105: H.T.C. Facility Services B.V. | D105: 824 | E105: Vivir wonen (Mendy)
A106: 0146 | B106: 30 | C106: Team Home Rentals B.V. | D106: 848 | E106: R. Bouius
A107: 0082 | B107: 23 | C107: S. Bakker OPH Verhuur | D107: 824 | E107: Vivir wonen (Mendy)
A108: 0193 | B108: 234 | C108: Labour Housing BV | D108: 300 | E108: JES Funding & Beheer B.V.
A109: 0159 | B109: 336 | C109: PRP Solutions Flex Sp. Z.O.O | D109: 542 | E109: Hopmans Flexstay
B110: 0 | C110: 0 | D110: 0 | E110: 0
A111: 0084 | B111: 17 | C111: Tradiro Services B.V. | D111: 43 | E111: De Pagter Vastgoed B.V.
A112: 0308 | B112: 149 | C112: Werckpost Service B.V. | D112: 849 | E112: Chalet Park Holiday
A113: 0309 | B113: 83 | C113: UAB Toromega | D113: 849 | E113: Chalet Park Holiday
A114: 0310 | B114: 234 | C114: Labour Housing BV | D114: 849 | E114: Chalet Park Holiday
A115: 0311 | B115: 83 | C115: UAB Toromega | D115: 766 | E115: C. van Driel e/o B.M. Verdouw
A116: 0312 | B116: 234 | C116: Labour Housing BV | D116: 849 | E116: Chalet Park Holiday
...
