Workbook

Sheet Dashboard
A1: COMPLETENESS DASHBOARD
A3: Adres | B3: Basis? | C3: GWE? | D3: Schoonmaak? | E3: STATUS
A4: {=_xlfn.SINGLE(_xlfn.UNIQUE(_xlfn._xlws.FILTER(Input!A2:A5000, Input!A2:A5000<>"")))} | B4: =IF(A4="","",IF(COUNTIFS(Input!$A:$A, A4, Input!$B:$B, "Basis")>0, "OK", "MISSING")) | C4: =IF(A4="","",IF(COUNTIFS(Input!$A:$A, A4, Input!$B:$B, "GWE")>0, "OK", "MISSING")) | D4: =IF(A4="","",IF(COUNTIFS(Input!$A:$A, A4, Input!$B:$B, "Schoonmaak")>0, "OK", "MISSING")) | E4: =IF(A4="","",IF(AND(B4="OK",C4="OK",D4="OK"), "✅ READY", "⚠️ INCOMPLETE"))
A5: =_xlfn.UNIQUE(_xlfn._xlws.FILTER(Input!A3:A5001, Input!A3:A5001<>"")) | B5: =IF(A5="","",IF(COUNTIFS(Input!$A:$A, A5, Input!$B:$B, "Basis")>0, "OK", "MISSING")) | C5: =IF(A5="","",IF(COUNTIFS(Input!$A:$A, A5, Input!$B:$B, "GWE")>0, "OK", "MISSING")) | D5: =IF(A5="","",IF(COUNTIFS(Input!$A:$A, A5, Input!$B:$B, "Schoonmaak")>0, "OK", "MISSING")) | E5: =IF(A5="","",IF(AND(B5="OK",C5="OK",D5="OK"), "✅ READY", "⚠️ INCOMPLETE"))
A6: =_xlfn.UNIQUE(_xlfn._xlws.FILTER(Input!A4:A5002, Input!A4:A5002<>"")) | B6: =IF(A6="","",IF(COUNTIFS(Input!$A:$A, A6, Input!$B:$B, "Basis")>0, "OK", "MISSING")) | C6: =IF(A6="","",IF(COUNTIFS(Input!$A:$A, A6, Input!$B:$B, "GWE")>0, "OK", "MISSING")) | D6: =IF(A6="","",IF(COUNTIFS(Input!$A:$A, A6, Input!$B:$B, "Schoonmaak")>0, "OK", "MISSING")) | E6: =IF(A6="","",IF(AND(B6="OK",C6="OK",D6="OK"), "✅ READY", "⚠️ INCOMPLETE"))
A7: =_xlfn.UNIQUE(_xlfn._xlws.FILTER(Input!A5:A5003, Input!A5:A5003<>"")) | B7: =IF(A7="","",IF(COUNTIFS(Input!$A:$A, A7, Input!$B:$B, "Basis")>0, "OK", "MISSING")) | C7: =IF(A7="","",IF(COUNTIFS(Input!$A:$A, A7, Input!$B:$B, "GWE")>0, "OK", "MISSING")) | D7: =IF(A7="","",IF(COUNTIFS(Input!$A:$A, A7, Input!$B:$B, "Schoonmaak")>0, "OK", "MISSING")) | E7: =IF(A7="","",IF(AND(B7="OK",C7="OK",D7="OK"), "✅ READY", "⚠️ INCOMPLETE"))
A8: =_xlfn.UNIQUE(_xlfn._xlws.FILTER(Input!A6:A5004, Input!A6:A5004<>"")) | B8: =IF(A8="","",IF(COUNTIFS(Input!$A:$A, A8, Input!$B:$B, "Basis")>0, "OK", "MISSING")) | C8: =IF(A8="","",IF(COUNTIFS(Input!$A:$A, A8, Input!$B:$B, "GWE")>0, "OK", "MISSING")) | D8: =IF(A8="","",IF(COUNTIFS(Input!$A:$A, A8, Input!$B:$B, "Schoonmaak")>0, "OK", "MISSING")) | E8: =IF(A8="","",IF(AND(B8="OK",C8="OK",D8="OK"), "✅ READY", "⚠️ INCOMPLETE"))
A9: =_xlfn.UNIQUE(_xlfn._xlws.FILTER(Input!A7:A5005, Input!A7:A5005<>"")) | B9: =IF(A9="","",IF(COUNTIFS(Input!$A:$A, A9, Input!$B:$B, "Basis")>0, "OK", "MISSING")) | C9: =IF(A9="","",IF(COUNTIFS(Input!$A:$A, A9, Input!$B:$B, "GWE")>0, "OK", "MISSING")) | D9: =IF(A9="","",IF(COUNTIFS(Input!$A:$A, A9, Input!$B:$B, "Schoonmaak")>0, "OK", "MISSING")) | E9: =IF(A9="","",IF(AND(B9="OK",C9="OK",D9="OK"), "✅ READY", "⚠️ INCOMPLETE"))
A10: =_xlfn.UNIQUE(_xlfn._xlws.FILTER(Input!A8:A5006, Input!A8:A5006<>"")) | B10: =IF(A10="","",IF(COUNTIFS(Input!$A:$A, A10, Input!$B:$B, "Basis")>0, "OK", "MISSING")) | C10: =IF(A10="","",IF(COUNTIFS(Input!$A:$A, A10, Input!$B:$B, "GWE")>0, "OK", "MISSING")) | D10: =IF(A10="","",IF(COUNTIFS(Input!$A:$A, A10, Input!$B:$B, "Schoonmaak")>0, "OK", "MISSING")) | E10: =IF(A10="","",IF(AND(B10="OK",C10="OK",D10="OK"), "✅ READY", "⚠️ INCOMPLETE"))
A11: =_xlfn.UNIQUE(_xlfn._xlws.FILTER(Input!A9:A5007, Input!A9:A5007<>"")) | B11: =IF(A11="","",IF(COUNTIFS(Input!$A:$A, A11, Input!$B:$B, "Basis")>0, "OK", "MISSING")) | C11: =IF(A11="","",IF(COUNTIFS(Input!$A:$A, A11, Input!$B:$B, "GWE")>0, "OK", "MISSING")) | D11: =IF(A11="","",IF(COUNTIFS(Input!$A:$A, A11, Input!$B:$B, "Schoonmaak")>0, "OK", "MISSING")) | E11: =IF(A11="","",IF(AND(B11="OK",C11="OK",D11="OK"), "✅ READY", "⚠️ INCOMPLETE"))
A12: =_xlfn.UNIQUE(_xlfn._xlws.FILTER(Input!A10:A5008, Input!A10:A5008<>"")) | B12: =IF(A12="","",IF(COUNTIFS(Input!$A:$A, A12, Input!$B:$B, "Basis")>0, "OK", "MISSING")) | C12: =IF(A12="","",IF(COUNTIFS(Input!$A:$A, A12, Input!$B:$B, "GWE")>0, "OK", "MISSING")) | D12: =IF(A12="","",IF(COUNTIFS(Input!$A:$A, A12, Input!$B:$B, "Schoonmaak")>0, "OK", "MISSING")) | E12: =IF(A12="","",IF(AND(B12="OK",C12="OK",D12="OK"), "✅ READY", "⚠️ INCOMPLETE"))
A13: =_xlfn.UNIQUE(_xlfn._xlws.FILTER(Input!A11:A5009, Input!A11:A5009<>"")) | B13: =IF(A13="","",IF(COUNTIFS(Input!$A:$A, A13, Input!$B:$B, "Basis")>0, "OK", "MISSING")) | C13: =IF(A13="","",IF(COUNTIFS(Input!$A:$A, A13, Input!$B:$B, "GWE")>0, "OK", "MISSING")) | D13: =IF(A13="","",IF(COUNTIFS(Input!$A:$A, A13, Input!$B:$B, "Schoonmaak")>0, "OK", "MISSING")) | E13: =IF(A13="","",IF(AND(B13="OK",C13="OK",D13="OK"), "✅ READY", "⚠️ INCOMPLETE"))
A14: =_xlfn.UNIQUE(_xlfn._xlws.FILTER(Input!A12:A5010, Input!A12:A5010<>"")) | B14: =IF(A14="","",IF(COUNTIFS(Input!$A:$A, A14, Input!$B:$B, "Basis")>0, "OK", "MISSING")) | C14: =IF(A14="","",IF(COUNTIFS(Input!$A:$A, A14, Input!$B:$B, "GWE")>0, "OK", "MISSING")) | D14: =IF(A14="","",IF(COUNTIFS(Input!$A:$A, A14, Input!$B:$B, "Schoonmaak")>0, "OK", "MISSING")) | E14: =IF(A14="","",IF(AND(B14="OK",C14="OK",D14="OK"), "✅ READY", "⚠️ INCOMPLETE"))
A15: =_xlfn.UNIQUE(_xlfn._xlws.FILTER(Input!A13:A5011, Input!A13:A5011<>"")) | B15: =IF(A15="","",IF(COUNTIFS(Input!$A:$A, A15, Input!$B:$B, "Basis")>0, "OK", "MISSING")) | C15: =IF(A15="","",IF(COUNTIFS(Input!$A:$A, A15, Input!$B:$B, "GWE")>0, "OK", "MISSING")) | D15: =IF(A15="","",IF(COUNTIFS(Input!$A:$A, A15, Input!$B:$B, "Schoonmaak")>0, "OK", "MISSING")) | E15: =IF(A15="","",IF(AND(B15="OK",C15="OK",D15="OK"), "✅ READY", "⚠️ INCOMPLETE"))
A16: =_xlfn.UNIQUE(_xlfn._xlws.FILTER(Input!A14:A5012, Input!A14:A5012<>"")) | B16: =IF(A16="","",IF(COUNTIFS(Input!$A:$A, A16, Input!$B:$B, "Basis")>0, "OK", "MISSING")) | C16: =IF(A16="","",IF(COUNTIFS(Input!$A:$A, A16, Input!$B:$B, "GWE")>0, "OK", "MISSING")) | D16: =IF(A16="","",IF(COUNTIFS(Input!$A:$A, A16, Input!$B:$B, "Schoonmaak")>0, "OK", "MISSING")) | E16: =IF(A16="","",IF(AND(B16="OK",C16="OK",D16="OK"), "✅ READY", "⚠️ INCOMPLETE"))
... A96: =_xlfn.UNIQUE(_xlfn._xlws.FILTER(Input!A94:A5092, Input!A94:A5092<>"")) | B96: =IF(A96="","",IF(COUNTIFS(Input!$A:$A, A96, Input!$B:$B, "Basis")>0, "OK", "MISSING")) | C96: =IF(A96="","",IF(COUNTIFS(Input!$A:$A, A96, Input!$B:$B, "GWE")>0, "OK", "MISSING")) | D96: =IF(A96="","",IF(COUNTIFS(Input!$A:$A, A96, Input!$B:$B, "Schoonmaak")>0, "OK", "MISSING")) | E96: =IF(A96="","",IF(AND(B96="OK",C96="OK",D96="OK"), "✅ READY", "⚠️ INCOMPLETE"))

Sheet Input
A1: Adres | B1: Type | C1: Klantnaam | D1: Object ID | E1: Klant Nr (Auto) | F1: RR Inspecteur | G1: Folder Link | H1: Check-in | I1: Check-out | J1: Borg (€) | K1: GWE Beheer | L1: GWE Maandbedrag (€) | M1: Voorschot GWE (Auto) | N1: Meterbeheerder | O1: Leverancier | P1: Leverancier Nr (Auto) | Q1: Contractnr | R1: Extra Voorschot (€) | S1: Extra Voor. Omschr. | T1: Elek Begin | U1: Elek Eind | V1: Gas Begin | W1: Gas Eind | X1: Water Begin | Y1: Water Eind | Z1: Schoon Maak Pakket | AA1: Schoon Uren | AB1: Uurtarief (€) | AC1: Totaal Excl (€) | AD1: BTW % | AE1: BTW Bedrag (€) | AF1: Totaal Incl (€) | AG1: Kosten Type | AH1: Eenheid | AI1: Beschrijving | AJ1: Aantal | AK1: Prijs/Stuk (€) | AL1: Totaal Excl (€) | AM1: BTW % | AN1: BTW Bedrag (€) | AO1: Totaal Incl (€)
A2: Test Straat 1 | B2: Basis | C2: Client Een | H2: 2024-01-01 | I2: 2024-01-31 | J2: 1000 | K2: Via RyanRent | M2: 250
A3: Test Straat 1 | B3: GWE | T3: 1000 | U3: 1200
A4: Test Straat 1 | B4: Schoonmaak | Z4: Basis Schoonmaak | AA4: 3 | AB4: 50
A5: Test Straat 2 | B5: Basis | C5: Client Twee | H5: 2024-02-01 | I5: 2024-02-28 | J5: 800 | K5: Eigen Beheer
A6: Test Straat 2 | B6: Schade | AG6: Overig | AI6: Gebroken Lamp | AJ6: 1 | AK6: 50 | AM6: 0.21
A7: Test Straat 3 | B7: Basis | C7: Client Drie | H7: 2024-03-01 | I7: 2024-03-31 | J7: 1500 | K7: Via RyanRent | M7: 300 | T7: 0 | U7: 0
A8: Test Straat 3 | B8: Schoonmaak | Z8: Intensief Schoonmaak | AA8: 10 | AB8: 60
D101: =IF(A101="","",VLOOKUP(A101,Lists!$A:$B,2,FALSE)) | E101: =IF(C101="","",VLOOKUP(C101,Lists!$C:$D,2,FALSE)) | J101: =IF(A101="","",IFERROR(VLOOKUP(A101,Lists!$A:$H,8,FALSE),0)) | L101: =IF(A101="","",IFERROR(VLOOKUP(A101,Lists!$A:$H,7,FALSE),0)) | M101: =IF(K101="Eigen Beheer",0,IF(AND(ISNUMBER(L101),I101<>"",H101<>""),(L101*12/365)*(I101-H101),0)) | P101: =IF(O101="","",VLOOKUP(O101,Lists!$E:$F,2,FALSE)) | AC101: =IF(AND(AA101<>"",AB101<>""),AA101*AB101,"") | AE101: =IF(AND(AC101<>"",AD101<>""),AC101*AD101,"") | AF101: =IF(AND(AC101<>"",AE101<>""),AC101+AE101,"") | AJ101: =IF($B101="GWE_Item",IF($AG101="Elektra",SUMIFS($U:$U,$A:$A,$A101,$B:$B,"GWE")-SUMIFS($T:$T,$A:$A,$A101,$B:$B,"GWE"),IF($AG101="Gas",SUMIFS($W:$W,$A:$A,$A101,$B:$B,"GWE")-SUMIFS($V:$V,$A:$A,$A101,$B:$B,"GWE"),IF($AG101="Water",SUMIFS($Y:$Y,$A:$A,$A101,$B:$B,"GWE")-SUMIFS($X:$X,$A:$A,$A101,$B:$B,"GWE"),""))),"") | AL101: =IF(AND(AJ101<>"",AK101<>""),AJ101*AK101,"") | AN101: =IF(AND(AL101<>"",AM101<>""),AL101*AM101,"") | AO101: =IF(AND(AL101<>"",AN101<>""),AL101+AN101,"")
D102: =IF(A102="","",VLOOKUP(A102,Lists!$A:$B,2,FALSE)) | E102: =IF(C102="","",VLOOKUP(C102,Lists!$C:$D,2,FALSE)) | J102: =IF(A102="","",IFERROR(VLOOKUP(A102,Lists!$A:$H,8,FALSE),0)) | L102: =IF(A102="","",IFERROR(VLOOKUP(A102,Lists!$A:$H,7,FALSE),0)) | M102: =IF(K102="Eigen Beheer",0,IF(AND(ISNUMBER(L102),I102<>"",H102<>""),(L102*12/365)*(I102-H102),0)) | P102: =IF(O102="","",VLOOKUP(O102,Lists!$E:$F,2,FALSE)) | AC102: =IF(AND(AA102<>"",AB102<>""),AA102*AB102,"") | AE102: =IF(AND(AC102<>"",AD102<>""),AC102*AD102,"") | AF102: =IF(AND(AC102<>"",AE102<>""),AC102+AE102,"") | AJ102: =IF($B102="GWE_Item",IF($AG102="Elektra",SUMIFS($U:$U,$A:$A,$A102,$B:$B,"GWE")-SUMIFS($T:$T,$A:$A,$A102,$B:$B,"GWE"),IF($AG102="Gas",SUMIFS($W:$W,$A:$A,$A102,$B:$B,"GWE")-SUMIFS($V:$V,$A:$A,$A102,$B:$B,"GWE"),IF($AG102="Water",SUMIFS($Y:$Y,$A:$A,$A102,$B:$B,"GWE")-SUMIFS($X:$X,$A:$A,$A102,$B:$B,"GWE"),""))),"") | AL102: =IF(AND(AJ102<>"",AK102<>""),AJ102*AK102,"") | AN102: =IF(AND(AL102<>"",AM102<>""),AL102*AM102,"") | AO102: =IF(AND(AL102<>"",AN102<>""),AL102+AN102,"")
D103: =IF(A103="","",VLOOKUP(A103,Lists!$A:$B,2,FALSE)) | E103: =IF(C103="","",VLOOKUP(C103,Lists!$C:$D,2,FALSE)) | J103: =IF(A103="","",IFERROR(VLOOKUP(A103,Lists!$A:$H,8,FALSE),0)) | L103: =IF(A103="","",IFERROR(VLOOKUP(A103,Lists!$A:$H,7,FALSE),0)) | M103: =IF(K103="Eigen Beheer",0,IF(AND(ISNUMBER(L103),I103<>"",H103<>""),(L103*12/365)*(I103-H103),0)) | P103: =IF(O103="","",VLOOKUP(O103,Lists!$E:$F,2,FALSE)) | AC103: =IF(AND(AA103<>"",AB103<>""),AA103*AB103,"") | AE103: =IF(AND(AC103<>"",AD103<>""),AC103*AD103,"") | AF103: =IF(AND(AC103<>"",AE103<>""),AC103+AE103,"") | AJ103: =IF($B103="GWE_Item",IF($AG103="Elektra",SUMIFS($U:$U,$A:$A,$A103,$B:$B,"GWE")-SUMIFS($T:$T,$A:$A,$A103,$B:$B,"GWE"),IF($AG103="Gas",SUMIFS($W:$W,$A:$A,$A103,$B:$B,"GWE")-SUMIFS($V:$V,$A:$A,$A103,$B:$B,"GWE"),IF($AG103="Water",SUMIFS($Y:$Y,$A:$A,$A103,$B:$B,"GWE")-SUMIFS($X:$X,$A:$A,$A103,$B:$B,"GWE"),""))),"") | AL103: =IF(AND(AJ103<>"",AK103<>""),AJ103*AK103,"") | AN103: =IF(AND(AL103<>"",AM103<>""),AL103*AM103,"") | AO103: =IF(AND(AL103<>"",AN103<>""),AL103+AN103,"")
D104: =IF(A104="","",VLOOKUP(A104,Lists!$A:$B,2,FALSE)) | E104: =IF(C104="","",VLOOKUP(C104,Lists!$C:$D,2,FALSE)) | J104: =IF(A104="","",IFERROR(VLOOKUP(A104,Lists!$A:$H,8,FALSE),0)) | L104: =IF(A104="","",IFERROR(VLOOKUP(A104,Lists!$A:$H,7,FALSE),0)) | M104: =IF(K104="Eigen Beheer",0,IF(AND(ISNUMBER(L104),I104<>"",H104<>""),(L104*12/365)*(I104-H104),0)) | P104: =IF(O104="","",VLOOKUP(O104,Lists!$E:$F,2,FALSE)) | AC104: =IF(AND(AA104<>"",AB104<>""),AA104*AB104,"") | AE104: =IF(AND(AC104<>"",AD104<>""),AC104*AD104,"") | AF104: =IF(AND(AC104<>"",AE104<>""),AC104+AE104,"") | AJ104: =IF($B104="GWE_Item",IF($AG104="Elektra",SUMIFS($U:$U,$A:$A,$A104,$B:$B,"GWE")-SUMIFS($T:$T,$A:$A,$A104,$B:$B,"GWE"),IF($AG104="Gas",SUMIFS($W:$W,$A:$A,$A104,$B:$B,"GWE")-SUMIFS($V:$V,$A:$A,$A104,$B:$B,"GWE"),IF($AG104="Water",SUMIFS($Y:$Y,$A:$A,$A104,$B:$B,"GWE")-SUMIFS($X:$X,$A:$A,$A104,$B:$B,"GWE"),""))),"") | AL104: =IF(AND(AJ104<>"",AK104<>""),AJ104*AK104,"") | AN104: =IF(AND(AL104<>"",AM104<>""),AL104*AM104,"") | AO104: =IF(AND(AL104<>"",AN104<>""),AL104+AN104,"")
D105: =IF(A105="","",VLOOKUP(A105,Lists!$A:$B,2,FALSE)) | E105: =IF(C105="","",VLOOKUP(C105,Lists!$C:$D,2,FALSE)) | J105: =IF(A105="","",IFERROR(VLOOKUP(A105,Lists!$A:$H,8,FALSE),0)) | L105: =IF(A105="","",IFERROR(VLOOKUP(A105,Lists!$A:$H,7,FALSE),0)) | M105: =IF(K105="Eigen Beheer",0,IF(AND(ISNUMBER(L105),I105<>"",H105<>""),(L105*12/365)*(I105-H105),0)) | P105: =IF(O105="","",VLOOKUP(O105,Lists!$E:$F,2,FALSE)) | AC105: =IF(AND(AA105<>"",AB105<>""),AA105*AB105,"") | AE105: =IF(AND(AC105<>"",AD105<>""),AC105*AD105,"") | AF105: =IF(AND(AC105<>"",AE105<>""),AC105+AE105,"") | AJ105: =IF($B105="GWE_Item",IF($AG105="Elektra",SUMIFS($U:$U,$A:$A,$A105,$B:$B,"GWE")-SUMIFS($T:$T,$A:$A,$A105,$B:$B,"GWE"),IF($AG105="Gas",SUMIFS($W:$W,$A:$A,$A105,$B:$B,"GWE")-SUMIFS($V:$V,$A:$A,$A105,$B:$B,"GWE"),IF($AG105="Water",SUMIFS($Y:$Y,$A:$A,$A105,$B:$B,"GWE")-SUMIFS($X:$X,$A:$A,$A105,$B:$B,"GWE"),""))),"") | AL105: =IF(AND(AJ105<>"",AK105<>""),AJ105*AK105,"") | AN105: =IF(AND(AL105<>"",AM105<>""),AL105*AM105,"") | AO105: =IF(AND(AL105<>"",AN105<>""),AL105+AN105,"")
D106: =IF(A106="","",VLOOKUP(A106,Lists!$A:$B,2,FALSE)) | E106: =IF(C106="","",VLOOKUP(C106,Lists!$C:$D,2,FALSE)) | J106: =IF(A106="","",IFERROR(VLOOKUP(A106,Lists!$A:$H,8,FALSE),0)) | L106: =IF(A106="","",IFERROR(VLOOKUP(A106,Lists!$A:$H,7,FALSE),0)) | M106: =IF(K106="Eigen Beheer",0,IF(AND(ISNUMBER(L106),I106<>"",H106<>""),(L106*12/365)*(I106-H106),0)) | P106: =IF(O106="","",VLOOKUP(O106,Lists!$E:$F,2,FALSE)) | AC106: =IF(AND(AA106<>"",AB106<>""),AA106*AB106,"") | AE106: =IF(AND(AC106<>"",AD106<>""),AC106*AD106,"") | AF106: =IF(AND(AC106<>"",AE106<>""),AC106+AE106,"") | AJ106: =IF($B106="GWE_Item",IF($AG106="Elektra",SUMIFS($U:$U,$A:$A,$A106,$B:$B,"GWE")-SUMIFS($T:$T,$A:$A,$A106,$B:$B,"GWE"),IF($AG106="Gas",SUMIFS($W:$W,$A:$A,$A106,$B:$B,"GWE")-SUMIFS($V:$V,$A:$A,$A106,$B:$B,"GWE"),IF($AG106="Water",SUMIFS($Y:$Y,$A:$A,$A106,$B:$B,"GWE")-SUMIFS($X:$X,$A:$A,$A106,$B:$B,"GWE"),""))),"") | AL106: =IF(AND(AJ106<>"",AK106<>""),AJ106*AK106,"") | AN106: =IF(AND(AL106<>"",AM106<>""),AL106*AM106,"") | AO106: =IF(AND(AL106<>"",AN106<>""),AL106+AN106,"")
D107: =IF(A107="","",VLOOKUP(A107,Lists!$A:$B,2,FALSE)) | E107: =IF(C107="","",VLOOKUP(C107,Lists!$C:$D,2,FALSE)) | J107: =IF(A107="","",IFERROR(VLOOKUP(A107,Lists!$A:$H,8,FALSE),0)) | L107: =IF(A107="","",IFERROR(VLOOKUP(A107,Lists!$A:$H,7,FALSE),0)) | M107: =IF(K107="Eigen Beheer",0,IF(AND(ISNUMBER(L107),I107<>"",H107<>""),(L107*12/365)*(I107-H107),0)) | P107: =IF(O107="","",VLOOKUP(O107,Lists!$E:$F,2,FALSE)) | AC107: =IF(AND(AA107<>"",AB107<>""),AA107*AB107,"") | AE107: =IF(AND(AC107<>"",AD107<>""),AC107*AD107,"") | AF107: =IF(AND(AC107<>"",AE107<>""),AC107+AE107,"") | AJ107: =IF($B107="GWE_Item",IF($AG107="Elektra",SUMIFS($U:$U,$A:$A,$A107,$B:$B,"GWE")-SUMIFS($T:$T,$A:$A,$A107,$B:$B,"GWE"),IF($AG107="Gas",SUMIFS($W:$W,$A:$A,$A107,$B:$B,"GWE")-SUMIFS($V:$V,$A:$A,$A107,$B:$B,"GWE"),IF($AG107="Water",SUMIFS($Y:$Y,$A:$A,$A107,$B:$B,"GWE")-SUMIFS($X:$X,$A:$A,$A107,$B:$B,"GWE"),""))),"") | AL107: =IF(AND(AJ107<>"",AK107<>""),AJ107*AK107,"") | AN107: =IF(AND(AL107<>"",AM107<>""),AL107*AM107,"") | AO107: =IF(AND(AL107<>"",AN107<>""),AL107+AN107,"")
D108: =IF(A108="","",VLOOKUP(A108,Lists!$A:$B,2,FALSE)) | E108: =IF(C108="","",VLOOKUP(C108,Lists!$C:$D,2,FALSE)) | J108: =IF(A108="","",IFERROR(VLOOKUP(A108,Lists!$A:$H,8,FALSE),0)) | L108: =IF(A108="","",IFERROR(VLOOKUP(A108,Lists!$A:$H,7,FALSE),0)) | M108: =IF(K108="Eigen Beheer",0,IF(AND(ISNUMBER(L108),I108<>"",H108<>""),(L108*12/365)*(I108-H108),0)) | P108: =IF(O108="","",VLOOKUP(O108,Lists!$E:$F,2,FALSE)) | AC108: =IF(AND(AA108<>"",AB108<>""),AA108*AB108,"") | AE108: =IF(AND(AC108<>"",AD108<>""),AC108*AD108,"") | AF108: =IF(AND(AC108<>"",AE108<>""),AC108+AE108,"") | AJ108: =IF($B108="GWE_Item",IF($AG108="Elektra",SUMIFS($U:$U,$A:$A,$A108,$B:$B,"GWE")-SUMIFS($T:$T,$A:$A,$A108,$B:$B,"GWE"),IF($AG108="Gas",SUMIFS($W:$W,$A:$A,$A108,$B:$B,"GWE")-SUMIFS($V:$V,$A:$A,$A108,$B:$B,"GWE"),IF($AG108="Water",SUMIFS($Y:$Y,$A:$A,$A108,$B:$B,"GWE")-SUMIFS($X:$X,$A:$A,$A108,$B:$B,"GWE"),""))),"") | AL108: =IF(AND(AJ108<>"",AK108<>""),AJ108*AK108,"") | AN108: =IF(AND(AL108<>"",AM108<>""),AL108*AM108,"") | AO108: =IF(AND(AL108<>"",AN108<>""),AL108+AN108,"")
D109: =IF(A109="","",VLOOKUP(A109,Lists!$A:$B,2,FALSE)) | E109: =IF(C109="","",VLOOKUP(C109,Lists!$C:$D,2,FALSE)) | J109: =IF(A109="","",IFERROR(VLOOKUP(A109,Lists!$A:$H,8,FALSE),0)) | L109: =IF(A109="","",IFERROR(VLOOKUP(A109,Lists!$A:$H,7,FALSE),0)) | M109: =IF(K109="Eigen Beheer",0,IF(AND(ISNUMBER(L109),I109<>"",H109<>""),(L109*12/365)*(I109-H109),0)) | P109: =IF(O109="","",VLOOKUP(O109,Lists!$E:$F,2,FALSE)) | AC109: =IF(AND(AA109<>"",AB109<>""),AA109*AB109,"") | AE109: =IF(AND(AC109<>"",AD109<>""),AC109*AD109,"") | AF109: =IF(AND(AC109<>"",AE109<>""),AC109+AE109,"") | AJ109: =IF($B109="GWE_Item",IF($AG109="Elektra",SUMIFS($U:$U,$A:$A,$A109,$B:$B,"GWE")-SUMIFS($T:$T,$A:$A,$A109,$B:$B,"GWE"),IF($AG109="Gas",SUMIFS($W:$W,$A:$A,$A109,$B:$B,"GWE")-SUMIFS($V:$V,$A:$A,$A109,$B:$B,"GWE"),IF($AG109="Water",SUMIFS($Y:$Y,$A:$A,$A109,$B:$B,"GWE")-SUMIFS($X:$X,$A:$A,$A109,$B:$B,"GWE"),""))),"") | AL109: =IF(AND(AJ109<>"",AK109<>""),AJ109*AK109,"") | AN109: =IF(AND(AL109<>"",AM109<>""),AL109*AM109,"") | AO109: =IF(AND(AL109<>"",AN109<>""),AL109+AN109,"")
D110: =IF(A110="","",VLOOKUP(A110,Lists!$A:$B,2,FALSE)) | E110: =IF(C110="","",VLOOKUP(C110,Lists!$C:$D,2,FALSE)) | J110: =IF(A110="","",IFERROR(VLOOKUP(A110,Lists!$A:$H,8,FALSE),0)) | L110: =IF(A110="","",IFERROR(VLOOKUP(A110,Lists!$A:$H,7,FALSE),0)) | M110: =IF(K110="Eigen Beheer",0,IF(AND(ISNUMBER(L110),I110<>"",H110<>""),(L110*12/365)*(I110-H110),0)) | P110: =IF(O110="","",VLOOKUP(O110,Lists!$E:$F,2,FALSE)) | AC110: =IF(AND(AA110<>"",AB110<>""),AA110*AB110,"") | AE110: =IF(AND(AC110<>"",AD110<>""),AC110*AD110,"") | AF110: =IF(AND(AC110<>"",AE110<>""),AC110+AE110,"") | AJ110: =IF($B110="GWE_Item",IF($AG110="Elektra",SUMIFS($U:$U,$A:$A,$A110,$B:$B,"GWE")-SUMIFS($T:$T,$A:$A,$A110,$B:$B,"GWE"),IF($AG110="Gas",SUMIFS($W:$W,$A:$A,$A110,$B:$B,"GWE")-SUMIFS($V:$V,$A:$A,$A110,$B:$B,"GWE"),IF($AG110="Water",SUMIFS($Y:$Y,$A:$A,$A110,$B:$B,"GWE")-SUMIFS($X:$X,$A:$A,$A110,$B:$B,"GWE"),""))),"") | AL110: =IF(AND(AJ110<>"",AK110<>""),AJ110*AK110,"") | AN110: =IF(AND(AL110<>"",AM110<>""),AL110*AM110,"") | AO110: =IF(AND(AL110<>"",AN110<>""),AL110+AN110,"")
D111: =IF(A111="","",VLOOKUP(A111,Lists!$A:$B,2,FALSE)) | E111: =IF(C111="","",VLOOKUP(C111,Lists!$C:$D,2,FALSE)) | J111: =IF(A111="","",IFERROR(VLOOKUP(A111,Lists!$A:$H,8,FALSE),0)) | L111: =IF(A111="","",IFERROR(VLOOKUP(A111,Lists!$A:$H,7,FALSE),0)) | M111: =IF(K111="Eigen Beheer",0,IF(AND(ISNUMBER(L111),I111<>"",H111<>""),(L111*12/365)*(I111-H111),0)) | P111: =IF(O111="","",VLOOKUP(O111,Lists!$E:$F,2,FALSE)) | AC111: =IF(AND(AA111<>"",AB111<>""),AA111*AB111,"") | AE111: =IF(AND(AC111<>"",AD111<>""),AC111*AD111,"") | AF111: =IF(AND(AC111<>"",AE111<>""),AC111+AE111,"") | AJ111: =IF($B111="GWE_Item",IF($AG111="Elektra",SUMIFS($U:$U,$A:$A,$A111,$B:$B,"GWE")-SUMIFS($T:$T,$A:$A,$A111,$B:$B,"GWE"),IF($AG111="Gas",SUMIFS($W:$W,$A:$A,$A111,$B:$B,"GWE")-SUMIFS($V:$V,$A:$A,$A111,$B:$B,"GWE"),IF($AG111="Water",SUMIFS($Y:$Y,$A:$A,$A111,$B:$B,"GWE")-SUMIFS($X:$X,$A:$A,$A111,$B:$B,"GWE"),""))),"") | AL111: =IF(AND(AJ111<>"",AK111<>""),AJ111*AK111,"") | AN111: =IF(AND(AL111<>"",AM111<>""),AL111*AM111,"") | AO111: =IF(AND(AL111<>"",AN111<>""),AL111+AN111,"")
D112: =IF(A112="","",VLOOKUP(A112,Lists!$A:$B,2,FALSE)) | E112: =IF(C112="","",VLOOKUP(C112,Lists!$C:$D,2,FALSE)) | J112: =IF(A112="","",IFERROR(VLOOKUP(A112,Lists!$A:$H,8,FALSE),0)) | L112: =IF(A112="","",IFERROR(VLOOKUP(A112,Lists!$A:$H,7,FALSE),0)) | M112: =IF(K112="Eigen Beheer",0,IF(AND(ISNUMBER(L112),I112<>"",H112<>""),(L112*12/365)*(I112-H112),0)) | P112: =IF(O112="","",VLOOKUP(O112,Lists!$E:$F,2,FALSE)) | AC112: =IF(AND(AA112<>"",AB112<>""),AA112*AB112,"") | AE112: =IF(AND(AC112<>"",AD112<>""),AC112*AD112,"") | AF112: =IF(AND(AC112<>"",AE112<>""),AC112+AE112,"") | AJ112: =IF($B112="GWE_Item",IF($AG112="Elektra",SUMIFS($U:$U,$A:$A,$A112,$B:$B,"GWE")-SUMIFS($T:$T,$A:$A,$A112,$B:$B,"GWE"),IF($AG112="Gas",SUMIFS($W:$W,$A:$A,$A112,$B:$B,"GWE")-SUMIFS($V:$V,$A:$A,$A112,$B:$B,"GWE"),IF($AG112="Water",SUMIFS($Y:$Y,$A:$A,$A112,$B:$B,"GWE")-SUMIFS($X:$X,$A:$A,$A112,$B:$B,"GWE"),""))),"") | AL112: =IF(AND(AJ112<>"",AK112<>""),AJ112*AK112,"") | AN112: =IF(AND(AL112<>"",AM112<>""),AL112*AM112,"") | AO112: =IF(AND(AL112<>"",AN112<>""),AL112+AN112,"")
... D201: =IF(A201="","",VLOOKUP(A201,Lists!$A:$B,2,FALSE)) | E201: =IF(C201="","",VLOOKUP(C201,Lists!$C:$D,2,FALSE)) | J201: =IF(A201="","",IFERROR(VLOOKUP(A201,Lists!$A:$H,8,FALSE),0)) | L201: =IF(A201="","",IFERROR(VLOOKUP(A201,Lists!$A:$H,7,FALSE),0)) | M201: =IF(K201="Eigen Beheer",0,IF(AND(ISNUMBER(L201),I201<>"",H201<>""),(L201*12/365)*(I201-H201),0)) | P201: =IF(O201="","",VLOOKUP(O201,Lists!$E:$F,2,FALSE)) | AC201: =IF(AND(AA201<>"",AB201<>""),AA201*AB201,"") | AE201: =IF(AND(AC201<>"",AD201<>""),AC201*AD201,"") | AF201: =IF(AND(AC201<>"",AE201<>""),AC201+AE201,"") | AJ201: =IF($B201="GWE_Item",IF($AG201="Elektra",SUMIFS($U:$U,$A:$A,$A201,$B:$B,"GWE")-SUMIFS($T:$T,$A:$A,$A201,$B:$B,"GWE"),IF($AG201="Gas",SUMIFS($W:$W,$A:$A,$A201,$B:$B,"GWE")-SUMIFS($V:$V,$A:$A,$A201,$B:$B,"GWE"),IF($AG201="Water",SUMIFS($Y:$Y,$A:$A,$A201,$B:$B,"GWE")-SUMIFS($X:$X,$A:$A,$A201,$B:$B,"GWE"),""))),"") | AL201: =IF(AND(AJ201<>"",AK201<>""),AJ201*AK201,"") | AN201: =IF(AND(AL201<>"",AM201<>""),AL201*AM201,"") | AO201: =IF(AND(AL201<>"",AN201<>""),AL201+AN201,"")

Sheet Lists
A1: Address | B1: Object ID | C1: Clients (Name) | D1: Clients (ID) | E1: Leveranciers (Name) | F1: Leveranciers (ID) | G1: GWE Voorschot (Default) | H1: Borg (Default)
A2: 1e Middellandstraat 104A | B2: 0388 | C2: 't Werkt B.V. | D2: 50223 | E2: C. van Winsen | F2: 98 | G2: 200 | H2: 0
A3: 2e Maasbosstraat 2 a | B3: 0148 | C3: 24/7 drive | D3: 50224 | E3: 4 Homes | F3: 82 | G3: 0 | H3: 0
A4: 2e Maasbosstraat 2 b | B4: 0149 | C4: 4 Homes B.V. | D4: 94 | E4: A. Brouwers & S. Brouwers- van Weert | F4: 95 | G4: 0 | H4: 3300
A5: 2e Maasbosstraat 2 c | B5: 0150 | C5: 4 Homes B.V. | D5: 100151 | E5: A. Ghali | F5: 81 | G5: 0 | H5: 2550
A6: 2e van Leydengaelstraat 6 | B6: 0022 | C6: A. Blaszcak | D6: 50146 | E6: A.H.S. Willemsen | F6: 28 | G6: 150 | H6: 2271.76
A7: Abelenlaan 143 | B7: 0014 | C7: A. Brouwers en S. Brouwers- van Weert | D7: 50405 | E7: A.P.W. Koedooder | F7: 24 | G7: 150 | H7: 1940
A8: Acacia 2 | B8: 0003 | C8: A. Dzaka | D8: 74 | E8: Aannemer Bouwman | F8: 6 | G8: 150 | H8: 2022.35
A9: Acacialaan 9 | B9: 0223 | C9: A. Ghali | D9: 50142 | E9: B. Bakker | F9: 46 | G9: 0 | H9: 2300
A10: Achterdijk 47A | B10: 0190 | C10: A. Verschueren | D10: 72 | E10: B. Bosch | F10: 85 | G10: 500 | H10: 2255
A11: Adriaan Baasstraat 34 | B11: 0007 | C11: A.H.S. Willemsen | D11: 100098 | E11: B. Verstegen & K. Maas | F11: 94 | G11: 250 | H11: 2594.12
A12: Akkerweg 41 [010] | B12: 0341 | C12: A.I.G. Lukkien | D12: 50189 | E12: B. van Abeelen | F12: 52 | G12: 0 | H12: 0
A13: Akkerweg 41 [011] | B13: 0372 | C13: A.P.W. Koedooder | D13: 86 | E13: Bart Vlastuin | F13: 45 | G13: 350 | H13: 0
... A125: Hendrik Deddenstraat 26 | B125: 0073 | C125: Flowerhill B.V. | D125: 40 | E125: Ziggo | F125: 3 | G125: 0 | H125: 0
A126: Hendriklaan 49 | B126: 0325 | C126: Focuzop-eu | D126: 50448 | G126: 450 | H126: 5500
A127: Herautpad 22 | B127: 0176 | C127: Fryslân Homes | D127: 84 | G127: 0 | H127: 1750
A128: Herenpad 20 A | B128: 0133 | C128: Furniture Lease | D128: 50026 | G128: 0 | H128: 3409.28
A129: Herenpad 20 B | B129: 0134 | C129: G.D. Dijkstra | D129: 50168 | G129: 0 | H129: 2363.07
A130: Hoefslag 8 | B130: 0107 | C130: G.K. Stoel | D130: 100125 | G130: 250 | H130: 2446.35
A131: Hof van zeeland 2 | B131: 0334 | C131: GAP Costruzioni S.r.l. | D131: 100262 | G131: 0 | H131: 0
A132: Hoge Noordweg 27B | B132: 0177 | C132: GMC KOVI Global Metal Construction | D132: 50433 | G132: 0 | H132: 1829.53
A133: Hoge Noordweg 28 | B133: 0178 | C133: GOTI Verhuur B.V. | D133: 7 | G133: 0 | H133: 0
A134: Hogenbanweg 331 | B134: 0031 | C134: GSI B.V. | D134: 50426 | G134: 150 | H134: 1974.12
A135: Hontenissestraat 124 | B135: 0181 | C135: Gap Costruzioni Dutch Branch | D135: 50394 | G135: 250 | H135: 2240.44
A136: Hoofdstraat 110 | B136: 0075 | C136: Gastvrijaanzee.nl | D136: 50439 | G136: 0 | H136: 2342.25
A137: Hooizolder 6 | B137: 0078 | C137: Gemeente Waadhoeke | D137: 50252 | G137: 250 | H137: 2602.5
... A376: Wilgensingel 63 | B376: 0139 | C376: van Heeswijk | D376: 57 | G376: 300 | H376: 0
A377: Wilgenstraat 37 | B377: 0140 | G377: 300 | H377: 3955.8
A378: Wilhelmina Druckerstraat 68 | B378: 0142 | G378: 350 | H378: 2394.3
A379: Wilhelminastraat 8 | B379: 0141 | G379: 300 | H379: 2700
A380: Willem Lodewijkstraat 8 | B380: 0143 | G380: 200 | H380: 2000
A381: Willem de Rijkelaan 134 | B381: 0161 | G381: 0 | H381: 2909.6
A382: Woutersweg 20 | B382: 0186 | G382: 0 | H382: 2394.3
A383: Wouwbaan 230 | B383: 0145 | G383: 0 | H383: 2928.69
A384: Zuidhoek 209D | B384: 0232 | G384: 250 | H384: 2316.23
A385: Zwethkade Zuid 30A | B385: 0376 | G385: 390 | H385: 0
A386: Zwingel 8B | B386: 0371 | G386: 0 | H386: 0
A387: de Genestetstraat 32 | B387: 0169 | G387: 0 | H387: 1700
A388: van Scorelstraat 73 | B388: 0016 | G388: 150 | H388: 2224.71
... A392: van der Werffstraat 240 | B392: 0245 | G392: 0 | H392: 0
