Workbook

Sheet Dashboard
A1: SALES DASHBOARD
A2: Gegenereerd: 21-01-2026 13:52
B4: Totaal Woningen | D4: Actief | F4: Beschikbaar | J4: Status | K4: Aantal | M4: Object | N4: Marge
B5: 514 | D5: 499 | F5: 173 | J5: Beschikbaar | K5: 173 | M5: 0291 - Koperwerf 28... | N5: 41710
B6: Verhuurd | D6: Binnenkort Vrij | F6: Inactief | J6: Verhuurd | K6: 311 | M6: 0474 - Honselaarsdijk 27... | N6: 15163.2
B7: 311 | D7: 15 | F7: 15 | J7: Binnenkort Vrij | K7: 15 | M7: 0325 - Hendriklaan 49... | N7: 6030
B8: Totale Marge/Maand | D8: Gem. Marge/Woning | F8: Jaarlijkse Omzet | J8: Inactief | K8: 15 | M8: 0409 - Noordstraat 26... | N8: 5883.03
B9: € 282.109,53 | D9: € 548,85 | F9: € 3.385.314,36 | M9: 0205 - Kreekrug 1... | N9: 4800
M10: 0383 - Akkerweg 41 [huis 20... | N10: 4515
M11: 0293 - Akkerweg 41 [huis 14... | N11: 3885
J12: Stad | K12: Woningen | M12: 0009 - Galgeweg 48-A... | N12: 3643.5
J13: Rotterdam | K13: 73 | M13: 0404 - Europalaan 50... | N13: 3615.03
J14: Schiedam | K14: 50 | M14: 0139 - Wilgensingel 63 ... | N14: 3457.68
J15: Vlaardingen | K15: 39
J16: VLAARDINGEN | K16: 21
J17: Hensbroek | K17: 17
J18: Maassluis | K18: 13
J19: Rozenburg | K19: 12
J20: Hoogvliet | K20: 11
J21: Den Oever | K21: 11
J22: Delft | K22: 11

Sheet Zoek Woning
A1: WONING OPZOEKEN
A3: Selecteer Object ID: | B3: 3
A5: WONING INFORMATIE | D5: EIGENAAR
A6: Object ID: | B6: =IFERROR(VLOOKUP($B$3,Data!$A:$CS,1,FALSE),"") | D6: Naam: | E6: =IFERROR(VLOOKUP($B$3,Data!$A:$CS,24,FALSE),"")
A7: Adres: | B7: =IFERROR(VLOOKUP($B$3,Data!$A:$CS,3,FALSE),"") | D7: Email: | E7: =IFERROR(VLOOKUP($B$3,Data!$A:$CS,27,FALSE),"")
A8: Postcode: | B8: =IFERROR(VLOOKUP($B$3,Data!$A:$CS,4,FALSE),"") | D8: Telefoon: | E8: =IFERROR(VLOOKUP($B$3,Data!$A:$CS,28,FALSE),"")
A9: Plaats: | B9: =IFERROR(VLOOKUP($B$3,Data!$A:$CS,5,FALSE),"") | D9: Adres: | E9: =IFERROR(VLOOKUP($B$3,Data!$A:$CS,29,FALSE),"")
A10: Type: | B10: =IFERROR(VLOOKUP($B$3,Data!$A:$CS,6,FALSE),"") | D10: IBAN: | E10: =IFERROR(VLOOKUP($B$3,Data!$A:$CS,35,FALSE),"")
A11: Oppervlakte: | B11: =IFERROR(VLOOKUP($B$3,Data!$A:$CS,7,FALSE),"")
A12: Slaapkamers: | B12: =IFERROR(VLOOKUP($B$3,Data!$A:$CS,8,FALSE),"") | D12: HUURDER
A13: Capaciteit: | B13: =IFERROR(VLOOKUP($B$3,Data!$A:$CS,9,FALSE),"") | D13: Naam: | E13: =IFERROR(VLOOKUP($B$3,Data!$A:$CS,56,FALSE),"")
A14: Status: | B14: =IFERROR(VLOOKUP($B$3,Data!$A:$CS,96,FALSE),"") | D14: Email: | E14: =IFERROR(VLOOKUP($B$3,Data!$A:$CS,59,FALSE),"")
A15: Dagen tot beschikbaar: | B15: =IFERROR(VLOOKUP($B$3,Data!$A:$CS,97,FALSE),"") | D15: Telefoon: | E15: =IFERROR(VLOOKUP($B$3,Data!$A:$CS,60,FALSE),"")
D16: Type: | E16: =IFERROR(VLOOKUP($B$3,Data!$A:$CS,57,FALSE),"")
A17: INHUUR CONTRACT | D17: VERHUUR CONTRACT
A18: Start: | B18: =IFERROR(VLOOKUP($B$3,Data!$A:$CS,37,FALSE),"") | D18: Start: | E18: =IFERROR(VLOOKUP($B$3,Data!$A:$CS,70,FALSE),"")
A19: Eind: | B19: =IFERROR(VLOOKUP($B$3,Data!$A:$CS,38,FALSE),"") | D19: Eind: | E19: =IFERROR(VLOOKUP($B$3,Data!$A:$CS,71,FALSE),"")
A20: Bedrag excl: | B20: =IFERROR(VLOOKUP($B$3,Data!$A:$CS,47,FALSE),"") | D20: Bedrag excl: | E20: =IFERROR(VLOOKUP($B$3,Data!$A:$CS,76,FALSE),"")
A21: Borg: | B21: =IFERROR(VLOOKUP($B$3,Data!$A:$CS,50,FALSE),"") | D21: Borg: | E21: =IFERROR(VLOOKUP($B$3,Data!$A:$CS,82,FALSE),"")
A23: MARGE ANALYSE
A24: Marge/maand: | B24: =IFERROR(VLOOKUP($B$3,Data!$A:$CS,93,FALSE),"")
A25: Marge/jaar: | B25: =IFERROR(VLOOKUP($B$3,Data!$A:$CS,94,FALSE),"")
A26: Marge %: | B26: =IFERROR(VLOOKUP($B$3,Data!$A:$CS,95,FALSE),"")
A28: DOCUMENTEN & LINKS
A29: Woning Folder: | B29: =IFERROR(VLOOKUP($B$3,Data!$A:$CS,16,FALSE),"")
A30: Inhuur Docs: | B30: =IFERROR(VLOOKUP($B$3,Data!$A:$CS,17,FALSE),"")
A31: Verhuur Docs: | B31: =IFERROR(VLOOKUP($B$3,Data!$A:$CS,18,FALSE),"")
A32: Overeenkomsten: | B32: =IFERROR(VLOOKUP($B$3,Data!$A:$CS,19,FALSE),"")
A33: Contract Link: | B33: =IFERROR(VLOOKUP($B$3,Data!$A:$CS,44,FALSE),"")

Sheet Print Kaart
A1: WONING INFORMATIEKAART
A3: Object: | B3: ='Zoek Woning'!B6 | D3: Status: | E3: ='Zoek Woning'!B14
A4: Adres: | B4: ='Zoek Woning'!B7
A7: WONING SPECIFICATIES
A8: Postcode: | B8: ='Zoek Woning'!B8 | C8: Plaats: | D8: ='Zoek Woning'!B9
A9: Type: | B9: ='Zoek Woning'!B10 | C9: Opp. (m²): | D9: ='Zoek Woning'!B11
A10: Slaapkamers: | B10: ='Zoek Woning'!B12 | C10: Capaciteit: | D10: ='Zoek Woning'!B13
A12: EIGENAAR
A13: Naam: | B13: ='Zoek Woning'!E6
A14: Email: | B14: ='Zoek Woning'!E7
A15: Telefoon: | B15: ='Zoek Woning'!E8
A17: HUIDIGE HUURDER
A18: Naam: | B18: ='Zoek Woning'!E13
A19: Email: | B19: s
A20: Telefoon: | B20: ='Zoek Woning'!E15
A22: FINANCIEEL OVERZICHT
A23: Inhuur/maand: | B23: ='Zoek Woning'!B20 | C23: Verhuur/maand: | D23: ='Zoek Woning'!E20
A24: Marge/maand: | B24: ='Zoek Woning'!B24 | C24: Marge/jaar: | D24: ='Zoek Woning'!B25
A25: Marge %: | B25: ='Zoek Woning'!B26
A27: CONTRACT DETAILS
A28: Inhuur start: | B28: ='Zoek Woning'!B18 | C28: Inhuur eind: | D28: ='Zoek Woning'!B19
A29: Verhuur start: | B29: ='Zoek Woning'!E18 | C29: Verhuur eind: | D29: ='Zoek Woning'!E19
A31: DOCUMENTEN
A32: Woning Folder: | B32: ='Zoek Woning'!B29
A33: Inhuur Docs: | B33: ='Zoek Woning'!B30
A34: Verhuur Docs: | B34: ='Zoek Woning'!B31
A36: Gegenereerd: 21-01-2026

Sheet Contacten
A1: CONTACTEN OVERZICHT
A3: EIGENAREN
A4: ID | B4: Naam | C4: Email | D4: Telefoon | E4: Adres | F4: Postcode | G4: Plaats | H4: Woningen
A5: 763 | B5: T. Eenhuistra/J. Pluimakers | H5: 3
A6: 326 | B6: S. Kleiren | C6: sabine.kleiren@gmail.com | H6: 2
A7: 984 | B7: Park Wonen BV | C7: info@parkwonen.nl | D7: 010 — 844 25 52 | E7: Kruisplein 488a | F7: 3012 CC | G7: Rotterdam | H7: 3
A8: 850 | B8: M. Kathiravelu | H8: 1
A9: 644 | B9: J.G. van Pieterson | E9: C.G. Roosweg 28 | G9: Schoonhoven | H9: 1
A10: 258 | B10: Parkwonen | C10: info@parkwonen.nl | E10: Kruisplein 488A | G10: Rotterdam | H10: 6
A11: 147 | B11: T. Hoolhorst | C11: t.hoolhorst@gmail.com | E11: Leliestraat 21 | G11: Utrecht | H11: 1
A12: 175 | B12: Dhr. J.L. Meerding | C12: jlmeerding@gmai.com | E12: Mauvezand 6 | G12: Laren NH | H12: 3
A13: 206 | B13: Dhr. T. Roestenberg en Mw. Roestenberg - Hustinx | C13: timoroestenberg@hotmail.com | D13: 06 199 144 13 | E13: De Haarmansenk 7 | G13: Schalkhaar | H13: 1
A14: 111 | B14: Hugo Vastgoed B.V. | C14: administratie@hemobeheer.nl | D14: 2076 515 45 06 | E14: Academiesingel 37 A | G14: BREDA | H14: 1
A15: 802 | B15: Maatschap vd Vlist -Teuben | H15: 1
A16: 806 | B16: Value+ Vastgoedmanagement | H16: 1
A17: 241 | B17: BJ Bakker | C17: bjbakker85@hotmail.com | E17: Spiens 3 | G17: Dokkum | H17: 1
A18: 701 | B18: Fransen Vastgoed / Holland Huisvesting B.V. | C18: info@fransenvastgoed.nl | E18: Lekdreef 2 | G18: Krimpen aan de Lek | H18: 3
A19: 630 | B19: J. van der Linde | H19: 1
A20: 839 | B20: J, van de Linde | H20: 1
A21: 271 | B21: Houses2Rent | C21: info@houses2rent.nl | D21: 06-20877085 | E21: Stellingmolen 42 | G21: Maassluis | H21: 10
A22: 314 | B22: G.K. Stoel | C22: rolfstoel@hotmail.com | D22: 06-14901449 | E22: Patrijsstraat 39 | G22: Papendrecht | H22: 1
A23: 795 | B23: J.P. Stoel | C23: Jpstoel@gma | D23: 06 408 960 47 | H23: 4
A24: 295 | B24: In Stijl Totaalbouw BV | C24: info@instijltotaalbouw.nl | D24: 06-44404678 | E24: Burgemeester Freijterslaan 1 | G24: Roosendaal | H24: 4
A25: 302 | B25: A.H.S. Willemsen | C25: huurwoningarnhem@gmail.com | H25: 1
A26: 823 | B26: City Estate (Reinier Derksen) | H26: 2
A27: 60 | B27: M. Poel | C27: monique_pruijsen@hotmail.com | D27: 20650128055 | E27: Esdoornlaan 64 | G27: ROZENBURG | H27: 1
A28: 824 | B28: Vivir wonen (Mendy) | H28: 1
A29: 792 | B29: H. Samson | H29: 1
A30: 783 | B30: Johan ven der Burg | H30: 3
A31: 7 | B31: Maatschap J.W. Meershoek & W.M. Meershoek | C31: j.meershoek1@chello.nl | E31: Grootzand 11 | G31: HOEK VAN HOLLAND | H31: 1
A32: 115 | B32: A. Ghali | E32: Rooseveltlaan 956 | G32: Utrecht | H32: 1
A33: 291 | B33: Johan van der Burg | C33: johanvanderburg87@gmail.com | H33: 2
A34: 836 | B34: Sjoerd Dolstra | H34: 1
A35: 602 | B35: Westhavendomein BV | C35: vastgoed@westhavendomein.nl | D35: 010-2477477 | H35: 3
A36: 803 | B36: M&M Hendriks | H36: 1
A37: 164 | B37: Dhr. R. Bekken | C37: renzo.bekken@gmail.com | D37: 206 24524308 | E37: Roemer Visscherlaan 57 | G37: Zeist | H37: 1
A38: 135 | B38: B. Bosch | C38: brucebosch@live.nl | E38: Stuartweg 29 | G38: Vianen | H38: 1
A39: 848 | B39: R. Bouius | C39: bouius@hotmail.com | D39: 06-13658480 | H39: 1
A40: 211 | B40: Homescout21 B.V. | C40: rene@homescout21.com | E40: Keizerstraat 28 1 | G40: 'S-GRAVENHAGE | H40: 10
A41: 542 | B41: Hopmans Flexstay | H41: 1
A42: 989 | B42: Nikozijn B.V. | D42: 06-53208852 | H42: 1
A43: 838 | B43: A. Brouwers & S. Brouwers- van Weert | H43: 1
A44: 840 | B44: Groen Holding / van Vliet | H44: 1
A45: 997 | B45: Prominent Groeneweg I OG BV | H45: 1
A46: 590 | B46: Digo Real Estate BV | C46: info@digorealestate.com | D46: +31 6 22 82 66 20 | H46: 1
A47: 17 | B47: Tradiro Services B.V. | C47: facturen@tradiro.nl | D47: null | E47: Honderdland 960 | F47: 2678 PS | G47: Maasdijk | H47: 5
A48: 970 | B48: Soul Inn B.B. B.V. | C48: service@hb-vb.nl | D48: 070-3615080 | E48: Dr. Lelykade 249 | F48: 2583 JZ | G48: Den Haag | H48: 1
A49: 983 | B49: Greenroads Beheer B.V. | E49: Kaapsebos 13 | F49: 2676 BX | G49: Maasdijk | H49: 1
A50: 979 | B50: Gebr van der Voort v.o.f. | E50: van Rijckevorsellaan 6 | G50: 's-Gravenzande | H50: 1
A51: 969 | B51: JES Funding en Beheer B.V. | C51: verhuur@jesbeheer.com | D51: 06-54615625 | E51: Koninginneweg 13 | F51: 1217 KP | G51: Hilversum | H51: 3
A52: 53 | B52: Business Housing | C52: eliane@zamens.nl | E52: Oosteinde 26 | G52: Oud Alblas | H52: 1
A53: 656 | B53: Uitzendburo Tradiro B.V. | H53: 1
A54: 993 | B54: Tradiro Housing BV | E54: James Wattweg 20 | F54: 3133 KK | G54: Vlaardingen | H54: 1
A55: 982 | B55: R.R. Kalmeijer en M.R. Klootwijk | E55: Laan van Magisch Realisme 5 | F55: 3059 VJ | G55: Rotterdam | H55: 1
A56: 300 | B56: JES Funding & Beheer B.V. | C56: info@jesbeheer.com | D56: 06-27270429 | H56: 1
A57: 311 | B57: P. Nederstigt | C57: p.nederstigt@casema.nl | E57: Frans Halsstraat 67 | G57: Lisse | H57: 4
A58: 954 | B58: De Rembrandt B.V. | C58: flip@eetcafedewitte.nl | D58: 06-41372342 | H58: 1
A59: 771 | B59: K. Zuidgeest | H59: 1
A60: 955 | B60: G. Hofland | C60: goos@hoflandfloweringplants.nl | D60: 0174-625887 | H60: 1
A61: 952 | B61: M. Nottet | C61: mnottet@caiway.nl | D61: 06-50502637 | H61: 4
A62: 957 | B62: H. van Leeuwen | C62: petra@huubvanleeuwen.nl | D62: 06-51262904 / 0174-248804 | H62: 1
A63: 759 | B63: J.S. Vink Vastgoed | H63: 1
A64: 956 | B64: M.J.W. van den Enden & B.M. van den Enden | C64: endem3@caiway.nl | D64: 06-51611737 Barbara / 06-54398790 Maup | H64: 2
A65: 786 | B65: T. Olsthoorn | H65: 1
A66: 766 | B66: C. van Driel e/o B.M. Verdouw | C66: drielviist@gmail.com / bmverdouw@gmail.com | D66: 06 53141599 | H66: 8
A67: 726 | B67: Cris | H67: 7
A68: 849 | B68: Chalet Park Holiday | H68: 14
A69: 821 | B69: R. Paalman | H69: 1
A70: 837 | B70: E. Beukema | C70: et.beukema@gmail.com | D70: 06 31077111 | H70: 1
A71: 85 | B71: 4 Homes B.V. | C71: factuur@4homes.nl | D71: 0167 - 745023 | E71: Prins Reinierstraat 18a | G71: Steenbergen | H71: 2
A72: 805 | B72: TH Mungroop | H72: 1
A73: 253 | B73: Facili Flex BV | C73: invoice@ifj.nl | D73: 0297-389680 | E73: Legmeerdijk 313 | G73: Aalsmeer | H73: 2
A74: 854 | B74: C.R. Valk & H.J. Valk | H74: 1
A75: 990 | B75: Comé Valk en Arjen Valk | H75: 1
A76: 681 | B76: Edward Bosch | H76: 1
A77: 816 | B77: Dockholland | H77: 6
A78: 121 | B78: CB-Homes B.V. | C78: info@cb-homes.nl | E78: Langeweg 3 a | G78: OOSTVOORNE | H78: 1
A79: 359 | B79: Kwekerij Stef Kleijweg | C79: Stefkleijweg@gmail.com | E79: Woudselaan 14 | G79: Den Hoorn ZH | H79: 1
A80: 683 | B80: Tetering en Martens | H80: 1
A81: 799 | B81: Z. Yilmaz | C81: zyilmaz@yilmazradijs.nt | D81: 50619418327 | H81: 2
A82: 958 | B82: P.C. Vijverberg | C82: piet@pietvijverberg.nl | D82: 06-53299575 | H82: 1
A83: 172 | B83: Flexvesting B.V. | C83: administratie@flexvesting.com | D83: 033 303 59 40 | E83: Wiekenweg 50b | G83: Amersfoort | H83: 1
A84: 832 | B84: R. Basil | H84: 1
A85: 84 | B85: Orange Investments Group | H85: 1
A86: 751 | B86: Orange Invesments Group | H86: 2
A87: 375 | B87: B. van Abeelen | C87: vanabeelenstucadoorsbedrijf@gmail.com | E87: Blauwloop 2 | G87: Loon op Zand | H87: 1
A88: 145 | B88: dockHolland Huisvesting B.V. | C88: inkoopfacturen@dockholland.com | E88: Industrieweg 130A | G88: Rotterdam | H88: 3
A89: 971 | B89: JS Vastgoed | E89: Achterom 117 | F89: 2991 AC | G89: Barendrecht | H89: 1
A92: HUURDERS
A93: ID | B93: Naam | C93: Type | D93: Email | E93: Telefoon | F93: Adres | G93: Postcode | H93: Plaats
A94: 17 | B94: Tradiro Services B.V. | C94: particulier | D94: facturen@tradiro.nl | E94: null | F94: Honderdland 960 | G94: 2678 PS | H94: Maasdijk
A95: 237 | B95: AKT Autoschade | C95: particulier | D95: facturen@aktautoschade.com | E95: 06 33417286 | F95: Goirkekanaaldijk 211-18 | H95: Tilburg
A96: 353 | B96: Optima Uitzendbureau B.V. | C96: particulier | D96: Financieel@optimauitzendburo.nl | E96: 0184 675 489 | F96: Kade 40 | H96: Hardinxveld Giessendam
A97: 154 | B97: InAxtion Vastgoed B.V. | C97: particulier | D97: Invoice.vastgoed@inaxtion.com | E97: 06 43 36 18 85 | F97: Wijnstraat 123 | H97: Dordrecht
A98: 236 | B98: NL Realty B.V. | C98: particulier | D98: administratie@nl-jobs.com | E98: 06 22 040 775 | F98: Honderdland 1 | H98: MAASDIJK
A99: 329 | B99: RNDV Industries | C99: particulier | D99: laura.brackiene@rndv.eu | E99: +37062054093 | F99: Taikos pr. 52C | H99: Klipeda
A100: 220 | B100: Impes Service S.p.A. | C100: particulier | D100: fatture.olanda@impesservice.it, Nicola.pisani@impesservice.it | E100: +31 6 87020773 | F100: President Kennedylaan 19 | H100: 's-Gravenhage
A101: 330 | B101: UAB Techsome | C101: particulier | D101: info@techsoma.lt | F101: Šėtos g. 116-311 | H101: Kėdainiai
A102: 286 | B102: Team Unica B.V. | C102: particulier | D102: facturen@teamunica.nl | E102: 206 142 186 41 | F102: Langeweg 15B | H102: Oostvoorne
A103: 312 | B103: Welcome Housing B.V. | C103: particulier | D103: Invoices@hobij.nl | E103: 0413-870000 | F103: Heilig Hartplein 1 | H103: Veghel
...

Sheet Tijdlijn
A1: CONTRACT TIJDLIJN
A3: Object | B3: Adres | C3: Huurder | D3: Start | E3: Eind | F3: Status | G3: Dagen Resterend
A4: 0332 | B4: Kerkweg 9a [huis 340] | C4: Orange Investments Group | D4: 2025-01-24 | E4: 2026-01-24 | F4: Actief | G4: 2
A5: 0329 | B5: Noordmolenstraat 36B | C5: BBTS (Vastgoed Spijkenisse) | D5: 2025-02-01 | E5: 2026-02-01 | F5: Actief | G5: 10
A6: 0328 | B6: Noordmolenstraat 36A | C6: BBTS (Vastgoed Spijkenisse) | D6: 2025-02-01 | E6: 2026-02-01 | F6: Actief | G6: 10
A7: 0333 | B7: Kethelweg 66D | C7: Tradiro Services B.V. | D7: 2025-02-01 | E7: 2026-02-01 | F7: Actief | G7: 10
A8: 0330 | B8: Noordmolenstraat 36C | C8: BBTS (Vastgoed Spijkenisse) | D8: 2025-02-01 | E8: 2026-02-01 | F8: Actief | G8: 10
A9: 0323 | B9: Marnixstraat 32 | C9: Flexvesting B.V. | D9: 2025-02-01 | E9: 2026-02-01 | F9: Actief | G9: 10
A10: 0340 | B10: Professor Poelslaan 58C | C10: Tradiro Services B.V. | D10: 2025-02-15 | E10: 2026-02-15 | F10: Actief | G10: 24
A11: 0340 | B11: Professor Poelslaan 58C | C11: Tradiro Services B.V. | D11: 2025-02-15 | E11: 2026-02-15 | F11: Actief | G11: 24
A12: 0337 | B12: Kruisweg 16 | C12: Tradiro Services B.V. | D12: 2025-02-25 | E12: 2026-02-25 | F12: Actief | G12: 34
A13: 0324 | B13: Van Swinderenstraat 21 | C13: Flexvesting B.V. | D13: 2025-03-01 | E13: 2026-02-28 | F13: Actief | G13: 37
A14: 0136 | B14: Elisadonk 220 | C14: EG Facility & Services BV | D14: 2024-03-01 | E14: 2026-02-28 | F14: Actief | G14: 37
A15: 0117 | B15: Prunuslaan 36 | C15: Workforce Housing International B.V | D15: 2021-05-03 | E15: 2026-02-28 | F15: Actief | G15: 37
... A109: 0258 | B109: Middenbaan Noord 22B | C109: BBTS (Vastgoed Spijkenisse) | D109: 2023-05-01 | E109: 2028-04-30 | F109: Actief | G109: 829
A110: 0158 | B110: Visartstraat 31 | C110: BBTS (Vastgoed Spijkenisse) | D110: 23-12-01 | E110: 24-11-30 | F110: Actief
A111: 0167 | B111: Vogelschorstraat 24 | C111: BBTS (Vastgoed Spijkenisse) | D111: 24-01-01 | E111: 29-12-31 | F111: Actief
A112: 0001 | B112: Nunspeetlaan 14 | C112: Tradiro Services B.V. | D112: 2026-01-14 | F112: Onbepaalde tijd | G112: 0
A113: 0002 | B113: Allard Piersonlaan 142 | C113: Tradiro Services B.V. | D113: 2026-01-14 | F113: Onbepaalde tijd | G113: 0
A114: 0009 | B114: Galgeweg 48-A | C114: Tradiro Services B.V. | D114: 2026-01-14 | F114: Onbepaalde tijd | G114: 0
A115: 0010 | B115: Kethelweg 1B | C115: Tradiro Services B.V. | D115: 2023-02-01 | F115: Onbepaalde tijd | G115: 0
A116: 0011 | B116: Kethelweg 1C | C116: Tradiro Services B.V. | D116: 2023-02-01 | F116: Onbepaalde tijd | G116: 0
A117: 0015 | B117: Maasdijk 69 | C117: Tradiro Services B.V. | D117: 2026-01-14 | F117: Onbepaalde tijd | G117: 0
A118: 0020 | B118: Mr. Troelstrastraat 37 | C118: Tradiro Services B.V. | D118: 2023-02-01 | F118: Onbepaalde tijd | G118: 0
A119: 0021 | B119: Vaartweg 106C | C119: Tradiro Services B.V. | D119: 2023-02-01 | F119: Onbepaalde tijd | G119: 0
A120: 0025 | B120: Groenelaan 30B | C120: Tradiro Services B.V. | D120: 2023-02-01 | F120: Onbepaalde tijd | G120: 0
A121: 0027 | B121: Buizerdstraat 210 | C121: Tradiro Services B.V. | D121: 2023-03-01 | F121: Onbepaalde tijd | G121: 0
A122: 0028 | B122: Lange kruisweg 12 | C122: Tradiro Services B.V. | D122: 2023-03-01 | F122: Onbepaalde tijd | G122: 0
A123: 0030 | B123: Curacaolaan 88 | C123: Tradiro Services B.V. | D123: 2026-01-14 | F123: Onbepaalde tijd | G123: 0
... A331: 0489 | B331: Woudseweg 146 | C331: Tradiro Services B.V. | D331: 2025-01-01 | F331: Onbepaalde tijd | G331: 0
A334: LEGENDA:
A335: < 30 dagen
A336: 30-60 dagen

Sheet Financieel
A1: FINANCIEEL OVERZICHT
A3: TOTALEN
A4: Totale Inhuur/maand: | B4: 405275.17 | C4: Jaarlijks: | D4: 4863302
A5: Totale Verhuur/maand: | B5: 687384.7 | D5: 8248616.4
A6: Totale Marge/maand: | B6: 282109.53 | D6: 3385314.4
A9: MARGE PER WONING
A10: Object | B10: Adres | C10: Inhuur | D10: Verhuur | E10: Marge/Maand | F10: Marge/Jaar | G10: Marge % | H10: Status
A11: 0291 | B11: Koperwerf 28 | D11: 41710 | E11: 41710 | F11: 500520 | H11: Verhuurd (onbepaald)
A12: 0474 | B12: Honselaarsdijk 27 | D12: 15163.2 | E12: 15163.2 | F12: 181958.4 | H12: Verhuurd (onbepaald)
A13: 0325 | B13: Hendriklaan 49 | D13: 6030 | E13: 6030 | F13: 72360 | H13: Beschikbaar
A14: 0409 | B14: Noordstraat 26 | D14: 5883.03 | E14: 5883.03 | F14: 70596.36 | H14: Verhuurd (onbepaald)
A15: 0205 | B15: Kreekrug 1 | D15: 4800 | E15: 4800 | F15: 57600 | H15: Verhuurd (onbepaald)
A16: 0383 | B16: Akkerweg 41 [huis 20] | D16: 4515 | E16: 4515 | F16: 54180 | H16: Inactief
A17: 0293 | B17: Akkerweg 41 [huis 14] | D17: 3885 | E17: 3885 | F17: 46620 | H17: Inactief
A18: 0009 | B18: Galgeweg 48-A | D18: 3643.5 | E18: 3643.5 | F18: 43722 | H18: Verhuurd (onbepaald)
A19: 0404 | B19: Europalaan 50 | D19: 3615.03 | E19: 3615.03 | F19: 43380.36 | H19: Verhuurd (onbepaald)
A20: 0139 | B20: Wilgensingel 63 | D20: 3457.68 | E20: 3457.68 | F20: 41492.16 | H20: Verhuurd (onbepaald)
A21: 0015 | B21: Maasdijk 69 | D21: 3400 | E21: 3400 | F21: 40800 | H21: Verhuurd (onbepaald)
A22: 0412 | B22: Hontenissestraat 162 | D22: 3347.25 | E22: 3347.25 | F22: 40167 | H22: Verhuurd (onbepaald)
... A59: 0156 | B59: Broersvest 74 c | D59: 2051.51 | E59: 2051.51 | F59: 24618.12 | H59: Verhuurd (onbepaald)
A60: 0067 | B60: Franz Liszstraat 5 | C60: 1665.6 | D60: 3643.5 | E60: 1977.9 | F60: 23734.8 | G60: 118.75 | H60: Verhuurd
A61: 0364 | B61: Rietdijkstraat 56B | D61: 1950 | E61: 1950 | F61: 23400 | H61: Verhuurd (onbepaald)
A62: 0279 | B62: Haagkamp 11 | D62: 1950 | E62: 1950 | F62: 23400 | H62: Verhuurd (onbepaald)
A63: 0174 | B63: Groeneweg 74 | D63: 1916 | E63: 1916 | F63: 22992 | H63: Verhuurd (onbepaald)
A64: 0005 | B64: Ringbaan Oost 327 | C64: 4300 | D64: 6210.93 | E64: 1910.93 | F64: 22931.16 | G64: 44.44 | H64: Verhuurd
A65: 0387 | B65: Verschansing 21 | C65: 2470 | D65: 4350 | E65: 1880 | F65: 22560 | G65: 76.11 | H65: Verhuurd
A66: 0210 | B66: Lorentzstraat 73 | D66: 1865.5 | E66: 1865.5 | F66: 22386 | H66: Verhuurd (onbepaald)
A67: 0173 | B67: Groeneweg 71 | D67: 1850 | E67: 1850 | F67: 22200 | H67: Verhuurd (onbepaald)
A68: 0021 | B68: Vaartweg 106C | D68: 1830.43 | E68: 1830.43 | F68: 21965.16 | H68: Verhuurd (onbepaald)
A69: 0002 | B69: Allard Piersonlaan 142 | D69: 1829.53 | E69: 1829.53 | F69: 21954.36 | H69: Verhuurd (onbepaald)
A70: 0001 | B70: Nunspeetlaan 14 | D70: 1829.53 | E70: 1829.53 | F70: 21954.36 | H70: Verhuurd (onbepaald)
A71: 0377 | B71: Rijpstraat 24 | D71: 1733.33 | E71: 1733.33 | F71: 20799.96 | H71: Verhuurd (onbepaald)
A72: 0020 | B72: Mr. Troelstrastraat 37 | D72: 1723.44 | E72: 1723.44 | F72: 20681.28 | H72: Verhuurd (onbepaald)
A73: 0057 | B73: Markt 5 | D73: 1715.6 | E73: 1715.6 | F73: 20587.2 | H73: Verhuurd (onbepaald)
A74: 0010 | B74: Kethelweg 1B | D74: 1708.41 | E74: 1708.41 | F74: 20500.92 | H74: Verhuurd (onbepaald)
A75: 0011 | B75: Kethelweg 1C | D75: 1708.41 | E75: 1708.41 | F75: 20500.92 | H75: Verhuurd (onbepaald)
A76: 0375 | B76: Cubalaan 25 | C76: 3600 | D76: 5300 | E76: 1700 | F76: 20400 | G76: 47.22 | H76: Verhuurd
A77: 0027 | B77: Buizerdstraat 210 | D77: 1677.89 | E77: 1677.89 | F77: 20134.68 | H77: Verhuurd (onbepaald)
A78: 0199 | B78: Kerstendijk 125 | C78: 1200 | D78: 2841.93 | E78: 1641.93 | F78: 19703.16 | G78: 136.83 | H78: Verhuurd (onbepaald)
A79: 0438 | B79: Franselaan 273-B | D79: 1641.12 | E79: 1641.12 | F79: 19693.44 | H79: Verhuurd (onbepaald)
A80: 0403 | B80: Hontenissestraat 124A | D80: 1574 | E80: 1574 | F80: 18888 | H80: Verhuurd (onbepaald)
A81: 0111 | B81: Oosterstraat 89 | D81: 1569.3 | E81: 1569.3 | F81: 18831.6 | H81: Verhuurd (onbepaald)
A82: 0216 | B82: Mendelssohnplein 46a | D82: 1561.5 | E82: 1561.5 | F82: 18738 | H82: Verhuurd (onbepaald)
A83: 0416 | B83: Jacob van Ruijsdaelstraat 28 | D83: 1560 | E83: 1560 | F83: 18720 | H83: Verhuurd (onbepaald)
A84: 0371 | B84: De Zwingel 8B | C84: 11526.66 | D84: 13043.23 | E84: 1516.57 | F84: 18198.84 | G84: 13.16 | H84: Verhuurd
A85: 0291 | B85: Koperwerf 28 | D85: 1500 | E85: 1500 | F85: 18000 | H85: Verhuurd (onbepaald)
A86: 0361 | B86: Putsebocht 136 B01 | D86: 1494.99 | E86: 1494.99 | F86: 17939.88 | H86: Verhuurd (onbepaald)
A87: 0333 | B87: Kethelweg 66D | C87: 1000 | D87: 2491.65 | E87: 1491.65 | F87: 17899.8 | G87: 149.17 | H87: Binnenkort beschikbaar
A88: 0114 | B88: Piersonstraat 8 | C88: 1191.08 | D88: 2650 | E88: 1458.92 | F88: 17507.04 | G88: 122.49 | H88: Verhuurd
A89: 0175 | B89: Hagastraat 8 | D89: 1451.23 | E89: 1451.23 | F89: 17414.76 | H89: Verhuurd (onbepaald)
A90: 0276 | B90: Burgemeester Cramerlaan 82 | D90: 1450 | E90: 1450 | F90: 17400 | H90: Verhuurd (onbepaald)
A91: 0025 | B91: Groenelaan 30B | D91: 1430 | E91: 1430 | F91: 17160 | H91: Verhuurd (onbepaald)
A92: 0467 | B92: St. Annalandstraat 116 | D92: 1415 | E92: 1415 | F92: 16980 | H92: Verhuurd (onbepaald)
A93: 0437 | B93: Dorpstraat 27 | D93: 1409.4 | E93: 1409.4 | F93: 16912.8 | H93: Verhuurd (onbepaald)
A94: 0196 | B94: Keesomstraat 54 | D94: 1405 | E94: 1405 | F94: 16860 | H94: Verhuurd (onbepaald)
A95: 0229 | B95: Parallelweg 98B | D95: 1397 | E95: 1397 | F95: 16764 | H95: Verhuurd (onbepaald)
A96: 0097 | B96: Burchstraat 16A | C96: 2607.5 | D96: 4000 | E96: 1392.5 | F96: 16710 | G96: 53.4 | H96: Verhuurd
A97: 0184 | B97: Mathenesserdijk 261 C03 | C97: 1545.73 | D97: 2932.63 | E97: 1386.9 | F97: 16642.8 | G97: 89.72 | H97: Verhuurd (onbepaald)
A98: 0280 | B98: Bovendijk 59 | D98: 1375 | E98: 1375 | F98: 16500 | H98: Verhuurd (onbepaald)
A99: 0109 | B99: Geldersestraat 91 | C99: 3500 | D99: 4872.2 | E99: 1372.2 | F99: 16466.4 | G99: 39.21 | H99: Verhuurd
A100: 0237 | B100: Schere 238 | D100: 1345.37 | E100: 1345.37 | F100: 16144.44 | H100: Verhuurd (onbepaald)
A101: 0299 | B101: Akkerweg 41 [huis 37] | C101: 3770.05 | D101: 5110.36 | E101: 1340.31 | F101: 16083.72 | G101: 35.55 | H101: Verhuurd
A102: 0363 | B102: Rietdijkstraat 56A | D102: 1300 | E102: 1300 | F102: 15600 | H102: Verhuurd (onbepaald)
A103: 0376 | B103: Zwethkade Zuid 30A | C103: 2600 | D103: 3890 | E103: 1290 | F103: 15480 | G103: 49.62 | H103: Verhuurd
A104: 0180 | B104: Liesveld 100 | D104: 1270.97 | E104: 1270.97 | F104: 15251.64 | H104: Inactief
A105: 0077 | B105: Voorstraat 10 | C105: 2622.95 | D105: 3868.8 | E105: 1245.85 | F105: 14950.2 | G105: 47.5 | H105: Verhuurd
A106: 0076 | B106: Molendijk 4 | C106: 2622.95 | D106: 3868.79 | E106: 1245.84 | F106: 14950.08 | G106: 47.5 | H106: Verhuurd
A107: 0254 | B107: Middenbaan Noord 20A | C107: 1927.44 | D107: 3159.6 | E107: 1232.16 | F107: 14785.92 | G107: 63.93 | H107: Verhuurd
A108: 0255 | B108: Middenbaan Noord 20B | C108: 1927.44 | D108: 3159.6 | E108: 1232.16 | F108: 14785.92 | G108: 63.93 | H108: Verhuurd
A109: 0256 | B109: Middenbaan Noord 20C | C109: 1927.44 | D109: 3159.6 | E109: 1232.16 | F109: 14785.92 | G109: 63.93 | H109: Verhuurd
A110: 0119 | B110: Koningin Julianastraat 27 | C110: 2500 | D110: 3709.28 | E110: 1209.28 | F110: 14511.36 | G110: 48.37 | H110: Verhuurd
A111: 0246 | B111: Socratesstraat 168 | D111: 1200 | E111: 1200 | F111: 14400 | H111: Verhuurd (onbepaald)
A112: 0144 | B112: Scheepjesbrug 433 | C112: 3000 | D112: 4200 | E112: 1200 | F112: 14400 | G112: 40 | H112: Binnenkort beschikbaar
A113: 0231 | B113: Platostraat 80 | D113: 1200 | E113: 1200 | F113: 14400 | H113: Verhuurd (onbepaald)
A114: 0386 | B114: Poolsestraat 29a | C114: 2060 | D114: 3250 | E114: 1190 | F114: 14280 | G114: 57.77 | H114: Verhuurd
A115: 0389 | B115: Kritostraat 54 | C115: 1365 | D115: 2550 | E115: 1185 | F115: 14220 | G115: 86.81 | H115: Verhuurd
A116: 0249 | B116: Tholenstraat 114 | C116: 1175 | D116: 2350 | E116: 1175 | F116: 14100 | G116: 100 | H116: Verhuurd (onbepaald)
A117: 0039 | B117: Inundatiestraat 3 | C117: 1500 | D117: 2625 | E117: 1125 | F117: 13500 | G117: 75 | H117: Verhuurd
A118: 0080 | B118: Voorstraat 25 | C118: 1300 | D118: 2420 | E118: 1120 | F118: 13440 | G118: 86.15 | H118: Verhuurd (onbepaald)
A119: 0120 | B119: Plaats 10 | C119: 2000 | D119: 3100 | E119: 1100 | F119: 13200 | G119: 55 | H119: Verhuurd
A120: 0120 | B120: Plaats 10 | C120: 2000 | D120: 3100 | E120: 1100 | F120: 13200 | G120: 55 | H120: Verhuurd (onbepaald)
A121: 0118 | B121: Marathonlaan 26 | C121: 2500 | D121: 3600 | E121: 1100 | F121: 13200 | G121: 44 | H121: Verhuurd
A122: 0095 | B122: Engelsestraat 16L3 | C122: 894 | D122: 1993.32 | E122: 1099.32 | F122: 13191.84 | G122: 122.97 | H122: Verhuurd (onbepaald)
A123: 0337 | B123: Kruisweg 16 | C123: 4330 | D123: 5350 | E123: 1020 | F123: 12240 | G123: 23.56 | H123: Binnenkort beschikbaar
A124: 0292 | B124: Burgemeester Stulemeijerlaan 71 | D124: 1019 | E124: 1019 | F124: 12228 | H124: Verhuurd (onbepaald)
A125: 0179 | B125: Rooseveltlaan 185 | C125: 2790.5 | D125: 3800 | E125: 1009.5 | F125: 12114 | G125: 36.18 | H125: Verhuurd
A126: 0294 | B126: Akkerweg 41 [huis 15] | C126: 2903.38 | D126: 3907.77 | E126: 1004.39 | F126: 12052.68 | G126: 34.59 | H126: Verhuurd
A127: 0344 | B127: Pastoor Gilisstraat 81-A | C127: 3000 | D127: 4000 | E127: 1000 | F127: 12000 | G127: 33.33 | H127: Binnenkort beschikbaar
A128: 0321 | B128: Kerkweg 9a [huis 453] | C128: 3181.45 | D128: 4175 | E128: 993.55 | F128: 11922.6 | G128: 31.23 | H128: Verhuurd
A129: 0134 | B129: Herenpad 20 B | D129: 992.34 | E129: 992.34 | F129: 11908.08 | H129: Verhuurd (onbepaald)
A130: 0402 | B130: Broersveld 150B | D130: 990.46 | E130: 990.46 | F130: 11885.52 | H130: Verhuurd (onbepaald)
A131: 0445 | B131: J. van Lennepstraat 13B | D131: 989.88 | E131: 989.88 | F131: 11878.56 | H131: Verhuurd (onbepaald)
A132: 0444 | B132: J. van Lennepstraat 13A | D132: 989.88 | E132: 989.88 | F132: 11878.56 | H132: Verhuurd (onbepaald)
A133: 0232 | B133: Zuidhoek 209D | C133: 1673 | D133: 2650 | E133: 977 | F133: 11724 | G133: 58.4 | H133: Verhuurd
A134: 0232 | B134: Zuidhoek 209D | C134: 1673 | D134: 2650 | E134: 977 | F134: 11724 | G134: 58.4 | H134: Verhuurd (onbepaald)
A135: 0454 | B135: Oostene 23 | D135: 972 | E135: 972 | F135: 11664 | H135: Verhuurd (onbepaald)
A136: 0138 | B136: Westercluft | C136: 2705 | D136: 3675 | E136: 970 | F136: 11640 | G136: 35.86 | H136: Verhuurd
A137: 0249 | B137: Tholenstraat 114 | C137: 1400.53 | D137: 2350 | E137: 949.47 | F137: 11393.64 | G137: 67.79 | H137: Verhuurd (onbepaald)
A138: 0332 | B138: Kerkweg 9a [huis 340] | C138: 2769.81 | D138: 3685 | E138: 915.19 | F138: 10982.28 | G138: 33.04 | H138: Binnenkort beschikbaar
A139: 0449 | B139: Korhaanstraat 6 | D139: 914.99 | E139: 914.99 | F139: 10979.88 | H139: Inactief
...

Sheet Data
A1: object_id | B1: house_id | C1: adres | D1: postcode | E1: plaats | F1: woning_type | G1: oppervlakte_m2 | H1: aantal_slaapkamers | I1: capaciteit_personen | J1: huis_actief | K1: facturatie_type | L1: kluis_code_1 | M1: kluis_code_2 | N1: meterbeheerder | O1: gwe_leverancier | P1: sharepoint_folder | Q1: sharepoint_inhuur | R1: sharepoint_verhuur | S1: sharepoint_inhuur_overeenkomsten | T1: borg_standaard | U1: voorschot_gwe_standaard | V1: voorschot_schoonmaak_standaard | W1: eigenaar_id | X1: eigenaar_naam | Y1: eigenaar_type | Z1: eigenaar_contactpersoon | AA1: eigenaar_email | AB1: eigenaar_telefoon | AC1: eigenaar_adres | AD1: eigenaar_postcode | AE1: eigenaar_plaats | AF1: eigenaar_land | AG1: eigenaar_kvk | AH1: eigenaar_btw | AI1: eigenaar_iban | AJ1: inhuur_contract_id | AK1: inhuur_start | AL1: inhuur_eind | AM1: inhuur_status | AN1: inhuur_min_duur | AO1: inhuur_opzegtermijn | AP1: inhuur_hovk | AQ1: inhuur_rechtsvorm | AR1: inhuur_contract_link | AS1: inhuur_notities | AT1: inhuur_kale_huur | AU1: inhuur_totaal_excl_btw | AV1: inhuur_totaal_incl_btw | AW1: inhuur_btw_percentage | AX1: inhuur_borg | AY1: inhuur_voorschot_gwe | AZ1: inhuur_vve_kosten | BA1: inhuur_overige_kosten | BB1: inhuur_internet_kosten | BC1: huurder_id | BD1: huurder_naam | BE1: huurder_type | BF1: huurder_contactpersoon | BG1: huurder_email | BH1: huurder_telefoon | BI1: huurder_adres | BJ1: huurder_postcode | BK1: huurder_plaats | BL1: huurder_land | BM1: huurder_kvk | BN1: huurder_btw | BO1: huurder_iban | BP1: huurder_marge_max | BQ1: verhuur_contract_id | BR1: verhuur_start | BS1: verhuur_eind | BT1: verhuur_duur_maanden | BU1: verhuur_contract_type | BV1: verhuur_status | BW1: verhuur_kale_huur | BX1: verhuur_totaal_excl_btw | BY1: verhuur_totaal_incl_btw | BZ1: verhuur_btw_percentage | CA1: verhuur_voorschot_gwe | CB1: verhuur_overige_kosten | CC1: verhuur_eindschoonmaak | CD1: verhuur_borg | CE1: gwe_verantwoordelijk | CF1: incl_stoffering | CG1: incl_meubilering | CH1: incl_internet | CI1: incl_schoonmaak_kwartaal | CJ1: incl_bedlinnen | CK1: incl_tuinonderhoud | CL1: incl_eindschoonmaak | CM1: incl_afvalverwerking | CN1: schoonmaak_pakket | CO1: marge_maand_excl_btw | CP1: marge_jaar_excl_btw | CQ1: marge_percentage | CR1: beschikbaarheid_status | CS1: dagen_tot_beschikbaar
A2: 0001 | B2: 23 | C2: Nunspeetlaan 14 | D2: 2573 HG | E2: Den Haag | F2: Vakantiepark | H2: 3 | I2: 4 | J2: 1 | K2: Factuur | P2: https://ryanrent.sharepoint.com/sites/RyanRent/Gedeelde%20documenten/Forms/AllItems.aspx?id=%2Fsites%2FRyanRent%2FGedeelde%20documenten%2FGeneral%2F01%5FRyanRent%26Co%2F01%5FWoningen%2FNunspeetlaan%2014%20Den%20Haag | Q2: https://ryanrent.sharepoint.com/sites/RyanRent/Gedeelde%20documenten/Forms/AllItems.aspx?id=%2Fsites%2FRyanRent%2FGedeelde%20documenten%2FGeneral%2F01%5FRyanRent%26Co%2F01%5FWoningen%2FNunspeetlaan%2014%20Den%20Haag%2F2%5FInhuur | R2: https://ryanrent.sharepoint.com/sites/RyanRent/Gedeelde%20documenten/Forms/AllItems.aspx?id=%2Fsites%2FRyanRent%2FGedeelde%20documenten%2FGeneral%2F01%5FRyanRent%26Co%2F01%5FWoningen%2FNunspeetlaan%2014%20Den%20Haag%2F3%5FVerhuur | S2: https://ryanrent.sharepoint.com/sites/RyanRent/Gedeelde%20documenten/Forms/AllItems.aspx?id=%2Fsites%2FRyanRent%2FGedeelde%20documenten%2FGeneral%2F01%5FRyanRent%26Co%2F01%5FWoningen%2FNunspeetlaan%2014%20Den%20Haag%2F2%5FInhuur%2F2%5FInhuurovereenkomsten | T2: 1816.47 | U2: 300 | V2: 0 | AM2: Geen inhuur | BC2: 17 | BD2: Tradiro Services B.V. | BE2: particulier | BG2: facturen@tradiro.nl | BH2: null | BI2: Honderdland 960 | BJ2: 2678 PS | BK2: Maasdijk | BL2: Nederland | BM2: 59979135.0 | BO2: NL05 RABO 0154 0739 89 | BQ2: 443 | BR2: 2026-01-14 | BU2: bepaalde_tijd | BV2: Onbepaalde tijd | BW2: 1829.53 | BX2: 1829.53 | BY2: 1994.19 | BZ2: 0.09 | CA2: 0 | CB2: 22.82 | CC2: 0 | CD2: 1816.47 | CE2: ryanrent | CF2: 1 | CG2: 1 | CH2: 1 | CI2: 0 | CJ2: 0 | CK2: 0 | CL2: 0 | CM2: 0 | CO2: 1829.53 | CP2: 21954.36 | CR2: Verhuurd (onbepaald) | CS2: 0
A3: 0002 | B3: 24 | C3: Allard Piersonlaan 142 | D3: 2522 MT | E3: Den Haag | F3: Appartement | H3: 3 | I3: 4 | J3: 1 | K3: DS | P3: https://ryanrent.sharepoint.com/sites/RyanRent/Gedeelde%20documenten/Forms/AllItems.aspx?id=%2Fsites%2FRyanRent%2FGedeelde%20documenten%2FGeneral%2F01%5FRyanRent%26Co%2F01%5FWoningen%2FAllard%20Piersonlaan%20142%20Den%20Haag | Q3: https://ryanrent.sharepoint.com/sites/RyanRent/Gedeelde%20documenten/Forms/AllItems.aspx?id=%2Fsites%2FRyanRent%2FGedeelde%20documenten%2FGeneral%2F01%5FRyanRent%26Co%2F01%5FWoningen%2FAllard%20Piersonlaan%20142%20Den%20Haag%2F2%5FInhuur | R3: https://ryanrent.sharepoint.com/sites/RyanRent/Gedeelde%20documenten/Forms/AllItems.aspx?id=%2Fsites%2FRyanRent%2FGedeelde%20documenten%2FGeneral%2F01%5FRyanRent%26Co%2F01%5FWoningen%2FAllard%20Piersonlaan%20142%20Den%20Haag%2F3%5FVerhuur | S3: https://ryanrent.sharepoint.com/sites/RyanRent/Gedeelde%20documenten/Forms/AllItems.aspx?id=%2Fsites%2FRyanRent%2FGedeelde%20documenten%2FGeneral%2F01%5FRyanRent%26Co%2F01%5FWoningen%2FAllard%20Piersonlaan%20142%20Den%20Haag%2F2%5FInhuur%2F2%5FInhuurovereenkomsten | T3: 1929.41 | U3: 0 | V3: 0 | AM3: Geen inhuur | BC3: 17 | BD3: Tradiro Services B.V. | BE3: particulier | BG3: facturen@tradiro.nl | BH3: null | BI3: Honderdland 960 | BJ3: 2678 PS | BK3: Maasdijk | BL3: Nederland | BM3: 59979135.0 | BO3: NL05 RABO 0154 0739 89 | BQ3: 299 | BR3: 2026-01-14 | BU3: bepaalde_tijd | BV3: Onbepaalde tijd | BW3: 1829.53 | BX3: 1829.53 | BY3: 1994.19 | BZ3: 0.09 | CA3: 0 | CB3: 25.1 | CC3: 0 | CD3: 1929.41 | CE3: ryanrent | CF3: 0 | CG3: 0 | CH3: 0 | CI3: 0 | CJ3: 0 | CK3: 0 | CL3: 0 | CM3: 0 | CO3: 1829.53 | CP3: 21954.36 | CR3: Verhuurd (onbepaald) | CS3: 0
A4: 0003 | B4: 25 | C4: Acacia 2 | D4: 3224EB | E4: Hellevoetsluis | F4: Appartement | H4: 5 | I4: 5 | J4: 1 | K4: Factuur | L4: 4202 | M4: 1005 | P4: https://ryanrent.sharepoint.com/sites/RyanRent/Gedeelde%20documenten/Forms/AllItems.aspx?id=%2Fsites%2FRyanRent%2FGedeelde%20documenten%2FGeneral%2F01%5FRyanRent%26Co%2F01%5FWoningen%2FAcacia%202%2C%20Hellevoetsluis | Q4: https://ryanrent.sharepoint.com/sites/RyanRent/Gedeelde%20documenten/Forms/AllItems.aspx?id=%2Fsites%2FRyanRent%2FGedeelde%20documenten%2FGeneral%2F01%5FRyanRent%26Co%2F01%5FWoningen%2FAcacia%202%2C%20Hellevoetsluis%2F2%5FInhuur | R4: https://ryanrent.sharepoint.com/sites/RyanRent/Gedeelde%20documenten/Forms/AllItems.aspx?id=%2Fsites%2FRyanRent%2FGedeelde%20documenten%2FGeneral%2F01%5FRyanRent%26Co%2F01%5FWoningen%2FAcacia%202%2C%20Hellevoetsluis%2F3%5FVerhuur | S4: https://ryanrent.sharepoint.com/sites/RyanRent/Gedeelde%20documenten/Forms/AllItems.aspx?id=%2Fsites%2FRyanRent%2FGedeelde%20documenten%2FGeneral%2F01%5FRyanRent%26Co%2F01%5FWoningen%2FAcacia%202%2C%20Hellevoetsluis%2F2%5FInhuur%2F2%5FInhuurovereenkomsten | T4: 2022.35 | U4: 0 | V4: 0 | AM4: Geen inhuur | BV4: Leegstand | CD4: 2022.35 | CO4: 0 | CP4: 0 | CR4: Beschikbaar | CS4: 0
A5: 0004 | B5: 26 | C5: Broekweg 25 | D5: 3131 HC | E5: Vlaardingen | F5: Appartement | I5: 4 | J5: 1 | K5: Factuur | P5: https://ryanrent.sharepoint.com/sites/RyanRent/Gedeelde%20documenten/Forms/AllItems.aspx?id=%2Fsites%2FRyanRent%2FGedeelde%20documenten%2FGeneral%2F01%5FRyanRent%26Co%2F01%5FWoningen%2FBroekweg%2025%20Vlaardingen | Q5: https://ryanrent.sharepoint.com/sites/RyanRent/Gedeelde%20documenten/Forms/AllItems.aspx?id=%2Fsites%2FRyanRent%2FGedeelde%20documenten%2FGeneral%2F01%5FRyanRent%26Co%2F01%5FWoningen%2FBroekweg%2025%20Vlaardingen%2F2%5FInhuur | R5: https://ryanrent.sharepoint.com/sites/RyanRent/Gedeelde%20documenten/Forms/AllItems.aspx?id=%2Fsites%2FRyanRent%2FGedeelde%20documenten%2FGeneral%2F01%5FRyanRent%26Co%2F01%5FWoningen%2FBroekweg%2025%20Vlaardingen%2F3%5FVerhuur | S5: https://ryanrent.sharepoint.com/sites/RyanRent/Gedeelde%20documenten/Forms/AllItems.aspx?id=%2Fsites%2FRyanRent%2FGedeelde%20documenten%2FGeneral%2F01%5FRyanRent%26Co%2F01%5FWoningen%2FBroekweg%2025%20Vlaardingen%2F2%5FInhuur%2F2%5FInhuurovereenkomsten | T5: 2111.76 | U5: 260.15 | V5: 0 | AM5: Geen inhuur | BV5: Leegstand | CD5: 2111.76 | CO5: 0 | CP5: 0 | CR5: Beschikbaar | CS5: 0
A6: 0005 | B6: 27 | C6: Ringbaan Oost 327 | D6: 5014 GG | E6: Tilburg | F6: Appartement | H6: 8 | I6: 8 | J6: 1 | K6: Factuur | L6: 1908 | P6: https://ryanrent.sharepoint.com/sites/RyanRent/Gedeelde%20documenten/Forms/AllItems.aspx?id=%2Fsites%2FRyanRent%2FGedeelde%20documenten%2FGeneral%2F01%5FRyanRent%26Co%2F01%5FWoningen%2FRingbaan%20Oost%20327%20Tilburg | Q6: https://ryanrent.sharepoint.com/sites/RyanRent/Gedeelde%20documenten/Forms/AllItems.aspx?id=%2Fsites%2FRyanRent%2FGedeelde%20documenten%2FGeneral%2F01%5FRyanRent%26Co%2F01%5FWoningen%2FRingbaan%20Oost%20327%20Tilburg%2F2%5FInhuur | R6: https://ryanrent.sharepoint.com/sites/RyanRent/Gedeelde%20documenten/Forms/AllItems.aspx?id=%2Fsites%2FRyanRent%2FGedeelde%20documenten%2FGeneral%2F01%5FRyanRent%26Co%2F01%5FWoningen%2FRingbaan%20Oost%20327%20Tilburg%2F3%5FVerhuur | T6: 2076.47 | U6: 500 | V6: 0 | W6: 763 | X6: T. Eenhuistra/J. Pluimakers | Y6: particulier | AJ6: 724 | AK6: 2025-08-01 | AL6: 2027-08-01 | AM6: Actief | AO6: 1 | AT6: 4300 | AU6: 4300 | AV6: 4687 | AW6: 0.09 | AX6: 0 | AY6: 0 | AZ6: 0 | BA6: 0 | BB6: 0 | BC6: 237 | BD6: AKT Autoschade | BE6: particulier | BG6: facturen@aktautoschade.com | BH6: 06 33417286 | BI6: Goirkekanaaldijk 211-18 | BK6: Tilburg | BL6: Nederland | BQ6: 216 | BR6: 2025-08-01 | BS6: 2027-08-01 | BT6: 12 | BU6: bepaalde_tijd | BV6: Actief | BW6: 5710.93 | BX6: 6210.93 | BY6: 6769.91 | BZ6: 0.09 | CA6: 500 | CB6: 0 | CC6: 0 | CD6: 2076.47 | CE6: ryanrent | CF6: 0 | CG6: 0 | CH6: 0 | CI6: 0 | CJ6: 0 | CK6: 0 | CL6: 0 | CM6: 0 | CO6: 1910.93 | CP6: 22931.16 | CQ6: 44.44 | CR6: Verhuurd | CS6: 556
A7: 0006 | B7: 28 | C7: Enschotsestraat 163 | D7: 5014 DD | E7: Tilburg | F7: Appartement | H7: 8 | I7: 8 | J7: 1 | K7: Factuur | L7: 1908 | P7: https://ryanrent.sharepoint.com/sites/RyanRent/Gedeelde%20documenten/Forms/AllItems.aspx?id=%2Fsites%2FRyanRent%2FGedeelde%20documenten%2FGeneral%2F01%5FRyanRent%26Co%2F01%5FWoningen%2FEnschotsestraat%20163%20Tilburg | Q7: https://ryanrent.sharepoint.com/sites/RyanRent/Gedeelde%20documenten/Forms/AllItems.aspx?id=%2Fsites%2FRyanRent%2FGedeelde%20documenten%2FGeneral%2F01%5FRyanRent%26Co%2F01%5FWoningen%2FEnschotsestraat%20163%20Tilburg%2F2%5FInhuur | R7: https://ryanrent.sharepoint.com/sites/RyanRent/Gedeelde%20documenten/Forms/AllItems.aspx?id=%2Fsites%2FRyanRent%2FGedeelde%20documenten%2FGeneral%2F01%5FRyanRent%26Co%2F01%5FWoningen%2FEnschotsestraat%20163%20Tilburg%2F3%5FVerhuur | T7: 2192.94 | U7: 450 | V7: 0 | W7: 763 | X7: T. Eenhuistra/J. Pluimakers | Y7: particulier | AJ7: 586 | AK7: 2025-08-01 | AL7: 2027-08-01 | AM7: Actief | AO7: 1 | AT7: 4300 | AU7: 4300 | AV7: 4687 | AW7: 0.09 | AX7: 0 | AY7: 0 | AZ7: 0 | BA7: 0 | BB7: 0 | BC7: 353 | BD7: Optima Uitzendbureau B.V. | BE7: particulier | BG7: Financieel@optimauitzendburo.nl | BH7: 0184 675 489 | BI7: Kade 40 | BK7: Hardinxveld Giessendam | BL7: Nederland | BM7: 24403530.0 | BQ7: 71 | BR7: 2025-08-01 | BS7: 2027-08-01 | BT7: 12 | BU7: bepaalde_tijd | BV7: Actief | BW7: 4575 | BX7: 4575 | BY7: 4986.75 | BZ7: 0.09 | CA7: 0 | CB7: 0 | CC7: 375 | CD7: 2192.94 | CE7: eigen_beheer | CF7: 0 | CG7: 0 | CH7: 0 | CI7: 0 | CJ7: 0 | CK7: 0 | CL7: 1 | CM7: 0 | CN7: intensief | CO7: 275 | CP7: 3300 | CQ7: 6.4 | CR7: Verhuurd | CS7: 556
A8: 0007 | B8: 29 | C8: Adriaan Baasstraat 34 | D8: 7902HN | E8: Hoogeveen | F8: Appartement | H8: 4 | I8: 4 | J8: 1 | K8: DS | L8: 7902 | M8: 1005 | P8: https://ryanrent.sharepoint.com/sites/RyanRent/Gedeelde%20documenten/Forms/AllItems.aspx?id=%2Fsites%2FRyanRent%2FGedeelde%20documenten%2FGeneral%2F01%5FRyanRent%26Co%2F01%5FWoningen%2FAdriaan%20Baasstraat%2034%2C%20Hoogeveen | Q8: https://ryanrent.sharepoint.com/sites/RyanRent/Gedeelde%20documenten/Forms/AllItems.aspx?id=%2Fsites%2FRyanRent%2FGedeelde%20documenten%2FGeneral%2F01%5FRyanRent%26Co%2F01%5FWoningen%2FAdriaan%20Baasstraat%2034%2C%20Hoogeveen%2F2%5FInhuur | R8: https://ryanrent.sharepoint.com/sites/RyanRent/Gedeelde%20documenten/Forms/AllItems.aspx?id=%2Fsites%2FRyanRent%2FGedeelde%20documenten%2FGeneral%2F01%5FRyanRent%26Co%2F01%5FWoningen%2FAdriaan%20Baasstraat%2034%2C%20Hoogeveen%2F3%5FVerhuur | S8: https://ryanrent.sharepoint.com/sites/RyanRent/Gedeelde%20documenten/Forms/AllItems.aspx?id=%2Fsites%2FRyanRent%2FGedeelde%20documenten%2FGeneral%2F01%5FRyanRent%26Co%2F01%5FWoningen%2FAdriaan%20Baasstraat%2034%2C%20Hoogeveen%2F2%5FInhuur%2F2%5FInhuurovereenkomsten | T8: 2594.12 | U8: 250 | V8: 0 | AM8: Geen inhuur | BC8: 154 | BD8: InAxtion Vastgoed B.V. | BE8: particulier | BG8: Invoice.vastgoed@inaxtion.com | BH8: 06 43 36 18 85 | BI8: Wijnstraat 123 | BK8: Dordrecht | BL8: Nederland | BM8: 16074829.0 | BO8: NL68 ABNA 0427 9222 08 | BQ8: 8 | BR8: 2025-04-18 | BS8: 2026-04-17 | BT8: 12 | BU8: bepaalde_tijd | BV8: Actief | BW8: 2200 | BX8: 2480 | BY8: 2703.2 | BZ8: 0.09 | CA8: 250 | CB8: 30 | CC8: 250 | CD8: 2594.12 | CE8: ryanrent | CF8: 1 | CG8: 1 | CH8: 1 | CI8: 0 | CJ8: 1 | CK8: 0 | CL8: 1 | CM8: 0 | CN8: basis | CO8: 2480 | CP8: 29760 | CR8: Verhuurd | CS8: 85
A9: 0008 | B9: 30 | C9: Arkelse Onderweg 24a | D9: 4206AH | E9: Gorinchem | F9: Appartement | H9: 3 | I9: 10000 | J9: 1 | K9: Factuur | L9: 2324 | M9: 1908 | T9: 1780 | U9: 0 | V9: 0 | AM9: Geen inhuur | BV9: Leegstand | CD9: 1780 | CO9: 0 | CP9: 0 | CR9: Beschikbaar | CS9: 0
A10: 0009 | B10: 31 | C10: Galgeweg 48-A | D10: 2691MG | E10: s-Gravenzande | F10: Appartement | H10: 3 | I10: 6 | J10: 1 | K10: Factuur | T10: 2058.82 | U10: 95.2 | V10: 0 | AM10: Geen inhuur | BC10: 17 | BD10: Tradiro Services B.V. | BE10: particulier | BG10: facturen@tradiro.nl | BH10: null | BI10: Honderdland 960 | BJ10: 2678 PS | BK10: Maasdijk | BL10: Nederland | BM10: 59979135.0 | BO10: NL05 RABO 0154 0739 89 | BQ10: 300 | BR10: 2026-01-14 | BU10: bepaalde_tijd | BV10: Onbepaalde tijd | BW10: 0 | BX10: 3643.5 | BY10: 3971.42 | BZ10: 0.09 | CA10: 773.78 | CB10: 50.37 | CC10: 0 | CD10: 2058.82 | CE10: ryanrent | CF10: 0 | CG10: 0 | CH10: 0 | CI10: 0 | CJ10: 0 | CK10: 0 | CL10: 0 | CM10: 0 | CO10: 3643.5 | CP10: 43722 | CR10: Verhuurd (onbepaald) | CS10: 0
A11: 0010 | B11: 32 | C11: Kethelweg 1B | D11: 3135 GA | E11: Vlaardingen | F11: Vakantiepark | H11: 3 | I11: 5 | J11: 1 | K11: Factuur | P11: https://ryanrent.sharepoint.com/sites/RyanRent/Gedeelde%20documenten/Forms/AllItems.aspx?id=%2Fsites%2FRyanRent%2FGedeelde%20documenten%2FGeneral%2F01%5FRyanRent%26Co%2F01%5FWoningen%2FKethelweg%201B%20Vlaardingen | T11: 2444.71 | U11: 85.24 | V11: 0 | AM11: Geen inhuur | BC11: 17 | BD11: Tradiro Services B.V. | BE11: particulier | BG11: facturen@tradiro.nl | BH11: null | BI11: Honderdland 960 | BJ11: 2678 PS | BK11: Maasdijk | BL11: Nederland | BM11: 59979135.0 | BO11: NL05 RABO 0154 0739 89 | BQ11: 270 | BR11: 2023-02-01 | BU11: onbepaalde_tijd | BV11: Onbepaalde tijd | BW11: 1708.41 | BX11: 1708.41 | BY11: 1862.17 | BZ11: 0.09 | CA11: 0 | CB11: 0 | CC11: 0 | CD11: 2444.71 | CE11: ryanrent | CF11: 1 | CG11: 1 | CH11: 1 | CI11: 0 | CJ11: 0 | CK11: 0 | CL11: 0 | CM11: 0 | CO11: 1708.41 | CP11: 20500.92 | CR11: Verhuurd (onbepaald) | CS11: 0
A12: 0011 | B12: 33 | C12: Kethelweg 1C | D12: 3135 GA | E12: Vlaardingen | F12: Vakantiepark | H12: 3 | I12: 3 | J12: 1 | K12: Factuur | P12: https://ryanrent.sharepoint.com/sites/RyanRent/Gedeelde%20documenten/Forms/AllItems.aspx?id=%2Fsites%2FRyanRent%2FGedeelde%20documenten%2FGeneral%2F01%5FRyanRent%26Co%2F01%5FWoningen%2FKethelweg%201C%20Vlaardingen | Q12: https://ryanrent.sharepoint.com/sites/RyanRent/Gedeelde%20documenten/Forms/AllItems.aspx?id=%2Fsites%2FRyanRent%2FGedeelde%20documenten%2FGeneral%2F01%5FRyanRent%26Co%2F01%5FWoningen%2FKethelweg%201C%20Vlaardingen%2F2%5FInhuur | R12: https://ryanrent.sharepoint.com/sites/RyanRent/Gedeelde%20documenten/Forms/AllItems.aspx?id=%2Fsites%2FRyanRent%2FGedeelde%20documenten%2FGeneral%2F01%5FRyanRent%26Co%2F01%5FWoningen%2FKethelweg%201C%20Vlaardingen%2F3%5FVerhuur | T12: 1769.41 | U12: 32.11 | V12: 0 | AM12: Geen inhuur | BC12: 17 | BD12: Tradiro Services B.V. | BE12: particulier | BG12: facturen@tradiro.nl | BH12: null | BI12: Honderdland 960 | BJ12: 2678 PS | BK12: Maasdijk | BL12: Nederland | BM12: 59979135.0 | BO12: NL05 RABO 0154 0739 89 | BQ12: 271 | BR12: 2023-02-01 | BU12: onbepaalde_tijd | BV12: Onbepaalde tijd | BW12: 1708.41 | BX12: 1708.41 | BY12: 1862.17 | BZ12: 0.09 | CA12: 0 | CB12: 0 | CC12: 0 | CD12: 1769.41 | CE12: ryanrent | CF12: 0 | CG12: 0 | CH12: 0 | CI12: 0 | CJ12: 0 | CK12: 0 | CL12: 0 | CM12: 0 | CO12: 1708.41 | CP12: 20500.92 | CR12: Verhuurd (onbepaald) | CS12: 0
A13: 0012 | B13: 34 | C13: Baarlelaan 27 | D13: 7906GB | E13: Hoogeveen | F13: Appartement | H13: 4 | I13: 4 | J13: 1 | K13: DS | L13: 1975 | M13: 1005 | P13: https://ryanrent.sharepoint.com/sites/RyanRent/Gedeelde%20documenten/Forms/AllItems.aspx?id=%2Fsites%2FRyanRent%2FGedeelde%20documenten%2FGeneral%2F01%5FRyanRent%26Co%2F01%5FWoningen%2FBaarlelaan%2027%2C%20Hoogeveen | Q13: https://ryanrent.sharepoint.com/sites/RyanRent/Gedeelde%20documenten/Forms/AllItems.aspx?id=%2Fsites%2FRyanRent%2FGedeelde%20documenten%2FGeneral%2F01%5FRyanRent%26Co%2F01%5FWoningen%2FBaarlelaan%2027%2C%20Hoogeveen%2F2%5FInhuur | R13: https://ryanrent.sharepoint.com/sites/RyanRent/Gedeelde%20documenten/Forms/AllItems.aspx?id=%2Fsites%2FRyanRent%2FGedeelde%20documenten%2FGeneral%2F01%5FRyanRent%26Co%2F01%5FWoningen%2FBaarlelaan%2027%2C%20Hoogeveen%2F3%5FVerhuur | S13: https://ryanrent.sharepoint.com/sites/RyanRent/Gedeelde%20documenten/Forms/AllItems.aspx?id=%2Fsites%2FRyanRent%2FGedeelde%20documenten%2FGeneral%2F01%5FRyanRent%26Co%2F01%5FWoningen%2FBaarlelaan%2027%2C%20Hoogeveen%2F2%5FInhuur%2F2%5FInhuurovereenkomsten | T13: 1965.88 | U13: 240 | V13: 0 | AM13: Geen inhuur | BV13: Leegstand | CD13: 1965.88 | CO13: 0 | CP13: 0 | CR13: Beschikbaar | CS13: 0
A14: 0013 | B14: 35 | C14: Baarsveen 197 | D14: 3205 BB | E14: Spijkenisse | F14: Appartement | H14: 5 | I14: 5 | J14: 1 | K14: DS | L14: 9197 | M14: 1144 | P14: https://ryanrent.sharepoint.com/sites/RyanRent/Gedeelde%20documenten/Forms/AllItems.aspx?id=%2Fsites%2FRyanRent%2FGedeelde%20documenten%2FGeneral%2F01%5FRyanRent%26Co%2F01%5FWoningen%2FBaarsveen%20197%2C%20Spijkenisse | Q14: https://ryanrent.sharepoint.com/sites/RyanRent/Gedeelde%20documenten/Forms/AllItems.aspx?id=%2Fsites%2FRyanRent%2FGedeelde%20documenten%2FGeneral%2F01%5FRyanRent%26Co%2F01%5FWoningen%2FBaarsveen%20197%2C%20Spijkenisse%2F2%5FInhuur | R14: https://ryanrent.sharepoint.com/sites/RyanRent/Gedeelde%20documenten/Forms/AllItems.aspx?id=%2Fsites%2FRyanRent%2FGedeelde%20documenten%2FGeneral%2F01%5FRyanRent%26Co%2F01%5FWoningen%2FBaarsveen%20197%2C%20Spijkenisse%2F3%5FVerhuur | S14: https://ryanrent.sharepoint.com/sites/RyanRent/Gedeelde%20documenten/Forms/AllItems.aspx?id=%2Fsites%2FRyanRent%2FGedeelde%20documenten%2FGeneral%2F01%5FRyanRent%26Co%2F01%5FWoningen%2FBaarsveen%20197%2C%20Spijkenisse%2F2%5FInhuur%2F2%5FInhuurovereenkomsten | T14: 1864.71 | U14: 325 | V14: 0 | AM14: Geen inhuur | BV14: Leegstand | CD14: 1864.71 | CO14: 0 | CP14: 0 | CR14: Beschikbaar | CS14: 0
A15: 0014 | B15: 36 | C15: Abelenlaan 143 | D15: 3181WD | E15: Rozenburg | F15: Appartement | H15: 3 | I15: 6 | J15: 1 | K15: Factuur | L15: 3143 | M15: 1005 | T15: 1940 | U15: 300 | V15: 0 | AM15: Geen inhuur | BV15: Leegstand | CD15: 1940 | CO15: 0 | CP15: 0 | CR15: Beschikbaar | CS15: 0
A16: 0015 | B16: 37 | C16: Maasdijk 69 | D16: 2691NZ | E16: S-Gravenzande | F16: Vakantiepark | H16: 3 | I16: 4 | J16: 1 | K16: Factuur | T16: 1934.12 | U16: 2470.8 | V16: 0 | AM16: Geen inhuur | BC16: 17 | BD16: Tradiro Services B.V. | BE16: particulier | BG16: facturen@tradiro.nl | BH16: null | BI16: Honderdland 960 | BJ16: 2678 PS | BK16: Maasdijk | BL16: Nederland | BM16: 59979135.0 | BO16: NL05 RABO 0154 0739 89 | BQ16: 301 | BR16: 2026-01-14 | BU16: bepaalde_tijd | BV16: Onbepaalde tijd | BW16: 0 | BX16: 3400 | BY16: 3706 | BZ16: 0.09 | CA16: 2470.8 | CB16: 0 | CC16: 0 | CD16: 1934.12 | CE16: ryanrent | CF16: 0 | CG16: 0 | CH16: 0 | CI16: 0 | CJ16: 0 | CK16: 0 | CL16: 0 | CM16: 0 | CO16: 3400 | CP16: 40800 | CR16: Verhuurd (onbepaald) | CS16: 0
A17: 0016 | B17: 38 | C17: van Scorelstraat 73 | D17: 3141 TH | E17: Maassluis | F17: Appartement | H17: 3 | I17: 5 | J17: 1 | K17: Factuur | P17: https://ryanrent.sharepoint.com/sites/RyanRent/Gedeelde%20documenten/Forms/AllItems.aspx?id=%2Fsites%2FRyanRent%2FGedeelde%20documenten%2FGeneral%2F01%5FRyanRent%26Co%2F01%5FWoningen%2FVan%20Scorelstraat%2073%20Maassluis | Q17: https://ryanrent.sharepoint.com/sites/RyanRent/Gedeelde%20documenten/Forms/AllItems.aspx?id=%2Fsites%2FRyanRent%2FGedeelde%20documenten%2FGeneral%2F01%5FRyanRent%26Co%2F01%5FWoningen%2FVan%20Scorelstraat%2073%20Maassluis%2F2%5FInhuur | R17: https://ryanrent.sharepoint.com/sites/RyanRent/Gedeelde%20documenten/Forms/AllItems.aspx?id=%2Fsites%2FRyanRent%2FGedeelde%20documenten%2FGeneral%2F01%5FRyanRent%26Co%2F01%5FWoningen%2FVan%20Scorelstraat%2073%20Maassluis%2F3%5FVerhuur | S17: https://ryanrent.sharepoint.com/sites/RyanRent/Gedeelde%20documenten/Forms/AllItems.aspx?id=%2Fsites%2FRyanRent%2FGedeelde%20documenten%2FGeneral%2F01%5FRyanRent%26Co%2F01%5FWoningen%2FVan%20Scorelstraat%2073%20Maassluis%2F2%5FInhuur%2F2%5FInhuurovereenkomsten | T17: 2224.71 | U17: 218.11 | V17: 0 | AM17: Geen inhuur | BV17: Leegstand | CD17: 2224.71 | CO17: 0 | CP17: 0 | CR17: Beschikbaar | CS17: 0
A18: 0017 | B18: 39 | C18: G.A. Brederolaan 75B | D18: 3141 CD | E18: Maassluis | F18: Appartement | H18: 3 | I18: 4 | J18: 1 | K18: Factuur | P18: https://ryanrent.sharepoint.com/sites/RyanRent/Gedeelde%20documenten/Forms/AllItems.aspx?id=%2Fsites%2FRyanRent%2FGedeelde%20documenten%2FGeneral%2F01%5FRyanRent%26Co%2F01%5FWoningen%2FG.A.%20Brederolaan%2075B%20Maassluis | T18: 1702.35 | U18: 208.85 | V18: 0 | AM18: Geen inhuur | BV18: Leegstand | CD18: 1702.35 | CO18: 0 | CP18: 0 | CR18: Beschikbaar | CS18: 0
A19: 0018 | B19: 40 | C19: Meester G. Groen van Prinsterlaan 313 | D19: 1181TV | E19: Amstelveen | F19: Appartement | H19: 2 | I19: 3 | J19: 1 | K19: DS | P19: https://ryanrent.sharepoint.com/sites/RyanRent/Gedeelde%20documenten/Forms/AllItems.aspx?id=%2Fsites%2FRyanRent%2FGedeelde%20documenten%2FGeneral%2F01%5FRyanRent%26Co%2F01%5FWoningen%2FMeester%20G.%20groen%20van%20Prinsterlaan%20313%2C%20Amstelveen | Q19: https://ryanrent.sharepoint.com/sites/RyanRent/Gedeelde%20documenten/Forms/AllItems.aspx?id=%2Fsites%2FRyanRent%2FGedeelde%20documenten%2FGeneral%2F01%5FRyanRent%26Co%2F01%5FWoningen%2FMeester%20G.%20groen%20van%20Prinsterlaan%20313%2C%20Amstelveen%2F2%5FInhuur | R19: https://ryanrent.sharepoint.com/sites/RyanRent/Gedeelde%20documenten/Forms/AllItems.aspx?id=%2Fsites%2FRyanRent%2FGedeelde%20documenten%2FGeneral%2F01%5FRyanRent%26Co%2F01%5FWoningen%2FMeester%20G.%20groen%20van%20Prinsterlaan%20313%2C%20Amstelveen%2F3%5FVerhuur | S19: https://ryanrent.sharepoint.com/sites/RyanRent/Gedeelde%20documenten/Forms/AllItems.aspx?id=%2Fsites%2FRyanRent%2FGedeelde%20documenten%2FGeneral%2F01%5FRyanRent%26Co%2F01%5FWoningen%2FMeester%20G.%20groen%20van%20Prinsterlaan%20313%2C%20Amstelveen%2F2%5FInhuur%2F2%5FInhuurovereenkomsten | T19: 1861.18 | U19: 200 | V19: 0 | AM19: Geen inhuur | BV19: Leegstand | CD19: 1861.18 | CO19: 0 | CP19: 0 | CR19: Beschikbaar | CS19: 0
A20: 0019 | B20: 41 | C20: Franselaan 273B | D20: 3028 AC | E20: Rotterdam | F20: Appartement | H20: 8 | I20: 8 | J20: 1 | K20: Factuur | T20: 2052.94 | U20: 39.24 | V20: 0 | AM20: Geen inhuur | BV20: Leegstand | CD20: 2052.94 | CO20: 0 | CP20: 0 | CR20: Beschikbaar | CS20: 0
A21: 0020 | B21: 42 | C21: Mr. Troelstrastraat 37 | D21: 3131 HR | E21: Vlaardingen | F21: Vakantiepark | H21: 2 | I21: 3 | J21: 1 | K21: Factuur | P21: https://ryanrent.sharepoint.com/sites/RyanRent/Gedeelde%20documenten/Forms/AllItems.aspx?id=%2Fsites%2FRyanRent%2FGedeelde%20documenten%2FGeneral%2F01%5FRyanRent%26Co%2F01%5FWoningen%2FMr.%20Troelstrastraat%2037%20Vlaardingen | T21: 1783.53 | U21: 181.36 | V21: 0 | AM21: Geen inhuur | BC21: 17 | BD21: Tradiro Services B.V. | BE21: particulier | BG21: facturen@tradiro.nl | BH21: null | BI21: Honderdland 960 | BJ21: 2678 PS | BK21: Maasdijk | BL21: Nederland | BM21: 59979135.0 | BO21: NL05 RABO 0154 0739 89 | BQ21: 269 | BR21: 2023-02-01 | BU21: onbepaalde_tijd | BV21: Onbepaalde tijd | BW21: 1723.44 | BX21: 1723.44 | BY21: 1878.55 | BZ21: 0.09 | CA21: 0 | CB21: 0 | CC21: 0 | CD21: 1783.53 | CE21: ryanrent | CF21: 0 | CG21: 0 | CH21: 0 | CI21: 0 | CJ21: 0 | CK21: 0 | CL21: 0 | CM21: 0 | CO21: 1723.44 | CP21: 20681.28 | CR21: Verhuurd (onbepaald) | CS21: 0
A22: 0021 | B22: 43 | C22: Vaartweg 106C | D22: 3131 HV | E22: Vlaardingen | F22: Appartement | H22: 3 | I22: 5 | J22: 1 | K22: Factuur | P22: https://ryanrent.sharepoint.com/sites/RyanRent/Gedeelde%20documenten/Forms/AllItems.aspx?id=%2Fsites%2FRyanRent%2FGedeelde%20documenten%2FGeneral%2F01%5FRyanRent%26Co%2F01%5FWoningen%2FVaartweg%20106C%2C%20Vlaardingen | Q22: https://ryanrent.sharepoint.com/sites/RyanRent/Gedeelde%20documenten/Forms/AllItems.aspx?id=%2Fsites%2FRyanRent%2FGedeelde%20documenten%2FGeneral%2F01%5FRyanRent%26Co%2F01%5FWoningen%2FVaartweg%20106C%2C%20Vlaardingen%2F2%5FInhuur | R22: https://ryanrent.sharepoint.com/sites/RyanRent/Gedeelde%20documenten/Forms/AllItems.aspx?id=%2Fsites%2FRyanRent%2FGedeelde%20documenten%2FGeneral%2F01%5FRyanRent%26Co%2F01%5FWoningen%2FVaartweg%20106C%2C%20Vlaardingen%2F3%5FVerhuur | S22: https://ryanrent.sharepoint.com/sites/RyanRent/Gedeelde%20documenten/Forms/AllItems.aspx?id=%2Fsites%2FRyanRent%2FGedeelde%20documenten%2FGeneral%2F01%5FRyanRent%26Co%2F01%5FWoningen%2FVaartweg%20106C%2C%20Vlaardingen%2F2%5FInhuur%2F2%5FInhuurovereenkomsten | T22: 2016.47 | U22: 256.89 | V22: 0 | AM22: Geen inhuur | BC22: 17 | BD22: Tradiro Services B.V. | BE22: particulier | BG22: facturen@tradiro.nl | BH22: null | BI22: Honderdland 960 | BJ22: 2678 PS | BK22: Maasdijk | BL22: Nederland | BM22: 59979135.0 | BO22: NL05 RABO 0154 0739 89 | BQ22: 267 | BR22: 2023-02-01 | BU22: onbepaalde_tijd | BV22: Onbepaalde tijd | BW22: 1830.43 | BX22: 1830.43 | BY22: 1995.17 | BZ22: 0.09 | CA22: 0 | CB22: 0 | CC22: 0 | CD22: 2016.47 | CE22: ryanrent | CF22: 0 | CG22: 0 | CH22: 0 | CI22: 0 | CJ22: 0 | CK22: 0 | CL22: 0 | CM22: 0 | CO22: 1830.43 | CP22: 21965.16 | CR22: Verhuurd (onbepaald) | CS22: 0
A23: 0022 | B23: 44 | C23: 2e van Leydengaelstraat 6 | D23: 3134 LL | E23: Vlaardingen | F23: Vakantiepark | H23: 4 | I23: 8 | J23: 1 | K23: Factuur | P23: https://ryanrent.sharepoint.com/sites/RyanRent/Gedeelde%20documenten/Forms/AllItems.aspx?id=%2Fsites%2FRyanRent%2FGedeelde%20documenten%2FGeneral%2F01%5FRyanRent%26Co%2F01%5FWoningen%2F2e%20van%20leyden%20gaelstraat%206%20Vlaardingen | Q23: https://ryanrent.sharepoint.com/sites/RyanRent/Gedeelde%20documenten/Forms/AllItems.aspx?id=%2Fsites%2FRyanRent%2FGedeelde%20documenten%2FGeneral%2F01%5FRyanRent%26Co%2F01%5FWoningen%2F2e%20van%20leyden%20gaelstraat%206%20Vlaardingen%2F2%5FInhuur | R23: https://ryanrent.sharepoint.com/sites/RyanRent/Gedeelde%20documenten/Forms/AllItems.aspx?id=%2Fsites%2FRyanRent%2FGedeelde%20documenten%2FGeneral%2F01%5FRyanRent%26Co%2F01%5FWoningen%2F2e%20van%20leyden%20gaelstraat%206%20Vlaardingen%2F3%5FVerhuur | S23: https://ryanrent.sharepoint.com/sites/RyanRent/Gedeelde%20documenten/Forms/AllItems.aspx?id=%2Fsites%2FRyanRent%2FGedeelde%20documenten%2FGeneral%2F01%5FRyanRent%26Co%2F01%5FWoningen%2F2e%20van%20leyden%20gaelstraat%206%20Vlaardingen%2F2%5FInhuur%2F2%5FInhuurovereenkomsten | T23: 2271.76 | U23: 0 | V23: 0 | AM23: Geen inhuur | BV23: Leegstand | CD23: 2271.76 | CO23: 0 | CP23: 0 | CR23: Beschikbaar | CS23: 0
A24: 0023 | B24: 45 | C24: Desiree Geerartstraat 1B | D24: 5111CH | E24: Baarle-Nassau | F24: Vakantiepark | H24: 5 | I24: 8 | J24: 1 | K24: DS | L24: 0107 | T24: 2018.82 | U24: 0 | V24: 0 | W24: 326 | X24: S. Kleiren | Y24: particulier | AA24: sabine.kleiren@gmail.com | AF24: Nederland | AI24: NL20 RABO 0103 8768 98 | AJ24: 574 | AK24: 2024-10-18 | AL24: 2027-10-18 | AM24: Actief | AO24: 1 | AT24: 3519 | AU24: 3519 | AV24: 3835.71 | AW24: 0.09 | AX24: 0 | AY24: 0 | AZ24: 0 | BA24: 0 | BB24: 0 | BC24: 236 | BD24: NL Realty B.V. | BE24: particulier | BG24: administratie@nl-jobs.com | BH24: 06 22 040 775 | BI24: Honderdland 1 | BK24: MAASDIJK | BL24: Nederland | BO24: NL90 RABO 0346 4019 25 | BQ24: 60 | BR24: 2024-10-18 | BS24: 2027-10-18 | BT24: 6 | BU24: bepaalde_tijd | BV24: Actief | BW24: 4033.88 | BX24: 4033.88 | BY24: 4396.93 | BZ24: 0.09 | CA24: 0 | CB24: 0 | CC24: 0 | CD24: 2018.82 | CE24: eigen_beheer | CF24: 0 | CG24: 0 | CH24: 0 | CI24: 0 | CJ24: 0 | CK24: 0 | CL24: 0 | CM24: 0 | CO24: 514.88 | CP24: 6178.56 | CQ24: 14.63 | CR24: Verhuurd | CS24: 634
A25: 0024 | B25: 46 | C25: Desiree Geerartstraat 1C | D25: 5111CH | E25: Baarle-Nassau | F25: Vakantiepark | H25: 6 | I25: 8 | J25: 1 | K25: DS | L25: 0107 | T25: 2510.59 | U25: 0 | V25: 0 | W25: 326 | X25: S. Kleiren | Y25: particulier | AA25: sabine.kleiren@gmail.com | AF25: Nederland | AI25: NL20 RABO 0103 8768 98 | AJ25: 575 | AK25: 2024-10-18 | AL25: 2027-10-18 | AM25: Actief | AO25: 1 | AT25: 3519 | AU25: 3519 | AV25: 3835.71 | AW25: 0.09 | AX25: 0 | AY25: 0 | AZ25: 0 | BA25: 0 | BB25: 0 | BC25: 236 | BD25: NL Realty B.V. | BE25: particulier | BG25: administratie@nl-jobs.com | BH25: 06 22 040 775 | BI25: Honderdland 1 | BK25: MAASDIJK | BL25: Nederland | BO25: NL90 RABO 0346 4019 25 | BQ25: 61 | BR25: 2024-10-18 | BS25: 2027-10-18 | BT25: 6 | BU25: bepaalde_tijd | BV25: Actief | BW25: 4033.88 | BX25: 4033.88 | BY25: 4396.93 | BZ25: 0.09 | CA25: 0 | CB25: 0 | CC25: 0 | CD25: 2510.59 | CE25: eigen_beheer | CF25: 0 | CG25: 0 | CH25: 0 | CI25: 0 | CJ25: 0 | CK25: 0 | CL25: 0 | CM25: 0 | CO25: 514.88 | CP25: 6178.56 | CQ25: 14.63 | CR25: Verhuurd | CS25: 634
A26: 0025 | B26: 47 | C26: Groenelaan 30B | D26: 3114 CH | E26: Schiedam | F26: Appartement | H26: 3 | I26: 3 | J26: 1 | K26: Factuur | L26: 2206 | P26: https://ryanrent.sharepoint.com/sites/RyanRent/Gedeelde%20documenten/Forms/AllItems.aspx?id=%2Fsites%2FRyanRent%2FGedeelde%20documenten%2FGeneral%2F01%5FRyanRent%26Co%2F01%5FWoningen%2FGroenelaan%2030B%2C%20Schiedam | Q26: https://ryanrent.sharepoint.com/sites/RyanRent/Gedeelde%20documenten/Forms/AllItems.aspx?id=%2Fsites%2FRyanRent%2FGedeelde%20documenten%2FGeneral%2F01%5FRyanRent%26Co%2F01%5FWoningen%2FGroenelaan%2030B%2C%20Schiedam%2F2%5FInhuur | R26: https://ryanrent.sharepoint.com/sites/RyanRent/Gedeelde%20documenten/Forms/AllItems.aspx?id=%2Fsites%2FRyanRent%2FGedeelde%20documenten%2FGeneral%2F01%5FRyanRent%26Co%2F01%5FWoningen%2FGroenelaan%2030B%2C%20Schiedam%2F3%5FVerhuur | S26: https://ryanrent.sharepoint.com/sites/RyanRent/Gedeelde%20documenten/Forms/AllItems.aspx?id=%2Fsites%2FRyanRent%2FGedeelde%20documenten%2FGeneral%2F01%5FRyanRent%26Co%2F01%5FWoningen%2FGroenelaan%2030B%2C%20Schiedam%2F2%5FInhuur%2F2%5FInhuurovereenkomsten | T26: 2165.88 | U26: 190.22 | V26: 0 | AM26: Geen inhuur | BC26: 17 | BD26: Tradiro Services B.V. | BE26: particulier | BG26: facturen@tradiro.nl | BH26: null | BI26: Honderdland 960 | BJ26: 2678 PS | BK26: Maasdijk | BL26: Nederland | BM26: 59979135.0 | BO26: NL05 RABO 0154 0739 89 | BQ26: 275 | BR26: 2023-02-01 | BU26: onbepaalde_tijd | BV26: Onbepaalde tijd | BW26: 1430 | BX26: 1430 | BY26: 1558.7 | BZ26: 0.09 | CA26: 0 | CB26: 0 | CC26: 250 | CD26: 2165.88 | CE26: ryanrent | CF26: 0 | CG26: 0 | CH26: 0 | CI26: 0 | CJ26: 0 | CK26: 0 | CL26: 1 | CM26: 0 | CN26: basis | CO26: 1430 | CP26: 17160 | CR26: Verhuurd (onbepaald) | CS26: 0
A27: 0026 | B27: 48 | C27: Chopinstraat 39C | D27: 3131 DB | E27: Vlaardingen | F27: Vakantiepark | H27: 3 | I27: 6 | J27: 1 | K27: Factuur | P27: https://ryanrent.sharepoint.com/sites/RyanRent/Gedeelde%20documenten/Forms/AllItems.aspx?id=%2Fsites%2FRyanRent%2FGedeelde%20documenten%2FGeneral%2F01%5FRyanRent%26Co%2F01%5FWoningen%2FChopinstraat%2039C%20Vlaardingen | Q27: https://ryanrent.sharepoint.com/sites/RyanRent/Gedeelde%20documenten/Forms/AllItems.aspx?id=%2Fsites%2FRyanRent%2FGedeelde%20documenten%2FGeneral%2F01%5FRyanRent%26Co%2F01%5FWoningen%2FChopinstraat%2039C%20Vlaardingen%2F2%5FInhuur | R27: https://ryanrent.sharepoint.com/sites/RyanRent/Gedeelde%20documenten/Forms/AllItems.aspx?id=%2Fsites%2FRyanRent%2FGedeelde%20documenten%2FGeneral%2F01%5FRyanRent%26Co%2F01%5FWoningen%2FChopinstraat%2039C%20Vlaardingen%2F3%5FVerhuur | S27: https://ryanrent.sharepoint.com/sites/RyanRent/Gedeelde%20documenten/Forms/AllItems.aspx?id=%2Fsites%2FRyanRent%2FGedeelde%20documenten%2FGeneral%2F01%5FRyanRent%26Co%2F01%5FWoningen%2FChopinstraat%2039C%20Vlaardingen%2F2%5FInhuur%2F2%5FInhuurovereenkomsten | T27: 1763.53 | U27: 255.59 | V27: 0 | W27: 984 | X27: Park Wonen BV | Y27: bedrijf | AA27: info@parkwonen.nl | AB27: 010 — 844 25 52 | AC27: Kruisplein 488a | AD27: 3012 CC | AE27: Rotterdam | AG27: 64549836 | AI27: NLO4 RABO 0307 5644 79 | AJ27: 818 | AK27: 2019-09-16 | AM27: Onbepaalde tijd | AN27: 12 | AO27: 1 | AT27: 0 | AU27: 1600 | AV27: 1744 | AW27: 0.09 | AY27: 0 | BA27: 0 | BB27: 0 | BV27: Leegstand | CD27: 1763.53 | CO27: -1600 | CP27: -19200 | CQ27: -100 | CR27: Beschikbaar | CS27: 0
A28: 0027 | B28: 49 | C28: Buizerdstraat 210 | D28: 3145 AD | E28: Maassluis | F28: Appartement | H28: 5 | I28: 5 | J28: 1 | K28: Factuur | P28: https://ryanrent.sharepoint.com/sites/RyanRent/Gedeelde%20documenten/Forms/AllItems.aspx?id=%2Fsites%2FRyanRent%2FGedeelde%20documenten%2FGeneral%2F01%5FRyanRent%26Co%2F01%5FWoningen%2FBuizerdstraat%20210%20Maassluis | Q28: https://ryanrent.sharepoint.com/sites/RyanRent/Gedeelde%20documenten/Forms/AllItems.aspx?id=%2Fsites%2FRyanRent%2FGedeelde%20documenten%2FGeneral%2F01%5FRyanRent%26Co%2F01%5FWoningen%2FBuizerdstraat%20210%20Maassluis%2F2%5FInhuur | R28: https://ryanrent.sharepoint.com/sites/RyanRent/Gedeelde%20documenten/Forms/AllItems.aspx?id=%2Fsites%2FRyanRent%2FGedeelde%20documenten%2FGeneral%2F01%5FRyanRent%26Co%2F01%5FWoningen%2FBuizerdstraat%20210%20Maassluis%2F3%5FVerhuur | S28: https://ryanrent.sharepoint.com/sites/RyanRent/Gedeelde%20documenten/Forms/AllItems.aspx?id=%2Fsites%2FRyanRent%2FGedeelde%20documenten%2FGeneral%2F01%5FRyanRent%26Co%2F01%5FWoningen%2FBuizerdstraat%20210%20Maassluis%2F2%5FInhuur%2F2%5FInhuurovereenkomsten | T28: 1442.35 | U28: 142.75 | V28: 0 | AM28: Geen inhuur | BC28: 17 | BD28: Tradiro Services B.V. | BE28: particulier | BG28: facturen@tradiro.nl | BH28: null | BI28: Honderdland 960 | BJ28: 2678 PS | BK28: Maasdijk | BL28: Nederland | BM28: 59979135.0 | BO28: NL05 RABO 0154 0739 89 | BQ28: 276 | BR28: 2023-03-01 | BU28: onbepaalde_tijd | BV28: Onbepaalde tijd | BW28: 1677.89 | BX28: 1677.89 | BY28: 1828.9 | BZ28: 0.09 | CA28: 0 | CB28: 0 | CC28: 0 | CD28: 0 | CE28: ryanrent | CF28: 0 | CG28: 0 | CH28: 0 | CI28: 0 | CJ28: 0 | CK28: 0 | CL28: 0 | CM28: 0 | CO28: 1677.89 | CP28: 20134.68 | CR28: Verhuurd (onbepaald) | CS28: 0
A29: 0028 | B29: 50 | C29: Lange kruisweg 12 | D29: 2676 BL | E29: Maasdijk | F29: Appartement | H29: 4 | I29: 8 | J29: 1 | K29: DS | M29: 1005 | P29: https://ryanrent.sharepoint.com/sites/RyanRent/Gedeelde%20documenten/Forms/AllItems.aspx?id=%2Fsites%2FRyanRent%2FGedeelde%20documenten%2FGeneral%2F01%5FRyanRent%26Co%2F01%5FWoningen%2FLange%20Kruisweg%2012%20Maasdijk | T29: 1954.12 | U29: 272.64 | V29: 0 | AM29: Geen inhuur | BC29: 17 | BD29: Tradiro Services B.V. | BE29: particulier | BG29: facturen@tradiro.nl | BH29: null | BI29: Honderdland 960 | BJ29: 2678 PS | BK29: Maasdijk | BL29: Nederland | BM29: 59979135.0 | BO29: NL05 RABO 0154 0739 89 | BQ29: 273 | BR29: 2023-03-01 | BU29: onbepaalde_tijd | BV29: Onbepaalde tijd | BW29: 2928.69 | BX29: 2928.69 | BY29: 3192.27 | BZ29: 0.09 | CA29: 0 | CB29: 0 | CC29: 0 | CD29: 1954.12 | CE29: ryanrent | CF29: 0 | CG29: 0 | CH29: 0 | CI29: 0 | CJ29: 0 | CK29: 0 | CL29: 0 | CM29: 0 | CO29: 2928.69 | CP29: 35144.28 | CR29: Verhuurd (onbepaald) | CS29: 0
A30: 0029 | B30: 51 | C30: Madeliefstraat 46C | D30: 3083TJ | E30: Rotterdam | F30: Appartement | H30: 3 | I30: 3 | J30: 1 | K30: DS | P30: https://ryanrent.sharepoint.com/sites/RyanRent/Gedeelde%20documenten/Forms/AllItems.aspx?id=%2Fsites%2FRyanRent%2FGedeelde%20documenten%2FGeneral%2F01%5FRyanRent%26Co%2F01%5FWoningen%2FMadeliefstraat%2046c%20Rotterdam | Q30: https://ryanrent.sharepoint.com/sites/RyanRent/Gedeelde%20documenten/Forms/AllItems.aspx?id=%2Fsites%2FRyanRent%2FGedeelde%20documenten%2FGeneral%2F01%5FRyanRent%26Co%2F01%5FWoningen%2FMadeliefstraat%2046c%20Rotterdam%2F2%5FInhuur | R30: https://ryanrent.sharepoint.com/sites/RyanRent/Gedeelde%20documenten/Forms/AllItems.aspx?id=%2Fsites%2FRyanRent%2FGedeelde%20documenten%2FGeneral%2F01%5FRyanRent%26Co%2F01%5FWoningen%2FMadeliefstraat%2046c%20Rotterdam%2F3%5FVerhuur | S30: https://ryanrent.sharepoint.com/sites/RyanRent/Gedeelde%20documenten/Forms/AllItems.aspx?id=%2Fsites%2FRyanRent%2FGedeelde%20documenten%2FGeneral%2F01%5FRyanRent%26Co%2F01%5FWoningen%2FMadeliefstraat%2046c%20Rotterdam%2F2%5FInhuur%2F2%5FInhuurovereenkomsten | T30: 1877.65 | U30: 200 | V30: 0 | W30: 850 | X30: M. Kathiravelu | Y30: particulier | AJ30: 659 | AK30: 2024-10-01 | AL30: 2026-09-30 | AM30: Actief | AO30: 1 | AT30: 1350 | AU30: 1350 | AV30: 1471.5 | AW30: 0.09 | AX30: 0 | AY30: 0 | AZ30: 0 | BA30: 0 | BB30: 0 | BC30: 329 | BD30: RNDV Industries | BE30: particulier | BG30: laura.brackiene@rndv.eu | BH30: +37062054093 | BI30: Taikos pr. 52C | BK30: Klipeda | BL30: Litouwen | BM30: 1304203983 | BQ30: 146 | BR30: 2024-10-01 | BS30: 2026-09-30 | BT30: 12 | BU30: bepaalde_tijd | BV30: Actief | BW30: 1977.9 | BX30: 2212.9 | BY30: 2412.06 | BZ30: 0.09 | CA30: 200 | CB30: 35 | CC30: 0 | CD30: 1877.65 | CE30: ryanrent | CF30: 1 | CG30: 1 | CH30: 1 | CI30: 0 | CJ30: 0 | CK30: 0 | CL30: 0 | CM30: 0 | CO30: 862.9 | CP30: 10354.8 | CQ30: 63.92 | CR30: Verhuurd | CS30: 251
A31: 0030 | B31: 52 | C31: Curacaolaan 88 | D31: 3131 XD | E31: Vlaardingen | F31: Vakantiepark | H31: 2 | I31: 3 | J31: 1 | K31: Factuur | P31: https://ryanrent.sharepoint.com/sites/RyanRent/Gedeelde%20documenten/Forms/AllItems.aspx?id=%2Fsites%2FRyanRent%2FGedeelde%20documenten%2FGeneral%2F01%5FRyanRent%26Co%2F01%5FWoningen%2FCuracaolaan%2088%20Vlaardingen | T31: 2054.12 | U31: 297.55 | V31: 0 | AM31: Geen inhuur | BC31: 17 | BD31: Tradiro Services B.V. | BE31: particulier | BG31: facturen@tradiro.nl | BH31: null | BI31: Honderdland 960 | BJ31: 2678 PS | BK31: Maasdijk | BL31: Nederland | BM31: 59979135.0 | BO31: NL05 RABO 0154 0739 89 | BQ31: 302 | BR31: 2026-01-14 | BU31: bepaalde_tijd | BV31: Onbepaalde tijd | BW31: 0 | BX31: 895 | BY31: 975.55 | BZ31: 0.09 | CA31: 297.55 | CB31: 354.76 | CC31: 0 | CD31: 2054.12 | CE31: ryanrent | CF31: 0 | CG31: 0 | CH31: 0 | CI31: 0 | CJ31: 0 | CK31: 0 | CL31: 0 | CM31: 0 | CO31: 895 | CP31: 10740 | CR31: Verhuurd (onbepaald) | CS31: 0
A32: 0031 | B32: 53 | C32: Hogenbanweg 331 | D32: 3112 CK | E32: Schiedam | F32: Appartement | H32: 2 | I32: 3 | J32: 1 | K32: DS | P32: https://ryanrent.sharepoint.com/sites/RyanRent/Gedeelde%20documenten/Forms/AllItems.aspx?id=%2Fsites%2FRyanRent%2FGedeelde%20documenten%2FGeneral%2F01%5FRyanRent%26Co%2F01%5FWoningen%2FHogenbanweg%20331%20Schiedam | T32: 1974.12 | U32: 195.97 | V32: 0 | AM32: Geen inhuur | BV32: Leegstand | CD32: 1974.12 | CO32: 0 | CP32: 0 | CR32: Beschikbaar | CS32: 0
A33: 0032 | B33: 54 | C33: Jacob van offwegenlaan 26 | D33: 2282 HR | E33: Rijswijk | F33: Appartement | H33: 4 | I33: 4 | J33: 1 | K33: Factuur | P33: https://ryanrent.sharepoint.com/sites/RyanRent/Gedeelde%20documenten/Forms/AllItems.aspx?id=%2Fsites%2FRyanRent%2FGedeelde%20documenten%2FGeneral%2F01%5FRyanRent%26Co%2F01%5FWoningen%2FJacob%20van%20Lennepstraat%2013a | T33: 2065.88 | U33: 200 | V33: 0 | AM33: Geen inhuur | BV33: Leegstand | CD33: 2065.88 | CO33: 0 | CP33: 0 | CR33: Beschikbaar | CS33: 0
A34: 0033 | B34: 55 | C34: Kethelweg 66C | D34: 3135 GM | E34: Vlaardingen | F34: Vakantiepark | H34: 3 | I34: 5 | J34: 1 | K34: Factuur | P34: https://ryanrent.sharepoint.com/sites/RyanRent/Gedeelde%20documenten/Forms/AllItems.aspx?id=%2Fsites%2FRyanRent%2FGedeelde%20documenten%2FGeneral%2F01%5FRyanRent%26Co%2F01%5FWoningen%2FKethelweg%2066C%20Vlaardingen | T34: 2444.71 | U34: 370.02 | V34: 0 | AM34: Geen inhuur | BC34: 17 | BD34: Tradiro Services B.V. | BE34: particulier | BG34: facturen@tradiro.nl | BH34: null | BI34: Honderdland 960 | BJ34: 2678 PS | BK34: Maasdijk | BL34: Nederland | BM34: 59979135.0 | BO34: NL05 RABO 0154 0739 89 | BQ34: 268 | BR34: 2023-03-01 | BU34: onbepaalde_tijd | BV34: Onbepaalde tijd | BW34: 2082 | BX34: 2082 | BY34: 2269.38 | BZ34: 0.09 | CA34: 0 | CB34: 0 | CC34: 375 | CD34: 2000 | CE34: ryanrent | CF34: 0 | CG34: 0 | CH34: 0 | CI34: 0 | CJ34: 0 | CK34: 0 | CL34: 1 | CM34: 0 | CN34: intensief | CO34: 2082 | CP34: 24984 | CR34: Verhuurd (onbepaald) | CS34: 0
A35: 0034 | B35: 56 | C35: Kethelweg 68A | D35: 3135 GM | E35: Vlaardingen | F35: Vakantiepark | H35: 3 | I35: 5 | J35: 1 | K35: Factuur | P35: https://ryanrent.sharepoint.com/sites/RyanRent/Gedeelde%20documenten/Forms/AllItems.aspx?id=%2Fsites%2FRyanRent%2FGedeelde%20documenten%2FGeneral%2F01%5FRyanRent%26Co%2F01%5FWoningen%2FKethelweg%2068A%20Vlaardingen | T35: 2108.7 | U35: 491.73 | V35: 0 | AM35: Geen inhuur | BC35: 17 | BD35: Tradiro Services B.V. | BE35: particulier | BG35: facturen@tradiro.nl | BH35: null | BI35: Honderdland 960 | BJ35: 2678 PS | BK35: Maasdijk | BL35: Nederland | BM35: 59979135.0 | BO35: NL05 RABO 0154 0739 89 | BQ35: 274 | BR35: 2023-03-01 | BU35: onbepaalde_tijd | BV35: Onbepaalde tijd | BW35: 2082 | BX35: 2082 | BY35: 2269.38 | BZ35: 0.09 | CA35: 0 | CB35: 0 | CC35: 0 | CD35: 2000 | CE35: ryanrent | CF35: 0 | CG35: 0 | CH35: 0 | CI35: 0 | CJ35: 0 | CK35: 0 | CL35: 0 | CM35: 0 | CO35: 2082 | CP35: 24984 | CR35: Verhuurd (onbepaald) | CS35: 0
A36: 0035 | B36: 57 | C36: Messchaertplein 39 | D36: 3131 TG | E36: Vlaardingen | F36: Vakantiepark | H36: 2 | I36: 3 | J36: 1 | K36: Factuur | P36: https://ryanrent.sharepoint.com/sites/RyanRent/Gedeelde%20documenten/Forms/AllItems.aspx?id=%2Fsites%2FRyanRent%2FGedeelde%20documenten%2FGeneral%2F01%5FRyanRent%26Co%2F01%5FWoningen%2FMesschaertplein%2039%20Vlaardingen | T36: 2160 | U36: 160.42 | V36: 0 | W36: 984 | X36: Park Wonen BV | Y36: bedrijf | AA36: info@parkwonen.nl | AB36: 010 — 844 25 52 | AC36: Kruisplein 488a | AD36: 3012 CC | AE36: Rotterdam | AG36: 64549836 | AI36: NLO4 RABO 0307 5644 79 | AJ36: 814 | AK36: 2022-11-14 | AM36: Onbepaalde tijd | AN36: 12 | AO36: 1 | AT36: 0 | AU36: 1300 | AV36: 1417 | AW36: 0.09 | AX36: 1300 | AY36: 0 | BA36: 0 | BB36: 0 | BV36: Leegstand | CD36: 2160 | CO36: -1300 | CP36: -15600 | CQ36: -100 | CR36: Beschikbaar | CS36: 0
A37: 0036 | B37: 58 | C37: Messchaertplein 40 | D37: 3131 TG | E37: Vlaardingen | F37: Vakantiepark | H37: 3 | I37: 5 | J37: 1 | K37: Factuur | P37: https://ryanrent.sharepoint.com/sites/RyanRent/Gedeelde%20documenten/Forms/AllItems.aspx?id=%2Fsites%2FRyanRent%2FGedeelde%20documenten%2FGeneral%2F01%5FRyanRent%26Co%2F01%5FWoningen%2FMesschaertplein%2040%20Vlaardingen | T37: 2149.41 | U37: 332.55 | V37: 0 | W37: 984 | X37: Park Wonen BV | Y37: bedrijf | AA37: info@parkwonen.nl | AB37: 010 — 844 25 52 | AC37: Kruisplein 488a | AD37: 3012 CC | AE37: Rotterdam | AG37: 64549836 | AI37: NLO4 RABO 0307 5644 79 | AJ37: 805 | AK37: 2022-11-14 | AM37: Onbepaalde tijd | AN37: 12 | AO37: 1 | AT37: 0 | AU37: 1300 | AV37: 1417 | AW37: 0.09 | AX37: 1300 | AY37: 0 | BA37: 0 | BB37: 0 | BV37: Leegstand | CD37: 2149.41 | CO37: -1300 | CP37: -15600 | CQ37: -100 | CR37: Beschikbaar | CS37: 0
A38: 0037 | B38: 59 | C38: Westfrankelandsestraat 108B | D38: 3117 AW | E38: Schiedam | F38: Vakantiepark | H38: 3 | I38: 4 | J38: 1 | K38: Factuur | T38: 1937.65 | U38: 350 | V38: 0 | AM38: Geen inhuur | BC38: 17 | BD38: Tradiro Services B.V. | BE38: particulier | BG38: facturen@tradiro.nl | BH38: null | BI38: Honderdland 960 | BJ38: 2678 PS | BK38: Maasdijk | BL38: Nederland | BM38: 59979135.0 | BO38: NL05 RABO 0154 0739 89 | BQ38: 420 | BR38: 2026-01-14 | BU38: bepaalde_tijd | BV38: Onbepaalde tijd | BW38: 2196.51 | BX38: 2546.51 | BY38: 2775.7 | BZ38: 0.09 | CA38: 350 | CB38: 43.49 | CC38: 0 | CD38: 1937.65 | CE38: ryanrent | CF38: 0 | CG38: 0 | CH38: 0 | CI38: 0 | CJ38: 0 | CK38: 0 | CL38: 0 | CM38: 0 | CO38: 2546.51 | CP38: 30558.12 | CR38: Verhuurd (onbepaald) | CS38: 0
A39: 0038 | B39: 60 | C39: Westfrankelandsestraat 108 | D39: 3117 AW | E39: Schiedam | F39: Appartement | H39: 4 | I39: 4 | J39: 1 | K39: Factuur | P39: https://ryanrent.sharepoint.com/sites/RyanRent/Gedeelde%20documenten/Forms/AllItems.aspx?id=%2Fsites%2FRyanRent%2FGedeelde%20documenten%2FGeneral%2F01%5FRyanRent%26Co%2F01%5FWoningen%2FWestfrankelandsestraat%20108%20Schiedam | Q39: https://ryanrent.sharepoint.com/sites/RyanRent/Gedeelde%20documenten/Forms/AllItems.aspx?id=%2Fsites%2FRyanRent%2FGedeelde%20documenten%2FGeneral%2F01%5FRyanRent%26Co%2F01%5FWoningen%2FWestfrankelandsestraat%20108%20Schiedam%2F2%5FInhuur | R39: https://ryanrent.sharepoint.com/sites/RyanRent/Gedeelde%20documenten/Forms/AllItems.aspx?id=%2Fsites%2FRyanRent%2FGedeelde%20documenten%2FGeneral%2F01%5FRyanRent%26Co%2F01%5FWoningen%2FWestfrankelandsestraat%20108%20Schiedam%2F3%5FVerhuur | S39: https://ryanrent.sharepoint.com/sites/RyanRent/Gedeelde%20documenten/Forms/AllItems.aspx?id=%2Fsites%2FRyanRent%2FGedeelde%20documenten%2FGeneral%2F01%5FRyanRent%26Co%2F01%5FWoningen%2FWestfrankelandsestraat%20108%20Schiedam%2F2%5FInhuur%2F2%5FInhuurovereenkomsten | T39: 2202.35 | U39: 30.28 | V39: 0 | AM39: Geen inhuur | BV39: Leegstand | CD39: 2202.35 | CO39: 0 | CP39: 0 | CR39: Beschikbaar | CS39: 0
A40: 0039 | B40: 61 | C40: Inundatiestraat 3 | D40: 4551VE | E40: Sas van Gent | F40: Appartement | H40: 4 | I40: 4 | J40: 1 | K40: DS | L40: 5103 | M40: 1005 | P40: https://ryanrent.sharepoint.com/sites/RyanRent/Gedeelde%20documenten/Forms/AllItems.aspx?id=%2Fsites%2FRyanRent%2FGedeelde%20documenten%2FGeneral%2F01%5FRyanRent%26Co%2F01%5FWoningen%2FInundatiestraat%203%20Sas%20van%20Gent | Q40: https://ryanrent.sharepoint.com/sites/RyanRent/Gedeelde%20documenten/Forms/AllItems.aspx?id=%2Fsites%2FRyanRent%2FGedeelde%20documenten%2FGeneral%2F01%5FRyanRent%26Co%2F01%5FWoningen%2FInundatiestraat%203%20Sas%20van%20Gent%2F2%5FInhuur | R40: https://ryanrent.sharepoint.com/sites/RyanRent/Gedeelde%20documenten/Forms/AllItems.aspx?id=%2Fsites%2FRyanRent%2FGedeelde%20documenten%2FGeneral%2F01%5FRyanRent%26Co%2F01%5FWoningen%2FInundatiestraat%203%20Sas%20van%20Gent%2F3%5FVerhuur | S40: https://ryanrent.sharepoint.com/sites/RyanRent/Gedeelde%20documenten/Forms/AllItems.aspx?id=%2Fsites%2FRyanRent%2FGedeelde%20documenten%2FGeneral%2F01%5FRyanRent%26Co%2F01%5FWoningen%2FInundatiestraat%203%20Sas%20van%20Gent%2F2%5FInhuur%2F2%5FInhuurovereenkomsten | T40: 2315.29 | U40: 250 | V40: 0 | W40: 644 | X40: J.G. van Pieterson | Y40: particulier | AC40: C.G. Roosweg 28 | AE40: Schoonhoven | AF40: Nederland | AI40: NL82 ABNA 0886 0378 24 | AJ40: 608 | AK40: 2024-09-01 | AL40: 2026-08-31 | AM40: Actief | AO40: 1 | AT40: 1500 | AU40: 1500 | AV40: 1635 | AW40: 0.09 | AX40: 0 | AY40: 0 | AZ40: 0 | BA40: 0 | BB40: 0 | BC40: 329 | BD40: RNDV Industries | BE40: particulier | BG40: laura.brackiene@rndv.eu | BH40: +37062054093 | BI40: Taikos pr. 52C | BK40: Klipeda | BL40: Litouwen | BM40: 1304203983 | BQ40: 90 | BR40: 2024-09-01 | BS40: 2026-08-31 | BT40: 6 | BU40: bepaalde_tijd | BV40: Actief | BW40: 2375 | BX40: 2625 | BY40: 2861.25 | BZ40: 0.09 | CA40: 250 | CB40: 0 | CC40: 375 | CD40: 2315.29 | CE40: ryanrent | CF40: 1 | CG40: 1 | CH40: 1 | CI40: 0 | CJ40: 0 | CK40: 0 | CL40: 1 | CM40: 0 | CN40: intensief | CO40: 1125 | CP40: 13500 | CQ40: 75 | CR40: Verhuurd | CS40: 221
A41: 0040 | B41: 62 | C41: Beatrixstraat 3 | D41: 3181GA | E41: Rozenburg | F41: Appartement | H41: 3 | I41: 3 | J41: 1 | K41: DS | L41: 1003 | M41: 1005 | P41: https://ryanrent.sharepoint.com/sites/RyanRent/Gedeelde%20documenten/Forms/AllItems.aspx?id=%2Fsites%2FRyanRent%2FGedeelde%20documenten%2FGeneral%2F01%5FRyanRent%26Co%2F01%5FWoningen%2FBeatrixstraat%203%2C%20Rozenburg | Q41: https://ryanrent.sharepoint.com/sites/RyanRent/Gedeelde%20documenten/Forms/AllItems.aspx?id=%2Fsites%2FRyanRent%2FGedeelde%20documenten%2FGeneral%2F01%5FRyanRent%26Co%2F01%5FWoningen%2FBeatrixstraat%203%2C%20Rozenburg%2F2%5FInhuur | R41: https://ryanrent.sharepoint.com/sites/RyanRent/Gedeelde%20documenten/Forms/AllItems.aspx?id=%2Fsites%2FRyanRent%2FGedeelde%20documenten%2FGeneral%2F01%5FRyanRent%26Co%2F01%5FWoningen%2FBeatrixstraat%203%2C%20Rozenburg%2F3%5FVerhuur | S41: https://ryanrent.sharepoint.com/sites/RyanRent/Gedeelde%20documenten/Forms/AllItems.aspx?id=%2Fsites%2FRyanRent%2FGedeelde%20documenten%2FGeneral%2F01%5FRyanRent%26Co%2F01%5FWoningen%2FBeatrixstraat%203%2C%20Rozenburg%2F2%5FInhuur%2F2%5FInhuurovereenkomsten | T41: 2507.06 | U41: 250 | V41: 0 | AM41: Geen inhuur | BC41: 220 | BD41: Impes Service S.p.A. | BE41: particulier | BG41: fatture.olanda@impesservice.it, Nicola.pisani@impesservice.it | BH41: +31 6 87020773 | BI41: President Kennedylaan 19 | BK41: 's-Gravenhage | BL41: Nederland | BQ41: 35 | BR41: 2022-10-01 | BS41: 2026-10-09 | BT41: 12 | BU41: bepaalde_tijd | BV41: Actief | BW41: 3050 | BX41: 3300 | BY41: 3597 | BZ41: 0.09 | CA41: 250 | CB41: 0 | CC41: 250 | CD41: 2507.06 | CE41: ryanrent | CF41: 0 | CG41: 0 | CH41: 0 | CI41: 0 | CJ41: 0 | CK41: 0 | CL41: 1 | CM41: 0 | CN41: basis | CO41: 3300 | CP41: 39600 | CR41: Verhuurd | CS41: 260
A42: 0041 | B42: 63 | C42: Nunspeetlaan 53 | D42: 2573 HB | E42: Den Haag | F42: Vakantiepark | H42: 5 | I42: 4 | J42: 1 | K42: Factuur | P42: https://ryanrent.sharepoint.com/sites/RyanRent/Gedeelde%20documenten/Forms/AllItems.aspx?id=%2Fsites%2FRyanRent%2FGedeelde%20documenten%2FGeneral%2F01%5FRyanRent%26Co%2F01%5FWoningen%2FNunspeetlaan%2053%20Den%20Haag | Q42: https://ryanrent.sharepoint.com/sites/RyanRent/Gedeelde%20documenten/Forms/AllItems.aspx?id=%2Fsites%2FRyanRent%2FGedeelde%20documenten%2FGeneral%2F01%5FRyanRent%26Co%2F01%5FWoningen%2FNunspeetlaan%2053%20Den%20Haag%2F2%5FInhuur | R42: https://ryanrent.sharepoint.com/sites/RyanRent/Gedeelde%20documenten/Forms/AllItems.aspx?id=%2Fsites%2FRyanRent%2FGedeelde%20documenten%2FGeneral%2F01%5FRyanRent%26Co%2F01%5FWoningen%2FNunspeetlaan%2053%20Den%20Haag%2F3%5FVerhuur | S42: https://ryanrent.sharepoint.com/sites/RyanRent/Gedeelde%20documenten/Forms/AllItems.aspx?id=%2Fsites%2FRyanRent%2FGedeelde%20documenten%2FGeneral%2F01%5FRyanRent%26Co%2F01%5FWoningen%2FNunspeetlaan%2053%20Den%20Haag%2F2%5FInhuur%2F2%5FInhuurovereenkomsten | T42: 1834.12 | U42: 0 | V42: 0 | AM42: Geen inhuur | BC42: 17 | BD42: Tradiro Services B.V. | BE42: particulier | BG42: facturen@tradiro.nl | BH42: null | BI42: Honderdland 960 | BJ42: 2678 PS | BK42: Maasdijk | BL42: Nederland | BM42: 59979135.0 | BO42: NL05 RABO 0154 0739 89 | BQ42: 444 | BR42: 2026-01-14 | BU42: bepaalde_tijd | BV42: Onbepaalde tijd | BW42: 0 | BX42: 0 | BY42: 0 | BZ42: 0.09 | CA42: 0 | CB42: 22.82 | CC42: 0 | CD42: 1834.12 | CE42: ryanrent | CF42: 0 | CG42: 0 | CH42: 0 | CI42: 0 | CJ42: 0 | CK42: 0 | CL42: 0 | CM42: 0 | CO42: 0 | CP42: 0 | CR42: Verhuurd (onbepaald) | CS42: 0
A43: 0042 | B43: 64 | C43: Parallelweg 110A | D43: 3131 DK | E43: Vlaardingen | F43: Vakantiepark | H43: 3 | I43: 5 | J43: 1 | K43: Factuur | P43: https://ryanrent.sharepoint.com/sites/RyanRent/Gedeelde%20documenten/Forms/AllItems.aspx?id=%2Fsites%2FRyanRent%2FGedeelde%20documenten%2FGeneral%2F01%5FRyanRent%26Co%2F01%5FWoningen%2FParallelweg%20110A%20Vlaardingen | Q43: https://ryanrent.sharepoint.com/sites/RyanRent/Gedeelde%20documenten/Forms/AllItems.aspx?id=%2Fsites%2FRyanRent%2FGedeelde%20documenten%2FGeneral%2F01%5FRyanRent%26Co%2F01%5FWoningen%2FParallelweg%20110A%20Vlaardingen%2F2%5FInhuur | R43: https://ryanrent.sharepoint.com/sites/RyanRent/Gedeelde%20documenten/Forms/AllItems.aspx?id=%2Fsites%2FRyanRent%2FGedeelde%20documenten%2FGeneral%2F01%5FRyanRent%26Co%2F01%5FWoningen%2FParallelweg%20110A%20Vlaardingen%2F3%5FVerhuur | S43: https://ryanrent.sharepoint.com/sites/RyanRent/Gedeelde%20documenten/Forms/AllItems.aspx?id=%2Fsites%2FRyanRent%2FGedeelde%20documenten%2FGeneral%2F01%5FRyanRent%26Co%2F01%5FWoningen%2FParallelweg%20110A%20Vlaardingen%2F2%5FInhuur%2F2%5FInhuurovereenkomsten | T43: 2056.47 | U43: 0 | V43: 0 | W43: 258 | X43: Parkwonen | Y43: particulier | AA43: info@parkwonen.nl | AC43: Kruisplein 488A | AE43: Rotterdam | AF43: Nederland | AI43: NL04 RABO 0307 5644 79 | AJ43: 871 | AM43: Onbepaalde tijd | AO43: 1 | AT43: 1688 | AU43: 1688 | AV43: 1839.92 | AW43: 0.09 | AX43: 0 | AY43: 0 | AZ43: 0 | BA43: 0 | BB43: 0 | BV43: Leegstand | CD43: 2056.47 | CO43: -1688 | CP43: -20256 | CQ43: -100 | CR43: Beschikbaar | CS43: 0
A44: 0043 | B44: 65 | C44: Amperelaan 23 | D44: 8451BW | E44: Oudeschoot | F44: Appartement | H44: 4 | I44: 4 | J44: 1 | K44: DS | L44: 0623 | M44: 1005 | T44: 2275.29 | U44: 300 | V44: 0 | AM44: Geen inhuur | BV44: Leegstand | CD44: 2275.29 | CO44: 0 | CP44: 0 | CR44: Beschikbaar | CS44: 0
A45: 0044 | B45: 66 | C45: Pleinweg 101a | D45: 3081JH | E45: Rotterdam | F45: Vakantiepark | H45: 2 | I45: 3 | J45: 1 | K45: Factuur | L45: 3010 | M45: 1005 | P45: https://ryanrent.sharepoint.com/sites/RyanRent/Gedeelde%20documenten/Forms/AllItems.aspx?id=%2Fsites%2FRyanRent%2FGedeelde%20documenten%2FGeneral%2F01%5FRyanRent%26Co%2F01%5FWoningen%2FPleinweg%20101a%2C%20Rotterdam | Q45: https://ryanrent.sharepoint.com/sites/RyanRent/Gedeelde%20documenten/Forms/AllItems.aspx?id=%2Fsites%2FRyanRent%2FGedeelde%20documenten%2FGeneral%2F01%5FRyanRent%26Co%2F01%5FWoningen%2FPleinweg%20101a%2C%20Rotterdam%2F2%5FInhuur | R45: https://ryanrent.sharepoint.com/sites/RyanRent/Gedeelde%20documenten/Forms/AllItems.aspx?id=%2Fsites%2FRyanRent%2FGedeelde%20documenten%2FGeneral%2F01%5FRyanRent%26Co%2F01%5FWoningen%2FPleinweg%20101a%2C%20Rotterdam%2F3%5FVerhuur | S45: https://ryanrent.sharepoint.com/sites/RyanRent/Gedeelde%20documenten/Forms/AllItems.aspx?id=%2Fsites%2FRyanRent%2FGedeelde%20documenten%2FGeneral%2F01%5FRyanRent%26Co%2F01%5FWoningen%2FPleinweg%20101a%2C%20Rotterdam%2F2%5FInhuur%2F2%5FInhuurovereenkomsten | T45: 2040 | U45: 200 | V45: 0 | AM45: Geen inhuur | BV45: Leegstand | CD45: 2040 | CO45: 0 | CP45: 0 | CR45: Beschikbaar | CS45: 0
A46: 0045 | B46: 67 | C46: Pleinweg 101b | D46: 3081JH | E46: Rotterdam | F46: Vakantiepark | H46: 2 | I46: 3 | J46: 1 | K46: Factuur | L46: 8110 | M46: 1005 | P46: https://ryanrent.sharepoint.com/sites/RyanRent/Gedeelde%20documenten/Forms/AllItems.aspx?id=%2Fsites%2FRyanRent%2FGedeelde%20documenten%2FGeneral%2F01%5FRyanRent%26Co%2F01%5FWoningen%2FPleinweg%20101b%2C%20Rotterdam | Q46: https://ryanrent.sharepoint.com/sites/RyanRent/Gedeelde%20documenten/Forms/AllItems.aspx?id=%2Fsites%2FRyanRent%2FGedeelde%20documenten%2FGeneral%2F01%5FRyanRent%26Co%2F01%5FWoningen%2FPleinweg%20101b%2C%20Rotterdam%2F2%5FInhuur | R46: https://ryanrent.sharepoint.com/sites/RyanRent/Gedeelde%20documenten/Forms/AllItems.aspx?id=%2Fsites%2FRyanRent%2FGedeelde%20documenten%2FGeneral%2F01%5FRyanRent%26Co%2F01%5FWoningen%2FPleinweg%20101b%2C%20Rotterdam%2F3%5FVerhuur | S46: https://ryanrent.sharepoint.com/sites/RyanRent/Gedeelde%20documenten/Forms/AllItems.aspx?id=%2Fsites%2FRyanRent%2FGedeelde%20documenten%2FGeneral%2F01%5FRyanRent%26Co%2F01%5FWoningen%2FPleinweg%20101b%2C%20Rotterdam%2F2%5FInhuur%2F2%5FInhuurovereenkomsten | T46: 2175.29 | U46: 200 | V46: 0 | AM46: Geen inhuur | BV46: Leegstand | CD46: 2175.29 | CO46: 0 | CP46: 0 | CR46: Beschikbaar | CS46: 0
A47: 0046 | B47: 68 | C47: Nieuwenhoornstraat 46B | D47: 3082 VJ | E47: Rotterdam | F47: Appartement | H47: 3 | J47: 1 | K47: Factuur | L47: 3046 | M47: 1005 | P47: https://ryanrent.sharepoint.com/sites/RyanRent/Gedeelde%20documenten/Forms/AllItems.aspx?id=%2Fsites%2FRyanRent%2FGedeelde%20documenten%2FGeneral%2F01%5FRyanRent%26Co%2F01%5FWoningen%2FNieuwenhoornstraat%2046B%2C%20Rotterdam | Q47: https://ryanrent.sharepoint.com/sites/RyanRent/Gedeelde%20documenten/Forms/AllItems.aspx?id=%2Fsites%2FRyanRent%2FGedeelde%20documenten%2FGeneral%2F01%5FRyanRent%26Co%2F01%5FWoningen%2FNieuwenhoornstraat%2046B%2C%20Rotterdam%2F2%5FInhuur | R47: https://ryanrent.sharepoint.com/sites/RyanRent/Gedeelde%20documenten/Forms/AllItems.aspx?id=%2Fsites%2FRyanRent%2FGedeelde%20documenten%2FGeneral%2F01%5FRyanRent%26Co%2F01%5FWoningen%2FNieuwenhoornstraat%2046B%2C%20Rotterdam%2F3%5FVerhuur | S47: https://ryanrent.sharepoint.com/sites/RyanRent/Gedeelde%20documenten/Forms/AllItems.aspx?id=%2Fsites%2FRyanRent%2FGedeelde%20documenten%2FGeneral%2F01%5FRyanRent%26Co%2F01%5FWoningen%2FNieuwenhoornstraat%2046B%2C%20Rotterdam%2F2%5FInhuur%2F2%5FInhuurovereenkomsten | T47: 1957.65 | U47: 200 | V47: 0 | AM47: Geen inhuur | BC47: 330 | BD47: UAB Techsome | BE47: particulier | BG47: info@techsoma.lt | BI47: Šėtos g. 116-311 | BK47: Kėdainiai | BL47: Litouwen | BM47: 95342265.0 | BO47: LT80 7300 0101 8868 2143 | BQ47: 174 | BR47: 2025-01-01 | BS47: 2026-01-01 | BT47: 12 | BU47: bepaalde_tijd | BV47: Verlopen | BW47: 2186.1 | BX47: 2386.1 | BY47: 2600.85 | BZ47: 0.09 | CA47: 200 | CB47: 0 | CC47: 250 | CD47: 1957.65 | CE47: ryanrent | CF47: 1 | CG47: 1 | CH47: 1 | CI47: 0 | CJ47: 0 | CK47: 0 | CL47: 1 | CM47: 0 | CN47: basis | CO47: 2386.1 | CP47: 28633.2 | CR47: Beschikbaar | CS47: 0
A48: 0047 | B48: 69 | C48: Bisschopstraat 68 | D48: 8325BD | E48: Vollenhove | F48: Appartement | H48: 7 | I48: 6 | J48: 1 | K48: DS | L48: 0246 | M48: 1005 | P48: https://ryanrent.sharepoint.com/sites/RyanRent/Gedeelde%20documenten/Forms/AllItems.aspx?id=%2Fsites%2FRyanRent%2FGedeelde%20documenten%2FGeneral%2F01%5FRyanRent%26Co%2F01%5FWoningen%2FBisschopstraat%2068%2C%20Vollenhove | Q48: https://ryanrent.sharepoint.com/sites/RyanRent/Gedeelde%20documenten/Forms/AllItems.aspx?id=%2Fsites%2FRyanRent%2FGedeelde%20documenten%2FGeneral%2F01%5FRyanRent%26Co%2F01%5FWoningen%2FBisschopstraat%2068%2C%20Vollenhove%2F2%5FInhuur | R48: https://ryanrent.sharepoint.com/sites/RyanRent/Gedeelde%20documenten/Forms/AllItems.aspx?id=%2Fsites%2FRyanRent%2FGedeelde%20documenten%2FGeneral%2F01%5FRyanRent%26Co%2F01%5FWoningen%2FBisschopstraat%2068%2C%20Vollenhove%2F3%5FVerhuur | S48: https://ryanrent.sharepoint.com/sites/RyanRent/Gedeelde%20documenten/Forms/AllItems.aspx?id=%2Fsites%2FRyanRent%2FGedeelde%20documenten%2FGeneral%2F01%5FRyanRent%26Co%2F01%5FWoningen%2FBisschopstraat%2068%2C%20Vollenhove%2F2%5FInhuur%2F2%5FInhuurovereenkomsten | T48: 2295.29 | U48: 500 | V48: 0 | W48: 147 | X48: T. Hoolhorst | Y48: particulier | AA48: t.hoolhorst@gmail.com | AC48: Leliestraat 21 | AE48: Utrecht | AF48: Nederland | AI48: NL13 KNAB 0405 5294 14 | AJ48: 554 | AK48: 2022-03-01 | AM48: Onbepaalde tijd | AO48: 1 | AT48: 2914.8 | AU48: 2914.8 | AV48: 3177.13 | AW48: 0.09 | AX48: 0 | AY48: 0 | AZ48: 0 | BA48: 0 | BB48: 0 | BV48: Leegstand | CD48: 2295.29 | CO48: -2914.8 | CP48: -34977.6 | CQ48: -100 | CR48: Beschikbaar | CS48: 0
A49: 0048 | B49: 70 | C49: Bliek 41 | D49: 3225XB | E49: Hellevoetsluis | F49: Appartement | H49: 5 | I49: 5 | J49: 1 | K49: DS | L49: 1841 | P49: https://ryanrent.sharepoint.com/sites/RyanRent/Gedeelde%20documenten/Forms/AllItems.aspx?id=%2Fsites%2FRyanRent%2FGedeelde%20documenten%2FGeneral%2F01%5FRyanRent%26Co%2F01%5FWoningen%2FBliek%2041%2C%20Hellevoetsluis | Q49: https://ryanrent.sharepoint.com/sites/RyanRent/Gedeelde%20documenten/Forms/AllItems.aspx?id=%2Fsites%2FRyanRent%2FGedeelde%20documenten%2FGeneral%2F01%5FRyanRent%26Co%2F01%5FWoningen%2FBliek%2041%2C%20Hellevoetsluis%2F2%5FInhuur | R49: https://ryanrent.sharepoint.com/sites/RyanRent/Gedeelde%20documenten/Forms/AllItems.aspx?id=%2Fsites%2FRyanRent%2FGedeelde%20documenten%2FGeneral%2F01%5FRyanRent%26Co%2F01%5FWoningen%2FBliek%2041%2C%20Hellevoetsluis%2F3%5FVerhuur | S49: https://ryanrent.sharepoint.com/sites/RyanRent/Gedeelde%20documenten/Forms/AllItems.aspx?id=%2Fsites%2FRyanRent%2FGedeelde%20documenten%2FGeneral%2F01%5FRyanRent%26Co%2F01%5FWoningen%2FBliek%2041%2C%20Hellevoetsluis%2F2%5FInhuur%2F2%5FInhuurovereenkomsten | T49: 2356.47 | U49: 400 | V49: 0 | AM49: Geen inhuur | BV49: Leegstand | CD49: 2356.47 | CO49: 0 | CP49: 0 | CR49: Beschikbaar | CS49: 0
A50: 0049 | B50: 71 | C50: Bornerbroeksestraat 129A | D50: 7601BE | E50: Almelo | F50: Appartement | H50: 4 | I50: 4 | J50: 1 | K50: DS | L50: 7229 | M50: 1005 | P50: https://ryanrent.sharepoint.com/sites/RyanRent/Gedeelde%20documenten/Forms/AllItems.aspx?id=%2Fsites%2FRyanRent%2FGedeelde%20documenten%2FGeneral%2F01%5FRyanRent%26Co%2F01%5FWoningen%2FBornerbroeksestraat%20129a%2C%20Almelo | Q50: https://ryanrent.sharepoint.com/sites/RyanRent/Gedeelde%20documenten/Forms/AllItems.aspx?id=%2Fsites%2FRyanRent%2FGedeelde%20documenten%2FGeneral%2F01%5FRyanRent%26Co%2F01%5FWoningen%2FBornerbroeksestraat%20129a%2C%20Almelo%2F2%5FInhuur | R50: https://ryanrent.sharepoint.com/sites/RyanRent/Gedeelde%20documenten/Forms/AllItems.aspx?id=%2Fsites%2FRyanRent%2FGedeelde%20documenten%2FGeneral%2F01%5FRyanRent%26Co%2F01%5FWoningen%2FBornerbroeksestraat%20129a%2C%20Almelo%2F3%5FVerhuur | S50: https://ryanrent.sharepoint.com/sites/RyanRent/Gedeelde%20documenten/Forms/AllItems.aspx?id=%2Fsites%2FRyanRent%2FGedeelde%20documenten%2FGeneral%2F01%5FRyanRent%26Co%2F01%5FWoningen%2FBornerbroeksestraat%20129a%2C%20Almelo%2F2%5FInhuur%2F2%5FInhuurovereenkomsten | T50: 1714.12 | U50: 250 | V50: 0 | W50: 175 | X50: Dhr. J.L. Meerding | Y50: particulier | AA50: jlmeerding@gmai.com | AC50: Mauvezand 6 | AE50: Laren NH | AF50: Nederland | AI50: NL29 ABNA 0416 0042 29 | AJ50: 558 | AK50: 2022-09-01 | AL50: 2027-08-31 | AM50: Actief | AO50: 1 | AT50: 1972.46 | AU50: 1972.46 | AV50: 2149.98 | AW50: 0.09 | AX50: 0 | AY50: 0 | AZ50: 0 | BA50: 0 | BB50: 0 | BC50: 286 | BD50: Team Unica B.V. | BE50: particulier | BG50: facturen@teamunica.nl | BH50: 206 142 186 41 | BI50: Langeweg 15B | BK50: Oostvoorne | BL50: Nederland | BM50: 76348881 | BQ50: 43 | BR50: 2022-09-01 | BS50: 2027-08-31 | BT50: 4 | BU50: bepaalde_tijd | BV50: Actief | BW50: 2350 | BX50: 2600 | BY50: 2834 | BZ50: 0.09 | CA50: 250 | CB50: 0 | CC50: 250 | CD50: 1714.12 | CE50: ryanrent | CF50: 1 | CG50: 1 | CH50: 1 | CI50: 0 | CJ50: 0 | CK50: 0 | CL50: 1 | CM50: 0 | CN50: basis | CO50: 627.54 | CP50: 7530.48 | CQ50: 31.82 | CR50: Verhuurd | CS50: 586
A51: 0050 | B51: 72 | C51: Sint Josephstraat 61 | D51: 5017GD | E51: Tilburg | F51: Appartement | H51: 7 | I51: 7 | J51: 1 | K51: Factuur | M51: 1908 | P51: https://ryanrent.sharepoint.com/sites/RyanRent/Gedeelde%20documenten/Forms/AllItems.aspx?id=%2Fsites%2FRyanRent%2FGedeelde%20documenten%2FGeneral%2F01%5FRyanRent%26Co%2F01%5FWoningen%2FSint%20Josephstraat%2061%2C%20Tilburg | Q51: https://ryanrent.sharepoint.com/sites/RyanRent/Gedeelde%20documenten/Forms/AllItems.aspx?id=%2Fsites%2FRyanRent%2FGedeelde%20documenten%2FGeneral%2F01%5FRyanRent%26Co%2F01%5FWoningen%2FSint%20Josephstraat%2061%2C%20Tilburg%2F2%5FInhuur | R51: https://ryanrent.sharepoint.com/sites/RyanRent/Gedeelde%20documenten/Forms/AllItems.aspx?id=%2Fsites%2FRyanRent%2FGedeelde%20documenten%2FGeneral%2F01%5FRyanRent%26Co%2F01%5FWoningen%2FSint%20Josephstraat%2061%2C%20Tilburg%2F3%5FVerhuur | S51: https://ryanrent.sharepoint.com/sites/RyanRent/Gedeelde%20documenten/Forms/AllItems.aspx?id=%2Fsites%2FRyanRent%2FGedeelde%20documenten%2FGeneral%2F01%5FRyanRent%26Co%2F01%5FWoningen%2FSint%20Josephstraat%2061%2C%20Tilburg%2F2%5FInhuur%2F2%5FInhuurovereenkomsten | T51: 1710.59 | U51: 400 | V51: 0 | W51: 763 | X51: T. Eenhuistra/J. Pluimakers | Y51: particulier | AJ51: 732 | AK51: 2024-08-03 | AL51: 2026-08-02 | AM51: Actief | AO51: 1 | AT51: 3710.32 | AU51: 3742.83 | AV51: 4079.68 | AW51: 0.09 | AX51: 0 | AY51: 0 | AZ51: 0 | BA51: 0 | BB51: 0 | BC51: 312 | BD51: Welcome Housing B.V. | BE51: particulier | BG51: Invoices@hobij.nl | BH51: 0413-870000 | BI51: Heilig Hartplein 1 | BK51: Veghel | BL51: Nederland | BQ51: 227 | BR51: 2024-08-03 | BS51: 2026-08-02 | BT51: 6 | BU51: bepaalde_tijd | BV51: Actief | BW51: 4164 | BX51: 4564 | BY51: 4974.76 | BZ51: 0.09 | CA51: 400 | CB51: 0 | CC51: 0 | CD51: 1710.59 | CE51: ryanrent | CF51: 0 | CG51: 0 | CH51: 0 | CI51: 0 | CJ51: 0 | CK51: 0 | CL51: 0 | CM51: 0 | CO51: 821.17 | CP51: 9854.04 | CQ51: 21.94 | CR51: Verhuurd | CS51: 192
A52: 0051 | B52: 73 | C52: Coehoorn van Scheltingaweg 12 | D52: 8442EX | E52: Heerenveen | F52: Vakantiepark | H52: 3 | I52: 4 | J52: 1 | K52: Factuur | L52: 0312 | M52: 1005 | P52: https://ryanrent.sharepoint.com/sites/RyanRent/Gedeelde%20documenten/Forms/AllItems.aspx?id=%2Fsites%2FRyanRent%2FGedeelde%20documenten%2FGeneral%2F01%5FRyanRent%26Co%2F01%5FWoningen%2FCoehoorn%20van%20Scheltingaweg%2012%2C%20Heerenveen | Q52: https://ryanrent.sharepoint.com/sites/RyanRent/Gedeelde%20documenten/Forms/AllItems.aspx?id=%2Fsites%2FRyanRent%2FGedeelde%20documenten%2FGeneral%2F01%5FRyanRent%26Co%2F01%5FWoningen%2FCoehoorn%20van%20Scheltingaweg%2012%2C%20Heerenveen%2F2%5FInhuur | R52: https://ryanrent.sharepoint.com/sites/RyanRent/Gedeelde%20documenten/Forms/AllItems.aspx?id=%2Fsites%2FRyanRent%2FGedeelde%20documenten%2FGeneral%2F01%5FRyanRent%26Co%2F01%5FWoningen%2FCoehoorn%20van%20Scheltingaweg%2012%2C%20Heerenveen%2F3%5FVerhuur | S52: https://ryanrent.sharepoint.com/sites/RyanRent/Gedeelde%20documenten/Forms/AllItems.aspx?id=%2Fsites%2FRyanRent%2FGedeelde%20documenten%2FGeneral%2F01%5FRyanRent%26Co%2F01%5FWoningen%2FCoehoorn%20van%20Scheltingaweg%2012%2C%20Heerenveen%2F2%5FInhuur%2F2%5FInhuurovereenkomsten | T52: 2143.53 | U52: 200 | V52: 0 | AM52: Geen inhuur | BV52: Leegstand | CD52: 2143.53 | CO52: 0 | CP52: 0 | CR52: Beschikbaar | CS52: 0
A53: 0052 | B53: 74 | C53: Coehoorn van Scheltingaweg 66 | D53: 8442GA | E53: Heerenveen | F53: Vakantiepark | H53: 3 | I53: 4 | J53: 1 | K53: Factuur | L53: 8366 | M53: 1005 | P53: https://ryanrent.sharepoint.com/sites/RyanRent/Gedeelde%20documenten/Forms/AllItems.aspx?id=%2Fsites%2FRyanRent%2FGedeelde%20documenten%2FGeneral%2F01%5FRyanRent%26Co%2F01%5FWoningen%2FCoehoorn%20van%20Scheltingaweg%2012%2C%20Heerenveen | Q53: https://ryanrent.sharepoint.com/sites/RyanRent/Gedeelde%20documenten/Forms/AllItems.aspx?id=%2Fsites%2FRyanRent%2FGedeelde%20documenten%2FGeneral%2F01%5FRyanRent%26Co%2F01%5FWoningen%2FCoehoorn%20van%20Scheltingaweg%2012%2C%20Heerenveen%2F2%5FInhuur | R53: https://ryanrent.sharepoint.com/sites/RyanRent/Gedeelde%20documenten/Forms/AllItems.aspx?id=%2Fsites%2FRyanRent%2FGedeelde%20documenten%2FGeneral%2F01%5FRyanRent%26Co%2F01%5FWoningen%2FCoehoorn%20van%20Scheltingaweg%2012%2C%20Heerenveen%2F3%5FVerhuur | S53: https://ryanrent.sharepoint.com/sites/RyanRent/Gedeelde%20documenten/Forms/AllItems.aspx?id=%2Fsites%2FRyanRent%2FGedeelde%20documenten%2FGeneral%2F01%5FRyanRent%26Co%2F01%5FWoningen%2FCoehoorn%20van%20Scheltingaweg%2012%2C%20Heerenveen%2F2%5FInhuur%2F2%5FInhuurovereenkomsten | T53: 2509.41 | U53: 175 | V53: 0 | AM53: Geen inhuur | BV53: Leegstand | CD53: 2509.41 | CO53: 0 | CP53: 0 | CR53: Beschikbaar | CS53: 0
A54: 0053 | B54: 75 | C54: Curcumastraat 39 | D54: 3193XA | E54: Hoogvliet | F54: Appartement | H54: 4 | I54: 4 | J54: 1 | K54: Factuur | L54: 3124 | M54: 2206 | P54: https://ryanrent.sharepoint.com/sites/RyanRent/Gedeelde%20documenten/Forms/AllItems.aspx?id=%2Fsites%2FRyanRent%2FGedeelde%20documenten%2FGeneral%2F01%5FRyanRent%26Co%2F01%5FWoningen%2FCurcumastraat%2039%2C%20Hoogvliet | Q54: https://ryanrent.sharepoint.com/sites/RyanRent/Gedeelde%20documenten/Forms/AllItems.aspx?id=%2Fsites%2FRyanRent%2FGedeelde%20documenten%2FGeneral%2F01%5FRyanRent%26Co%2F01%5FWoningen%2FCurcumastraat%2039%2C%20Hoogvliet%2F2%5FInhuur | R54: https://ryanrent.sharepoint.com/sites/RyanRent/Gedeelde%20documenten/Forms/AllItems.aspx?id=%2Fsites%2FRyanRent%2FGedeelde%20documenten%2FGeneral%2F01%5FRyanRent%26Co%2F01%5FWoningen%2FCurcumastraat%2039%2C%20Hoogvliet%2F3%5FVerhuur | S54: https://ryanrent.sharepoint.com/sites/RyanRent/Gedeelde%20documenten/Forms/AllItems.aspx?id=%2Fsites%2FRyanRent%2FGedeelde%20documenten%2FGeneral%2F01%5FRyanRent%26Co%2F01%5FWoningen%2FCurcumastraat%2039%2C%20Hoogvliet%2F2%5FInhuur%2F2%5FInhuurovereenkomsten | T54: 1700 | U54: 250 | V54: 0 | AM54: Geen inhuur | BV54: Leegstand | CD54: 1700 | CO54: 0 | CP54: 0 | CR54: Beschikbaar | CS54: 0
A55: 0054 | B55: 76 | C55: De Gasperistraat 11 | D55: 4463 KJ | E55: Goes | F55: Appartement | I55: 10000 | J55: 1 | K55: Factuur | L55: 0911 | M55: 2206 | T55: 1580 | U55: 260 | V55: 0 | AM55: Geen inhuur | BV55: Leegstand | CD55: 1580 | CO55: 0 | CP55: 0 | CR55: Beschikbaar | CS55: 0
A56: 0055 | B56: 77 | C56: Baanhoek 139 | D56: 3361 GC | E56: Sliedrecht | F56: Vakantiepark | H56: 4 | I56: 4 | J56: 1 | K56: DS | L56: 6139 | M56: 1005 | P56: https://ryanrent.sharepoint.com/sites/RyanRent/Gedeelde%20documenten/Forms/AllItems.aspx?id=%2Fsites%2FRyanRent%2FGedeelde%20documenten%2FGeneral%2F01%5FRyanRent%26Co%2F01%5FWoningen%2FBaanhoek%20139%2C%20Sliedrecht | Q56: https://ryanrent.sharepoint.com/sites/RyanRent/Gedeelde%20documenten/Forms/AllItems.aspx?id=%2Fsites%2FRyanRent%2FGedeelde%20documenten%2FGeneral%2F01%5FRyanRent%26Co%2F01%5FWoningen%2FBaanhoek%20139%2C%20Sliedrecht%2F2%5FInhuur | R56: https://ryanrent.sharepoint.com/sites/RyanRent/Gedeelde%20documenten/Forms/AllItems.aspx?id=%2Fsites%2FRyanRent%2FGedeelde%20documenten%2FGeneral%2F01%5FRyanRent%26Co%2F01%5FWoningen%2FBaanhoek%20139%2C%20Sliedrecht%2F3%5FVerhuur | S56: https://ryanrent.sharepoint.com/sites/RyanRent/Gedeelde%20documenten/Forms/AllItems.aspx?id=%2Fsites%2FRyanRent%2FGedeelde%20documenten%2FGeneral%2F01%5FRyanRent%26Co%2F01%5FWoningen%2FBaanhoek%20139%2C%20Sliedrecht%2F2%5FInhuur%2F2%5FInhuurovereenkomsten | T56: 2314.12 | U56: 250 | V56: 0 | AM56: Geen inhuur | BV56: Leegstand | CD56: 2314.12 | CO56: 0 | CP56: 0 | CR56: Beschikbaar | CS56: 0
A57: 0056 | B57: 78 | C57: De Hooidollen 606 | D57: 8918JZ | E57: Leeuwarden | F57: Appartement | H57: 4 | I57: 4 | J57: 1 | K57: DS | L57: 2506 | M57: 1005 | P57: https://ryanrent.sharepoint.com/sites/RyanRent/Gedeelde%20documenten/Forms/AllItems.aspx?id=%2Fsites%2FRyanRent%2FGedeelde%20documenten%2FGeneral%2F01%5FRyanRent%26Co%2F01%5FWoningen%2FDe%20Hooidollen%20606%2C%20Leeuwarden | Q57: https://ryanrent.sharepoint.com/sites/RyanRent/Gedeelde%20documenten/Forms/AllItems.aspx?id=%2Fsites%2FRyanRent%2FGedeelde%20documenten%2FGeneral%2F01%5FRyanRent%26Co%2F01%5FWoningen%2FDe%20Hooidollen%20606%2C%20Leeuwarden%2F2%5FInhuur | R57: https://ryanrent.sharepoint.com/sites/RyanRent/Gedeelde%20documenten/Forms/AllItems.aspx?id=%2Fsites%2FRyanRent%2FGedeelde%20documenten%2FGeneral%2F01%5FRyanRent%26Co%2F01%5FWoningen%2FDe%20Hooidollen%20606%2C%20Leeuwarden%2F3%5FVerhuur | S57: https://ryanrent.sharepoint.com/sites/RyanRent/Gedeelde%20documenten/Forms/AllItems.aspx?id=%2Fsites%2FRyanRent%2FGedeelde%20documenten%2FGeneral%2F01%5FRyanRent%26Co%2F01%5FWoningen%2FDe%20Hooidollen%20606%2C%20Leeuwarden%2F2%5FInhuur%2F2%5FInhuurovereenkomsten | T57: 1768.24 | U57: 450 | V57: 0 | AM57: Geen inhuur | BV57: Leegstand | CD57: 1768.24 | CO57: 0 | CP57: 0 | CR57: Beschikbaar | CS57: 0
A58: 0057 | B58: 79 | C58: Markt 5 | D58: 3142 GE | E58: Maassluis | F58: Appartement | H58: 6 | I58: 8 | J58: 1 | K58: Factuur | P58: https://ryanrent.sharepoint.com/sites/RyanRent/Gedeelde%20documenten/Forms/AllItems.aspx?id=%2Fsites%2FRyanRent%2FGedeelde%20documenten%2FGeneral%2F01%5FRyanRent%26Co%2F01%5FWoningen%2FMarkt%205%2C%20Maassluis | Q58: https://ryanrent.sharepoint.com/sites/RyanRent/Gedeelde%20documenten/Forms/AllItems.aspx?id=%2Fsites%2FRyanRent%2FGedeelde%20documenten%2FGeneral%2F01%5FRyanRent%26Co%2F01%5FWoningen%2FMarkt%205%2C%20Maassluis%2F2%5FInhuur | R58: https://ryanrent.sharepoint.com/sites/RyanRent/Gedeelde%20documenten/Forms/AllItems.aspx?id=%2Fsites%2FRyanRent%2FGedeelde%20documenten%2FGeneral%2F01%5FRyanRent%26Co%2F01%5FWoningen%2FMarkt%205%2C%20Maassluis%2F3%5FVerhuur | S58: https://ryanrent.sharepoint.com/sites/RyanRent/Gedeelde%20documenten/Forms/AllItems.aspx?id=%2Fsites%2FRyanRent%2FGedeelde%20documenten%2FGeneral%2F01%5FRyanRent%26Co%2F01%5FWoningen%2FMarkt%205%2C%20Maassluis%2F2%5FInhuur%2F2%5FInhuurovereenkomsten | T58: 4033.88 | U58: 395.02 | V58: 0 | AM58: Geen inhuur | BC58: 17 | BD58: Tradiro Services B.V. | BE58: particulier | BG58: facturen@tradiro.nl | BH58: null | BI58: Honderdland 960 | BJ58: 2678 PS | BK58: Maasdijk | BL58: Nederland | BM58: 59979135.0 | BO58: NL05 RABO 0154 0739 89 | BQ58: 303 | BR58: 2026-01-14 | BU58: bepaalde_tijd | BV58: Onbepaalde tijd | BW58: 0 | BX58: 1715.6 | BY58: 1870 | BZ58: 0.09 | CA58: 395.02 | CB58: 43.39 | CC58: 0 | CD58: 4033.88 | CE58: ryanrent | CF58: 1 | CG58: 1 | CH58: 1 | CI58: 0 | CJ58: 0 | CK58: 0 | CL58: 0 | CM58: 0 | CO58: 1715.6 | CP58: 20587.2 | CR58: Verhuurd (onbepaald) | CS58: 0
A59: 0058 | B59: 80 | C59: Deugenweerd 18 | D59: 7271XT | E59: Borculo | F59: Appartement | H59: 6 | I59: 6 | J59: 1 | K59: DS | L59: 2418 | M59: 1005 | T59: 2750 | U59: 500 | V59: 0 | W59: 206 | X59: Dhr. T. Roestenberg en Mw. Roestenberg - Hustinx | Y59: particulier | AA59: timoroestenberg@hotmail.com | AB59: 06 199 144 13 | AC59: De Haarmansenk 7 | AE59: Schalkhaar | AF59: Nederland | AI59: NL42 ASNB 8832 1748 71 | AJ59: 576 | AM59: Onbepaalde tijd | AO59: 1 | AT59: 2407 | AU59: 2407 | AV59: 2623.63 | AW59: 0.09 | AX59: 0 | AY59: 0 | AZ59: 0 | BA59: 0 | BB59: 0 | BV59: Leegstand | CD59: 2750 | CO59: -2407 | CP59: -28884 | CQ59: -100 | CR59: Beschikbaar | CS59: 0
A60: 0059 | B60: 81 | C60: Dieptol 63 | D60: 8332BK | E60: Steenwijk | F60: Appartement | H60: 6 | I60: 6 | J60: 1 | K60: DS | L60: 1063 | M60: 1005 | P60: https://ryanrent.sharepoint.com/sites/RyanRent/Gedeelde%20documenten/Forms/AllItems.aspx?id=%2Fsites%2FRyanRent%2FGedeelde%20documenten%2FGeneral%2F01%5FRyanRent%26Co%2F01%5FWoningen%2FDieptol%2063%2C%20Steenwijk | Q60: https://ryanrent.sharepoint.com/sites/RyanRent/Gedeelde%20documenten/Forms/AllItems.aspx?id=%2Fsites%2FRyanRent%2FGedeelde%20documenten%2FGeneral%2F01%5FRyanRent%26Co%2F01%5FWoningen%2FDieptol%2063%2C%20Steenwijk%2F2%5FInhuur | R60: https://ryanrent.sharepoint.com/sites/RyanRent/Gedeelde%20documenten/Forms/AllItems.aspx?id=%2Fsites%2FRyanRent%2FGedeelde%20documenten%2FGeneral%2F01%5FRyanRent%26Co%2F01%5FWoningen%2FDieptol%2063%2C%20Steenwijk%2F3%5FVerhuur | S60: https://ryanrent.sharepoint.com/sites/RyanRent/Gedeelde%20documenten/Forms/AllItems.aspx?id=%2Fsites%2FRyanRent%2FGedeelde%20documenten%2FGeneral%2F01%5FRyanRent%26Co%2F01%5FWoningen%2FDieptol%2063%2C%20Steenwijk%2F2%5FInhuur%2F2%5FInhuurovereenkomsten | T60: 3300 | U60: 400 | V60: 0 | AM60: Geen inhuur | BV60: Leegstand | CD60: 3300 | CO60: 0 | CP60: 0 | CR60: Beschikbaar | CS60: 0
A61: 0060 | B61: 82 | C61: Besterdring 6 | D61: 5014 HG | E61: Tilburg | F61: Appartement | H61: 8 | I61: 15 | J61: 1 | K61: Factuur | L61: 1405 | M61: 1005 | T61: 3450 | U61: 0 | V61: 0 | AM61: Geen inhuur | BV61: Leegstand | CD61: 3450 | CO61: 0 | CP61: 0 | CR61: Beschikbaar | CS61: 0
A62: 0061 | B62: 83 | C62: Dwarsweg 44 | D62: 3181HG | E62: Rozenburg | F62: Appartement | H62: 5 | I62: 5 | J62: 1 | K62: Factuur | L62: 0244 | M62: 9090 | P62: https://ryanrent.sharepoint.com/sites/RyanRent/Gedeelde%20documenten/Forms/AllItems.aspx?id=%2Fsites%2FRyanRent%2FGedeelde%20documenten%2FGeneral%2F01%5FRyanRent%26Co%2F01%5FWoningen%2FDwarsweg%2044%2C%20Rozenburg | Q62: https://ryanrent.sharepoint.com/sites/RyanRent/Gedeelde%20documenten/Forms/AllItems.aspx?id=%2Fsites%2FRyanRent%2FGedeelde%20documenten%2FGeneral%2F01%5FRyanRent%26Co%2F01%5FWoningen%2FDwarsweg%2044%2C%20Rozenburg%2F2%5FInhuur | R62: https://ryanrent.sharepoint.com/sites/RyanRent/Gedeelde%20documenten/Forms/AllItems.aspx?id=%2Fsites%2FRyanRent%2FGedeelde%20documenten%2FGeneral%2F01%5FRyanRent%26Co%2F01%5FWoningen%2FDwarsweg%2044%2C%20Rozenburg%2F3%5FVerhuur | S62: https://ryanrent.sharepoint.com/sites/RyanRent/Gedeelde%20documenten/Forms/AllItems.aspx?id=%2Fsites%2FRyanRent%2FGedeelde%20documenten%2FGeneral%2F01%5FRyanRent%26Co%2F01%5FWoningen%2FDwarsweg%2044%2C%20Rozenburg%2F2%5FInhuur%2F2%5FInhuurovereenkomsten | T62: 4530 | U62: 200 | V62: 0 | W62: 111 | X62: Hugo Vastgoed B.V. | Y62: particulier | AA62: administratie@hemobeheer.nl | AB62: 2076 515 45 06 | AC62: Academiesingel 37 A | AE62: BREDA | AF62: Nederland | AG62: 81215169.0 | AI62: NL06 ABNA 0889 9369 43 | AJ62: 580 | AM62: Onbepaalde tijd | AO62: 1 | AP62: onbepaalde tijd | AT62: 3393.32 | AU62: 3393.32 | AV62: 3698.72 | AW62: 0.09 | AX62: 0 | AY62: 0 | AZ62: 0 | BA62: 0 | BB62: 0 | BV62: Leegstand | CD62: 4530 | CO62: -3393.32 | CP62: -40719.84 | CQ62: -100 | CR62: Beschikbaar | CS62: 0
A63: 0062 | B63: 84 | C63: Eendrachtstraat 22 | D63: 3241CD | E63: Middelharnis | F63: Appartement | H63: 9 | I63: 9 | J63: 1 | K63: Factuur | L63: 8522 | M63: 1005 | T63: 6140.29 | U63: 525 | V63: 0 | AM63: Geen inhuur | BV63: Leegstand | CD63: 6140.29 | CO63: 0 | CP63: 0 | CR63: Beschikbaar | CS63: 0
A64: 0063 | B64: 1 | C64: Energieweg 40 | D64: 3133EC | E64: Vlaardingen | F64: Appartement | H64: 3 | I64: 6 | J64: 1 | K64: Factuur | L64: 1140 | M64: 9090 | P64: https://ryanrent.sharepoint.com/sites/RyanRent/Gedeelde%20documenten/Forms/AllItems.aspx?id=%2Fsites%2FRyanRent%2FGedeelde%20documenten%2FGeneral%2F01%5FRyanRent%26Co%2F01%5FWoningen%2FEnergieweg%2040%2C%20Vlaardingen | Q64: https://ryanrent.sharepoint.com/sites/RyanRent/Gedeelde%20documenten/Forms/AllItems.aspx?id=%2Fsites%2FRyanRent%2FGedeelde%20documenten%2FGeneral%2F01%5FRyanRent%26Co%2F01%5FWoningen%2FEnergieweg%2040%2C%20Vlaardingen%2F2%5FInhuur | R64: https://ryanrent.sharepoint.com/sites/RyanRent/Gedeelde%20documenten/Forms/AllItems.aspx?id=%2Fsites%2FRyanRent%2FGedeelde%20documenten%2FGeneral%2F01%5FRyanRent%26Co%2F01%5FWoningen%2FEnergieweg%2040%2C%20Vlaardingen%2F3%5FVerhuur | S64: https://ryanrent.sharepoint.com/sites/RyanRent/Gedeelde%20documenten/Forms/AllItems.aspx?id=%2Fsites%2FRyanRent%2FGedeelde%20documenten%2FGeneral%2F01%5FRyanRent%26Co%2F01%5FWoningen%2FEnergieweg%2040%2C%20Vlaardingen%2F2%5FInhuur%2F2%5FInhuurovereenkomsten | T64: 4755.44 | U64: 266.49 | V64: 0 | AM64: Geen inhuur | BC64: 17 | BD64: Tradiro Services B.V. | BE64: particulier | BG64: facturen@tradiro.nl | BH64: null | BI64: Honderdland 960 | BJ64: 2678 PS | BK64: Maasdijk | BL64: Nederland | BM64: 59979135.0 | BO64: NL05 RABO 0154 0739 89 | BQ64: 421 | BR64: 2026-01-14 | BU64: bepaalde_tijd | BV64: Onbepaalde tijd | BW64: 2841.93 | BX64: 2841.93 | BY64: 3097.7 | BZ64: 0.09 | CA64: 266.49 | CB64: 25.1 | CC64: 0 | CD64: 4755.44 | CE64: ryanrent | CF64: 1 | CG64: 1 | CH64: 1 | CI64: 0 | CJ64: 0 | CK64: 0 | CL64: 0 | CM64: 0 | CO64: 2841.93 | CP64: 34103.16 | CR64: Verhuurd (onbepaald) | CS64: 0
A65: 0064 | B65: 85 | C65: Enk 6 | D65: 7621ES | E65: Borne | F65: Appartement | H65: 4 | I65: 5 | J65: 1 | K65: DS | L65: 7806 | M65: 2206 | P65: https://ryanrent.sharepoint.com/sites/RyanRent/Gedeelde%20documenten/Forms/AllItems.aspx?id=%2Fsites%2FRyanRent%2FGedeelde%20documenten%2FGeneral%2F01%5FRyanRent%26Co%2F01%5FWoningen%2FEnk%206%2C%20Borne | Q65: https://ryanrent.sharepoint.com/sites/RyanRent/Gedeelde%20documenten/Forms/AllItems.aspx?id=%2Fsites%2FRyanRent%2FGedeelde%20documenten%2FGeneral%2F01%5FRyanRent%26Co%2F01%5FWoningen%2FEnk%206%2C%20Borne%2F2%5FInhuur | R65: https://ryanrent.sharepoint.com/sites/RyanRent/Gedeelde%20documenten/Forms/AllItems.aspx?id=%2Fsites%2FRyanRent%2FGedeelde%20documenten%2FGeneral%2F01%5FRyanRent%26Co%2F01%5FWoningen%2FEnk%206%2C%20Borne%2F3%5FVerhuur | S65: https://ryanrent.sharepoint.com/sites/RyanRent/Gedeelde%20documenten/Forms/AllItems.aspx?id=%2Fsites%2FRyanRent%2FGedeelde%20documenten%2FGeneral%2F01%5FRyanRent%26Co%2F01%5FWoningen%2FEnk%206%2C%20Borne%2F2%5FInhuur%2F2%5FInhuurovereenkomsten | T65: 2253.77 | U65: 250 | V65: 0 | AM65: Geen inhuur | BV65: Leegstand | CD65: 2253.77 | CO65: 0 | CP65: 0 | CR65: Beschikbaar | CS65: 0
A66: 0065 | B66: 86 | C66: Esdoornlaan 68 | D66: 3181XD | E66: Rozenburg | F66: Appartement | H66: 4 | I66: 6 | J66: 1 | K66: DS | L66: 1768 | M66: 2206 | P66: https://ryanrent.sharepoint.com/sites/RyanRent/Gedeelde%20documenten/Forms/AllItems.aspx?id=%2Fsites%2FRyanRent%2FGedeelde%20documenten%2FGeneral%2F01%5FRyanRent%26Co%2F01%5FWoningen%2FEsdoornlaan%2068%2C%20Rozenburg | Q66: https://ryanrent.sharepoint.com/sites/RyanRent/Gedeelde%20documenten/Forms/AllItems.aspx?id=%2Fsites%2FRyanRent%2FGedeelde%20documenten%2FGeneral%2F01%5FRyanRent%26Co%2F01%5FWoningen%2FEsdoornlaan%2068%2C%20Rozenburg%2F2%5FInhuur | R66: https://ryanrent.sharepoint.com/sites/RyanRent/Gedeelde%20documenten/Forms/AllItems.aspx?id=%2Fsites%2FRyanRent%2FGedeelde%20documenten%2FGeneral%2F01%5FRyanRent%26Co%2F01%5FWoningen%2FEsdoornlaan%2068%2C%20Rozenburg%2F3%5FVerhuur | S66: https://ryanrent.sharepoint.com/sites/RyanRent/Gedeelde%20documenten/Forms/AllItems.aspx?id=%2Fsites%2FRyanRent%2FGedeelde%20documenten%2FGeneral%2F01%5FRyanRent%26Co%2F01%5FWoningen%2FEsdoornlaan%2068%2C%20Rozenburg%2F2%5FInhuur%2F2%5FInhuurovereenkomsten | T66: 2446.35 | U66: 300 | V66: 0 | AM66: Geen inhuur | BV66: Leegstand | CD66: 2446.35 | CO66: 0 | CP66: 0 | CR66: Beschikbaar | CS66: 0
A67: 0066 | B67: 87 | C67: Dorpsstraat 73 | D67: 2841 BH | E67: Moordrecht | F67: Vakantiepark | H67: 9 | I67: 9 | J67: 1 | K67: Factuur | L67: 4173 | M67: 1005 | P67: https://ryanrent.sharepoint.com/sites/RyanRent/Gedeelde%20documenten/Forms/AllItems.aspx?id=%2Fsites%2FRyanRent%2FGedeelde%20documenten%2FGeneral%2F01%5FRyanRent%26Co%2F01%5FWoningen%2FDorpsstraat%2073%2C%20Moordrecht | Q67: https://ryanrent.sharepoint.com/sites/RyanRent/Gedeelde%20documenten/Forms/AllItems.aspx?id=%2Fsites%2FRyanRent%2FGedeelde%20documenten%2FGeneral%2F01%5FRyanRent%26Co%2F01%5FWoningen%2FDorpsstraat%2073%2C%20Moordrecht%2F2%5FInhuur | R67: https://ryanrent.sharepoint.com/sites/RyanRent/Gedeelde%20documenten/Forms/AllItems.aspx?id=%2Fsites%2FRyanRent%2FGedeelde%20documenten%2FGeneral%2F01%5FRyanRent%26Co%2F01%5FWoningen%2FDorpsstraat%2073%2C%20Moordrecht%2F3%5FVerhuur | S67: https://ryanrent.sharepoint.com/sites/RyanRent/Gedeelde%20documenten/Forms/AllItems.aspx?id=%2Fsites%2FRyanRent%2FGedeelde%20documenten%2FGeneral%2F01%5FRyanRent%26Co%2F01%5FWoningen%2FDorpsstraat%2073%2C%20Moordrecht%2F2%5FInhuur%2F2%5FInhuurovereenkomsten | T67: 6140.29 | U67: 400 | V67: 0 | W67: 802 | X67: Maatschap vd Vlist -Teuben | Y67: particulier | AJ67: 579 | AM67: Onbepaalde tijd | AO67: 1 | AT67: 5779.72 | AU67: 5779.72 | AV67: 6299.89 | AW67: 0.09 | AX67: 0 | AY67: 0 | AZ67: 0 | BA67: 0 | BB67: 0 | BV67: Leegstand | CD67: 6140.29 | CO67: -5779.72 | CP67: -69356.64 | CQ67: -100 | CR67: Beschikbaar | CS67: 0
A68: 0067 | B68: 88 | C68: Franz Liszstraat 5 | D68: 4536EA | E68: Terneuzen | F68: Appartement | H68: 4 | I68: 7 | J68: 1 | K68: Factuur | L68: 4405 | M68: 1005 | P68: https://ryanrent.sharepoint.com/sites/RyanRent/Gedeelde%20documenten/Forms/AllItems.aspx?id=%2Fsites%2FRyanRent%2FGedeelde%20documenten%2FGeneral%2F01%5FRyanRent%26Co%2F01%5FWoningen%2FFranzliszstraat%205%2C%20Terneuzen | Q68: https://ryanrent.sharepoint.com/sites/RyanRent/Gedeelde%20documenten/Forms/AllItems.aspx?id=%2Fsites%2FRyanRent%2FGedeelde%20documenten%2FGeneral%2F01%5FRyanRent%26Co%2F01%5FWoningen%2FFranzliszstraat%205%2C%20Terneuzen%2F2%5FInhuur | R68: https://ryanrent.sharepoint.com/sites/RyanRent/Gedeelde%20documenten/Forms/AllItems.aspx?id=%2Fsites%2FRyanRent%2FGedeelde%20documenten%2FGeneral%2F01%5FRyanRent%26Co%2F01%5FWoningen%2FFranzliszstraat%205%2C%20Terneuzen%2F3%5FVerhuur | S68: https://ryanrent.sharepoint.com/sites/RyanRent/Gedeelde%20documenten/Forms/AllItems.aspx?id=%2Fsites%2FRyanRent%2FGedeelde%20documenten%2FGeneral%2F01%5FRyanRent%26Co%2F01%5FWoningen%2FFranzliszstraat%205%2C%20Terneuzen%2F2%5FInhuur%2F2%5FInhuurovereenkomsten | T68: 3643.5 | U68: 631.65 | V68: 0 | W68: 806 | X68: Value+ Vastgoedmanagement | Y68: particulier | AJ68: 589 | AK68: 2022-01-21 | AL68: 2027-01-20 | AM68: Actief | AO68: 1 | AT68: 1665.6 | AU68: 1665.6 | AV68: 1815.5 | AW68: 0.09 | AX68: 0 | AY68: 0 | AZ68: 0 | BA68: 0 | BB68: 0 | BC68: 17 | BD68: Tradiro Services B.V. | BE68: particulier | BG68: facturen@tradiro.nl | BH68: null | BI68: Honderdland 960 | BJ68: 2678 PS | BK68: Maasdijk | BL68: Nederland | BM68: 59979135.0 | BO68: NL05 RABO 0154 0739 89 | BQ68: 74 | BR68: 2022-01-21 | BS68: 2027-01-20 | BT68: 12 | BU68: bepaalde_tijd | BV68: Actief | BW68: 3643.5 | BX68: 3643.5 | BY68: 3971.42 | BZ68: 0.09 | CA68: 0 | CB68: 0 | CC68: 0 | CD68: 3643.5 | CE68: eigen_beheer | CF68: 1 | CG68: 1 | CH68: 1 | CI68: 0 | CJ68: 0 | CK68: 0 | CL68: 0 | CM68: 0 | CO68: 1977.9 | CP68: 23734.8 | CQ68: 118.75 | CR68: Verhuurd | CS68: 363
A69: 0068 | B69: 89 | C69: F.Erensstraat 21 | D69: 6136JE | E69: Sittard | F69: Appartement | H69: 4 | I69: 5 | J69: 1 | K69: Factuur | L69: 1969 | M69: 2206 | T69: 2253.77 | U69: 200 | V69: 0 | AM69: Geen inhuur | BV69: Leegstand | CD69: 2253.77 | CO69: 0 | CP69: 0 | CR69: Beschikbaar | CS69: 0
A70: 0069 | B70: 90 | C70: Gaffelaar 3 | D70: 8802NR | E70: Franeker | F70: Appartement | H70: 8 | I70: 8 | J70: 1 | K70: Factuur | L70: 1970 | M70: 9191 | T70: 4575 | U70: 200 | V70: 0 | AM70: Geen inhuur | BV70: Leegstand | CD70: 4575 | CO70: 0 | CP70: 0 | CR70: Beschikbaar | CS70: 0
A71: 0070 | B71: 91 | C71: Geleenstraat 1 | D71: 6133XK | E71: Sittard | F71: Appartement | H71: 3 | I71: 3 | J71: 1 | K71: DS | L71: 7001 | M71: 1005 | P71: https://ryanrent.sharepoint.com/sites/RyanRent/Gedeelde%20documenten/Forms/AllItems.aspx?id=%2Fsites%2FRyanRent%2FGedeelde%20documenten%2FGeneral%2F01%5FRyanRent%26Co%2F01%5FWoningen%2FGeleenstraat%201%2C%20Sittard | Q71: https://ryanrent.sharepoint.com/sites/RyanRent/Gedeelde%20documenten/Forms/AllItems.aspx?id=%2Fsites%2FRyanRent%2FGedeelde%20documenten%2FGeneral%2F01%5FRyanRent%26Co%2F01%5FWoningen%2FGeleenstraat%201%2C%20Sittard%2F2%5FInhuur | R71: https://ryanrent.sharepoint.com/sites/RyanRent/Gedeelde%20documenten/Forms/AllItems.aspx?id=%2Fsites%2FRyanRent%2FGedeelde%20documenten%2FGeneral%2F01%5FRyanRent%26Co%2F01%5FWoningen%2FGeleenstraat%201%2C%20Sittard%2F3%5FVerhuur | S71: https://ryanrent.sharepoint.com/sites/RyanRent/Gedeelde%20documenten/Forms/AllItems.aspx?id=%2Fsites%2FRyanRent%2FGedeelde%20documenten%2FGeneral%2F01%5FRyanRent%26Co%2F01%5FWoningen%2FGeleenstraat%201%2C%20Sittard%2F2%5FInhuur%2F2%5FInhuurovereenkomsten | T71: 3239.85 | U71: 200 | V71: 0 | AM71: Geen inhuur | BV71: Leegstand | CD71: 3239.85 | CO71: 0 | CP71: 0 | CR71: Beschikbaar | CS71: 0
A72: 0071 | B72: 92 | C72: H. Algraplein 25 | D72: 8802RE | E72: Franeker | F72: Appartement | H72: 4 | I72: 7 | J72: 1 | K72: DS | L72: 1970 | M72: 1005 | P72: https://ryanrent.sharepoint.com/sites/RyanRent/Gedeelde%20documenten/Forms/AllItems.aspx?id=%2Fsites%2FRyanRent%2FGedeelde%20documenten%2FGeneral%2F01%5FRyanRent%26Co%2F01%5FWoningen%2FH.%20Algraplein%2025%2C%20Franeker | Q72: https://ryanrent.sharepoint.com/sites/RyanRent/Gedeelde%20documenten/Forms/AllItems.aspx?id=%2Fsites%2FRyanRent%2FGedeelde%20documenten%2FGeneral%2F01%5FRyanRent%26Co%2F01%5FWoningen%2FH.%20Algraplein%2025%2C%20Franeker%2F2%5FInhuur | R72: https://ryanrent.sharepoint.com/sites/RyanRent/Gedeelde%20documenten/Forms/AllItems.aspx?id=%2Fsites%2FRyanRent%2FGedeelde%20documenten%2FGeneral%2F01%5FRyanRent%26Co%2F01%5FWoningen%2FH.%20Algraplein%2025%2C%20Franeker%2F3%5FVerhuur | S72: https://ryanrent.sharepoint.com/sites/RyanRent/Gedeelde%20documenten/Forms/AllItems.aspx?id=%2Fsites%2FRyanRent%2FGedeelde%20documenten%2FGeneral%2F01%5FRyanRent%26Co%2F01%5FWoningen%2FH.%20Algraplein%2025%2C%20Franeker%2F2%5FInhuur%2F2%5FInhuurovereenkomsten | T72: 2575 | U72: 250 | V72: 0 | W72: 241 | X72: BJ Bakker | Y72: particulier | AA72: bjbakker85@hotmail.com | AC72: Spiens 3 | AE72: Dokkum | AF72: Nederland | AI72: NL36 RABO 0302 0165 70 | AJ72: 594 | AM72: Onbepaalde tijd | AO72: 1 | AT72: 2150 | AU72: 2150 | AV72: 2343.5 | AW72: 0.09 | AX72: 0 | AY72: 0 | AZ72: 0 | BA72: 0 | BB72: 0 | BC72: 210 | BD72: DIT en Larex Vakpersoneel B.V. | BE72: particulier | BG72: factuur@ditenlarexvakpersoneel.nl | BH72: 06 117 50 200 | BI72: Maagdenburgstraat 10 | BK72: DEVENTER | BL72: Nederland | BM72: 8116290.0 | BO72: NL17 RABO 0320 0278 72 | BQ72: 79 | BR72: 2025-08-16 | BS72: 2026-06-15 | BT72: 10 | BU72: bepaalde_tijd | BV72: Actief | BW72: 2575 | BX72: 2825 | BY72: 3079.25 | BZ72: 0.09 | CA72: 250 | CB72: 0 | CC72: 250 | CD72: 2575 | CE72: ryanrent | CF72: 1 | CG72: 1 | CH72: 1 | CI72: 0 | CJ72: 0 | CK72: 0 | CL72: 1 | CM72: 0 | CN72: basis | CO72: 675 | CP72: 8100 | CQ72: 31.4 | CR72: Verhuurd | CS72: 144
A73: 0072 | B73: 93 | C73: Heemskerkstraat 19 | D73: 9866AR | E73: Lutjegast | F73: Appartement | H73: 4 | I73: 4 | J73: 1 | K73: DS | L73: 1970 | M73: 1005 | P73: https://ryanrent.sharepoint.com/sites/RyanRent/Gedeelde%20documenten/Forms/AllItems.aspx?id=%2Fsites%2FRyanRent%2FGedeelde%20documenten%2FGeneral%2F01%5FRyanRent%26Co%2F01%5FWoningen%2FHeemskerkstraat%2019%2C%20Lutjegast | Q73: https://ryanrent.sharepoint.com/sites/RyanRent/Gedeelde%20documenten/Forms/AllItems.aspx?id=%2Fsites%2FRyanRent%2FGedeelde%20documenten%2FGeneral%2F01%5FRyanRent%26Co%2F01%5FWoningen%2FHeemskerkstraat%2019%2C%20Lutjegast%2F2%5FInhuur | R73: https://ryanrent.sharepoint.com/sites/RyanRent/Gedeelde%20documenten/Forms/AllItems.aspx?id=%2Fsites%2FRyanRent%2FGedeelde%20documenten%2FGeneral%2F01%5FRyanRent%26Co%2F01%5FWoningen%2FHeemskerkstraat%2019%2C%20Lutjegast%2F3%5FVerhuur | S73: https://ryanrent.sharepoint.com/sites/RyanRent/Gedeelde%20documenten/Forms/AllItems.aspx?id=%2Fsites%2FRyanRent%2FGedeelde%20documenten%2FGeneral%2F01%5FRyanRent%26Co%2F01%5FWoningen%2FHeemskerkstraat%2019%2C%20Lutjegast%2F2%5FInhuur%2F2%5FInhuurovereenkomsten | T73: 2250 | U73: 250 | V73: 0 | AM73: Geen inhuur | BV73: Leegstand | CD73: 2250 | CO73: 0 | CP73: 0 | CR73: Beschikbaar | CS73: 0
A74: 0073 | B74: 94 | C74: Hendrik Deddenstraat 26 | D74: 8395PX | E74: Steggerda | F74: Appartement | H74: 5 | I74: 5 | J74: 1 | K74: DS | L74: 6426 | M74: 1005 | P74: https://ryanrent.sharepoint.com/sites/RyanRent/Gedeelde%20documenten/Forms/AllItems.aspx?id=%2Fsites%2FRyanRent%2FGedeelde%20documenten%2FGeneral%2F01%5FRyanRent%26Co%2F01%5FWoningen%2FHendrik%20Deddenstraat%2026%2C%20Steggerda | Q74: https://ryanrent.sharepoint.com/sites/RyanRent/Gedeelde%20documenten/Forms/AllItems.aspx?id=%2Fsites%2FRyanRent%2FGedeelde%20documenten%2FGeneral%2F01%5FRyanRent%26Co%2F01%5FWoningen%2FHendrik%20Deddenstraat%2026%2C%20Steggerda%2F2%5FInhuur | R74: https://ryanrent.sharepoint.com/sites/RyanRent/Gedeelde%20documenten/Forms/AllItems.aspx?id=%2Fsites%2FRyanRent%2FGedeelde%20documenten%2FGeneral%2F01%5FRyanRent%26Co%2F01%5FWoningen%2FHendrik%20Deddenstraat%2026%2C%20Steggerda%2F3%5FVerhuur | S74: https://ryanrent.sharepoint.com/sites/RyanRent/Gedeelde%20documenten/Forms/AllItems.aspx?id=%2Fsites%2FRyanRent%2FGedeelde%20documenten%2FGeneral%2F01%5FRyanRent%26Co%2F01%5FWoningen%2FHendrik%20Deddenstraat%2026%2C%20Steggerda%2F2%5FInhuur%2F2%5FInhuurovereenkomsten | T74: 1750 | U74: 300 | V74: 0 | AM74: Geen inhuur | BV74: Leegstand | CD74: 1750 | CO74: 0 | CP74: 0 | CR74: Beschikbaar | CS74: 0
A75: 0074 | B75: 95 | C75: Mgr. W.M. Bekkerslaan 34 | D75: 3141SK | E75: Maassluis | F75: Appartement | H75: 4 | I75: 4 | J75: 1 | K75: Factuur | T75: 2450 | U75: 68.19 | V75: 0 | W75: 701 | X75: Fransen Vastgoed / Holland Huisvesting B.V. | Y75: particulier | AA75: info@fransenvastgoed.nl | AC75: Lekdreef 2 | AE75: Krimpen aan de Lek | AF75: Nederland | AI75: NL80 RABO 0190 7126 43 | AJ75: 667 | AM75: Onbepaalde tijd | AO75: 1 | AT75: 2459.85 | AU75: 2509.85 | AV75: 2735.74 | AW75: 0.09 | AX75: 0 | AY75: 0 | AZ75: 0 | BA75: 0 | BB75: 0 | BC75: 17 | BD75: Tradiro Services B.V. | BE75: particulier | BG75: facturen@tradiro.nl | BH75: null | BI75: Honderdland 960 | BJ75: 2678 PS | BK75: Maasdijk | BL75: Nederland | BM75: 59979135.0 | BO75: NL05 RABO 0154 0739 89 | BQ75: 154 | BR75: 2025-01-01 | BU75: onbepaalde_tijd | BV75: Onbepaalde tijd | BW75: 0 | BX75: 0 | BY75: 0 | BZ75: 0.09 | CA75: 0 | CB75: 0 | CC75: 0 | CD75: 2450 | CE75: eigen_beheer | CF75: 0 | CG75: 0 | CH75: 0 | CI75: 0 | CJ75: 0 | CK75: 0 | CL75: 0 | CM75: 0 | CO75: -2509.85 | CP75: -30118.2 | CQ75: -100 | CR75: Verhuurd (onbepaald) | CS75: 0
A76: 0074 | B76: 95 | C76: Mgr. W.M. Bekkerslaan 34 | D76: 3141SK | E76: Maassluis | F76: Appartement | H76: 4 | I76: 4 | J76: 1 | K76: Factuur | T76: 2450 | U76: 68.19 | V76: 0 | W76: 701 | X76: Fransen Vastgoed / Holland Huisvesting B.V. | Y76: particulier | AA76: info@fransenvastgoed.nl | AC76: Lekdreef 2 | AE76: Krimpen aan de Lek | AF76: Nederland | AI76: NL80 RABO 0190 7126 43 | AJ76: 667 | AM76: Onbepaalde tijd | AO76: 1 | AT76: 2459.85 | AU76: 2509.85 | AV76: 2735.74 | AW76: 0.09 | AX76: 0 | AY76: 0 | AZ76: 0 | BA76: 0 | BB76: 0 | BC76: 17 | BD76: Tradiro Services B.V. | BE76: particulier | BG76: facturen@tradiro.nl | BH76: null | BI76: Honderdland 960 | BJ76: 2678 PS | BK76: Maasdijk | BL76: Nederland | BM76: 59979135.0 | BO76: NL05 RABO 0154 0739 89 | BQ76: 413 | BR76: 2026-01-14 | BU76: bepaalde_tijd | BV76: Onbepaalde tijd | BW76: 0 | BX76: 2509.85 | BY76: 2735.74 | BZ76: 0.09 | CA76: 267.5 | CB76: 43.39 | CC76: 0 | CD76: 2450 | CE76: ryanrent | CF76: 0 | CG76: 0 | CH76: 0 | CI76: 0 | CJ76: 0 | CK76: 0 | CL76: 0 | CM76: 0 | CO76: 0 | CP76: 0 | CQ76: 0 | CR76: Verhuurd (onbepaald) | CS76: 0
A77: 0075 | B77: 96 | C77: Hoofdstraat 110 | D77: 5473AT | E77: Heeswijk-Dinther | F77: Appartement | H77: 4 | I77: 4 | J77: 1 | K77: Factuur | L77: 2710 | M77: 1005 | P77: https://ryanrent.sharepoint.com/sites/RyanRent/Gedeelde%20documenten/Forms/AllItems.aspx?id=%2Fsites%2FRyanRent%2FGedeelde%20documenten%2FGeneral%2F01%5FRyanRent%26Co%2F01%5FWoningen%2FHoofdstraat%20110%2C%20Heeswijk | Q77: https://ryanrent.sharepoint.com/sites/RyanRent/Gedeelde%20documenten/Forms/AllItems.aspx?id=%2Fsites%2FRyanRent%2FGedeelde%20documenten%2FGeneral%2F01%5FRyanRent%26Co%2F01%5FWoningen%2FHoofdstraat%20110%2C%20Heeswijk%2F2%5FInhuur | R77: https://ryanrent.sharepoint.com/sites/RyanRent/Gedeelde%20documenten/Forms/AllItems.aspx?id=%2Fsites%2FRyanRent%2FGedeelde%20documenten%2FGeneral%2F01%5FRyanRent%26Co%2F01%5FWoningen%2FHoofdstraat%20110%2C%20Heeswijk%2F3%5FVerhuur | S77: https://ryanrent.sharepoint.com/sites/RyanRent/Gedeelde%20documenten/Forms/AllItems.aspx?id=%2Fsites%2FRyanRent%2FGedeelde%20documenten%2FGeneral%2F01%5FRyanRent%26Co%2F01%5FWoningen%2FHoofdstraat%20110%2C%20Heeswijk%2F2%5FInhuur%2F2%5FInhuurovereenkomsten | T77: 2342.25 | U77: 150 | V77: 0 | AM77: Geen inhuur | BV77: Leegstand | CD77: 2342.25 | CO77: 0 | CP77: 0 | CR77: Beschikbaar | CS77: 0
A78: 0076 | B78: 97 | C78: Molendijk 4 | D78: 3255AL | E78: Oude-Tonge | F78: Appartement | H78: 4 | I78: 4 | J78: 1 | K78: Factuur | L78: 5504 | M78: 1005 | P78: https://ryanrent.sharepoint.com/sites/RyanRent/Gedeelde%20documenten/Forms/AllItems.aspx?id=%2Fsites%2FRyanRent%2FGedeelde%20documenten%2FGeneral%2F01%5FRyanRent%26Co%2F01%5FWoningen%2FMolendijk%204%2C%20Oude%20Tonge | Q78: https://ryanrent.sharepoint.com/sites/RyanRent/Gedeelde%20documenten/Forms/AllItems.aspx?id=%2Fsites%2FRyanRent%2FGedeelde%20documenten%2FGeneral%2F01%5FRyanRent%26Co%2F01%5FWoningen%2FMolendijk%204%2C%20Oude%20Tonge%2F2%5FInhuur | R78: https://ryanrent.sharepoint.com/sites/RyanRent/Gedeelde%20documenten/Forms/AllItems.aspx?id=%2Fsites%2FRyanRent%2FGedeelde%20documenten%2FGeneral%2F01%5FRyanRent%26Co%2F01%5FWoningen%2FMolendijk%204%2C%20Oude%20Tonge%2F3%5FVerhuur | S78: https://ryanrent.sharepoint.com/sites/RyanRent/Gedeelde%20documenten/Forms/AllItems.aspx?id=%2Fsites%2FRyanRent%2FGedeelde%20documenten%2FGeneral%2F01%5FRyanRent%26Co%2F01%5FWoningen%2FMolendijk%204%2C%20Oude%20Tonge%2F2%5FInhuur%2F2%5FInhuurovereenkomsten | T78: 3608.79 | U78: 260 | V78: 0 | W78: 630 | X78: J. van der Linde | Y78: particulier | AF78: Nederland | AI78: NL90 RABO 0352 2550 99 | AJ78: 677 | AK78: 2024-06-01 | AL78: 2026-05-31 | AM78: Actief | AO78: 1 | AT78: 2550.45 | AU78: 2622.95 | AV78: 2859.02 | AW78: 0.09 | AX78: 0 | AY78: 0 | AZ78: 0 | BA78: 0 | BB78: 0 | BC78: 324 | BD78: Multiservizi Romania SRL | BE78: particulier | BG78: amministrazionepythagoras@gmail.com | BI78: Sector 1 str academiei nr 35-37 scb et2 | BK78: Bucuresti | BL78: Roemenië | BQ78: 167 | BR78: 2024-06-01 | BS78: 2026-05-31 | BT78: 12 | BU78: bepaalde_tijd | BV78: Actief | BW78: 3608.79 | BX78: 3868.79 | BY78: 4216.98 | BZ78: 0.09 | CA78: 260 | CB78: 0 | CC78: 0 | CD78: 3608.79 | CE78: ryanrent | CF78: 1 | CG78: 1 | CH78: 1 | CI78: 0 | CJ78: 0 | CK78: 0 | CL78: 0 | CM78: 0 | CO78: 1245.84 | CP78: 14950.08 | CQ78: 47.5 | CR78: Verhuurd | CS78: 129
A79: 0077 | B79: 98 | C79: Voorstraat 10 | D79: 3255AX | E79: Oude-Tonge | F79: Vakantiepark | H79: 4 | I79: 4 | J79: 1 | K79: Factuur | L79: 5510 | M79: 1005 | P79: https://ryanrent.sharepoint.com/sites/RyanRent/Gedeelde%20documenten/Forms/AllItems.aspx?id=%2Fsites%2FRyanRent%2FGedeelde%20documenten%2FGeneral%2F01%5FRyanRent%26Co%2F01%5FWoningen%2FVoorstraat%2010%2C%20Oude%20Tonge | Q79: https://ryanrent.sharepoint.com/sites/RyanRent/Gedeelde%20documenten/Forms/AllItems.aspx?id=%2Fsites%2FRyanRent%2FGedeelde%20documenten%2FGeneral%2F01%5FRyanRent%26Co%2F01%5FWoningen%2FVoorstraat%2010%2C%20Oude%20Tonge%2F2%5FInhuur | R79: https://ryanrent.sharepoint.com/sites/RyanRent/Gedeelde%20documenten/Forms/AllItems.aspx?id=%2Fsites%2FRyanRent%2FGedeelde%20documenten%2FGeneral%2F01%5FRyanRent%26Co%2F01%5FWoningen%2FVoorstraat%2010%2C%20Oude%20Tonge%2F3%5FVerhuur | S79: https://ryanrent.sharepoint.com/sites/RyanRent/Gedeelde%20documenten/Forms/AllItems.aspx?id=%2Fsites%2FRyanRent%2FGedeelde%20documenten%2FGeneral%2F01%5FRyanRent%26Co%2F01%5FWoningen%2FVoorstraat%2010%2C%20Oude%20Tonge%2F2%5FInhuur%2F2%5FInhuurovereenkomsten | T79: 3608.8 | U79: 260 | V79: 0 | W79: 839 | X79: J, van de Linde | Y79: particulier | AJ79: 754 | AK79: 2024-06-01 | AL79: 2026-05-31 | AM79: Actief | AO79: 1 | AT79: 0 | AU79: 2622.95 | AV79: 2859.02 | AW79: 0.09 | AX79: 0 | AY79: 0 | AZ79: 0 | BA79: 0 | BB79: 0 | BC79: 324 | BD79: Multiservizi Romania SRL | BE79: particulier | BG79: amministrazionepythagoras@gmail.com | BI79: Sector 1 str academiei nr 35-37 scb et2 | BK79: Bucuresti | BL79: Roemenië | BQ79: 250 | BR79: 2024-06-01 | BS79: 2026-05-31 | BT79: 12 | BU79: bepaalde_tijd | BV79: Actief | BW79: 3608.8 | BX79: 3868.8 | BY79: 4216.99 | BZ79: 0.09 | CA79: 260 | CB79: 0 | CC79: 0 | CD79: 3608.8 | CE79: ryanrent | CF79: 1 | CG79: 1 | CH79: 1 | CI79: 0 | CJ79: 0 | CK79: 0 | CL79: 0 | CM79: 0 | CO79: 1245.85 | CP79: 14950.2 | CQ79: 47.5 | CR79: Verhuurd | CS79: 129
A80: 0078 | B80: 99 | C80: Hooizolder 6 | D80: 9205 CA | E80: Drachten | F80: Appartement | H80: 4 | I80: 4 | J80: 1 | K80: DS | L80: 9260 | M80: 1005 | P80: https://ryanrent.sharepoint.com/sites/RyanRent/Gedeelde%20documenten/Forms/AllItems.aspx?id=%2Fsites%2FRyanRent%2FGedeelde%20documenten%2FGeneral%2F01%5FRyanRent%26Co%2F01%5FWoningen%2FHooizolder%206%2C%20Drachten | Q80: https://ryanrent.sharepoint.com/sites/RyanRent/Gedeelde%20documenten/Forms/AllItems.aspx?id=%2Fsites%2FRyanRent%2FGedeelde%20documenten%2FGeneral%2F01%5FRyanRent%26Co%2F01%5FWoningen%2FHooizolder%206%2C%20Drachten%2F2%5FInhuur | R80: https://ryanrent.sharepoint.com/sites/RyanRent/Gedeelde%20documenten/Forms/AllItems.aspx?id=%2Fsites%2FRyanRent%2FGedeelde%20documenten%2FGeneral%2F01%5FRyanRent%26Co%2F01%5FWoningen%2FHooizolder%206%2C%20Drachten%2F3%5FVerhuur | S80: https://ryanrent.sharepoint.com/sites/RyanRent/Gedeelde%20documenten/Forms/AllItems.aspx?id=%2Fsites%2FRyanRent%2FGedeelde%20documenten%2FGeneral%2F01%5FRyanRent%26Co%2F01%5FWoningen%2FHooizolder%206%2C%20Drachten%2F2%5FInhuur%2F2%5FInhuurovereenkomsten | T80: 2602.5 | U80: 250 | V80: 0 | AM80: Geen inhuur | BV80: Leegstand | CD80: 2602.5 | CO80: 0 | CP80: 0 | CR80: Beschikbaar | CS80: 0
A81: 0079 | B81: 100 | C81: Ploegstraat 2a | D81: 3114NP | E81: Schiedam | F81: Appartement | H81: 2 | I81: 4 | J81: 1 | K81: Factuur | L81: 3102 | M81: 1005 | P81: https://ryanrent.sharepoint.com/sites/RyanRent/Gedeelde%20documenten/Forms/AllItems.aspx?id=%2Fsites%2FRyanRent%2FGedeelde%20documenten%2FGeneral%2F01%5FRyanRent%26Co%2F01%5FWoningen%2FPloegstraat%202A%2C%20Schiedam | Q81: https://ryanrent.sharepoint.com/sites/RyanRent/Gedeelde%20documenten/Forms/AllItems.aspx?id=%2Fsites%2FRyanRent%2FGedeelde%20documenten%2FGeneral%2F01%5FRyanRent%26Co%2F01%5FWoningen%2FPloegstraat%202A%2C%20Schiedam%2F2%5FInhuur | R81: https://ryanrent.sharepoint.com/sites/RyanRent/Gedeelde%20documenten/Forms/AllItems.aspx?id=%2Fsites%2FRyanRent%2FGedeelde%20documenten%2FGeneral%2F01%5FRyanRent%26Co%2F01%5FWoningen%2FPloegstraat%202A%2C%20Schiedam%2F3%5FVerhuur | S81: https://ryanrent.sharepoint.com/sites/RyanRent/Gedeelde%20documenten/Forms/AllItems.aspx?id=%2Fsites%2FRyanRent%2FGedeelde%20documenten%2FGeneral%2F01%5FRyanRent%26Co%2F01%5FWoningen%2FPloegstraat%202A%2C%20Schiedam%2F2%5FInhuur%2F2%5FInhuurovereenkomsten | T81: 2166.65 | U81: 107.58 | V81: 0 | W81: 271 | X81: Houses2Rent | Y81: particulier | AA81: info@houses2rent.nl | AB81: 06-20877085 | AC81: Stellingmolen 42 | AE81: Maassluis | AF81: Nederland | AI81: NL17 INGB 0390 7692 58 | AJ81: 713 | AM81: Onbepaalde tijd | AO81: 1 | AT81: 1300 | AU81: 1300 | AV81: 1417 | AW81: 0.09 | AX81: 0 | AY81: 0 | AZ81: 0 | BA81: 0 | BB81: 0 | BC81: 17 | BD81: Tradiro Services B.V. | BE81: particulier | BG81: facturen@tradiro.nl | BH81: null | BI81: Honderdland 960 | BJ81: 2678 PS | BK81: Maasdijk | BL81: Nederland | BM81: 59979135.0 | BO81: NL05 RABO 0154 0739 89 | BQ81: 205 | BR81: 2024-06-01 | BU81: onbepaalde_tijd | BV81: Onbepaalde tijd | BW81: 1734.98 | BX81: 1734.98 | BY81: 1891.13 | BZ81: 0.09 | CA81: 0 | CB81: 0 | CC81: 0 | CD81: 2166.65 | CE81: eigen_beheer | CF81: 0 | CG81: 0 | CH81: 0 | CI81: 0 | CJ81: 0 | CK81: 0 | CL81: 0 | CM81: 0 | CO81: 434.98 | CP81: 5219.76 | CQ81: 33.46 | CR81: Verhuurd (onbepaald) | CS81: 0
A82: 0080 | B82: 101 | C82: Voorstraat 25 | D82: 3135HV | E82: Vlaardingen | F82: Vakantiepark | H82: 2 | I82: 4 | J82: 1 | K82: Factuur | L82: 3125 | M82: 1005 | P82: https://ryanrent.sharepoint.com/sites/RyanRent/Gedeelde%20documenten/Forms/AllItems.aspx?id=%2Fsites%2FRyanRent%2FGedeelde%20documenten%2FGeneral%2F01%5FRyanRent%26Co%2F01%5FWoningen%2FVoorstraat%2025%2C%20Vlaardingen | Q82: https://ryanrent.sharepoint.com/sites/RyanRent/Gedeelde%20documenten/Forms/AllItems.aspx?id=%2Fsites%2FRyanRent%2FGedeelde%20documenten%2FGeneral%2F01%5FRyanRent%26Co%2F01%5FWoningen%2FVoorstraat%2025%2C%20Vlaardingen%2F2%5FInhuur | R82: https://ryanrent.sharepoint.com/sites/RyanRent/Gedeelde%20documenten/Forms/AllItems.aspx?id=%2Fsites%2FRyanRent%2FGedeelde%20documenten%2FGeneral%2F01%5FRyanRent%26Co%2F01%5FWoningen%2FVoorstraat%2025%2C%20Vlaardingen%2F3%5FVerhuur | S82: https://ryanrent.sharepoint.com/sites/RyanRent/Gedeelde%20documenten/Forms/AllItems.aspx?id=%2Fsites%2FRyanRent%2FGedeelde%20documenten%2FGeneral%2F01%5FRyanRent%26Co%2F01%5FWoningen%2FVoorstraat%2025%2C%20Vlaardingen%2F2%5FInhuur%2F2%5FInhuurovereenkomsten | T82: 2170 | U82: 553.95 | V82: 0 | W82: 271 | X82: Houses2Rent | Y82: particulier | AA82: info@houses2rent.nl | AB82: 06-20877085 | AC82: Stellingmolen 42 | AE82: Maassluis | AF82: Nederland | AI82: NL17 INGB 0390 7692 58 | AJ82: 755 | AM82: Onbepaalde tijd | AO82: 1 | AT82: 0 | AU82: 1300 | AV82: 1417 | AW82: 0.09 | AX82: 0 | AY82: 0 | AZ82: 0 | BA82: 0 | BB82: 0 | BC82: 17 | BD82: Tradiro Services B.V. | BE82: particulier | BG82: facturen@tradiro.nl | BH82: null | BI82: Honderdland 960 | BJ82: 2678 PS | BK82: Maasdijk | BL82: Nederland | BM82: 59979135.0 | BO82: NL05 RABO 0154 0739 89 | BQ82: 251 | BR82: 2025-06-06 | BU82: onbepaalde_tijd | BV82: Onbepaalde tijd | BW82: 2170 | BX82: 2420 | BY82: 2637.8 | BZ82: 0.09 | CA82: 250 | CB82: 0 | CC82: 250 | CD82: 2170 | CE82: ryanrent | CF82: 0 | CG82: 0 | CH82: 0 | CI82: 0 | CJ82: 0 | CK82: 0 | CL82: 1 | CM82: 0 | CN82: basis | CO82: 1120 | CP82: 13440 | CQ82: 86.15 | CR82: Verhuurd (onbepaald) | CS82: 0
A83: 0081 | B83: 102 | C83: Patrijsstraat 39 | D83: 3353AZ | E83: Papendrecht | F83: Appartement | H83: 3 | I83: 4 | J83: 1 | K83: Factuur | P83: https://ryanrent.sharepoint.com/sites/RyanRent/Gedeelde%20documenten/Forms/AllItems.aspx?id=%2Fsites%2FRyanRent%2FGedeelde%20documenten%2FGeneral%2F01%5FRyanRent%26Co%2F01%5FWoningen%2FPatrijsstraat%2039%20Papendrecht | Q83: https://ryanrent.sharepoint.com/sites/RyanRent/Gedeelde%20documenten/Forms/AllItems.aspx?id=%2Fsites%2FRyanRent%2FGedeelde%20documenten%2FGeneral%2F01%5FRyanRent%26Co%2F01%5FWoningen%2FPatrijsstraat%2039%20Papendrecht%2F2%5FInhuur | R83: https://ryanrent.sharepoint.com/sites/RyanRent/Gedeelde%20documenten/Forms/AllItems.aspx?id=%2Fsites%2FRyanRent%2FGedeelde%20documenten%2FGeneral%2F01%5FRyanRent%26Co%2F01%5FWoningen%2FPatrijsstraat%2039%20Papendrecht%2F3%5FVerhuur | S83: https://ryanrent.sharepoint.com/sites/RyanRent/Gedeelde%20documenten/Forms/AllItems.aspx?id=%2Fsites%2FRyanRent%2FGedeelde%20documenten%2FGeneral%2F01%5FRyanRent%26Co%2F01%5FWoningen%2FPatrijsstraat%2039%20Papendrecht%2F2%5FInhuur%2F2%5FInhuurovereenkomsten | T83: 2394.3 | U83: 250 | V83: 0 | W83: 314 | X83: G.K. Stoel | Y83: particulier | AA83: rolfstoel@hotmail.com | AB83: 06-14901449 | AC83: Patrijsstraat 39 | AE83: Papendrecht | AF83: Nederland | AJ83: 697 | AM83: Onbepaalde tijd | AO83: 1 | AT83: 1872 | AU83: 1872 | AV83: 2040.48 | AW83: 0.09 | AX83: 0 | AY83: 0 | AZ83: 0 | BA83: 0 | BB83: 0 | BV83: Leegstand | CD83: 2394.3 | CO83: -1872 | CP83: -22464 | CQ83: -100 | CR83: Beschikbaar | CS83: 0
A84: 0082 | B84: 103 | C84: Kanaal van Steenenhoek Z.Z. 10 | D84: 4202LS | E84: Gorinchem | F84: Appartement | H84: 6 | I84: 6 | J84: 1 | K84: Factuur | L84: 4210 | M84: 1005 | P84: https://ryanrent.sharepoint.com/sites/RyanRent/Gedeelde%20documenten/Forms/AllItems.aspx?id=%2Fsites%2FRyanRent%2FGedeelde%20documenten%2FGeneral%2F01%5FRyanRent%26Co%2F01%5FWoningen%2FKanaal%20van%20Steenenhoek%20Z.%20Z.%2010%2C%20Gorinchem | Q84: https://ryanrent.sharepoint.com/sites/RyanRent/Gedeelde%20documenten/Forms/AllItems.aspx?id=%2Fsites%2FRyanRent%2FGedeelde%20documenten%2FGeneral%2F01%5FRyanRent%26Co%2F01%5FWoningen%2FKanaal%20van%20Steenenhoek%20Z.%20Z.%2010%2C%20Gorinchem%2F2%5FInhuur | R84: https://ryanrent.sharepoint.com/sites/RyanRent/Gedeelde%20documenten/Forms/AllItems.aspx?id=%2Fsites%2FRyanRent%2FGedeelde%20documenten%2FGeneral%2F01%5FRyanRent%26Co%2F01%5FWoningen%2FKanaal%20van%20Steenenhoek%20Z.%20Z.%2010%2C%20Gorinchem%2F3%5FVerhuur | S84: https://ryanrent.sharepoint.com/sites/RyanRent/Gedeelde%20documenten/Forms/AllItems.aspx?id=%2Fsites%2FRyanRent%2FGedeelde%20documenten%2FGeneral%2F01%5FRyanRent%26Co%2F01%5FWoningen%2FKanaal%20van%20Steenenhoek%20Z.%20Z.%2010%2C%20Gorinchem%2F2%5FInhuur%2F2%5FInhuurovereenkomsten | T84: 2575 | U84: 350 | V84: 0 | AM84: Geen inhuur | BV84: Leegstand | CD84: 2575 | CO84: 0 | CP84: 0 | CR84: Beschikbaar | CS84: 0
A85: 0083 | B85: 104 | C85: Pastoriedijk 89 | D85: 3195HA | E85: Pernis | F85: Appartement | H85: 4 | I85: 4 | J85: 1 | K85: Factuur | L85: 3189 | M85: 2206 | T85: 2250 | U85: 200 | V85: 0 | AM85: Geen inhuur | BV85: Leegstand | CD85: 2250 | CO85: 0 | CP85: 0 | CR85: Beschikbaar | CS85: 0
A86: 0084 | B86: 105 | C86: Kerkdreef 42 | D86: 4571GJ | E86: Axel | F86: Appartement | H86: 2 | I86: 4 | J86: 1 | K86: Factuur | M86: 1005 | P86: https://ryanrent.sharepoint.com/sites/RyanRent/Gedeelde%20documenten/Forms/AllItems.aspx?id=%2Fsites%2FRyanRent%2FGedeelde%20documenten%2FGeneral%2F01%5FRyanRent%26Co%2F01%5FWoningen%2FKerkdreef%2042%2C%20Axel | Q86: https://ryanrent.sharepoint.com/sites/RyanRent/Gedeelde%20documenten/Forms/AllItems.aspx?id=%2Fsites%2FRyanRent%2FGedeelde%20documenten%2FGeneral%2F01%5FRyanRent%26Co%2F01%5FWoningen%2FKerkdreef%2042%2C%20Axel%2F2%5FInhuur | R86: https://ryanrent.sharepoint.com/sites/RyanRent/Gedeelde%20documenten/Forms/AllItems.aspx?id=%2Fsites%2FRyanRent%2FGedeelde%20documenten%2FGeneral%2F01%5FRyanRent%26Co%2F01%5FWoningen%2FKerkdreef%2042%2C%20Axel%2F3%5FVerhuur | S86: https://ryanrent.sharepoint.com/sites/RyanRent/Gedeelde%20documenten/Forms/AllItems.aspx?id=%2Fsites%2FRyanRent%2FGedeelde%20documenten%2FGeneral%2F01%5FRyanRent%26Co%2F01%5FWoningen%2FKerkdreef%2042%2C%20Axel%2F2%5FInhuur%2F2%5FInhuurovereenkomsten | T86: 2250 | U86: 250 | V86: 0 | AM86: Geen inhuur | BV86: Leegstand | CD86: 2250 | CO86: 0 | CP86: 0 | CR86: Beschikbaar | CS86: 0
A87: 0085 | B87: 106 | C87: Kierkegaardhof 54 | D87: 1277 AL | E87: Huizen | F87: Appartement | H87: 3 | I87: 3 | J87: 1 | K87: DS | L87: 2954 | M87: 1005 | P87: https://ryanrent.sharepoint.com/sites/RyanRent/Gedeelde%20documenten/Forms/AllItems.aspx?id=%2Fsites%2FRyanRent%2FGedeelde%20documenten%2FGeneral%2F01%5FRyanRent%26Co%2F01%5FWoningen%2FKierkegaardhof%2054%2C%20Huizen | Q87: https://ryanrent.sharepoint.com/sites/RyanRent/Gedeelde%20documenten/Forms/AllItems.aspx?id=%2Fsites%2FRyanRent%2FGedeelde%20documenten%2FGeneral%2F01%5FRyanRent%26Co%2F01%5FWoningen%2FKierkegaardhof%2054%2C%20Huizen%2F2%5FInhuur | R87: https://ryanrent.sharepoint.com/sites/RyanRent/Gedeelde%20documenten/Forms/AllItems.aspx?id=%2Fsites%2FRyanRent%2FGedeelde%20documenten%2FGeneral%2F01%5FRyanRent%26Co%2F01%5FWoningen%2FKierkegaardhof%2054%2C%20Huizen%2F3%5FVerhuur | S87: https://ryanrent.sharepoint.com/sites/RyanRent/Gedeelde%20documenten/Forms/AllItems.aspx?id=%2Fsites%2FRyanRent%2FGedeelde%20documenten%2FGeneral%2F01%5FRyanRent%26Co%2F01%5FWoningen%2FKierkegaardhof%2054%2C%20Huizen%2F2%5FInhuur%2F2%5FInhuurovereenkomsten | T87: 2400 | U87: 200 | V87: 0 | AM87: Geen inhuur | BV87: Leegstand | CD87: 2400 | CO87: 0 | CP87: 0 | CR87: Beschikbaar | CS87: 0
A88: 0086 | B88: 107 | C88: Kleine Beer 60 | D88: 7904 LV | E88: Hoogeveen | F88: Appartement | H88: 6 | I88: 7 | J88: 1 | K88: DS | L88: 9360 | M88: 1005 | P88: https://ryanrent.sharepoint.com/sites/RyanRent/Gedeelde%20documenten/Forms/AllItems.aspx?id=%2Fsites%2FRyanRent%2FGedeelde%20documenten%2FGeneral%2F01%5FRyanRent%26Co%2F01%5FWoningen%2FKleine%20Beer%2060%2C%20Hoogeveen | Q88: https://ryanrent.sharepoint.com/sites/RyanRent/Gedeelde%20documenten/Forms/AllItems.aspx?id=%2Fsites%2FRyanRent%2FGedeelde%20documenten%2FGeneral%2F01%5FRyanRent%26Co%2F01%5FWoningen%2FKleine%20Beer%2060%2C%20Hoogeveen%2F2%5FInhuur | R88: https://ryanrent.sharepoint.com/sites/RyanRent/Gedeelde%20documenten/Forms/AllItems.aspx?id=%2Fsites%2FRyanRent%2FGedeelde%20documenten%2FGeneral%2F01%5FRyanRent%26Co%2F01%5FWoningen%2FKleine%20Beer%2060%2C%20Hoogeveen%2F3%5FVerhuur | S88: https://ryanrent.sharepoint.com/sites/RyanRent/Gedeelde%20documenten/Forms/AllItems.aspx?id=%2Fsites%2FRyanRent%2FGedeelde%20documenten%2FGeneral%2F01%5FRyanRent%26Co%2F01%5FWoningen%2FKleine%20Beer%2060%2C%20Hoogeveen%2F2%5FInhuur%2F2%5FInhuurovereenkomsten | T88: 4000 | U88: 550 | V88: 0 | W88: 175 | X88: Dhr. J.L. Meerding | Y88: particulier | AA88: jlmeerding@gmai.com | AC88: Mauvezand 6 | AE88: Laren NH | AF88: Nederland | AI88: NL29 ABNA 0416 0042 29 | AJ88: 643 | AK88: 2022-09-01 | AL88: 2027-08-31 | AM88: Actief | AO88: 1 | AT88: 3555.36 | AU88: 3555.36 | AV88: 3875.34 | AW88: 0.09 | AX88: 0 | AY88: 0 | AZ88: 0 | BA88: 0 | BB88: 0 | BV88: Leegstand | CD88: 4000 | CO88: -3555.36 | CP88: -42664.32 | CQ88: -100 | CR88: Beschikbaar | CS88: 0
A89: 0087 | B89: 108 | C89: Jasmijnring 37 | D89: 4881HT | E89: Zundert | F89: Appartement | H89: 4 | I89: 6 | J89: 1 | K89: Factuur | L89: 8137 | M89: 1005 | P89: https://ryanrent.sharepoint.com/sites/RyanRent/Gedeelde%20documenten/Forms/AllItems.aspx?id=%2Fsites%2FRyanRent%2FGedeelde%20documenten%2FGeneral%2F01%5FRyanRent%26Co%2F01%5FWoningen%2FJasmijnring%2037%2C%20Zundert | Q89: https://ryanrent.sharepoint.com/sites/RyanRent/Gedeelde%20documenten/Forms/AllItems.aspx?id=%2Fsites%2FRyanRent%2FGedeelde%20documenten%2FGeneral%2F01%5FRyanRent%26Co%2F01%5FWoningen%2FJasmijnring%2037%2C%20Zundert%2F2%5FInhuur | R89: https://ryanrent.sharepoint.com/sites/RyanRent/Gedeelde%20documenten/Forms/AllItems.aspx?id=%2Fsites%2FRyanRent%2FGedeelde%20documenten%2FGeneral%2F01%5FRyanRent%26Co%2F01%5FWoningen%2FJasmijnring%2037%2C%20Zundert%2F3%5FVerhuur | S89: https://ryanrent.sharepoint.com/sites/RyanRent/Gedeelde%20documenten/Forms/AllItems.aspx?id=%2Fsites%2FRyanRent%2FGedeelde%20documenten%2FGeneral%2F01%5FRyanRent%26Co%2F01%5FWoningen%2FJasmijnring%2037%2C%20Zundert%2F2%5FInhuur%2F2%5FInhuurovereenkomsten | T89: 3250 | U89: 350 | V89: 0 | AM89: Geen inhuur | BV89: Leegstand | CD89: 3250 | CO89: 0 | CP89: 0 | CR89: Beschikbaar | CS89: 0
A90: 0088 | B90: 109 | C90: Kethelweg 66A | D90: 3135 GM | E90: Vlaardingen | F90: Vakantiepark | H90: 3 | I90: 5 | J90: 1 | K90: Factuur | P90: https://ryanrent.sharepoint.com/sites/RyanRent/Gedeelde%20documenten/Forms/AllItems.aspx?id=%2Fsites%2FRyanRent%2FGedeelde%20documenten%2FGeneral%2F01%5FRyanRent%26Co%2F01%5FWoningen%2FKethelweg%2066A%2C%20Vlaardingen | Q90: https://ryanrent.sharepoint.com/sites/RyanRent/Gedeelde%20documenten/Forms/AllItems.aspx?id=%2Fsites%2FRyanRent%2FGedeelde%20documenten%2FGeneral%2F01%5FRyanRent%26Co%2F01%5FWoningen%2FKethelweg%2066A%2C%20Vlaardingen%2F2%5FInhuur | R90: https://ryanrent.sharepoint.com/sites/RyanRent/Gedeelde%20documenten/Forms/AllItems.aspx?id=%2Fsites%2FRyanRent%2FGedeelde%20documenten%2FGeneral%2F01%5FRyanRent%26Co%2F01%5FWoningen%2FKethelweg%2066A%2C%20Vlaardingen%2F3%5FVerhuur | S90: https://ryanrent.sharepoint.com/sites/RyanRent/Gedeelde%20documenten/Forms/AllItems.aspx?id=%2Fsites%2FRyanRent%2FGedeelde%20documenten%2FGeneral%2F01%5FRyanRent%26Co%2F01%5FWoningen%2FKethelweg%2066A%2C%20Vlaardingen%2F2%5FInhuur%2F2%5FInhuurovereenkomsten | T90: 2593.81 | U90: 151.41 | V90: 0 | AM90: Geen inhuur | BV90: Leegstand | CD90: 2593.81 | CO90: 0 | CP90: 0 | CR90: Beschikbaar | CS90: 0
A91: 0089 | B91: 110 | C91: Van Maanenstraat 14A | D91: 3038 CZ | E91: Rotterdam | F91: Appartement | H91: 2 | I91: 2 | J91: 1 | K91: Factuur | P91: https://ryanrent.sharepoint.com/sites/RyanRent/Gedeelde%20documenten/Forms/AllItems.aspx?id=%2Fsites%2FRyanRent%2FGedeelde%20documenten%2FGeneral%2F01%5FRyanRent%26Co%2F01%5FWoningen%2FVan%20Maanenstraat%2014A%2C%20Rotterdam | Q91: https://ryanrent.sharepoint.com/sites/RyanRent/Gedeelde%20documenten/Forms/AllItems.aspx?id=%2Fsites%2FRyanRent%2FGedeelde%20documenten%2FGeneral%2F01%5FRyanRent%26Co%2F01%5FWoningen%2FVan%20Maanenstraat%2014A%2C%20Rotterdam%2F2%5FInhuur | R91: https://ryanrent.sharepoint.com/sites/RyanRent/Gedeelde%20documenten/Forms/AllItems.aspx?id=%2Fsites%2FRyanRent%2FGedeelde%20documenten%2FGeneral%2F01%5FRyanRent%26Co%2F01%5FWoningen%2FVan%20Maanenstraat%2014A%2C%20Rotterdam%2F3%5FVerhuur | S91: https://ryanrent.sharepoint.com/sites/RyanRent/Gedeelde%20documenten/Forms/AllItems.aspx?id=%2Fsites%2FRyanRent%2FGedeelde%20documenten%2FGeneral%2F01%5FRyanRent%26Co%2F01%5FWoningen%2FVan%20Maanenstraat%2014A%2C%20Rotterdam%2F2%5FInhuur%2F2%5FInhuurovereenkomsten | T91: 1650 | U91: 120 | V91: 0 | W91: 795 | X91: J.P. Stoel | Y91: particulier | AA91: Jpstoel@gma | AB91: 06 408 960 47 | AJ91: 744 | AK91: 2024-06-01 | AL91: 2026-05-31 | AM91: Actief | AO91: 1 | AT91: 0 | AW91: 0.09 | AX91: 0 | AY91: 0 | AZ91: 0 | BA91: 0 | BB91: 0 | BC91: 290 | BD91: Focuzop-eu | BE91: particulier | BG91: administratie@focuzop-eu.com | BH91: 06-45085584 | BI91: Amperestraat 7-14 | BK91: Harderwijk | BL91: Nederland | BM91: 85020184 | BQ91: 240 | BR91: 2024-06-01 | BS91: 2026-05-31 | BT91: 3 | BU91: bepaalde_tijd | BV91: Actief | BW91: 0 | BX91: 120 | BY91: 130.8 | BZ91: 0.09 | CA91: 120 | CB91: 0 | CC91: 250 | CD91: 1650 | CE91: ryanrent | CF91: 1 | CG91: 1 | CH91: 1 | CI91: 0 | CJ91: 0 | CK91: 0 | CL91: 1 | CM91: 0 | CN91: basis | CO91: 120 | CP91: 1440 | CR91: Verhuurd | CS91: 129
A92: 0090 | B92: 111 | C92: Laan van Nieuw Blankenburg 278 | D92: 3181AL | E92: Rozenburg | F92: Vakantiepark | H92: 3 | I92: 4 | J92: 1 | K92: DS | P92: https://ryanrent.sharepoint.com/sites/RyanRent/Gedeelde%20documenten/Forms/AllItems.aspx?id=%2Fsites%2FRyanRent%2FGedeelde%20documenten%2FGeneral%2F01%5FRyanRent%26Co%2F01%5FWoningen%2FLaan%20van%20Nieuw%20Blankenburg%20328%2C%20Rozenburg | Q92: https://ryanrent.sharepoint.com/sites/RyanRent/Gedeelde%20documenten/Forms/AllItems.aspx?id=%2Fsites%2FRyanRent%2FGedeelde%20documenten%2FGeneral%2F01%5FRyanRent%26Co%2F01%5FWoningen%2FLaan%20van%20Nieuw%20Blankenburg%20328%2C%20Rozenburg%2F2%5FInhuur | R92: https://ryanrent.sharepoint.com/sites/RyanRent/Gedeelde%20documenten/Forms/AllItems.aspx?id=%2Fsites%2FRyanRent%2FGedeelde%20documenten%2FGeneral%2F01%5FRyanRent%26Co%2F01%5FWoningen%2FLaan%20van%20Nieuw%20Blankenburg%20328%2C%20Rozenburg%2F3%5FVerhuur | S92: https://ryanrent.sharepoint.com/sites/RyanRent/Gedeelde%20documenten/Forms/AllItems.aspx?id=%2Fsites%2FRyanRent%2FGedeelde%20documenten%2FGeneral%2F01%5FRyanRent%26Co%2F01%5FWoningen%2Fvan%20Ruijsdaellaan%2072a%20Schiedam%2F2%5FInhuur%2F2%5FInhuurovereenkomsten | T92: 2855.46 | U92: 200 | V92: 0 | AM92: Geen inhuur | BV92: Leegstand | CD92: 2855.46 | CO92: 0 | CP92: 0 | CR92: Beschikbaar | CS92: 0
A93: 0091 | B93: 112 | C93: Landsteinerhof 68 | D93: 7908 BC | E93: Hoogeveen | F93: Appartement | H93: 5 | I93: 5 | J93: 1 | K93: DS | L93: 5768 | M93: 1005 | P93: https://ryanrent.sharepoint.com/sites/RyanRent/Gedeelde%20documenten/Forms/AllItems.aspx?id=%2Fsites%2FRyanRent%2FGedeelde%20documenten%2FGeneral%2F01%5FRyanRent%26Co%2F01%5FWoningen%2FLandsteinerhof%2068%2C%20Hoogeveen | Q93: https://ryanrent.sharepoint.com/sites/RyanRent/Gedeelde%20documenten/Forms/AllItems.aspx?id=%2Fsites%2FRyanRent%2FGedeelde%20documenten%2FGeneral%2F01%5FRyanRent%26Co%2F01%5FWoningen%2FLandsteinerhof%2068%2C%20Hoogeveen%2F2%5FInhuur | R93: https://ryanrent.sharepoint.com/sites/RyanRent/Gedeelde%20documenten/Forms/AllItems.aspx?id=%2Fsites%2FRyanRent%2FGedeelde%20documenten%2FGeneral%2F01%5FRyanRent%26Co%2F01%5FWoningen%2FLandsteinerhof%2068%2C%20Hoogeveen%2F3%5FVerhuur | S93: https://ryanrent.sharepoint.com/sites/RyanRent/Gedeelde%20documenten/Forms/AllItems.aspx?id=%2Fsites%2FRyanRent%2FGedeelde%20documenten%2FGeneral%2F01%5FRyanRent%26Co%2F01%5FWoningen%2FLandsteinerhof%2068%2C%20Hoogeveen%2F2%5FInhuur%2F2%5FInhuurovereenkomsten | T93: 2914.8 | U93: 300 | V93: 0 | AM93: Geen inhuur | BV93: Leegstand | CD93: 2914.8 | CO93: 0 | CP93: 0 | CR93: Beschikbaar | CS93: 0
A94: 0092 | B94: 113 | C94: Lange Brink 3 | D94: 8315AH | E94: Luttelgeest | F94: Appartement | H94: 5 | I94: 8 | J94: 1 | K94: Factuur | L94: 5003 | M94: 1005 | P94: https://ryanrent.sharepoint.com/sites/RyanRent/Gedeelde%20documenten/Forms/AllItems.aspx?id=%2Fsites%2FRyanRent%2FGedeelde%20documenten%2FGeneral%2F01%5FRyanRent%26Co%2F01%5FWoningen%2FLange%20Brink%203%2C%20Luttelgeest | Q94: https://ryanrent.sharepoint.com/sites/RyanRent/Gedeelde%20documenten/Forms/AllItems.aspx?id=%2Fsites%2FRyanRent%2FGedeelde%20documenten%2FGeneral%2F01%5FRyanRent%26Co%2F01%5FWoningen%2FLange%20Brink%203%2C%20Luttelgeest%2F2%5FInhuur | R94: https://ryanrent.sharepoint.com/sites/RyanRent/Gedeelde%20documenten/Forms/AllItems.aspx?id=%2Fsites%2FRyanRent%2FGedeelde%20documenten%2FGeneral%2F01%5FRyanRent%26Co%2F01%5FWoningen%2FLange%20Brink%203%2C%20Luttelgeest%2F3%5FVerhuur | T94: 3643.5 | U94: 433.33 | V94: 0 | AM94: Geen inhuur | BV94: Leegstand | CD94: 3643.5 | CO94: 0 | CP94: 0 | CR94: Beschikbaar | CS94: 0
A95: 0093 | B95: 114 | C95: Fabristraat 34A | D95: 3117 ML | E95: Schiedam | F95: Vakantiepark | H95: 4 | I95: 4 | J95: 1 | K95: Factuur | L95: 3134 | M95: 1005 | T95: 2602.5 | U95: 100 | V95: 0 | AM95: Geen inhuur | BV95: Leegstand | CD95: 2602.5 | CO95: 0 | CP95: 0 | CR95: Beschikbaar | CS95: 0
A96: 0094 | B96: 115 | C96: Fabristraat 34B | D96: 3117 ML | E96: Schiedam | F96: Vakantiepark | H96: 4 | I96: 6 | J96: 1 | K96: Factuur | L96: 1734 | M96: 1005 | T96: 3426.56 | U96: 0 | V96: 0 | AM96: Geen inhuur | BV96: Leegstand | CD96: 3426.56 | CO96: 0 | CP96: 0 | CR96: Beschikbaar | CS96: 0
A97: 0095 | B97: 116 | C97: Engelsestraat 16L3 | D97: 3028CG | E97: Rotterdam | F97: Vakantiepark | H97: 2 | I97: 3 | J97: 1 | K97: Factuur | P97: https://ryanrent.sharepoint.com/sites/RyanRent/Gedeelde%20documenten/Forms/AllItems.aspx?id=%2Fsites%2FRyanRent%2FGedeelde%20documenten%2FGeneral%2F01%5FRyanRent%26Co%2F01%5FWoningen%2FEngelsestraat%2016L3%2C%20Rotterdam | Q97: https://ryanrent.sharepoint.com/sites/RyanRent/Gedeelde%20documenten/Forms/AllItems.aspx?id=%2Fsites%2FRyanRent%2FGedeelde%20documenten%2FGeneral%2F01%5FRyanRent%26Co%2F01%5FWoningen%2FEngelsestraat%2016L3%2C%20Rotterdam%2F2%5FInhuur | R97: https://ryanrent.sharepoint.com/sites/RyanRent/Gedeelde%20documenten/Forms/AllItems.aspx?id=%2Fsites%2FRyanRent%2FGedeelde%20documenten%2FGeneral%2F01%5FRyanRent%26Co%2F01%5FWoningen%2FEngelsestraat%2016L3%2C%20Rotterdam%2F3%5FVerhuur | S97: https://ryanrent.sharepoint.com/sites/RyanRent/Gedeelde%20documenten/Forms/AllItems.aspx?id=%2Fsites%2FRyanRent%2FGedeelde%20documenten%2FGeneral%2F01%5FRyanRent%26Co%2F01%5FWoningen%2FEngelsestraat%2016L3%2C%20Rotterdam%2F2%5FInhuur%2F2%5FInhuurovereenkomsten | T97: 1993.32 | U97: 58.43 | V97: 0 | W97: 295 | X97: In Stijl Totaalbouw BV | Y97: particulier | AA97: info@instijltotaalbouw.nl | AB97: 06-44404678 | AC97: Burgemeester Freijterslaan 1 | AE97: Roosendaal | AF97: Nederland | AJ97: 584 | AM97: Onbepaalde tijd | AO97: 1 | AT97: 0 | AU97: 894 | AV97: 974.46 | AW97: 0.09 | AX97: 0 | AY97: 0 | AZ97: 0 | BA97: 0 | BB97: 0 | BC97: 17 | BD97: Tradiro Services B.V. | BE97: particulier | BG97: facturen@tradiro.nl | BH97: null | BI97: Honderdland 960 | BJ97: 2678 PS | BK97: Maasdijk | BL97: Nederland | BM97: 59979135.0 | BO97: NL05 RABO 0154 0739 89 | BQ97: 69 | BR97: 2025-01-01 | BU97: onbepaalde_tijd | BV97: Onbepaalde tijd | BW97: 1993.32 | BX97: 1993.32 | BY97: 2172.72 | BZ97: 0.09 | CA97: 58.43 | CB97: 25.1 | CC97: 250 | CD97: 1993.32 | CE97: eigen_beheer | CF97: 0 | CG97: 0 | CH97: 0 | CI97: 0 | CJ97: 0 | CK97: 0 | CL97: 1 | CM97: 0 | CN97: basis | CO97: 1099.32 | CP97: 13191.84 | CQ97: 122.97 | CR97: Verhuurd (onbepaald) | CS97: 0
A98: 0096 | B98: 117 | C98: Loggerstraat 3 | D98: 8862ZN | E98: Harlingen | F98: Appartement | H98: 4 | J98: 1 | K98: Factuur | L98: 8803 | M98: 2206 | T98: 2375 | U98: 250 | V98: 0 | AM98: Geen inhuur | BV98: Leegstand | CD98: 2375 | CO98: 0 | CP98: 0 | CR98: Beschikbaar | CS98: 0
A99: 0097 | B99: 118 | C99: Burchstraat 16A | D99: 4501 BJ | E99: Oostburg | F99: Appartement | H99: 7 | I99: 7 | J99: 1 | K99: DS | L99: 4516 | M99: 1005 | T99: 3850 | U99: 450 | V99: 0 | W99: 302 | X99: A.H.S. Willemsen | Y99: particulier | AA99: huurwoningarnhem@gmail.com | AF99: Nederland | AI99: NL90 ABNA 0861 1395 26 | AJ99: 563 | AK99: 2024-05-01 | AL99: 2026-04-30 | AM99: Actief | AO99: 1 | AT99: 2582.5 | AU99: 2607.5 | AV99: 2842.18 | AW99: 0.09 | AX99: 0 | AY99: 0 | AZ99: 0 | BA99: 0 | BB99: 0 | BC99: 17 | BD99: Tradiro Services B.V. | BE99: particulier | BG99: facturen@tradiro.nl | BH99: null | BI99: Honderdland 960 | BJ99: 2678 PS | BK99: Maasdijk | BL99: Nederland | BM99: 59979135.0 | BO99: NL05 RABO 0154 0739 89 | BQ99: 46 | BR99: 2024-05-01 | BS99: 2026-04-30 | BU99: onbepaalde_tijd | BV99: Actief | BW99: 3550 | BX99: 4000 | BY99: 4360 | BZ99: 0.09 | CA99: 450 | CB99: 0 | CC99: 375 | CD99: 3850 | CE99: ryanrent | CF99: 0 | CG99: 0 | CH99: 0 | CI99: 0 | CJ99: 0 | CK99: 0 | CL99: 1 | CM99: 0 | CN99: intensief | CO99: 1392.5 | CP99: 16710 | CQ99: 53.4 | CR99: Verhuurd | CS99: 98
A100: 0098 | B100: 119 | C100: Melis Stokezijde 94 | D100: 2543GG | E100: Den Haag | F100: Appartement | H100: 4 | I100: 4 | J100: 1 | K100: DS | P100: https://ryanrent.sharepoint.com/sites/RyanRent/Gedeelde%20documenten/Forms/AllItems.aspx?id=%2Fsites%2FRyanRent%2FGedeelde%20documenten%2FGeneral%2F01%5FRyanRent%26Co%2F01%5FWoningen%2FMelis%20Stokezijde%2094%2C%20Den%20Haag | Q100: https://ryanrent.sharepoint.com/sites/RyanRent/Gedeelde%20documenten/Forms/AllItems.aspx?id=%2Fsites%2FRyanRent%2FGedeelde%20documenten%2FGeneral%2F01%5FRyanRent%26Co%2F01%5FWoningen%2FMelis%20Stokezijde%2094%2C%20Den%20Haag%2F2%5FInhuur | R100: https://ryanrent.sharepoint.com/sites/RyanRent/Gedeelde%20documenten/Forms/AllItems.aspx?id=%2Fsites%2FRyanRent%2FGedeelde%20documenten%2FGeneral%2F01%5FRyanRent%26Co%2F01%5FWoningen%2FMelis%20Stokezijde%2094%2C%20Den%20Haag%2F3%5FVerhuur | S100: https://ryanrent.sharepoint.com/sites/RyanRent/Gedeelde%20documenten/Forms/AllItems.aspx?id=%2Fsites%2FRyanRent%2FGedeelde%20documenten%2FGeneral%2F01%5FRyanRent%26Co%2F01%5FWoningen%2FMelis%20Stokezijde%2094%2C%20Den%20Haag%2F2%5FInhuur%2F2%5FInhuurovereenkomsten | T100: 3250 | U100: 200 | V100: 0 | AM100: Geen inhuur | BV100: Leegstand | CD100: 3250 | CO100: 0 | CP100: 0 | CR100: Beschikbaar | CS100: 0
...
